Workbook

Sheet Cashflow Matrix
A1: Private Equity Commitment Planning Tool
A2: Cashflow Matrix
A3: Netto kasstroom projectie per jaar - Pas de grijze cellen aan om uw eigen scenario te modelleren
J7: PROJECTED
A8: FONDSTYPE | B8: CURR. | C8: COMMITMENT | D8: IRR | E8: INSTAP | F8: 2025 | G8: 2026 | H8: 2027 | I8: 2028 | J8: 2029 | K8: 2030 | L8: 2031 | M8: 2032 | N8: 2033 | O8: 2034 | P8: 2035 | Q8: 2036 | R8: 2037 | S8: 2038 | T8: 2039 | U8: 2040 | V8: 2041 | W8: 2042 | X8: 2043 | Y8: 2044 | Z8: 2045 | AA8: 2046 | AB8: 2047 | AC8: 2048 | AD8: 2049 | AE8: 2050 | AF8: 2051 | AG8: 2052 | AH8: 2053 | AI8: 2054 | AJ8: 2055 | AK8: 2056 | AL8: 2057 | AM8: 2058 | AN8: 2059 | AO8: 2060 | AP8: 2061 | AQ8: 2062 | AR8: 2063 | AS8: 2064 | AT8: 2065
A102: Beschikbaar Kapitaal | F102: =C102-F104 -> 0 | G102: =C102-G104 -> 0 | H102: =C102-H104 -> 0 | I102: =C102-I104 -> 0 | J102: =C102-J104 -> 0 | K102: =C102-K104 -> 0 | L102: =C102-L104 -> 0 | M102: =C102-M104 -> 0 | N102: =C102-N104 -> 0 | O102: =C102-O104 -> 0 | P102: =C102-P104 -> 0 | Q102: =C102-Q104 -> 0 | R102: =C102-R104 -> 0 | S102: =C102-S104 -> 0 | T102: =C102-T104 -> 0 | U102: =C102-U104 -> 0 | V102: =C102-V104 -> 0 | W102: =C102-W104 -> 0 | X102: =C102-X104 -> 0 | Y102: =C98-Y100 -> 0 | Z102: =C98-Z100 -> 0 | AA102: =C98-AA100 -> 0 | AB102: =C98-AB100 -> 0 | AC102: =C98-AC100 -> 0 | AD102: =C98-AD100 -> 0 | AE102: =C98-AE100 -> 0 | AF102: =C98-AF100 -> 0 | AG102: =C98-AG100 -> 0 | AH102: =C98-AH100 -> 0 | AI102: =C98-AI100 -> 0 | AJ102: =C98-AJ100 -> 0 | AK102: =C98-AK100 -> 0 | AL102: =C98-AL100 -> 0 | AM102: =C98-AM100 -> 0 | AN102: =C98-AN100 -> 0 | AO102: =C98-AO100 -> 0 | AP102: =C98-AP100 -> 0 | AQ102: =C98-AQ100 -> 0 | AR102: =C98-AR100 -> 0 | AS102: =C98-AS100 -> 0 | AT102: =C98-AT100 -> 0
A103: Jaarlijkse Netto Cashflow | F103: =SUM(F9:F99) -> 0 | G103: =SUM(G9:G99) -> 0 | H103: =SUM(H9:H99) -> 0 | I103: =SUM(I9:I99) -> 0 | J103: =SUM(J9:J99) -> 0 | K103: =SUM(K9:K99) -> 0 | L103: =SUM(L9:L99) -> 0 | M103: =SUM(M9:M99) -> 0 | ... X103: =SUM(X9:X99) -> 0 | Y103: =SUM(Y5:Y95) -> 2044 | Z103: =SUM(Z5:Z95) -> 2045 | AA103: =SUM(AA5:AA95) -> 2046 | AB103: =SUM(AB5:AB95) -> 2047 | AC103: =SUM(AC5:AC95) -> 2048 | AD103: =SUM(AD5:AD95) -> 2049 | AE103: =SUM(AE5:AE95) -> 2050 | AF103: =SUM(AF5:AF95) -> 2051 | ... AT103: =SUM(AT5:AT95) -> 2065
A104: Geïnvesteerd Kapitaal (Capital Called) | F104: =ABS(MIN(F9:F99,0)) -> 0 | G104: =F104+ABS(MIN(G9:G99,0)) -> 0 | H104: =G104+ABS(MIN(H9:H99,0)) -> 0 | I104: =H104+ABS(MIN(I9:I99,0)) -> 0 | J104: =I104+ABS(MIN(J9:J99,0)) -> 0 | K104: =J104+ABS(MIN(K9:K99,0)) -> 0 | L104: =K104+ABS(MIN(L9:L99,0)) -> 0 | M104: =L104+ABS(MIN(M9:M99,0)) -> 0 | N104: =M104+ABS(MIN(N9:N99,0)) -> 0 | ... X104: =W104+ABS(MIN(X9:X99,0)) -> 0 | Y104: =X100+ABS(MIN(Y5:Y95,0)) -> 0 | Z104: =Y100+ABS(MIN(Z5:Z95,0)) -> 0 | AA104: =Z100+ABS(MIN(AA5:AA95,0)) -> 0 | AB104: =AA100+ABS(MIN(AB5:AB95,0)) -> 0 | AC104: =AB100+ABS(MIN(AC5:AC95,0)) -> 0 | AD104: =AC100+ABS(MIN(AD5:AD95,0)) -> 0 | AE104: =AD100+ABS(MIN(AE5:AE95,0)) -> 0 | AF104: =AE100+ABS(MIN(AF5:AF95,0)) -> 0 | ... AT104: =AS100+ABS(MIN(AT5:AT95,0)) -> 0

Sheet Portfolio Projectie
A1: Portfolio Projectie
A2: Visuele weergave van cash en exposure
A4: Jaar | B4: Beschikbaar Kapitaal | C4: Geïnvesteerd Kapitaal | D4: Totale Waarde (NAV + Cash)
A5: 2025 | B5: ='Cashflow Matrix'!F98 | C5: ='Cashflow Matrix'!F100 | D5: =B5+C5*1.5 -> 0
A6: 2026 | B6: ='Cashflow Matrix'!G98 | C6: ='Cashflow Matrix'!G100 | D6: =B6+C6*1.5 -> 0
A7: 2027 | B7: ='Cashflow Matrix'!H98 | C7: ='Cashflow Matrix'!H100 | D7: =B7+C7*1.5 -> 0
A8: 2028 | B8: ='Cashflow Matrix'!I98 | C8: ='Cashflow Matrix'!I100 | D8: =B8+C8*1.5 -> 0
A9: 2029 | B9: ='Cashflow Matrix'!J98 | C9: ='Cashflow Matrix'!J100 | D9: =B9+C9*1.5 -> 0
A10: 2030 | B10: ='Cashflow Matrix'!K98 | C10: ='Cashflow Matrix'!K100 | D10: =B10+C10*1.5 -> 0
A11: 2031 | B11: ='Cashflow Matrix'!L98 | C11: ='Cashflow Matrix'!L100 | D11: =B11+C11*1.5 -> 0
A12: 2032 | B12: ='Cashflow Matrix'!M98 | C12: ='Cashflow Matrix'!M100 | D12: =B12+C12*1.5 -> 0
A13: 2033 | B13: ='Cashflow Matrix'!N98 | C13: ='Cashflow Matrix'!N100 | D13: =B13+C13*1.5 -> 0
A14: 2034 | B14: ='Cashflow Matrix'!O98 | C14: ='Cashflow Matrix'!O100 | D14: =B14+C14*1.5 -> 0
A15: 2035 | B15: ='Cashflow Matrix'!P98 | C15: ='Cashflow Matrix'!P100 | D15: =B15+C15*1.5 -> 0
A16: 2036 | B16: ='Cashflow Matrix'!Q98 | C16: ='Cashflow Matrix'!Q100 | D16: =B16+C16*1.5 -> 0
A17: 2037 | B17: ='Cashflow Matrix'!R98 | C17: ='Cashflow Matrix'!R100 | D17: =B17+C17*1.5 -> 0
A18: 2038 | B18: ='Cashflow Matrix'!S98 | C18: ='Cashflow Matrix'!S100 | D18: =B18+C18*1.5 -> 0
A19: 2039 | B19: ='Cashflow Matrix'!T98 | C19: ='Cashflow Matrix'!T100 | D19: =B19+C19*1.5 -> 0

Sheet Parameters
A1: Default Parameters per Fondstype
A3: Fondstype | B3: IRR | C3: Duration (jaren) | D3: J-Curve Diepte | E3: Peak Year
A4: Secondaries | B4: 0.132 | C4: 7 | D4: 0.2 | E4: 3
A5: PE | B5: 0.147 | C5: 10 | D5: 0.4 | E5: 5
A6: VC | B6: 0.185 | C6: 12 | D6: 0.6 | E6: 7

Sheet Fondsen
A1: Fondsen Master Database
A3: Fondsnaam | B3: Type | C3: IRR | D3: Duration | E3: Vintage | F3: Status | G3: Notities
A4: Alpinvest | B4: PE | C4: 0.16 | D4: 10 | E4: 2020 | F4: Active | G4: Leading European PE
A5: Rhein Invest II | B5: PE | C5: 0.14 | D5: 10 | E5: 2021 | F5: Active | G5: German mid-market
A6: OGF II | B6: VC | C6: 0.22 | D6: 12 | E6: 2019 | F6: Active | G6: Tech focused VC
A7: ICG I - LP Fund | B7: Secondaries | C7: 0.13 | D7: 7 | E7: 2022 | F7: Active | G7: Credit focused
A8: Bcapital II | B8: Secondaries | C8: 0.12 | D8: 6 | E8: 2023 | F8: Active | G8: European secondaries
