Workbook
Name __G90000: #REF!
Name _1_0DAI: #REF!
Name _10R: #REF!
Name _2DAI: #REF!
Name _3_0P: #REF!
Name _4P: #REF!
Name _5_?_0P: #REF!
Name _6_?__P: #REF!
Name _7_0P: #REF!
Name _8_0R: #REF!
Name _9P: #REF!
Name _G90000: #REF!
Name _G900000: #REF!
Name _PRG1: #REF!
Name _PRG2: #REF!
Name _PRG3: #REF!
Name _PRG31: #REF!
Name _PRG4: #REF!
Name _PRG5: #REF!
Name _RPG4: #REF!
Name _VSA1: #REF!
Name _VSA2: #REF!
Name _vsa3: #REF!
Name aaa: #REF!
Name ASFIII: #REF!
Name AUM: #REF!
Name AUMCheck: #REF!
Name AUMCurrency: #REF!
Name Baselinedata: #REF!
Name bis: #REF!
Name biz: #REF!
Name BoardDate: #REF!
Name Carlyle1: #REF!
Name Carlyle2: #REF!
Name carlyle3: #REF!
Name Cashflows: #REF!
Name Client_GainLoss: #REF!
Name ClientsCheck: #REF!
Name ClientType: #REF!
Name closingdate: #REF!
Name closingdateexample: #REF!
Name COL_C_C_ACTIVITY: #REF!
Name COL_C_C_COMMENT: #REF!
Name COL_C_C_CREATION_DATE: #REF!
Name COL_C_C_CURRENCY: #REF!
Name COL_C_C_EFRONTFORMULAPARAM1: #REF!
Name COL_C_C_EFRONTFORMULAPARAM2: #REF!
Name COL_C_C_FUNDING: #REF!
Name COL_C_C_ID: #REF!
Name COL_C_C_INV_MANAGER: #REF!
Name COL_C_C_NAME: #REF!
Name COL_C_C_NOMINAL_VALUE: #REF!
Name COL_C_C_NOMINAL_VALUE_CURRENCY: #REF!
Name COL_C_C_NR_SHARES_FD: #REF!
Name COL_C_C_NR_SHARES_FD_OBSOLETE: #REF!
Name COL_C_C_NR_SHARES_NFD: #REF!
Name COL_C_ID1: #REF!
Name COL_CF_CF_EXIT_CCY: #REF!
Name COL_CF_CF_ID: #REF!
Name COL_CF_CF_INCOMES_CCY: #REF!

Sheet Samenvatting
C1: Private Equity and Private Debt Exposure
C2: John Huiberts
C3: ="Commitment of € " & TEXT(SUM(F43:F100), "#.##0,00") -> Commitment of € 51.268.000,00
L40: Projected
E41: Currency | F41: Commitment | G41: Deelnemingsvrijstelling | H41: IRR | I41: Close | K41: Instap Jaar | L41: 46387 | M41: =EOMONTH(L41,12) -> 46752 | N41: =EOMONTH(M41,12) -> 47118 | O41: =EOMONTH(N41,12) -> 47483 | P41: =EOMONTH(O41,12) -> 47848 | Q41: =EOMONTH(P41,12) -> 48213 | R41: =EOMONTH(Q41,12) -> 48579 | S41: =EOMONTH(R41,12) -> 48944 | T41: =EOMONTH(S41,12) -> 49309 | ... AU41: =EOMONTH(AT41,12) -> 59171
C42: Capital calls | D42: Fondstype | E42: currency | F42: bedrag
C43: Secondaries Dummy | D43: =_xlfn.XLOOKUP(C43,Fondsen!B:B,Fondsen!C:C,"0",0,1) -> Secondaries | E43: EUR | F43: 5400000 | G43: =IFERROR(IF(SUM(OFFSET(INDEX('Capital Call&Distributions data'!A:A,MATCH(D43,'Capital Call&Distributions data'!A:A,0)),-1,2,1,1000))=0,"✔",""),"") | H43: =IFERROR(IRR(L43:AD43),"") -> 0.13229301 | I43: 46023 | J43: =YEAR(K43)-YEAR(I43) -> 0 | K43: 46023 | L43: {=IFERROR(IF(L$41<$K43,0,$F43*_xlfn.XLOOKUP($D43,'Capital Call&Distributions data'!$A:$A,INDEX('Capital Call&Distributions data'!$C:$Q,0,MIN(MAX(YEAR(L$41)-YEAR($K43)+$J43+1,1),14)))),0)} -> -2874338.1 | M43: {=IFERROR(IF(M$41<$K43,0,$F43*_xlfn.XLOOKUP($D43,'Capital Call&Distributions data'!$A:$A,INDEX('Capital Call&Distributions data'!$C:$Q,0,MIN(MAX(YEAR(M$41)-YEAR($K43)+$J43+1,1),14)))),0)} -> -257661.94 | N43: {=IFERROR(IF(N$41<$K43,0,$F43*_xlfn.XLOOKUP($D43,'Capital Call&Distributions data'!$A:$A,INDEX('Capital Call&Distributions data'!$C:$Q,0,MIN(MAX(YEAR(N$41)-YEAR($K43)+$J43+1,1),14)))),0)} -> 1376644.4 | O43: {=IFERROR(IF(O$41<$K43,0,$F43*_xlfn.XLOOKUP($D43,'Capital Call&Distributions data'!$A:$A,INDEX('Capital Call&Distributions data'!$C:$Q,0,MIN(MAX(YEAR(O$41)-YEAR($K43)+$J43+1,1),14)))),0)} -> 1132342.3 | P43: {=IFERROR(IF(P$41<$K43,0,$F43*_xlfn.XLOOKUP($D43,'Capital Call&Distributions data'!$A:$A,INDEX('Capital Call&Distributions data'!$C:$Q,0,MIN(MAX(YEAR(P$41)-YEAR($K43)+$J43+1,1),14)))),0)} -> 785231.73 | Q43: {=IFERROR(IF(Q$41<$K43,0,$F43*_xlfn.XLOOKUP($D43,'Capital Call&Distributions data'!$A:$A,INDEX('Capital Call&Distributions data'!$C:$Q,0,MIN(MAX(YEAR(Q$41)-YEAR($K43)+$J43+1,1),14)))),0)} -> 442209.49 | R43: {=IFERROR(IF(R$41<$K43,0,$F43*_xlfn.XLOOKUP($D43,'Capital Call&Distributions data'!$A:$A,INDEX('Capital Call&Distributions data'!$C:$Q,0,MIN(MAX(YEAR(R$41)-YEAR($K43)+$J43+1,1),14)))),0)} -> 496557.37 | S43: {=IFERROR(IF(S$41<$K43,0,$F43*_xlfn.XLOOKUP($D43,'Capital Call&Distributions data'!$A:$A,INDEX('Capital Call&Distributions data'!$C:$Q,0,MIN(MAX(YEAR(S$41)-YEAR($K43)+$J43+1,1),14)))),0)} -> 410140.86 | T43: {=IFERROR(IF(T$41<$K43,0,$F43*_xlfn.XLOOKUP($D43,'Capital Call&Distributions data'!$A:$A,INDEX('Capital Call&Distributions data'!$C:$Q,0,MIN(MAX(YEAR(T$41)-YEAR($K43)+$J43+1,1),14)))),0)} -> 284566.87 | U43: {=IFERROR(IF(U$41<$K43,0,$F43*_xlfn.XLOOKUP($D43,'Capital Call&Distributions data'!$A:$A,INDEX('Capital Call&Distributions data'!$C:$O,0,MIN(MAX(YEAR(U$41)-YEAR($K43)+$J43+1,1),14)))),0)} -> 44220.949 | V43: {=IFERROR(IF(V$41<$K43,0,$F43*_xlfn.XLOOKUP($D43,'Capital Call&Distributions data'!$A:$A,INDEX('Capital Call&Distributions data'!$C:$O,0,MIN(MAX(YEAR(V$41)-YEAR($K43)+$J43+1,1),14)))),0)} -> 19241.176 | W43: {=IFERROR(IF(W$41<$K43,0,$F43*_xlfn.XLOOKUP($D43,'Capital Call&Distributions data'!$A:$A,INDEX('Capital Call&Distributions data'!$C:$O,0,MIN(MAX(YEAR(W$41)-YEAR($K43)+$J43+1,1),14)))),0)} -> 0 | X43: {=IFERROR(IF(X$41<$K43,0,$F43*_xlfn.XLOOKUP($D43,'Capital Call&Distributions data'!$A:$A,INDEX('Capital Call&Distributions data'!$C:$O,0,MIN(MAX(YEAR(X$41)-YEAR($K43)+$J43+1,1),14)))),0)} -> 0 | Y43: {=IFERROR(IF(Y$41<$K43,0,$F43*_xlfn.XLOOKUP($D43,'Capital Call&Distributions data'!$A:$A,INDEX('Capital Call&Distributions data'!$C:$O,0,MIN(MAX(YEAR(Y$41)-YEAR($K43)+$J43+1,1),14)))),0)} -> 0 | Z43: {=IFERROR(IF(Z$41<$K43,0,$F43*_xlfn.XLOOKUP($D43,'Capital Call&Distributions data'!$A:$A,INDEX('Capital Call&Distributions data'!$C:$O,0,MIN(MAX(YEAR(Z$41)-YEAR($K43)+$J43+1,1),14)))),0)} -> 0 | AA43: {=IFERROR(IF(AA$41<$K43,0,$F43*_xlfn.XLOOKUP($D43,'Capital Call&Distributions data'!$A:$A,INDEX('Capital Call&Distributions data'!$C:$O,0,MIN(MAX(YEAR(AA$41)-YEAR($K43)+$J43+1,1),14)))),0)} -> 0 | AB43: {=IFERROR(IF(AB$41<$K43,0,$F43*_xlfn.XLOOKUP($D43,'Capital Call&Distributions data'!$A:$A,INDEX('Capital Call&Distributions data'!$C:$O,0,MIN(MAX(YEAR(AB$41)-YEAR($K43)+$J43+1,1),14)))),0)} -> 0 | ... AU43: {=IFERROR(IF(AU$41<$K43,0,$F43*_xlfn.XLOOKUP($D43,'Capital Call&Distributions data'!$A:$A,INDEX('Capital Call&Distributions data'!$C:$O,0,MIN(MAX(YEAR(AU$41)-YEAR($K43)+$J43+1,1),14)))),0)} -> 0
C44: PE dummy | D44: =_xlfn.XLOOKUP(C44,Fondsen!B:B,Fondsen!C:C,"0",0,1) -> PE | E44: EUR | F44: 2500000 | G44: =IFERROR(IF(SUM(OFFSET(INDEX('Capital Call&Distributions data'!A:A,MATCH(D44,'Capital Call&Distributions data'!A:A,0)),-1,2,1,1000))=0,"✔",""),"") | H44: =IFERROR(IRR(L44:AD44),"") -> 0.1472451 | I44: 46023 | J44: =YEAR(K44)-YEAR(I44) -> 0 | K44: 46023 | L44: {=IFERROR(IF(L$41<$K44,0,$F44*_xlfn.XLOOKUP($D44,'Capital Call&Distributions data'!$A:$A,INDEX('Capital Call&Distributions data'!$C:$O,0,MIN(MAX(YEAR(L$41)-YEAR($K44)+$J44+1,1),14)))),0)} -> -786543.29 | M44: {=IFERROR(IF(M$41<$K44,0,$F44*_xlfn.XLOOKUP($D44,'Capital Call&Distributions data'!$A:$A,INDEX('Capital Call&Distributions data'!$C:$O,0,MIN(MAX(YEAR(M$41)-YEAR($K44)+$J44+1,1),14)))),0)} -> -546580.93 | N44: {=IFERROR(IF(N$41<$K44,0,$F44*_xlfn.XLOOKUP($D44,'Capital Call&Distributions data'!$A:$A,INDEX('Capital Call&Distributions data'!$C:$O,0,MIN(MAX(YEAR(N$41)-YEAR($K44)+$J44+1,1),14)))),0)} -> -546580.93 | O44: {=IFERROR(IF(O$41<$K44,0,$F44*_xlfn.XLOOKUP($D44,'Capital Call&Distributions data'!$A:$A,INDEX('Capital Call&Distributions data'!$C:$O,0,MIN(MAX(YEAR(O$41)-YEAR($K44)+$J44+1,1),14)))),0)} -> -245294.86 | P44: {=IFERROR(IF(P$41<$K44,0,$F44*_xlfn.XLOOKUP($D44,'Capital Call&Distributions data'!$A:$A,INDEX('Capital Call&Distributions data'!$C:$O,0,MIN(MAX(YEAR(P$41)-YEAR($K44)+$J44+1,1),14)))),0)} -> 633993.2 | Q44: {=IFERROR(IF(Q$41<$K44,0,$F44*_xlfn.XLOOKUP($D44,'Capital Call&Distributions data'!$A:$A,INDEX('Capital Call&Distributions data'!$C:$O,0,MIN(MAX(YEAR(Q$41)-YEAR($K44)+$J44+1,1),14)))),0)} -> 1046504.1 | R44: {=IFERROR(IF(R$41<$K44,0,$F44*_xlfn.XLOOKUP($D44,'Capital Call&Distributions data'!$A:$A,INDEX('Capital Call&Distributions data'!$C:$O,0,MIN(MAX(YEAR(R$41)-YEAR($K44)+$J44+1,1),14)))),0)} -> 1042664 | S44: {=IFERROR(IF(S$41<$K44,0,$F44*_xlfn.XLOOKUP($D44,'Capital Call&Distributions data'!$A:$A,INDEX('Capital Call&Distributions data'!$C:$O,0,MIN(MAX(YEAR(S$41)-YEAR($K44)+$J44+1,1),14)))),0)} -> 628564.66 | ... AU44: {=IFERROR(IF(AU$41<$K44,0,$F44*_xlfn.XLOOKUP($D44,'Capital Call&Distributions data'!$A:$A,INDEX('Capital Call&Distributions data'!$C:$O,0,MIN(MAX(YEAR(AU$41)-YEAR($K44)+$J44+1,1),14)))),0)} -> 0
C45: Secondaries Dummy | D45: =_xlfn.XLOOKUP(C45,Fondsen!B:B,Fondsen!C:C,"0",0,1) -> Secondaries | E45: EUR | F45: 5100000 | G45: =IFERROR(IF(SUM(OFFSET(INDEX('Capital Call&Distributions data'!A:A,MATCH(D45,'Capital Call&Distributions data'!A:A,0)),-1,2,1,1000))=0,"✔",""),"") | H45: =IFERROR(IRR(L45:AD45),"") -> 0.13229301 | I45: 46388 | J45: =YEAR(K45)-YEAR(I45) -> 0 | K45: 46388 | L45: {=IFERROR(IF(L$41<$K45,0,$F45*_xlfn.XLOOKUP($D45,'Capital Call&Distributions data'!$A:$A,INDEX('Capital Call&Distributions data'!$C:$O,0,MIN(MAX(YEAR(L$41)-YEAR($K45)+$J45+1,1),14)))),0)} -> 0 | M45: {=IFERROR(IF(M$41<$K45,0,$F45*_xlfn.XLOOKUP($D45,'Capital Call&Distributions data'!$A:$A,INDEX('Capital Call&Distributions data'!$C:$O,0,MIN(MAX(YEAR(M$41)-YEAR($K45)+$J45+1,1),14)))),0)} -> -2714652.6 | N45: {=IFERROR(IF(N$41<$K45,0,$F45*_xlfn.XLOOKUP($D45,'Capital Call&Distributions data'!$A:$A,INDEX('Capital Call&Distributions data'!$C:$O,0,MIN(MAX(YEAR(N$41)-YEAR($K45)+$J45+1,1),14)))),0)} -> -243347.39 | O45: {=IFERROR(IF(O$41<$K45,0,$F45*_xlfn.XLOOKUP($D45,'Capital Call&Distributions data'!$A:$A,INDEX('Capital Call&Distributions data'!$C:$O,0,MIN(MAX(YEAR(O$41)-YEAR($K45)+$J45+1,1),14)))),0)} -> 1300164.2 | P45: {=IFERROR(IF(P$41<$K45,0,$F45*_xlfn.XLOOKUP($D45,'Capital Call&Distributions data'!$A:$A,INDEX('Capital Call&Distributions data'!$C:$O,0,MIN(MAX(YEAR(P$41)-YEAR($K45)+$J45+1,1),14)))),0)} -> 1069434.4 | Q45: {=IFERROR(IF(Q$41<$K45,0,$F45*_xlfn.XLOOKUP($D45,'Capital Call&Distributions data'!$A:$A,INDEX('Capital Call&Distributions data'!$C:$O,0,MIN(MAX(YEAR(Q$41)-YEAR($K45)+$J45+1,1),14)))),0)} -> 741607.74 | R45: {=IFERROR(IF(R$41<$K45,0,$F45*_xlfn.XLOOKUP($D45,'Capital Call&Distributions data'!$A:$A,INDEX('Capital Call&Distributions data'!$C:$O,0,MIN(MAX(YEAR(R$41)-YEAR($K45)+$J45+1,1),14)))),0)} -> 417642.29 | S45: {=IFERROR(IF(S$41<$K45,0,$F45*_xlfn.XLOOKUP($D45,'Capital Call&Distributions data'!$A:$A,INDEX('Capital Call&Distributions data'!$C:$O,0,MIN(MAX(YEAR(S$41)-YEAR($K45)+$J45+1,1),14)))),0)} -> 468970.85 | ... AU45: {=IFERROR(IF(AU$41<$K45,0,$F45*_xlfn.XLOOKUP($D45,'Capital Call&Distributions data'!$A:$A,INDEX('Capital Call&Distributions data'!$C:$O,0,MIN(MAX(YEAR(AU$41)-YEAR($K45)+$J45+1,1),14)))),0)} -> 0
C46: PE dummy | D46: =_xlfn.XLOOKUP(C46,Fondsen!B:B,Fondsen!C:C,"0",0,1) -> PE | E46: EUR | F46: 2020000 | G46: =IFERROR(IF(SUM(OFFSET(INDEX('Capital Call&Distributions data'!A:A,MATCH(D46,'Capital Call&Distributions data'!A:A,0)),-1,2,1,1000))=0,"✔",""),"") | H46: =IFERROR(IRR(L46:AD46),"") -> 0.1472451 | I46: 46388 | J46: =YEAR(K46)-YEAR(I46) -> 0 | K46: 46388 | L46: {=IFERROR(IF(L$41<$K46,0,$F46*_xlfn.XLOOKUP($D46,'Capital Call&Distributions data'!$A:$A,INDEX('Capital Call&Distributions data'!$C:$O,0,MIN(MAX(YEAR(L$41)-YEAR($K46)+$J46+1,1),14)))),0)} -> 0 | M46: {=IFERROR(IF(M$41<$K46,0,$F46*_xlfn.XLOOKUP($D46,'Capital Call&Distributions data'!$A:$A,INDEX('Capital Call&Distributions data'!$C:$O,0,MIN(MAX(YEAR(M$41)-YEAR($K46)+$J46+1,1),14)))),0)} -> -635526.98 | N46: {=IFERROR(IF(N$41<$K46,0,$F46*_xlfn.XLOOKUP($D46,'Capital Call&Distributions data'!$A:$A,INDEX('Capital Call&Distributions data'!$C:$O,0,MIN(MAX(YEAR(N$41)-YEAR($K46)+$J46+1,1),14)))),0)} -> -441637.39 | O46: {=IFERROR(IF(O$41<$K46,0,$F46*_xlfn.XLOOKUP($D46,'Capital Call&Distributions data'!$A:$A,INDEX('Capital Call&Distributions data'!$C:$O,0,MIN(MAX(YEAR(O$41)-YEAR($K46)+$J46+1,1),14)))),0)} -> -441637.39 | P46: {=IFERROR(IF(P$41<$K46,0,$F46*_xlfn.XLOOKUP($D46,'Capital Call&Distributions data'!$A:$A,INDEX('Capital Call&Distributions data'!$C:$O,0,MIN(MAX(YEAR(P$41)-YEAR($K46)+$J46+1,1),14)))),0)} -> -198198.24 | Q46: {=IFERROR(IF(Q$41<$K46,0,$F46*_xlfn.XLOOKUP($D46,'Capital Call&Distributions data'!$A:$A,INDEX('Capital Call&Distributions data'!$C:$O,0,MIN(MAX(YEAR(Q$41)-YEAR($K46)+$J46+1,1),14)))),0)} -> 512266.5 | R46: {=IFERROR(IF(R$41<$K46,0,$F46*_xlfn.XLOOKUP($D46,'Capital Call&Distributions data'!$A:$A,INDEX('Capital Call&Distributions data'!$C:$O,0,MIN(MAX(YEAR(R$41)-YEAR($K46)+$J46+1,1),14)))),0)} -> 845575.28 | S46: {=IFERROR(IF(S$41<$K46,0,$F46*_xlfn.XLOOKUP($D46,'Capital Call&Distributions data'!$A:$A,INDEX('Capital Call&Distributions data'!$C:$O,0,MIN(MAX(YEAR(S$41)-YEAR($K46)+$J46+1,1),14)))),0)} -> 842472.5 | ... AU46: {=IFERROR(IF(AU$41<$K46,0,$F46*_xlfn.XLOOKUP($D46,'Capital Call&Distributions data'!$A:$A,INDEX('Capital Call&Distributions data'!$C:$O,0,MIN(MAX(YEAR(AU$41)-YEAR($K46)+$J46+1,1),14)))),0)} -> 0
C47: Secondaries Dummy | D47: =_xlfn.XLOOKUP(C47,Fondsen!B:B,Fondsen!C:C,"0",0,1) -> Secondaries | E47: EUR | F47: 3200000 | G47: =IFERROR(IF(SUM(OFFSET(INDEX('Capital Call&Distributions data'!A:A,MATCH(D47,'Capital Call&Distributions data'!A:A,0)),-1,2,1,1000))=0,"✔",""),"") | H47: =IFERROR(IRR(L47:AD47),"") -> 0.13229301 | I47: 46753 | J47: =YEAR(K47)-YEAR(I47) -> 0 | K47: 46753 | L47: {=IFERROR(IF(L$41<$K47,0,$F47*_xlfn.XLOOKUP($D47,'Capital Call&Distributions data'!$A:$A,INDEX('Capital Call&Distributions data'!$C:$O,0,MIN(MAX(YEAR(L$41)-YEAR($K47)+$J47+1,1),14)))),0)} -> 0 | M47: {=IFERROR(IF(M$41<$K47,0,$F47*_xlfn.XLOOKUP($D47,'Capital Call&Distributions data'!$A:$A,INDEX('Capital Call&Distributions data'!$C:$O,0,MIN(MAX(YEAR(M$41)-YEAR($K47)+$J47+1,1),14)))),0)} -> 0 | N47: {=IFERROR(IF(N$41<$K47,0,$F47*_xlfn.XLOOKUP($D47,'Capital Call&Distributions data'!$A:$A,INDEX('Capital Call&Distributions data'!$C:$O,0,MIN(MAX(YEAR(N$41)-YEAR($K47)+$J47+1,1),14)))),0)} -> -1703311.4 | O47: {=IFERROR(IF(O$41<$K47,0,$F47*_xlfn.XLOOKUP($D47,'Capital Call&Distributions data'!$A:$A,INDEX('Capital Call&Distributions data'!$C:$O,0,MIN(MAX(YEAR(O$41)-YEAR($K47)+$J47+1,1),14)))),0)} -> -152688.56 | P47: {=IFERROR(IF(P$41<$K47,0,$F47*_xlfn.XLOOKUP($D47,'Capital Call&Distributions data'!$A:$A,INDEX('Capital Call&Distributions data'!$C:$O,0,MIN(MAX(YEAR(P$41)-YEAR($K47)+$J47+1,1),14)))),0)} -> 815789.28 | Q47: {=IFERROR(IF(Q$41<$K47,0,$F47*_xlfn.XLOOKUP($D47,'Capital Call&Distributions data'!$A:$A,INDEX('Capital Call&Distributions data'!$C:$O,0,MIN(MAX(YEAR(Q$41)-YEAR($K47)+$J47+1,1),14)))),0)} -> 671017.69 | R47: {=IFERROR(IF(R$41<$K47,0,$F47*_xlfn.XLOOKUP($D47,'Capital Call&Distributions data'!$A:$A,INDEX('Capital Call&Distributions data'!$C:$O,0,MIN(MAX(YEAR(R$41)-YEAR($K47)+$J47+1,1),14)))),0)} -> 465322.5 | S47: {=IFERROR(IF(S$41<$K47,0,$F47*_xlfn.XLOOKUP($D47,'Capital Call&Distributions data'!$A:$A,INDEX('Capital Call&Distributions data'!$C:$O,0,MIN(MAX(YEAR(S$41)-YEAR($K47)+$J47+1,1),14)))),0)} -> 262050.07 | ... AU47: {=IFERROR(IF(AU$41<$K47,0,$F47*_xlfn.XLOOKUP($D47,'Capital Call&Distributions data'!$A:$A,INDEX('Capital Call&Distributions data'!$C:$O,0,MIN(MAX(YEAR(AU$41)-YEAR($K47)+$J47+1,1),14)))),0)} -> 0
C48: PE dummy | D48: =_xlfn.XLOOKUP(C48,Fondsen!B:B,Fondsen!C:C,"0",0,1) -> PE | E48: EUR | F48: 2000000 | G48: =IFERROR(IF(SUM(OFFSET(INDEX('Capital Call&Distributions data'!A:A,MATCH(D48,'Capital Call&Distributions data'!A:A,0)),-1,2,1,1000))=0,"✔",""),"") | H48: =IFERROR(IRR(L48:AJ48),"") -> 0.1472451 | I48: 46753 | J48: =YEAR(K48)-YEAR(I48) -> 0 | K48: 46753 | L48: {=IFERROR(IF(L$41<$K48,0,$F48*_xlfn.XLOOKUP($D48,'Capital Call&Distributions data'!$A:$A,INDEX('Capital Call&Distributions data'!$C:$O,0,MIN(MAX(YEAR(L$41)-YEAR($K48)+$J48+1,1),14)))),0)} -> 0 | M48: {=IFERROR(IF(M$41<$K48,0,$F48*_xlfn.XLOOKUP($D48,'Capital Call&Distributions data'!$A:$A,INDEX('Capital Call&Distributions data'!$C:$O,0,MIN(MAX(YEAR(M$41)-YEAR($K48)+$J48+1,1),14)))),0)} -> 0 | N48: {=IFERROR(IF(N$41<$K48,0,$F48*_xlfn.XLOOKUP($D48,'Capital Call&Distributions data'!$A:$A,INDEX('Capital Call&Distributions data'!$C:$O,0,MIN(MAX(YEAR(N$41)-YEAR($K48)+$J48+1,1),14)))),0)} -> -629234.63 | O48: {=IFERROR(IF(O$41<$K48,0,$F48*_xlfn.XLOOKUP($D48,'Capital Call&Distributions data'!$A:$A,INDEX('Capital Call&Distributions data'!$C:$O,0,MIN(MAX(YEAR(O$41)-YEAR($K48)+$J48+1,1),14)))),0)} -> -437264.74 | P48: {=IFERROR(IF(P$41<$K48,0,$F48*_xlfn.XLOOKUP($D48,'Capital Call&Distributions data'!$A:$A,INDEX('Capital Call&Distributions data'!$C:$O,0,MIN(MAX(YEAR(P$41)-YEAR($K48)+$J48+1,1),14)))),0)} -> -437264.74 | Q48: {=IFERROR(IF(Q$41<$K48,0,$F48*_xlfn.XLOOKUP($D48,'Capital Call&Distributions data'!$A:$A,INDEX('Capital Call&Distributions data'!$C:$O,0,MIN(MAX(YEAR(Q$41)-YEAR($K48)+$J48+1,1),14)))),0)} -> -196235.88 | R48: {=IFERROR(IF(R$41<$K48,0,$F48*_xlfn.XLOOKUP($D48,'Capital Call&Distributions data'!$A:$A,INDEX('Capital Call&Distributions data'!$C:$O,0,MIN(MAX(YEAR(R$41)-YEAR($K48)+$J48+1,1),14)))),0)} -> 507194.56 | S48: {=IFERROR(IF(S$41<$K48,0,$F48*_xlfn.XLOOKUP($D48,'Capital Call&Distributions data'!$A:$A,INDEX('Capital Call&Distributions data'!$C:$O,0,MIN(MAX(YEAR(S$41)-YEAR($K48)+$J48+1,1),14)))),0)} -> 837203.24 | ... AU48: {=IFERROR(IF(AU$41<$K48,0,$F48*_xlfn.XLOOKUP($D48,'Capital Call&Distributions data'!$A:$A,INDEX('Capital Call&Distributions data'!$C:$O,0,MIN(MAX(YEAR(AU$41)-YEAR($K48)+$J48+1,1),14)))),0)} -> 0
C49: Secondaries Dummy | D49: =_xlfn.XLOOKUP(C49,Fondsen!B:B,Fondsen!C:C,"0",0,1) -> Secondaries | E49: EUR | F49: 1580000 | G49: =IFERROR(IF(SUM(OFFSET(INDEX('Capital Call&Distributions data'!A:A,MATCH(D49,'Capital Call&Distributions data'!A:A,0)),-1,2,1,1000))=0,"✔",""),"") | H49: =IFERROR(IRR(L49:AK49),"") -> 0.13229301 | I49: 47119 | J49: =YEAR(K49)-YEAR(I49) -> 0 | K49: 47119 | L49: {=IFERROR(IF(L$41<$K49,0,$F49*_xlfn.XLOOKUP($D49,'Capital Call&Distributions data'!$A:$A,INDEX('Capital Call&Distributions data'!$C:$O,0,MIN(MAX(YEAR(L$41)-YEAR($K49)+$J49+1,1),14)))),0)} -> 0 | M49: {=IFERROR(IF(M$41<$K49,0,$F49*_xlfn.XLOOKUP($D49,'Capital Call&Distributions data'!$A:$A,INDEX('Capital Call&Distributions data'!$C:$O,0,MIN(MAX(YEAR(M$41)-YEAR($K49)+$J49+1,1),14)))),0)} -> 0 | N49: {=IFERROR(IF(N$41<$K49,0,$F49*_xlfn.XLOOKUP($D49,'Capital Call&Distributions data'!$A:$A,INDEX('Capital Call&Distributions data'!$C:$O,0,MIN(MAX(YEAR(N$41)-YEAR($K49)+$J49+1,1),14)))),0)} -> 0 | O49: {=IFERROR(IF(O$41<$K49,0,$F49*_xlfn.XLOOKUP($D49,'Capital Call&Distributions data'!$A:$A,INDEX('Capital Call&Distributions data'!$C:$O,0,MIN(MAX(YEAR(O$41)-YEAR($K49)+$J49+1,1),14)))),0)} -> -841010.02 | P49: {=IFERROR(IF(P$41<$K49,0,$F49*_xlfn.XLOOKUP($D49,'Capital Call&Distributions data'!$A:$A,INDEX('Capital Call&Distributions data'!$C:$O,0,MIN(MAX(YEAR(P$41)-YEAR($K49)+$J49+1,1),14)))),0)} -> -75389.976 | Q49: {=IFERROR(IF(Q$41<$K49,0,$F49*_xlfn.XLOOKUP($D49,'Capital Call&Distributions data'!$A:$A,INDEX('Capital Call&Distributions data'!$C:$O,0,MIN(MAX(YEAR(Q$41)-YEAR($K49)+$J49+1,1),14)))),0)} -> 402795.96 | R49: {=IFERROR(IF(R$41<$K49,0,$F49*_xlfn.XLOOKUP($D49,'Capital Call&Distributions data'!$A:$A,INDEX('Capital Call&Distributions data'!$C:$O,0,MIN(MAX(YEAR(R$41)-YEAR($K49)+$J49+1,1),14)))),0)} -> 331314.98 | S49: {=IFERROR(IF(S$41<$K49,0,$F49*_xlfn.XLOOKUP($D49,'Capital Call&Distributions data'!$A:$A,INDEX('Capital Call&Distributions data'!$C:$O,0,MIN(MAX(YEAR(S$41)-YEAR($K49)+$J49+1,1),14)))),0)} -> 229752.99 | ... AU49: {=IFERROR(IF(AU$41<$K49,0,$F49*_xlfn.XLOOKUP($D49,'Capital Call&Distributions data'!$A:$A,INDEX('Capital Call&Distributions data'!$C:$O,0,MIN(MAX(YEAR(AU$41)-YEAR($K49)+$J49+1,1),14)))),0)} -> 0
C50: PE dummy | D50: =_xlfn.XLOOKUP(C50,Fondsen!B:B,Fondsen!C:C,"0",0,1) -> PE | E50: EUR | F50: 1000000 | G50: =IFERROR(IF(SUM(OFFSET(INDEX('Capital Call&Distributions data'!A:A,MATCH(D50,'Capital Call&Distributions data'!A:A,0)),-1,2,1,1000))=0,"✔",""),"") | H50: =IFERROR(IRR(L50:AL50),"") -> 0.1472451 | I50: 47119 | J50: =YEAR(K50)-YEAR(I50) -> 0 | K50: 47119 | L50: {=IFERROR(IF(L$41<$K50,0,$F50*_xlfn.XLOOKUP($D50,'Capital Call&Distributions data'!$A:$A,INDEX('Capital Call&Distributions data'!$C:$O,0,MIN(MAX(YEAR(L$41)-YEAR($K50)+$J50+1,1),14)))),0)} -> 0 | M50: {=IFERROR(IF(M$41<$K50,0,$F50*_xlfn.XLOOKUP($D50,'Capital Call&Distributions data'!$A:$A,INDEX('Capital Call&Distributions data'!$C:$O,0,MIN(MAX(YEAR(M$41)-YEAR($K50)+$J50+1,1),14)))),0)} -> 0 | N50: {=IFERROR(IF(N$41<$K50,0,$F50*_xlfn.XLOOKUP($D50,'Capital Call&Distributions data'!$A:$A,INDEX('Capital Call&Distributions data'!$C:$O,0,MIN(MAX(YEAR(N$41)-YEAR($K50)+$J50+1,1),14)))),0)} -> 0 | O50: {=IFERROR(IF(O$41<$K50,0,$F50*_xlfn.XLOOKUP($D50,'Capital Call&Distributions data'!$A:$A,INDEX('Capital Call&Distributions data'!$C:$O,0,MIN(MAX(YEAR(O$41)-YEAR($K50)+$J50+1,1),14)))),0)} -> -314617.31 | P50: {=IFERROR(IF(P$41<$K50,0,$F50*_xlfn.XLOOKUP($D50,'Capital Call&Distributions data'!$A:$A,INDEX('Capital Call&Distributions data'!$C:$O,0,MIN(MAX(YEAR(P$41)-YEAR($K50)+$J50+1,1),14)))),0)} -> -218632.37 | Q50: {=IFERROR(IF(Q$41<$K50,0,$F50*_xlfn.XLOOKUP($D50,'Capital Call&Distributions data'!$A:$A,INDEX('Capital Call&Distributions data'!$C:$O,0,MIN(MAX(YEAR(Q$41)-YEAR($K50)+$J50+1,1),14)))),0)} -> -218632.37 | R50: {=IFERROR(IF(R$41<$K50,0,$F50*_xlfn.XLOOKUP($D50,'Capital Call&Distributions data'!$A:$A,INDEX('Capital Call&Distributions data'!$C:$O,0,MIN(MAX(YEAR(R$41)-YEAR($K50)+$J50+1,1),14)))),0)} -> -98117.942 | S50: {=IFERROR(IF(S$41<$K50,0,$F50*_xlfn.XLOOKUP($D50,'Capital Call&Distributions data'!$A:$A,INDEX('Capital Call&Distributions data'!$C:$O,0,MIN(MAX(YEAR(S$41)-YEAR($K50)+$J50+1,1),14)))),0)} -> 253597.28 | ... AU50: {=IFERROR(IF(AU$41<$K50,0,$F50*_xlfn.XLOOKUP($D50,'Capital Call&Distributions data'!$A:$A,INDEX('Capital Call&Distributions data'!$C:$O,0,MIN(MAX(YEAR(AU$41)-YEAR($K50)+$J50+1,1),14)))),0)} -> 0
C51: Secondaries Dummy | D51: =_xlfn.XLOOKUP(C51,Fondsen!B:B,Fondsen!C:C,"0",0,1) -> Secondaries | E51: EUR | F51: 3280000 | G51: =IFERROR(IF(SUM(OFFSET(INDEX('Capital Call&Distributions data'!A:A,MATCH(D51,'Capital Call&Distributions data'!A:A,0)),-1,2,1,1000))=0,"✔",""),"") | H51: =IFERROR(IRR(L51:AD51),"") -> 0.13229301 | I51: 47484 | J51: =YEAR(K51)-YEAR(I51) -> 0 | K51: 47484 | L51: {=IFERROR(IF(L$41<$K51,0,$F51*_xlfn.XLOOKUP($D51,'Capital Call&Distributions data'!$A:$A,INDEX('Capital Call&Distributions data'!$C:$O,0,MIN(MAX(YEAR(L$41)-YEAR($K51)+$J51+1,1),14)))),0)} -> 0 | M51: {=IFERROR(IF(M$41<$K51,0,$F51*_xlfn.XLOOKUP($D51,'Capital Call&Distributions data'!$A:$A,INDEX('Capital Call&Distributions data'!$C:$O,0,MIN(MAX(YEAR(M$41)-YEAR($K51)+$J51+1,1),14)))),0)} -> 0 | N51: {=IFERROR(IF(N$41<$K51,0,$F51*_xlfn.XLOOKUP($D51,'Capital Call&Distributions data'!$A:$A,INDEX('Capital Call&Distributions data'!$C:$O,0,MIN(MAX(YEAR(N$41)-YEAR($K51)+$J51+1,1),14)))),0)} -> 0 | O51: {=IFERROR(IF(O$41<$K51,0,$F51*_xlfn.XLOOKUP($D51,'Capital Call&Distributions data'!$A:$A,INDEX('Capital Call&Distributions data'!$C:$O,0,MIN(MAX(YEAR(O$41)-YEAR($K51)+$J51+1,1),14)))),0)} -> 0 | P51: {=IFERROR(IF(P$41<$K51,0,$F51*_xlfn.XLOOKUP($D51,'Capital Call&Distributions data'!$A:$A,INDEX('Capital Call&Distributions data'!$C:$O,0,MIN(MAX(YEAR(P$41)-YEAR($K51)+$J51+1,1),14)))),0)} -> -1745894.2 | Q51: {=IFERROR(IF(Q$41<$K51,0,$F51*_xlfn.XLOOKUP($D51,'Capital Call&Distributions data'!$A:$A,INDEX('Capital Call&Distributions data'!$C:$O,0,MIN(MAX(YEAR(Q$41)-YEAR($K51)+$J51+1,1),14)))),0)} -> -156505.77 | R51: {=IFERROR(IF(R$41<$K51,0,$F51*_xlfn.XLOOKUP($D51,'Capital Call&Distributions data'!$A:$A,INDEX('Capital Call&Distributions data'!$C:$O,0,MIN(MAX(YEAR(R$41)-YEAR($K51)+$J51+1,1),14)))),0)} -> 836184.02 | S51: {=IFERROR(IF(S$41<$K51,0,$F51*_xlfn.XLOOKUP($D51,'Capital Call&Distributions data'!$A:$A,INDEX('Capital Call&Distributions data'!$C:$O,0,MIN(MAX(YEAR(S$41)-YEAR($K51)+$J51+1,1),14)))),0)} -> 687793.13 | ... AU51: {=IFERROR(IF(AU$41<$K51,0,$F51*_xlfn.XLOOKUP($D51,'Capital Call&Distributions data'!$A:$A,INDEX('Capital Call&Distributions data'!$C:$O,0,MIN(MAX(YEAR(AU$41)-YEAR($K51)+$J51+1,1),14)))),0)} -> 0
C52: PE dummy | D52: =_xlfn.XLOOKUP(C52,Fondsen!B:B,Fondsen!C:C,"0",0,1) -> PE | E52: EUR | F52: 2000000 | G52: =IFERROR(IF(SUM(OFFSET(INDEX('Capital Call&Distributions data'!A:A,MATCH(D52,'Capital Call&Distributions data'!A:A,0)),-1,2,1,1000))=0,"✔",""),"") | H52: =IFERROR(IRR(L52:AD52),"") -> 0.1472451 | I52: 47484 | J52: =YEAR(K52)-YEAR(I52) -> 0 | K52: 47484 | L52: {=IFERROR(IF(L$41<$K52,0,$F52*_xlfn.XLOOKUP($D52,'Capital Call&Distributions data'!$A:$A,INDEX('Capital Call&Distributions data'!$C:$O,0,MIN(MAX(YEAR(L$41)-YEAR($K52)+$J52+1,1),14)))),0)} -> 0 | M52: {=IFERROR(IF(M$41<$K52,0,$F52*_xlfn.XLOOKUP($D52,'Capital Call&Distributions data'!$A:$A,INDEX('Capital Call&Distributions data'!$C:$O,0,MIN(MAX(YEAR(M$41)-YEAR($K52)+$J52+1,1),14)))),0)} -> 0 | N52: {=IFERROR(IF(N$41<$K52,0,$F52*_xlfn.XLOOKUP($D52,'Capital Call&Distributions data'!$A:$A,INDEX('Capital Call&Distributions data'!$C:$O,0,MIN(MAX(YEAR(N$41)-YEAR($K52)+$J52+1,1),14)))),0)} -> 0 | O52: {=IFERROR(IF(O$41<$K52,0,$F52*_xlfn.XLOOKUP($D52,'Capital Call&Distributions data'!$A:$A,INDEX('Capital Call&Distributions data'!$C:$O,0,MIN(MAX(YEAR(O$41)-YEAR($K52)+$J52+1,1),14)))),0)} -> 0 | P52: {=IFERROR(IF(P$41<$K52,0,$F52*_xlfn.XLOOKUP($D52,'Capital Call&Distributions data'!$A:$A,INDEX('Capital Call&Distributions data'!$C:$O,0,MIN(MAX(YEAR(P$41)-YEAR($K52)+$J52+1,1),14)))),0)} -> -629234.63 | Q52: {=IFERROR(IF(Q$41<$K52,0,$F52*_xlfn.XLOOKUP($D52,'Capital Call&Distributions data'!$A:$A,INDEX('Capital Call&Distributions data'!$C:$O,0,MIN(MAX(YEAR(Q$41)-YEAR($K52)+$J52+1,1),14)))),0)} -> -437264.74 | R52: {=IFERROR(IF(R$41<$K52,0,$F52*_xlfn.XLOOKUP($D52,'Capital Call&Distributions data'!$A:$A,INDEX('Capital Call&Distributions data'!$C:$O,0,MIN(MAX(YEAR(R$41)-YEAR($K52)+$J52+1,1),14)))),0)} -> -437264.74 | S52: {=IFERROR(IF(S$41<$K52,0,$F52*_xlfn.XLOOKUP($D52,'Capital Call&Distributions data'!$A:$A,INDEX('Capital Call&Distributions data'!$C:$O,0,MIN(MAX(YEAR(S$41)-YEAR($K52)+$J52+1,1),14)))),0)} -> -196235.88 | ... AU52: {=IFERROR(IF(AU$41<$K52,0,$F52*_xlfn.XLOOKUP($D52,'Capital Call&Distributions data'!$A:$A,INDEX('Capital Call&Distributions data'!$C:$O,0,MIN(MAX(YEAR(AU$41)-YEAR($K52)+$J52+1,1),14)))),0)} -> 0
C53: Secondaries Dummy | D53: =_xlfn.XLOOKUP(C53,Fondsen!B:B,Fondsen!C:C,"0",0,1) -> Secondaries | E53: EUR | F53: 4000000 | G53: =IFERROR(IF(SUM(OFFSET(INDEX('Capital Call&Distributions data'!A:A,MATCH(D53,'Capital Call&Distributions data'!A:A,0)),-1,2,1,1000))=0,"✔",""),"") | H53: =IFERROR(IRR(L53:AD53),"") -> 0.13229301 | I53: 47849 | J53: =YEAR(K53)-YEAR(I53) -> 0 | K53: 47849 | L53: {=IFERROR(IF(L$41<$K53,0,$F53*_xlfn.XLOOKUP($D53,'Capital Call&Distributions data'!$A:$A,INDEX('Capital Call&Distributions data'!$C:$O,0,MIN(MAX(YEAR(L$41)-YEAR($K53)+$J53+1,1),14)))),0)} -> 0 | M53: {=IFERROR(IF(M$41<$K53,0,$F53*_xlfn.XLOOKUP($D53,'Capital Call&Distributions data'!$A:$A,INDEX('Capital Call&Distributions data'!$C:$O,0,MIN(MAX(YEAR(M$41)-YEAR($K53)+$J53+1,1),14)))),0)} -> 0 | N53: {=IFERROR(IF(N$41<$K53,0,$F53*_xlfn.XLOOKUP($D53,'Capital Call&Distributions data'!$A:$A,INDEX('Capital Call&Distributions data'!$C:$O,0,MIN(MAX(YEAR(N$41)-YEAR($K53)+$J53+1,1),14)))),0)} -> 0 | O53: {=IFERROR(IF(O$41<$K53,0,$F53*_xlfn.XLOOKUP($D53,'Capital Call&Distributions data'!$A:$A,INDEX('Capital Call&Distributions data'!$C:$O,0,MIN(MAX(YEAR(O$41)-YEAR($K53)+$J53+1,1),14)))),0)} -> 0 | P53: {=IFERROR(IF(P$41<$K53,0,$F53*_xlfn.XLOOKUP($D53,'Capital Call&Distributions data'!$A:$A,INDEX('Capital Call&Distributions data'!$C:$O,0,MIN(MAX(YEAR(P$41)-YEAR($K53)+$J53+1,1),14)))),0)} -> 0 | Q53: {=IFERROR(IF(Q$41<$K53,0,$F53*_xlfn.XLOOKUP($D53,'Capital Call&Distributions data'!$A:$A,INDEX('Capital Call&Distributions data'!$C:$O,0,MIN(MAX(YEAR(Q$41)-YEAR($K53)+$J53+1,1),14)))),0)} -> -2129139.3 | R53: {=IFERROR(IF(R$41<$K53,0,$F53*_xlfn.XLOOKUP($D53,'Capital Call&Distributions data'!$A:$A,INDEX('Capital Call&Distributions data'!$C:$O,0,MIN(MAX(YEAR(R$41)-YEAR($K53)+$J53+1,1),14)))),0)} -> -190860.7 | S53: {=IFERROR(IF(S$41<$K53,0,$F53*_xlfn.XLOOKUP($D53,'Capital Call&Distributions data'!$A:$A,INDEX('Capital Call&Distributions data'!$C:$O,0,MIN(MAX(YEAR(S$41)-YEAR($K53)+$J53+1,1),14)))),0)} -> 1019736.6 | ... AU53: {=IFERROR(IF(AU$41<$K53,0,$F53*_xlfn.XLOOKUP($D53,'Capital Call&Distributions data'!$A:$A,INDEX('Capital Call&Distributions data'!$C:$O,0,MIN(MAX(YEAR(AU$41)-YEAR($K53)+$J53+1,1),14)))),0)} -> 0
C54: PE dummy | D54: =_xlfn.XLOOKUP(C54,Fondsen!B:B,Fondsen!C:C,"0",0,1) -> PE | E54: EUR | F54: 2150000 | G54: =IFERROR(IF(SUM(OFFSET(INDEX('Capital Call&Distributions data'!A:A,MATCH(D54,'Capital Call&Distributions data'!A:A,0)),-1,2,1,1000))=0,"✔",""),"") | H54: =IFERROR(IRR(L54:AD54),"") -> 0.1472451 | I54: 47849 | J54: =YEAR(K54)-YEAR(I54) -> 0 | K54: 47849 | L54: {=IFERROR(IF(L$41<$K54,0,$F54*_xlfn.XLOOKUP($D54,'Capital Call&Distributions data'!$A:$A,INDEX('Capital Call&Distributions data'!$C:$O,0,MIN(MAX(YEAR(L$41)-YEAR($K54)+$J54+1,1),14)))),0)} -> 0 | M54: {=IFERROR(IF(M$41<$K54,0,$F54*_xlfn.XLOOKUP($D54,'Capital Call&Distributions data'!$A:$A,INDEX('Capital Call&Distributions data'!$C:$O,0,MIN(MAX(YEAR(M$41)-YEAR($K54)+$J54+1,1),14)))),0)} -> 0 | N54: {=IFERROR(IF(N$41<$K54,0,$F54*_xlfn.XLOOKUP($D54,'Capital Call&Distributions data'!$A:$A,INDEX('Capital Call&Distributions data'!$C:$O,0,MIN(MAX(YEAR(N$41)-YEAR($K54)+$J54+1,1),14)))),0)} -> 0 | O54: {=IFERROR(IF(O$41<$K54,0,$F54*_xlfn.XLOOKUP($D54,'Capital Call&Distributions data'!$A:$A,INDEX('Capital Call&Distributions data'!$C:$O,0,MIN(MAX(YEAR(O$41)-YEAR($K54)+$J54+1,1),14)))),0)} -> 0 | P54: {=IFERROR(IF(P$41<$K54,0,$F54*_xlfn.XLOOKUP($D54,'Capital Call&Distributions data'!$A:$A,INDEX('Capital Call&Distributions data'!$C:$O,0,MIN(MAX(YEAR(P$41)-YEAR($K54)+$J54+1,1),14)))),0)} -> 0 | Q54: {=IFERROR(IF(Q$41<$K54,0,$F54*_xlfn.XLOOKUP($D54,'Capital Call&Distributions data'!$A:$A,INDEX('Capital Call&Distributions data'!$C:$O,0,MIN(MAX(YEAR(Q$41)-YEAR($K54)+$J54+1,1),14)))),0)} -> -676427.23 | R54: {=IFERROR(IF(R$41<$K54,0,$F54*_xlfn.XLOOKUP($D54,'Capital Call&Distributions data'!$A:$A,INDEX('Capital Call&Distributions data'!$C:$O,0,MIN(MAX(YEAR(R$41)-YEAR($K54)+$J54+1,1),14)))),0)} -> -470059.6 | S54: {=IFERROR(IF(S$41<$K54,0,$F54*_xlfn.XLOOKUP($D54,'Capital Call&Distributions data'!$A:$A,INDEX('Capital Call&Distributions data'!$C:$O,0,MIN(MAX(YEAR(S$41)-YEAR($K54)+$J54+1,1),14)))),0)} -> -470059.6 | ... AU54: {=IFERROR(IF(AU$41<$K54,0,$F54*_xlfn.XLOOKUP($D54,'Capital Call&Distributions data'!$A:$A,INDEX('Capital Call&Distributions data'!$C:$O,0,MIN(MAX(YEAR(AU$41)-YEAR($K54)+$J54+1,1),14)))),0)} -> 0
C55: Secondaries Dummy | D55: =_xlfn.XLOOKUP(C55,Fondsen!B:B,Fondsen!C:C,"0",0,1) -> Secondaries | E55: EUR | F55: 5265000 | G55: =IFERROR(IF(SUM(OFFSET(INDEX('Capital Call&Distributions data'!A:A,MATCH(D55,'Capital Call&Distributions data'!A:A,0)),-1,2,1,1000))=0,"✔",""),"") | H55: =IFERROR(IRR(L55:AD55),"") -> 0.13229301 | I55: 48214 | J55: =YEAR(K55)-YEAR(I55) -> 0 | K55: 48214 | L55: {=IFERROR(IF(L$41<$K55,0,$F55*_xlfn.XLOOKUP($D55,'Capital Call&Distributions data'!$A:$A,INDEX('Capital Call&Distributions data'!$C:$O,0,MIN(MAX(YEAR(L$41)-YEAR($K55)+$J55+1,1),14)))),0)} -> 0 | M55: {=IFERROR(IF(M$41<$K55,0,$F55*_xlfn.XLOOKUP($D55,'Capital Call&Distributions data'!$A:$A,INDEX('Capital Call&Distributions data'!$C:$O,0,MIN(MAX(YEAR(M$41)-YEAR($K55)+$J55+1,1),14)))),0)} -> 0 | N55: {=IFERROR(IF(N$41<$K55,0,$F55*_xlfn.XLOOKUP($D55,'Capital Call&Distributions data'!$A:$A,INDEX('Capital Call&Distributions data'!$C:$O,0,MIN(MAX(YEAR(N$41)-YEAR($K55)+$J55+1,1),14)))),0)} -> 0 | O55: {=IFERROR(IF(O$41<$K55,0,$F55*_xlfn.XLOOKUP($D55,'Capital Call&Distributions data'!$A:$A,INDEX('Capital Call&Distributions data'!$C:$O,0,MIN(MAX(YEAR(O$41)-YEAR($K55)+$J55+1,1),14)))),0)} -> 0 | P55: {=IFERROR(IF(P$41<$K55,0,$F55*_xlfn.XLOOKUP($D55,'Capital Call&Distributions data'!$A:$A,INDEX('Capital Call&Distributions data'!$C:$O,0,MIN(MAX(YEAR(P$41)-YEAR($K55)+$J55+1,1),14)))),0)} -> 0 | Q55: {=IFERROR(IF(Q$41<$K55,0,$F55*_xlfn.XLOOKUP($D55,'Capital Call&Distributions data'!$A:$A,INDEX('Capital Call&Distributions data'!$C:$O,0,MIN(MAX(YEAR(Q$41)-YEAR($K55)+$J55+1,1),14)))),0)} -> 0 | R55: {=IFERROR(IF(R$41<$K55,0,$F55*_xlfn.XLOOKUP($D55,'Capital Call&Distributions data'!$A:$A,INDEX('Capital Call&Distributions data'!$C:$O,0,MIN(MAX(YEAR(R$41)-YEAR($K55)+$J55+1,1),14)))),0)} -> -2802479.6 | S55: {=IFERROR(IF(S$41<$K55,0,$F55*_xlfn.XLOOKUP($D55,'Capital Call&Distributions data'!$A:$A,INDEX('Capital Call&Distributions data'!$C:$O,0,MIN(MAX(YEAR(S$41)-YEAR($K55)+$J55+1,1),14)))),0)} -> -251220.39 | ... AU55: {=IFERROR(IF(AU$41<$K55,0,$F55*_xlfn.XLOOKUP($D55,'Capital Call&Distributions data'!$A:$A,INDEX('Capital Call&Distributions data'!$C:$O,0,MIN(MAX(YEAR(AU$41)-YEAR($K55)+$J55+1,1),14)))),0)} -> 0
C56: PE dummy | D56: =_xlfn.XLOOKUP(C56,Fondsen!B:B,Fondsen!C:C,"0",0,1) -> PE | E56: EUR | F56: 3000000 | G56: =IFERROR(IF(SUM(OFFSET(INDEX('Capital Call&Distributions data'!A:A,MATCH(D56,'Capital Call&Distributions data'!A:A,0)),-1,2,1,1000))=0,"✔",""),"") | H56: =IFERROR(IRR(L56:AD56),"") -> 0.1472451 | I56: 48214 | J56: =YEAR(K56)-YEAR(I56) -> 0 | K56: 48214 | L56: {=IFERROR(IF(L$41<$K56,0,$F56*_xlfn.XLOOKUP($D56,'Capital Call&Distributions data'!$A:$A,INDEX('Capital Call&Distributions data'!$C:$O,0,MIN(MAX(YEAR(L$41)-YEAR($K56)+$J56+1,1),14)))),0)} -> 0 | M56: {=IFERROR(IF(M$41<$K56,0,$F56*_xlfn.XLOOKUP($D56,'Capital Call&Distributions data'!$A:$A,INDEX('Capital Call&Distributions data'!$C:$O,0,MIN(MAX(YEAR(M$41)-YEAR($K56)+$J56+1,1),14)))),0)} -> 0 | N56: {=IFERROR(IF(N$41<$K56,0,$F56*_xlfn.XLOOKUP($D56,'Capital Call&Distributions data'!$A:$A,INDEX('Capital Call&Distributions data'!$C:$O,0,MIN(MAX(YEAR(N$41)-YEAR($K56)+$J56+1,1),14)))),0)} -> 0 | O56: {=IFERROR(IF(O$41<$K56,0,$F56*_xlfn.XLOOKUP($D56,'Capital Call&Distributions data'!$A:$A,INDEX('Capital Call&Distributions data'!$C:$O,0,MIN(MAX(YEAR(O$41)-YEAR($K56)+$J56+1,1),14)))),0)} -> 0 | P56: {=IFERROR(IF(P$41<$K56,0,$F56*_xlfn.XLOOKUP($D56,'Capital Call&Distributions data'!$A:$A,INDEX('Capital Call&Distributions data'!$C:$O,0,MIN(MAX(YEAR(P$41)-YEAR($K56)+$J56+1,1),14)))),0)} -> 0 | Q56: {=IFERROR(IF(Q$41<$K56,0,$F56*_xlfn.XLOOKUP($D56,'Capital Call&Distributions data'!$A:$A,INDEX('Capital Call&Distributions data'!$C:$O,0,MIN(MAX(YEAR(Q$41)-YEAR($K56)+$J56+1,1),14)))),0)} -> 0 | R56: {=IFERROR(IF(R$41<$K56,0,$F56*_xlfn.XLOOKUP($D56,'Capital Call&Distributions data'!$A:$A,INDEX('Capital Call&Distributions data'!$C:$O,0,MIN(MAX(YEAR(R$41)-YEAR($K56)+$J56+1,1),14)))),0)} -> -943851.94 | S56: {=IFERROR(IF(S$41<$K56,0,$F56*_xlfn.XLOOKUP($D56,'Capital Call&Distributions data'!$A:$A,INDEX('Capital Call&Distributions data'!$C:$O,0,MIN(MAX(YEAR(S$41)-YEAR($K56)+$J56+1,1),14)))),0)} -> -655897.11 | ... AU56: {=IFERROR(IF(AU$41<$K56,0,$F56*_xlfn.XLOOKUP($D56,'Capital Call&Distributions data'!$A:$A,INDEX('Capital Call&Distributions data'!$C:$O,0,MIN(MAX(YEAR(AU$41)-YEAR($K56)+$J56+1,1),14)))),0)} -> 0
C57: Secondaries Dummy | D57: =_xlfn.XLOOKUP(C57,Fondsen!B:B,Fondsen!C:C,"0",0,1) -> Secondaries | E57: EUR | F57: 6000000 | G57: =IFERROR(IF(SUM(OFFSET(INDEX('Capital Call&Distributions data'!A:A,MATCH(D57,'Capital Call&Distributions data'!A:A,0)),-1,2,1,1000))=0,"✔",""),"") | H57: =IFERROR(IRR(L57:AD57),"") -> 0.13229301 | I57: 48580 | J57: =YEAR(K57)-YEAR(I57) -> 0 | K57: 48580 | L57: {=IFERROR(IF(L$41<$K57,0,$F57*_xlfn.XLOOKUP($D57,'Capital Call&Distributions data'!$A:$A,INDEX('Capital Call&Distributions data'!$C:$O,0,MIN(MAX(YEAR(L$41)-YEAR($K57)+$J57+1,1),14)))),0)} -> 0 | M57: {=IFERROR(IF(M$41<$K57,0,$F57*_xlfn.XLOOKUP($D57,'Capital Call&Distributions data'!$A:$A,INDEX('Capital Call&Distributions data'!$C:$O,0,MIN(MAX(YEAR(M$41)-YEAR($K57)+$J57+1,1),14)))),0)} -> 0 | N57: {=IFERROR(IF(N$41<$K57,0,$F57*_xlfn.XLOOKUP($D57,'Capital Call&Distributions data'!$A:$A,INDEX('Capital Call&Distributions data'!$C:$O,0,MIN(MAX(YEAR(N$41)-YEAR($K57)+$J57+1,1),14)))),0)} -> 0 | O57: {=IFERROR(IF(O$41<$K57,0,$F57*_xlfn.XLOOKUP($D57,'Capital Call&Distributions data'!$A:$A,INDEX('Capital Call&Distributions data'!$C:$O,0,MIN(MAX(YEAR(O$41)-YEAR($K57)+$J57+1,1),14)))),0)} -> 0 | P57: {=IFERROR(IF(P$41<$K57,0,$F57*_xlfn.XLOOKUP($D57,'Capital Call&Distributions data'!$A:$A,INDEX('Capital Call&Distributions data'!$C:$O,0,MIN(MAX(YEAR(P$41)-YEAR($K57)+$J57+1,1),14)))),0)} -> 0 | Q57: {=IFERROR(IF(Q$41<$K57,0,$F57*_xlfn.XLOOKUP($D57,'Capital Call&Distributions data'!$A:$A,INDEX('Capital Call&Distributions data'!$C:$O,0,MIN(MAX(YEAR(Q$41)-YEAR($K57)+$J57+1,1),14)))),0)} -> 0 | R57: {=IFERROR(IF(R$41<$K57,0,$F57*_xlfn.XLOOKUP($D57,'Capital Call&Distributions data'!$A:$A,INDEX('Capital Call&Distributions data'!$C:$O,0,MIN(MAX(YEAR(R$41)-YEAR($K57)+$J57+1,1),14)))),0)} -> 0 | S57: {=IFERROR(IF(S$41<$K57,0,$F57*_xlfn.XLOOKUP($D57,'Capital Call&Distributions data'!$A:$A,INDEX('Capital Call&Distributions data'!$C:$O,0,MIN(MAX(YEAR(S$41)-YEAR($K57)+$J57+1,1),14)))),0)} -> -3193709 | ... AU57: {=IFERROR(IF(AU$41<$K57,0,$F57*_xlfn.XLOOKUP($D57,'Capital Call&Distributions data'!$A:$A,INDEX('Capital Call&Distributions data'!$C:$O,0,MIN(MAX(YEAR(AU$41)-YEAR($K57)+$J57+1,1),14)))),0)} -> 0
C58: PE dummy | D58: =_xlfn.XLOOKUP(C58,Fondsen!B:B,Fondsen!C:C,"0",0,1) -> PE | E58: EUR | F58: 2773000 | G58: =IFERROR(IF(SUM(OFFSET(INDEX('Capital Call&Distributions data'!A:A,MATCH(D58,'Capital Call&Distributions data'!A:A,0)),-1,2,1,1000))=0,"✔",""),"") | H58: =IFERROR(IRR(L58:AD58),"") -> 0.1472451 | I58: 48580 | J58: =YEAR(K58)-YEAR(I58) -> 0 | K58: 48580 | L58: {=IFERROR(IF(L$41<$K58,0,$F58*_xlfn.XLOOKUP($D58,'Capital Call&Distributions data'!$A:$A,INDEX('Capital Call&Distributions data'!$C:$O,0,MIN(MAX(YEAR(L$41)-YEAR($K58)+$J58+1,1),14)))),0)} -> 0 | M58: {=IFERROR(IF(M$41<$K58,0,$F58*_xlfn.XLOOKUP($D58,'Capital Call&Distributions data'!$A:$A,INDEX('Capital Call&Distributions data'!$C:$O,0,MIN(MAX(YEAR(M$41)-YEAR($K58)+$J58+1,1),14)))),0)} -> 0 | N58: {=IFERROR(IF(N$41<$K58,0,$F58*_xlfn.XLOOKUP($D58,'Capital Call&Distributions data'!$A:$A,INDEX('Capital Call&Distributions data'!$C:$O,0,MIN(MAX(YEAR(N$41)-YEAR($K58)+$J58+1,1),14)))),0)} -> 0 | O58: {=IFERROR(IF(O$41<$K58,0,$F58*_xlfn.XLOOKUP($D58,'Capital Call&Distributions data'!$A:$A,INDEX('Capital Call&Distributions data'!$C:$O,0,MIN(MAX(YEAR(O$41)-YEAR($K58)+$J58+1,1),14)))),0)} -> 0 | P58: {=IFERROR(IF(P$41<$K58,0,$F58*_xlfn.XLOOKUP($D58,'Capital Call&Distributions data'!$A:$A,INDEX('Capital Call&Distributions data'!$C:$O,0,MIN(MAX(YEAR(P$41)-YEAR($K58)+$J58+1,1),14)))),0)} -> 0 | Q58: {=IFERROR(IF(Q$41<$K58,0,$F58*_xlfn.XLOOKUP($D58,'Capital Call&Distributions data'!$A:$A,INDEX('Capital Call&Distributions data'!$C:$O,0,MIN(MAX(YEAR(Q$41)-YEAR($K58)+$J58+1,1),14)))),0)} -> 0 | R58: {=IFERROR(IF(R$41<$K58,0,$F58*_xlfn.XLOOKUP($D58,'Capital Call&Distributions data'!$A:$A,INDEX('Capital Call&Distributions data'!$C:$O,0,MIN(MAX(YEAR(R$41)-YEAR($K58)+$J58+1,1),14)))),0)} -> 0 | S58: {=IFERROR(IF(S$41<$K58,0,$F58*_xlfn.XLOOKUP($D58,'Capital Call&Distributions data'!$A:$A,INDEX('Capital Call&Distributions data'!$C:$O,0,MIN(MAX(YEAR(S$41)-YEAR($K58)+$J58+1,1),14)))),0)} -> -872433.81 | ... AU58: {=IFERROR(IF(AU$41<$K58,0,$F58*_xlfn.XLOOKUP($D58,'Capital Call&Distributions data'!$A:$A,INDEX('Capital Call&Distributions data'!$C:$O,0,MIN(MAX(YEAR(AU$41)-YEAR($K58)+$J58+1,1),14)))),0)} -> 0
D59: =_xlfn.XLOOKUP(C59,Fondsen!B:B,Fondsen!C:C,"0",0,1) -> 0 | E59: EUR | G59: =IFERROR(IF(SUM(OFFSET(INDEX('Capital Call&Distributions data'!A:A,MATCH(D59,'Capital Call&Distributions data'!A:A,0)),-1,2,1,1000))=0,"✔",""),"") | H59: =IFERROR(IRR(L59:AD59),"") | I59: 47484 | J59: =YEAR(K59)-YEAR(I59) -> 0 | K59: 47484 | L59: {=IFERROR(IF(L$41<$K59,0,$F59*_xlfn.XLOOKUP($D59,'Capital Call&Distributions data'!$A:$A,INDEX('Capital Call&Distributions data'!$C:$O,0,MIN(MAX(YEAR(L$41)-YEAR($K59)+$J59+1,1),14)))),0)} -> 0 | M59: {=IFERROR(IF(M$41<$K59,0,$F59*_xlfn.XLOOKUP($D59,'Capital Call&Distributions data'!$A:$A,INDEX('Capital Call&Distributions data'!$C:$O,0,MIN(MAX(YEAR(M$41)-YEAR($K59)+$J59+1,1),14)))),0)} -> 0 | N59: {=IFERROR(IF(N$41<$K59,0,$F59*_xlfn.XLOOKUP($D59,'Capital Call&Distributions data'!$A:$A,INDEX('Capital Call&Distributions data'!$C:$O,0,MIN(MAX(YEAR(N$41)-YEAR($K59)+$J59+1,1),14)))),0)} -> 0 | O59: {=IFERROR(IF(O$41<$K59,0,$F59*_xlfn.XLOOKUP($D59,'Capital Call&Distributions data'!$A:$A,INDEX('Capital Call&Distributions data'!$C:$O,0,MIN(MAX(YEAR(O$41)-YEAR($K59)+$J59+1,1),14)))),0)} -> 0 | P59: {=IFERROR(IF(P$41<$K59,0,$F59*_xlfn.XLOOKUP($D59,'Capital Call&Distributions data'!$A:$A,INDEX('Capital Call&Distributions data'!$C:$O,0,MIN(MAX(YEAR(P$41)-YEAR($K59)+$J59+1,1),14)))),0)} -> 0 | Q59: {=IFERROR(IF(Q$41<$K59,0,$F59*_xlfn.XLOOKUP($D59,'Capital Call&Distributions data'!$A:$A,INDEX('Capital Call&Distributions data'!$C:$O,0,MIN(MAX(YEAR(Q$41)-YEAR($K59)+$J59+1,1),14)))),0)} -> 0 | R59: {=IFERROR(IF(R$41<$K59,0,$F59*_xlfn.XLOOKUP($D59,'Capital Call&Distributions data'!$A:$A,INDEX('Capital Call&Distributions data'!$C:$O,0,MIN(MAX(YEAR(R$41)-YEAR($K59)+$J59+1,1),14)))),0)} -> 0 | S59: {=IFERROR(IF(S$41<$K59,0,$F59*_xlfn.XLOOKUP($D59,'Capital Call&Distributions data'!$A:$A,INDEX('Capital Call&Distributions data'!$C:$O,0,MIN(MAX(YEAR(S$41)-YEAR($K59)+$J59+1,1),14)))),0)} -> 0 | ... AU59: {=IFERROR(IF(AU$41<$K59,0,$F59*_xlfn.XLOOKUP($D59,'Capital Call&Distributions data'!$A:$A,INDEX('Capital Call&Distributions data'!$C:$O,0,MIN(MAX(YEAR(AU$41)-YEAR($K59)+$J59+1,1),14)))),0)} -> 0
D60: =_xlfn.XLOOKUP(C60,Fondsen!B:B,Fondsen!C:C,"0",0,1) -> 0 | E60: EUR | G60: =IFERROR(IF(SUM(OFFSET(INDEX('Capital Call&Distributions data'!A:A,MATCH(D60,'Capital Call&Distributions data'!A:A,0)),-1,2,1,1000))=0,"✔",""),"") | H60: =IFERROR(IRR(L60:AD60),"") | I60: 47484 | J60: =YEAR(K60)-YEAR(I60) -> 0 | K60: 47484 | L60: {=IFERROR(IF(L$41<$K60,0,$F60*_xlfn.XLOOKUP($D60,'Capital Call&Distributions data'!$A:$A,INDEX('Capital Call&Distributions data'!$C:$O,0,MIN(MAX(YEAR(L$41)-YEAR($K60)+$J60+1,1),14)))),0)} -> 0 | M60: {=IFERROR(IF(M$41<$K60,0,$F60*_xlfn.XLOOKUP($D60,'Capital Call&Distributions data'!$A:$A,INDEX('Capital Call&Distributions data'!$C:$O,0,MIN(MAX(YEAR(M$41)-YEAR($K60)+$J60+1,1),14)))),0)} -> 0 | N60: {=IFERROR(IF(N$41<$K60,0,$F60*_xlfn.XLOOKUP($D60,'Capital Call&Distributions data'!$A:$A,INDEX('Capital Call&Distributions data'!$C:$O,0,MIN(MAX(YEAR(N$41)-YEAR($K60)+$J60+1,1),14)))),0)} -> 0 | O60: {=IFERROR(IF(O$41<$K60,0,$F60*_xlfn.XLOOKUP($D60,'Capital Call&Distributions data'!$A:$A,INDEX('Capital Call&Distributions data'!$C:$O,0,MIN(MAX(YEAR(O$41)-YEAR($K60)+$J60+1,1),14)))),0)} -> 0 | P60: {=IFERROR(IF(P$41<$K60,0,$F60*_xlfn.XLOOKUP($D60,'Capital Call&Distributions data'!$A:$A,INDEX('Capital Call&Distributions data'!$C:$O,0,MIN(MAX(YEAR(P$41)-YEAR($K60)+$J60+1,1),14)))),0)} -> 0 | Q60: {=IFERROR(IF(Q$41<$K60,0,$F60*_xlfn.XLOOKUP($D60,'Capital Call&Distributions data'!$A:$A,INDEX('Capital Call&Distributions data'!$C:$O,0,MIN(MAX(YEAR(Q$41)-YEAR($K60)+$J60+1,1),14)))),0)} -> 0 | R60: {=IFERROR(IF(R$41<$K60,0,$F60*_xlfn.XLOOKUP($D60,'Capital Call&Distributions data'!$A:$A,INDEX('Capital Call&Distributions data'!$C:$O,0,MIN(MAX(YEAR(R$41)-YEAR($K60)+$J60+1,1),14)))),0)} -> 0 | S60: {=IFERROR(IF(S$41<$K60,0,$F60*_xlfn.XLOOKUP($D60,'Capital Call&Distributions data'!$A:$A,INDEX('Capital Call&Distributions data'!$C:$O,0,MIN(MAX(YEAR(S$41)-YEAR($K60)+$J60+1,1),14)))),0)} -> 0 | ... AU60: {=IFERROR(IF(AU$41<$K60,0,$F60*_xlfn.XLOOKUP($D60,'Capital Call&Distributions data'!$A:$A,INDEX('Capital Call&Distributions data'!$C:$O,0,MIN(MAX(YEAR(AU$41)-YEAR($K60)+$J60+1,1),14)))),0)} -> 0
D61: =_xlfn.XLOOKUP(C61,Fondsen!B:B,Fondsen!C:C,"0",0,1) -> 0 | E61: EUR | G61: =IFERROR(IF(SUM(OFFSET(INDEX('Capital Call&Distributions data'!A:A,MATCH(D61,'Capital Call&Distributions data'!A:A,0)),-1,2,1,1000))=0,"✔",""),"") | H61: =IFERROR(IRR(L61:AD61),"") | I61: 47849 | J61: =YEAR(K61)-YEAR(I61) -> 0 | K61: 47849 | L61: {=IFERROR(IF(L$41<$K61,0,$F61*_xlfn.XLOOKUP($D61,'Capital Call&Distributions data'!$A:$A,INDEX('Capital Call&Distributions data'!$C:$O,0,MIN(MAX(YEAR(L$41)-YEAR($K61)+$J61+1,1),14)))),0)} -> 0 | M61: {=IFERROR(IF(M$41<$K61,0,$F61*_xlfn.XLOOKUP($D61,'Capital Call&Distributions data'!$A:$A,INDEX('Capital Call&Distributions data'!$C:$O,0,MIN(MAX(YEAR(M$41)-YEAR($K61)+$J61+1,1),14)))),0)} -> 0 | N61: {=IFERROR(IF(N$41<$K61,0,$F61*_xlfn.XLOOKUP($D61,'Capital Call&Distributions data'!$A:$A,INDEX('Capital Call&Distributions data'!$C:$O,0,MIN(MAX(YEAR(N$41)-YEAR($K61)+$J61+1,1),14)))),0)} -> 0 | O61: {=IFERROR(IF(O$41<$K61,0,$F61*_xlfn.XLOOKUP($D61,'Capital Call&Distributions data'!$A:$A,INDEX('Capital Call&Distributions data'!$C:$O,0,MIN(MAX(YEAR(O$41)-YEAR($K61)+$J61+1,1),14)))),0)} -> 0 | P61: {=IFERROR(IF(P$41<$K61,0,$F61*_xlfn.XLOOKUP($D61,'Capital Call&Distributions data'!$A:$A,INDEX('Capital Call&Distributions data'!$C:$O,0,MIN(MAX(YEAR(P$41)-YEAR($K61)+$J61+1,1),14)))),0)} -> 0 | Q61: {=IFERROR(IF(Q$41<$K61,0,$F61*_xlfn.XLOOKUP($D61,'Capital Call&Distributions data'!$A:$A,INDEX('Capital Call&Distributions data'!$C:$O,0,MIN(MAX(YEAR(Q$41)-YEAR($K61)+$J61+1,1),14)))),0)} -> 0 | R61: {=IFERROR(IF(R$41<$K61,0,$F61*_xlfn.XLOOKUP($D61,'Capital Call&Distributions data'!$A:$A,INDEX('Capital Call&Distributions data'!$C:$O,0,MIN(MAX(YEAR(R$41)-YEAR($K61)+$J61+1,1),14)))),0)} -> 0 | S61: {=IFERROR(IF(S$41<$K61,0,$F61*_xlfn.XLOOKUP($D61,'Capital Call&Distributions data'!$A:$A,INDEX('Capital Call&Distributions data'!$C:$O,0,MIN(MAX(YEAR(S$41)-YEAR($K61)+$J61+1,1),14)))),0)} -> 0 | ... AU61: {=IFERROR(IF(AU$41<$K61,0,$F61*_xlfn.XLOOKUP($D61,'Capital Call&Distributions data'!$A:$A,INDEX('Capital Call&Distributions data'!$C:$O,0,MIN(MAX(YEAR(AU$41)-YEAR($K61)+$J61+1,1),14)))),0)} -> 0
D62: =_xlfn.XLOOKUP(C62,Fondsen!B:B,Fondsen!C:C,"0",0,1) -> 0 | E62: EUR | G62: =IFERROR(IF(SUM(OFFSET(INDEX('Capital Call&Distributions data'!A:A,MATCH(D62,'Capital Call&Distributions data'!A:A,0)),-1,2,1,1000))=0,"✔",""),"") | H62: =IFERROR(IRR(L62:AD62),"") | I62: 47849 | J62: =YEAR(K62)-YEAR(I62) -> 0 | K62: 47849 | L62: {=IFERROR(IF(L$41<$K62,0,$F62*_xlfn.XLOOKUP($D62,'Capital Call&Distributions data'!$A:$A,INDEX('Capital Call&Distributions data'!$C:$O,0,MIN(MAX(YEAR(L$41)-YEAR($K62)+$J62+1,1),14)))),0)} -> 0 | M62: {=IFERROR(IF(M$41<$K62,0,$F62*_xlfn.XLOOKUP($D62,'Capital Call&Distributions data'!$A:$A,INDEX('Capital Call&Distributions data'!$C:$O,0,MIN(MAX(YEAR(M$41)-YEAR($K62)+$J62+1,1),14)))),0)} -> 0 | N62: {=IFERROR(IF(N$41<$K62,0,$F62*_xlfn.XLOOKUP($D62,'Capital Call&Distributions data'!$A:$A,INDEX('Capital Call&Distributions data'!$C:$O,0,MIN(MAX(YEAR(N$41)-YEAR($K62)+$J62+1,1),14)))),0)} -> 0 | O62: {=IFERROR(IF(O$41<$K62,0,$F62*_xlfn.XLOOKUP($D62,'Capital Call&Distributions data'!$A:$A,INDEX('Capital Call&Distributions data'!$C:$O,0,MIN(MAX(YEAR(O$41)-YEAR($K62)+$J62+1,1),14)))),0)} -> 0 | P62: {=IFERROR(IF(P$41<$K62,0,$F62*_xlfn.XLOOKUP($D62,'Capital Call&Distributions data'!$A:$A,INDEX('Capital Call&Distributions data'!$C:$O,0,MIN(MAX(YEAR(P$41)-YEAR($K62)+$J62+1,1),14)))),0)} -> 0 | Q62: {=IFERROR(IF(Q$41<$K62,0,$F62*_xlfn.XLOOKUP($D62,'Capital Call&Distributions data'!$A:$A,INDEX('Capital Call&Distributions data'!$C:$O,0,MIN(MAX(YEAR(Q$41)-YEAR($K62)+$J62+1,1),14)))),0)} -> 0 | R62: {=IFERROR(IF(R$41<$K62,0,$F62*_xlfn.XLOOKUP($D62,'Capital Call&Distributions data'!$A:$A,INDEX('Capital Call&Distributions data'!$C:$O,0,MIN(MAX(YEAR(R$41)-YEAR($K62)+$J62+1,1),14)))),0)} -> 0 | S62: {=IFERROR(IF(S$41<$K62,0,$F62*_xlfn.XLOOKUP($D62,'Capital Call&Distributions data'!$A:$A,INDEX('Capital Call&Distributions data'!$C:$O,0,MIN(MAX(YEAR(S$41)-YEAR($K62)+$J62+1,1),14)))),0)} -> 0 | ... AU62: {=IFERROR(IF(AU$41<$K62,0,$F62*_xlfn.XLOOKUP($D62,'Capital Call&Distributions data'!$A:$A,INDEX('Capital Call&Distributions data'!$C:$O,0,MIN(MAX(YEAR(AU$41)-YEAR($K62)+$J62+1,1),14)))),0)} -> 0
D63: =_xlfn.XLOOKUP(C63,Fondsen!B:B,Fondsen!C:C,"0",0,1) -> 0 | E63: EUR | G63: =IFERROR(IF(SUM(OFFSET(INDEX('Capital Call&Distributions data'!A:A,MATCH(D63,'Capital Call&Distributions data'!A:A,0)),-1,2,1,1000))=0,"✔",""),"") | H63: =IFERROR(IRR(L63:AD63),"") | I63: 47849 | J63: =YEAR(K63)-YEAR(I63) -> 0 | K63: 47849 | L63: {=IFERROR(IF(L$41<$K63,0,$F63*_xlfn.XLOOKUP($D63,'Capital Call&Distributions data'!$A:$A,INDEX('Capital Call&Distributions data'!$C:$O,0,MIN(MAX(YEAR(L$41)-YEAR($K63)+$J63+1,1),14)))),0)} -> 0 | M63: {=IFERROR(IF(M$41<$K63,0,$F63*_xlfn.XLOOKUP($D63,'Capital Call&Distributions data'!$A:$A,INDEX('Capital Call&Distributions data'!$C:$O,0,MIN(MAX(YEAR(M$41)-YEAR($K63)+$J63+1,1),14)))),0)} -> 0 | N63: {=IFERROR(IF(N$41<$K63,0,$F63*_xlfn.XLOOKUP($D63,'Capital Call&Distributions data'!$A:$A,INDEX('Capital Call&Distributions data'!$C:$O,0,MIN(MAX(YEAR(N$41)-YEAR($K63)+$J63+1,1),14)))),0)} -> 0 | O63: {=IFERROR(IF(O$41<$K63,0,$F63*_xlfn.XLOOKUP($D63,'Capital Call&Distributions data'!$A:$A,INDEX('Capital Call&Distributions data'!$C:$O,0,MIN(MAX(YEAR(O$41)-YEAR($K63)+$J63+1,1),14)))),0)} -> 0 | P63: {=IFERROR(IF(P$41<$K63,0,$F63*_xlfn.XLOOKUP($D63,'Capital Call&Distributions data'!$A:$A,INDEX('Capital Call&Distributions data'!$C:$O,0,MIN(MAX(YEAR(P$41)-YEAR($K63)+$J63+1,1),14)))),0)} -> 0 | Q63: {=IFERROR(IF(Q$41<$K63,0,$F63*_xlfn.XLOOKUP($D63,'Capital Call&Distributions data'!$A:$A,INDEX('Capital Call&Distributions data'!$C:$O,0,MIN(MAX(YEAR(Q$41)-YEAR($K63)+$J63+1,1),14)))),0)} -> 0 | R63: {=IFERROR(IF(R$41<$K63,0,$F63*_xlfn.XLOOKUP($D63,'Capital Call&Distributions data'!$A:$A,INDEX('Capital Call&Distributions data'!$C:$O,0,MIN(MAX(YEAR(R$41)-YEAR($K63)+$J63+1,1),14)))),0)} -> 0 | S63: {=IFERROR(IF(S$41<$K63,0,$F63*_xlfn.XLOOKUP($D63,'Capital Call&Distributions data'!$A:$A,INDEX('Capital Call&Distributions data'!$C:$O,0,MIN(MAX(YEAR(S$41)-YEAR($K63)+$J63+1,1),14)))),0)} -> 0 | ... AU63: {=IFERROR(IF(AU$41<$K63,0,$F63*_xlfn.XLOOKUP($D63,'Capital Call&Distributions data'!$A:$A,INDEX('Capital Call&Distributions data'!$C:$O,0,MIN(MAX(YEAR(AU$41)-YEAR($K63)+$J63+1,1),14)))),0)} -> 0
D64: =_xlfn.XLOOKUP(C64,Fondsen!B:B,Fondsen!C:C,"0",0,1) -> 0 | E64: EUR | G64: =IFERROR(IF(SUM(OFFSET(INDEX('Capital Call&Distributions data'!A:A,MATCH(D64,'Capital Call&Distributions data'!A:A,0)),-1,2,1,1000))=0,"✔",""),"") | H64: =IFERROR(IRR(L64:AD64),"") | I64: 48214 | J64: =YEAR(K64)-YEAR(I64) -> 0 | K64: 48214 | L64: {=IFERROR(IF(L$41<$K64,0,$F64*_xlfn.XLOOKUP($D64,'Capital Call&Distributions data'!$A:$A,INDEX('Capital Call&Distributions data'!$C:$O,0,MIN(MAX(YEAR(L$41)-YEAR($K64)+$J64+1,1),14)))),0)} -> 0 | M64: {=IFERROR(IF(M$41<$K64,0,$F64*_xlfn.XLOOKUP($D64,'Capital Call&Distributions data'!$A:$A,INDEX('Capital Call&Distributions data'!$C:$O,0,MIN(MAX(YEAR(M$41)-YEAR($K64)+$J64+1,1),14)))),0)} -> 0 | N64: {=IFERROR(IF(N$41<$K64,0,$F64*_xlfn.XLOOKUP($D64,'Capital Call&Distributions data'!$A:$A,INDEX('Capital Call&Distributions data'!$C:$O,0,MIN(MAX(YEAR(N$41)-YEAR($K64)+$J64+1,1),14)))),0)} -> 0 | O64: {=IFERROR(IF(O$41<$K64,0,$F64*_xlfn.XLOOKUP($D64,'Capital Call&Distributions data'!$A:$A,INDEX('Capital Call&Distributions data'!$C:$O,0,MIN(MAX(YEAR(O$41)-YEAR($K64)+$J64+1,1),14)))),0)} -> 0 | P64: {=IFERROR(IF(P$41<$K64,0,$F64*_xlfn.XLOOKUP($D64,'Capital Call&Distributions data'!$A:$A,INDEX('Capital Call&Distributions data'!$C:$O,0,MIN(MAX(YEAR(P$41)-YEAR($K64)+$J64+1,1),14)))),0)} -> 0 | Q64: {=IFERROR(IF(Q$41<$K64,0,$F64*_xlfn.XLOOKUP($D64,'Capital Call&Distributions data'!$A:$A,INDEX('Capital Call&Distributions data'!$C:$O,0,MIN(MAX(YEAR(Q$41)-YEAR($K64)+$J64+1,1),14)))),0)} -> 0 | R64: {=IFERROR(IF(R$41<$K64,0,$F64*_xlfn.XLOOKUP($D64,'Capital Call&Distributions data'!$A:$A,INDEX('Capital Call&Distributions data'!$C:$O,0,MIN(MAX(YEAR(R$41)-YEAR($K64)+$J64+1,1),14)))),0)} -> 0 | S64: {=IFERROR(IF(S$41<$K64,0,$F64*_xlfn.XLOOKUP($D64,'Capital Call&Distributions data'!$A:$A,INDEX('Capital Call&Distributions data'!$C:$O,0,MIN(MAX(YEAR(S$41)-YEAR($K64)+$J64+1,1),14)))),0)} -> 0 | ... AU64: {=IFERROR(IF(AU$41<$K64,0,$F64*_xlfn.XLOOKUP($D64,'Capital Call&Distributions data'!$A:$A,INDEX('Capital Call&Distributions data'!$C:$O,0,MIN(MAX(YEAR(AU$41)-YEAR($K64)+$J64+1,1),14)))),0)} -> 0
D65: =_xlfn.XLOOKUP(C65,Fondsen!B:B,Fondsen!C:C,"0",0,1) -> 0 | E65: EUR | G65: =IFERROR(IF(SUM(OFFSET(INDEX('Capital Call&Distributions data'!A:A,MATCH(D65,'Capital Call&Distributions data'!A:A,0)),-1,2,1,1000))=0,"✔",""),"") | H65: =IFERROR(IRR(L65:AD65),"") | I65: 48214 | J65: =YEAR(K65)-YEAR(I65) -> 0 | K65: 48214 | L65: {=IFERROR(IF(L$41<$K65,0,$F65*_xlfn.XLOOKUP($D65,'Capital Call&Distributions data'!$A:$A,INDEX('Capital Call&Distributions data'!$C:$O,0,MIN(MAX(YEAR(L$41)-YEAR($K65)+$J65+1,1),14)))),0)} -> 0 | M65: {=IFERROR(IF(M$41<$K65,0,$F65*_xlfn.XLOOKUP($D65,'Capital Call&Distributions data'!$A:$A,INDEX('Capital Call&Distributions data'!$C:$O,0,MIN(MAX(YEAR(M$41)-YEAR($K65)+$J65+1,1),14)))),0)} -> 0 | N65: {=IFERROR(IF(N$41<$K65,0,$F65*_xlfn.XLOOKUP($D65,'Capital Call&Distributions data'!$A:$A,INDEX('Capital Call&Distributions data'!$C:$O,0,MIN(MAX(YEAR(N$41)-YEAR($K65)+$J65+1,1),14)))),0)} -> 0 | O65: {=IFERROR(IF(O$41<$K65,0,$F65*_xlfn.XLOOKUP($D65,'Capital Call&Distributions data'!$A:$A,INDEX('Capital Call&Distributions data'!$C:$O,0,MIN(MAX(YEAR(O$41)-YEAR($K65)+$J65+1,1),14)))),0)} -> 0 | P65: {=IFERROR(IF(P$41<$K65,0,$F65*_xlfn.XLOOKUP($D65,'Capital Call&Distributions data'!$A:$A,INDEX('Capital Call&Distributions data'!$C:$O,0,MIN(MAX(YEAR(P$41)-YEAR($K65)+$J65+1,1),14)))),0)} -> 0 | Q65: {=IFERROR(IF(Q$41<$K65,0,$F65*_xlfn.XLOOKUP($D65,'Capital Call&Distributions data'!$A:$A,INDEX('Capital Call&Distributions data'!$C:$O,0,MIN(MAX(YEAR(Q$41)-YEAR($K65)+$J65+1,1),14)))),0)} -> 0 | R65: {=IFERROR(IF(R$41<$K65,0,$F65*_xlfn.XLOOKUP($D65,'Capital Call&Distributions data'!$A:$A,INDEX('Capital Call&Distributions data'!$C:$O,0,MIN(MAX(YEAR(R$41)-YEAR($K65)+$J65+1,1),14)))),0)} -> 0 | S65: {=IFERROR(IF(S$41<$K65,0,$F65*_xlfn.XLOOKUP($D65,'Capital Call&Distributions data'!$A:$A,INDEX('Capital Call&Distributions data'!$C:$O,0,MIN(MAX(YEAR(S$41)-YEAR($K65)+$J65+1,1),14)))),0)} -> 0 | ... AU65: {=IFERROR(IF(AU$41<$K65,0,$F65*_xlfn.XLOOKUP($D65,'Capital Call&Distributions data'!$A:$A,INDEX('Capital Call&Distributions data'!$C:$O,0,MIN(MAX(YEAR(AU$41)-YEAR($K65)+$J65+1,1),14)))),0)} -> 0
D66: =_xlfn.XLOOKUP(C66,Fondsen!B:B,Fondsen!C:C,"0",0,1) -> 0 | E66: EUR | G66: =IFERROR(IF(SUM(OFFSET(INDEX('Capital Call&Distributions data'!A:A,MATCH(D66,'Capital Call&Distributions data'!A:A,0)),-1,2,1,1000))=0,"✔",""),"") | H66: =IFERROR(IRR(L66:AD66),"") | I66: 48214 | J66: =YEAR(K66)-YEAR(I66) -> 0 | K66: 48214 | L66: {=IFERROR(IF(L$41<$K66,0,$F66*_xlfn.XLOOKUP($D66,'Capital Call&Distributions data'!$A:$A,INDEX('Capital Call&Distributions data'!$C:$O,0,MIN(MAX(YEAR(L$41)-YEAR($K66)+$J66+1,1),14)))),0)} -> 0 | M66: {=IFERROR(IF(M$41<$K66,0,$F66*_xlfn.XLOOKUP($D66,'Capital Call&Distributions data'!$A:$A,INDEX('Capital Call&Distributions data'!$C:$O,0,MIN(MAX(YEAR(M$41)-YEAR($K66)+$J66+1,1),14)))),0)} -> 0 | N66: {=IFERROR(IF(N$41<$K66,0,$F66*_xlfn.XLOOKUP($D66,'Capital Call&Distributions data'!$A:$A,INDEX('Capital Call&Distributions data'!$C:$O,0,MIN(MAX(YEAR(N$41)-YEAR($K66)+$J66+1,1),14)))),0)} -> 0 | O66: {=IFERROR(IF(O$41<$K66,0,$F66*_xlfn.XLOOKUP($D66,'Capital Call&Distributions data'!$A:$A,INDEX('Capital Call&Distributions data'!$C:$O,0,MIN(MAX(YEAR(O$41)-YEAR($K66)+$J66+1,1),14)))),0)} -> 0 | P66: {=IFERROR(IF(P$41<$K66,0,$F66*_xlfn.XLOOKUP($D66,'Capital Call&Distributions data'!$A:$A,INDEX('Capital Call&Distributions data'!$C:$O,0,MIN(MAX(YEAR(P$41)-YEAR($K66)+$J66+1,1),14)))),0)} -> 0 | Q66: {=IFERROR(IF(Q$41<$K66,0,$F66*_xlfn.XLOOKUP($D66,'Capital Call&Distributions data'!$A:$A,INDEX('Capital Call&Distributions data'!$C:$O,0,MIN(MAX(YEAR(Q$41)-YEAR($K66)+$J66+1,1),14)))),0)} -> 0 | R66: {=IFERROR(IF(R$41<$K66,0,$F66*_xlfn.XLOOKUP($D66,'Capital Call&Distributions data'!$A:$A,INDEX('Capital Call&Distributions data'!$C:$O,0,MIN(MAX(YEAR(R$41)-YEAR($K66)+$J66+1,1),14)))),0)} -> 0 | S66: {=IFERROR(IF(S$41<$K66,0,$F66*_xlfn.XLOOKUP($D66,'Capital Call&Distributions data'!$A:$A,INDEX('Capital Call&Distributions data'!$C:$O,0,MIN(MAX(YEAR(S$41)-YEAR($K66)+$J66+1,1),14)))),0)} -> 0 | ... AU66: {=IFERROR(IF(AU$41<$K66,0,$F66*_xlfn.XLOOKUP($D66,'Capital Call&Distributions data'!$A:$A,INDEX('Capital Call&Distributions data'!$C:$O,0,MIN(MAX(YEAR(AU$41)-YEAR($K66)+$J66+1,1),14)))),0)} -> 0
D67: =_xlfn.XLOOKUP(C67,Fondsen!B:B,Fondsen!C:C,"0",0,1) -> 0 | E67: EUR | G67: =IFERROR(IF(SUM(OFFSET(INDEX('Capital Call&Distributions data'!A:A,MATCH(D67,'Capital Call&Distributions data'!A:A,0)),-1,2,1,1000))=0,"✔",""),"") | H67: =IFERROR(IRR(L67:AD67),"") | I67: 45658 | J67: =YEAR(K67)-YEAR(I67) -> 0 | K67: 45658 | L67: {=IFERROR(IF(L$41<$K67,0,$F67*_xlfn.XLOOKUP($D67,'Capital Call&Distributions data'!$A:$A,INDEX('Capital Call&Distributions data'!$C:$O,0,MIN(MAX(YEAR(L$41)-YEAR($K67)+$J67+1,1),14)))),0)} -> 0 | M67: {=IFERROR(IF(M$41<$K67,0,$F67*_xlfn.XLOOKUP($D67,'Capital Call&Distributions data'!$A:$A,INDEX('Capital Call&Distributions data'!$C:$O,0,MIN(MAX(YEAR(M$41)-YEAR($K67)+$J67+1,1),14)))),0)} -> 0 | N67: {=IFERROR(IF(N$41<$K67,0,$F67*_xlfn.XLOOKUP($D67,'Capital Call&Distributions data'!$A:$A,INDEX('Capital Call&Distributions data'!$C:$O,0,MIN(MAX(YEAR(N$41)-YEAR($K67)+$J67+1,1),14)))),0)} -> 0 | O67: {=IFERROR(IF(O$41<$K67,0,$F67*_xlfn.XLOOKUP($D67,'Capital Call&Distributions data'!$A:$A,INDEX('Capital Call&Distributions data'!$C:$O,0,MIN(MAX(YEAR(O$41)-YEAR($K67)+$J67+1,1),14)))),0)} -> 0 | P67: {=IFERROR(IF(P$41<$K67,0,$F67*_xlfn.XLOOKUP($D67,'Capital Call&Distributions data'!$A:$A,INDEX('Capital Call&Distributions data'!$C:$O,0,MIN(MAX(YEAR(P$41)-YEAR($K67)+$J67+1,1),14)))),0)} -> 0 | Q67: {=IFERROR(IF(Q$41<$K67,0,$F67*_xlfn.XLOOKUP($D67,'Capital Call&Distributions data'!$A:$A,INDEX('Capital Call&Distributions data'!$C:$O,0,MIN(MAX(YEAR(Q$41)-YEAR($K67)+$J67+1,1),14)))),0)} -> 0 | R67: {=IFERROR(IF(R$41<$K67,0,$F67*_xlfn.XLOOKUP($D67,'Capital Call&Distributions data'!$A:$A,INDEX('Capital Call&Distributions data'!$C:$O,0,MIN(MAX(YEAR(R$41)-YEAR($K67)+$J67+1,1),14)))),0)} -> 0 | S67: {=IFERROR(IF(S$41<$K67,0,$F67*_xlfn.XLOOKUP($D67,'Capital Call&Distributions data'!$A:$A,INDEX('Capital Call&Distributions data'!$C:$O,0,MIN(MAX(YEAR(S$41)-YEAR($K67)+$J67+1,1),14)))),0)} -> 0 | ... AU67: {=IFERROR(IF(AU$41<$K67,0,$F67*_xlfn.XLOOKUP($D67,'Capital Call&Distributions data'!$A:$A,INDEX('Capital Call&Distributions data'!$C:$O,0,MIN(MAX(YEAR(AU$41)-YEAR($K67)+$J67+1,1),14)))),0)} -> 0
D68: =_xlfn.XLOOKUP(C68,Fondsen!B:B,Fondsen!C:C,"0",0,1) -> 0 | E68: EUR | G68: =IFERROR(IF(SUM(OFFSET(INDEX('Capital Call&Distributions data'!A:A,MATCH(D68,'Capital Call&Distributions data'!A:A,0)),-1,2,1,1000))=0,"✔",""),"") | H68: =IFERROR(IRR(L68:AD68),"") | I68: 45658 | J68: =YEAR(K68)-YEAR(I68) -> 0 | K68: 45658 | L68: {=IFERROR(IF(L$41<$K68,0,$F68*_xlfn.XLOOKUP($D68,'Capital Call&Distributions data'!$A:$A,INDEX('Capital Call&Distributions data'!$C:$O,0,MIN(MAX(YEAR(L$41)-YEAR($K68)+$J68+1,1),14)))),0)} -> 0 | M68: {=IFERROR(IF(M$41<$K68,0,$F68*_xlfn.XLOOKUP($D68,'Capital Call&Distributions data'!$A:$A,INDEX('Capital Call&Distributions data'!$C:$O,0,MIN(MAX(YEAR(M$41)-YEAR($K68)+$J68+1,1),14)))),0)} -> 0 | N68: {=IFERROR(IF(N$41<$K68,0,$F68*_xlfn.XLOOKUP($D68,'Capital Call&Distributions data'!$A:$A,INDEX('Capital Call&Distributions data'!$C:$O,0,MIN(MAX(YEAR(N$41)-YEAR($K68)+$J68+1,1),14)))),0)} -> 0 | O68: {=IFERROR(IF(O$41<$K68,0,$F68*_xlfn.XLOOKUP($D68,'Capital Call&Distributions data'!$A:$A,INDEX('Capital Call&Distributions data'!$C:$O,0,MIN(MAX(YEAR(O$41)-YEAR($K68)+$J68+1,1),14)))),0)} -> 0 | P68: {=IFERROR(IF(P$41<$K68,0,$F68*_xlfn.XLOOKUP($D68,'Capital Call&Distributions data'!$A:$A,INDEX('Capital Call&Distributions data'!$C:$O,0,MIN(MAX(YEAR(P$41)-YEAR($K68)+$J68+1,1),14)))),0)} -> 0 | Q68: {=IFERROR(IF(Q$41<$K68,0,$F68*_xlfn.XLOOKUP($D68,'Capital Call&Distributions data'!$A:$A,INDEX('Capital Call&Distributions data'!$C:$O,0,MIN(MAX(YEAR(Q$41)-YEAR($K68)+$J68+1,1),14)))),0)} -> 0 | R68: {=IFERROR(IF(R$41<$K68,0,$F68*_xlfn.XLOOKUP($D68,'Capital Call&Distributions data'!$A:$A,INDEX('Capital Call&Distributions data'!$C:$O,0,MIN(MAX(YEAR(R$41)-YEAR($K68)+$J68+1,1),14)))),0)} -> 0 | S68: {=IFERROR(IF(S$41<$K68,0,$F68*_xlfn.XLOOKUP($D68,'Capital Call&Distributions data'!$A:$A,INDEX('Capital Call&Distributions data'!$C:$O,0,MIN(MAX(YEAR(S$41)-YEAR($K68)+$J68+1,1),14)))),0)} -> 0 | ... AU68: {=IFERROR(IF(AU$41<$K68,0,$F68*_xlfn.XLOOKUP($D68,'Capital Call&Distributions data'!$A:$A,INDEX('Capital Call&Distributions data'!$C:$O,0,MIN(MAX(YEAR(AU$41)-YEAR($K68)+$J68+1,1),14)))),0)} -> 0
D69: =_xlfn.XLOOKUP(C69,Fondsen!B:B,Fondsen!C:C,"0",0,1) -> 0 | E69: EUR | G69: =IFERROR(IF(SUM(OFFSET(INDEX('Capital Call&Distributions data'!A:A,MATCH(D69,'Capital Call&Distributions data'!A:A,0)),-1,2,1,1000))=0,"✔",""),"") | H69: =IFERROR(IRR(L69:AD69),"") | I69: 45658 | J69: =YEAR(K69)-YEAR(I69) -> 0 | K69: 45658 | L69: {=IFERROR(IF(L$41<$K69,0,$F69*_xlfn.XLOOKUP($D69,'Capital Call&Distributions data'!$A:$A,INDEX('Capital Call&Distributions data'!$C:$O,0,MIN(MAX(YEAR(L$41)-YEAR($K69)+$J69+1,1),14)))),0)} -> 0 | M69: {=IFERROR(IF(M$41<$K69,0,$F69*_xlfn.XLOOKUP($D69,'Capital Call&Distributions data'!$A:$A,INDEX('Capital Call&Distributions data'!$C:$O,0,MIN(MAX(YEAR(M$41)-YEAR($K69)+$J69+1,1),14)))),0)} -> 0 | N69: {=IFERROR(IF(N$41<$K69,0,$F69*_xlfn.XLOOKUP($D69,'Capital Call&Distributions data'!$A:$A,INDEX('Capital Call&Distributions data'!$C:$O,0,MIN(MAX(YEAR(N$41)-YEAR($K69)+$J69+1,1),14)))),0)} -> 0 | O69: {=IFERROR(IF(O$41<$K69,0,$F69*_xlfn.XLOOKUP($D69,'Capital Call&Distributions data'!$A:$A,INDEX('Capital Call&Distributions data'!$C:$O,0,MIN(MAX(YEAR(O$41)-YEAR($K69)+$J69+1,1),14)))),0)} -> 0 | P69: {=IFERROR(IF(P$41<$K69,0,$F69*_xlfn.XLOOKUP($D69,'Capital Call&Distributions data'!$A:$A,INDEX('Capital Call&Distributions data'!$C:$O,0,MIN(MAX(YEAR(P$41)-YEAR($K69)+$J69+1,1),14)))),0)} -> 0 | Q69: {=IFERROR(IF(Q$41<$K69,0,$F69*_xlfn.XLOOKUP($D69,'Capital Call&Distributions data'!$A:$A,INDEX('Capital Call&Distributions data'!$C:$O,0,MIN(MAX(YEAR(Q$41)-YEAR($K69)+$J69+1,1),14)))),0)} -> 0 | R69: {=IFERROR(IF(R$41<$K69,0,$F69*_xlfn.XLOOKUP($D69,'Capital Call&Distributions data'!$A:$A,INDEX('Capital Call&Distributions data'!$C:$O,0,MIN(MAX(YEAR(R$41)-YEAR($K69)+$J69+1,1),14)))),0)} -> 0 | S69: {=IFERROR(IF(S$41<$K69,0,$F69*_xlfn.XLOOKUP($D69,'Capital Call&Distributions data'!$A:$A,INDEX('Capital Call&Distributions data'!$C:$O,0,MIN(MAX(YEAR(S$41)-YEAR($K69)+$J69+1,1),14)))),0)} -> 0 | ... AU69: {=IFERROR(IF(AU$41<$K69,0,$F69*_xlfn.XLOOKUP($D69,'Capital Call&Distributions data'!$A:$A,INDEX('Capital Call&Distributions data'!$C:$O,0,MIN(MAX(YEAR(AU$41)-YEAR($K69)+$J69+1,1),14)))),0)} -> 0
D70: =_xlfn.XLOOKUP(C70,Fondsen!B:B,Fondsen!C:C,"0",0,1) -> 0 | E70: EUR | G70: =IFERROR(IF(SUM(OFFSET(INDEX('Capital Call&Distributions data'!A:A,MATCH(D70,'Capital Call&Distributions data'!A:A,0)),-1,2,1,1000))=0,"✔",""),"") | H70: =IFERROR(IRR(L70:AD70),"") | I70: 45658 | J70: =YEAR(K70)-YEAR(I70) -> 0 | K70: 45658 | L70: {=IFERROR(IF(L$41<$K70,0,$F70*_xlfn.XLOOKUP($D70,'Capital Call&Distributions data'!$A:$A,INDEX('Capital Call&Distributions data'!$C:$O,0,MIN(MAX(YEAR(L$41)-YEAR($K70)+$J70+1,1),14)))),0)} -> 0 | M70: {=IFERROR(IF(M$41<$K70,0,$F70*_xlfn.XLOOKUP($D70,'Capital Call&Distributions data'!$A:$A,INDEX('Capital Call&Distributions data'!$C:$O,0,MIN(MAX(YEAR(M$41)-YEAR($K70)+$J70+1,1),14)))),0)} -> 0 | N70: {=IFERROR(IF(N$41<$K70,0,$F70*_xlfn.XLOOKUP($D70,'Capital Call&Distributions data'!$A:$A,INDEX('Capital Call&Distributions data'!$C:$O,0,MIN(MAX(YEAR(N$41)-YEAR($K70)+$J70+1,1),14)))),0)} -> 0 | O70: {=IFERROR(IF(O$41<$K70,0,$F70*_xlfn.XLOOKUP($D70,'Capital Call&Distributions data'!$A:$A,INDEX('Capital Call&Distributions data'!$C:$O,0,MIN(MAX(YEAR(O$41)-YEAR($K70)+$J70+1,1),14)))),0)} -> 0 | P70: {=IFERROR(IF(P$41<$K70,0,$F70*_xlfn.XLOOKUP($D70,'Capital Call&Distributions data'!$A:$A,INDEX('Capital Call&Distributions data'!$C:$O,0,MIN(MAX(YEAR(P$41)-YEAR($K70)+$J70+1,1),14)))),0)} -> 0 | Q70: {=IFERROR(IF(Q$41<$K70,0,$F70*_xlfn.XLOOKUP($D70,'Capital Call&Distributions data'!$A:$A,INDEX('Capital Call&Distributions data'!$C:$O,0,MIN(MAX(YEAR(Q$41)-YEAR($K70)+$J70+1,1),14)))),0)} -> 0 | R70: {=IFERROR(IF(R$41<$K70,0,$F70*_xlfn.XLOOKUP($D70,'Capital Call&Distributions data'!$A:$A,INDEX('Capital Call&Distributions data'!$C:$O,0,MIN(MAX(YEAR(R$41)-YEAR($K70)+$J70+1,1),14)))),0)} -> 0 | S70: {=IFERROR(IF(S$41<$K70,0,$F70*_xlfn.XLOOKUP($D70,'Capital Call&Distributions data'!$A:$A,INDEX('Capital Call&Distributions data'!$C:$O,0,MIN(MAX(YEAR(S$41)-YEAR($K70)+$J70+1,1),14)))),0)} -> 0 | ... AU70: {=IFERROR(IF(AU$41<$K70,0,$F70*_xlfn.XLOOKUP($D70,'Capital Call&Distributions data'!$A:$A,INDEX('Capital Call&Distributions data'!$C:$O,0,MIN(MAX(YEAR(AU$41)-YEAR($K70)+$J70+1,1),14)))),0)} -> 0
... D80: =_xlfn.XLOOKUP(C80,Fondsen!B:B,Fondsen!C:C,"0",0,1) -> 0 | E80: EUR | G80: =IFERROR(IF(SUM(OFFSET(INDEX('Capital Call&Distributions data'!A:A,MATCH(D80,'Capital Call&Distributions data'!A:A,0)),-1,2,1,1000))=0,"✔",""),"") | H80: =IFERROR(IRR(L80:AD80),"") | I80: 45658 | J80: =YEAR(K80)-YEAR(I80) -> 0 | K80: 45658 | L80: {=IFERROR(IF(L$41<$K80,0,$F80*_xlfn.XLOOKUP($D80,'Capital Call&Distributions data'!$A:$A,INDEX('Capital Call&Distributions data'!$C:$O,0,MIN(MAX(YEAR(L$41)-YEAR($K80)+$J80+1,1),14)))),0)} -> 0 | M80: {=IFERROR(IF(M$41<$K80,0,$F80*_xlfn.XLOOKUP($D80,'Capital Call&Distributions data'!$A:$A,INDEX('Capital Call&Distributions data'!$C:$O,0,MIN(MAX(YEAR(M$41)-YEAR($K80)+$J80+1,1),14)))),0)} -> 0 | N80: {=IFERROR(IF(N$41<$K80,0,$F80*_xlfn.XLOOKUP($D80,'Capital Call&Distributions data'!$A:$A,INDEX('Capital Call&Distributions data'!$C:$O,0,MIN(MAX(YEAR(N$41)-YEAR($K80)+$J80+1,1),14)))),0)} -> 0 | O80: {=IFERROR(IF(O$41<$K80,0,$F80*_xlfn.XLOOKUP($D80,'Capital Call&Distributions data'!$A:$A,INDEX('Capital Call&Distributions data'!$C:$O,0,MIN(MAX(YEAR(O$41)-YEAR($K80)+$J80+1,1),14)))),0)} -> 0 | P80: {=IFERROR(IF(P$41<$K80,0,$F80*_xlfn.XLOOKUP($D80,'Capital Call&Distributions data'!$A:$A,INDEX('Capital Call&Distributions data'!$C:$O,0,MIN(MAX(YEAR(P$41)-YEAR($K80)+$J80+1,1),14)))),0)} -> 0 | Q80: {=IFERROR(IF(Q$41<$K80,0,$F80*_xlfn.XLOOKUP($D80,'Capital Call&Distributions data'!$A:$A,INDEX('Capital Call&Distributions data'!$C:$O,0,MIN(MAX(YEAR(Q$41)-YEAR($K80)+$J80+1,1),14)))),0)} -> 0 | R80: {=IFERROR(IF(R$41<$K80,0,$F80*_xlfn.XLOOKUP($D80,'Capital Call&Distributions data'!$A:$A,INDEX('Capital Call&Distributions data'!$C:$O,0,MIN(MAX(YEAR(R$41)-YEAR($K80)+$J80+1,1),14)))),0)} -> 0 | S80: {=IFERROR(IF(S$41<$K80,0,$F80*_xlfn.XLOOKUP($D80,'Capital Call&Distributions data'!$A:$A,INDEX('Capital Call&Distributions data'!$C:$O,0,MIN(MAX(YEAR(S$41)-YEAR($K80)+$J80+1,1),14)))),0)} -> 0 | ... AU80: {=IFERROR(IF(AU$41<$K80,0,$F80*_xlfn.XLOOKUP($D80,'Capital Call&Distributions data'!$A:$A,INDEX('Capital Call&Distributions data'!$C:$O,0,MIN(MAX(YEAR(AU$41)-YEAR($K80)+$J80+1,1),14)))),0)} -> 0
D81: =_xlfn.XLOOKUP(C81,Fondsen!B:B,Fondsen!C:C,"0",0,1) -> 0 | E81: EUR | F81: Netted in year 2/3 | G81: =IFERROR(IF(SUM(OFFSET(INDEX('Capital Call&Distributions data'!A:A,MATCH(D81,'Capital Call&Distributions data'!A:A,0)),-1,2,1,1000))=0,"✔",""),"") | H81: =IFERROR(IRR(L81:AD81),"") | I81: 45658 | J81: =YEAR(K81)-YEAR(I81) -> 0 | K81: 45658 | L81: {=IFERROR(IF(L$41<$K81,0,$F81*_xlfn.XLOOKUP($D81,'Capital Call&Distributions data'!$A:$A,INDEX('Capital Call&Distributions data'!$C:$O,0,MIN(MAX(YEAR(L$41)-YEAR($K81)+$J81+1,1),14)))),0)} -> 0 | M81: {=IFERROR(IF(M$41<$K81,0,$F81*_xlfn.XLOOKUP($D81,'Capital Call&Distributions data'!$A:$A,INDEX('Capital Call&Distributions data'!$C:$O,0,MIN(MAX(YEAR(M$41)-YEAR($K81)+$J81+1,1),14)))),0)} -> 0 | N81: {=IFERROR(IF(N$41<$K81,0,$F81*_xlfn.XLOOKUP($D81,'Capital Call&Distributions data'!$A:$A,INDEX('Capital Call&Distributions data'!$C:$O,0,MIN(MAX(YEAR(N$41)-YEAR($K81)+$J81+1,1),14)))),0)} -> 0 | O81: {=IFERROR(IF(O$41<$K81,0,$F81*_xlfn.XLOOKUP($D81,'Capital Call&Distributions data'!$A:$A,INDEX('Capital Call&Distributions data'!$C:$O,0,MIN(MAX(YEAR(O$41)-YEAR($K81)+$J81+1,1),14)))),0)} -> 0 | P81: {=IFERROR(IF(P$41<$K81,0,$F81*_xlfn.XLOOKUP($D81,'Capital Call&Distributions data'!$A:$A,INDEX('Capital Call&Distributions data'!$C:$O,0,MIN(MAX(YEAR(P$41)-YEAR($K81)+$J81+1,1),14)))),0)} -> 0 | Q81: {=IFERROR(IF(Q$41<$K81,0,$F81*_xlfn.XLOOKUP($D81,'Capital Call&Distributions data'!$A:$A,INDEX('Capital Call&Distributions data'!$C:$O,0,MIN(MAX(YEAR(Q$41)-YEAR($K81)+$J81+1,1),14)))),0)} -> 0 | R81: {=IFERROR(IF(R$41<$K81,0,$F81*_xlfn.XLOOKUP($D81,'Capital Call&Distributions data'!$A:$A,INDEX('Capital Call&Distributions data'!$C:$O,0,MIN(MAX(YEAR(R$41)-YEAR($K81)+$J81+1,1),14)))),0)} -> 0 | S81: {=IFERROR(IF(S$41<$K81,0,$F81*_xlfn.XLOOKUP($D81,'Capital Call&Distributions data'!$A:$A,INDEX('Capital Call&Distributions data'!$C:$O,0,MIN(MAX(YEAR(S$41)-YEAR($K81)+$J81+1,1),14)))),0)} -> 0 | ... AU81: {=IFERROR(IF(AU$41<$K81,0,$F81*_xlfn.XLOOKUP($D81,'Capital Call&Distributions data'!$A:$A,INDEX('Capital Call&Distributions data'!$C:$O,0,MIN(MAX(YEAR(AU$41)-YEAR($K81)+$J81+1,1),14)))),0)} -> 0
D82: =_xlfn.XLOOKUP(C82,Fondsen!B:B,Fondsen!C:C,"0",0,1) -> 0 | E82: EUR | F82: Netted in year 2/3 | G82: =IFERROR(IF(SUM(OFFSET(INDEX('Capital Call&Distributions data'!A:A,MATCH(D82,'Capital Call&Distributions data'!A:A,0)),-1,2,1,1000))=0,"✔",""),"") | H82: =IFERROR(IRR(L82:AD82),"") | I82: 45658 | J82: =YEAR(K82)-YEAR(I82) -> 0 | K82: 45658 | L82: {=IFERROR(IF(L$41<$K82,0,$F82*_xlfn.XLOOKUP($D82,'Capital Call&Distributions data'!$A:$A,INDEX('Capital Call&Distributions data'!$C:$O,0,MIN(MAX(YEAR(L$41)-YEAR($K82)+$J82+1,1),14)))),0)} -> 0 | M82: {=IFERROR(IF(M$41<$K82,0,$F82*_xlfn.XLOOKUP($D82,'Capital Call&Distributions data'!$A:$A,INDEX('Capital Call&Distributions data'!$C:$O,0,MIN(MAX(YEAR(M$41)-YEAR($K82)+$J82+1,1),14)))),0)} -> 0 | N82: {=IFERROR(IF(N$41<$K82,0,$F82*_xlfn.XLOOKUP($D82,'Capital Call&Distributions data'!$A:$A,INDEX('Capital Call&Distributions data'!$C:$O,0,MIN(MAX(YEAR(N$41)-YEAR($K82)+$J82+1,1),14)))),0)} -> 0 | O82: {=IFERROR(IF(O$41<$K82,0,$F82*_xlfn.XLOOKUP($D82,'Capital Call&Distributions data'!$A:$A,INDEX('Capital Call&Distributions data'!$C:$O,0,MIN(MAX(YEAR(O$41)-YEAR($K82)+$J82+1,1),14)))),0)} -> 0 | P82: {=IFERROR(IF(P$41<$K82,0,$F82*_xlfn.XLOOKUP($D82,'Capital Call&Distributions data'!$A:$A,INDEX('Capital Call&Distributions data'!$C:$O,0,MIN(MAX(YEAR(P$41)-YEAR($K82)+$J82+1,1),14)))),0)} -> 0 | Q82: {=IFERROR(IF(Q$41<$K82,0,$F82*_xlfn.XLOOKUP($D82,'Capital Call&Distributions data'!$A:$A,INDEX('Capital Call&Distributions data'!$C:$O,0,MIN(MAX(YEAR(Q$41)-YEAR($K82)+$J82+1,1),14)))),0)} -> 0 | R82: {=IFERROR(IF(R$41<$K82,0,$F82*_xlfn.XLOOKUP($D82,'Capital Call&Distributions data'!$A:$A,INDEX('Capital Call&Distributions data'!$C:$O,0,MIN(MAX(YEAR(R$41)-YEAR($K82)+$J82+1,1),14)))),0)} -> 0 | S82: {=IFERROR(IF(S$41<$K82,0,$F82*_xlfn.XLOOKUP($D82,'Capital Call&Distributions data'!$A:$A,INDEX('Capital Call&Distributions data'!$C:$O,0,MIN(MAX(YEAR(S$41)-YEAR($K82)+$J82+1,1),14)))),0)} -> 0 | ... AU82: {=IFERROR(IF(AU$41<$K82,0,$F82*_xlfn.XLOOKUP($D82,'Capital Call&Distributions data'!$A:$A,INDEX('Capital Call&Distributions data'!$C:$O,0,MIN(MAX(YEAR(AU$41)-YEAR($K82)+$J82+1,1),14)))),0)} -> 0
D83: =_xlfn.XLOOKUP(C83,Fondsen!B:B,Fondsen!C:C,"0",0,1) -> 0 | E83: EUR | F83: Netted in year 2/3 | G83: =IFERROR(IF(SUM(OFFSET(INDEX('Capital Call&Distributions data'!A:A,MATCH(D83,'Capital Call&Distributions data'!A:A,0)),-1,2,1,1000))=0,"✔",""),"") | H83: =IFERROR(IRR(L83:AD83),"") | I83: 45658 | J83: =YEAR(K83)-YEAR(I83) -> 0 | K83: 45658 | L83: {=IFERROR(IF(L$41<$K83,0,$F83*_xlfn.XLOOKUP($D83,'Capital Call&Distributions data'!$A:$A,INDEX('Capital Call&Distributions data'!$C:$O,0,MIN(MAX(YEAR(L$41)-YEAR($K83)+$J83+1,1),14)))),0)} -> 0 | M83: {=IFERROR(IF(M$41<$K83,0,$F83*_xlfn.XLOOKUP($D83,'Capital Call&Distributions data'!$A:$A,INDEX('Capital Call&Distributions data'!$C:$O,0,MIN(MAX(YEAR(M$41)-YEAR($K83)+$J83+1,1),14)))),0)} -> 0 | N83: {=IFERROR(IF(N$41<$K83,0,$F83*_xlfn.XLOOKUP($D83,'Capital Call&Distributions data'!$A:$A,INDEX('Capital Call&Distributions data'!$C:$O,0,MIN(MAX(YEAR(N$41)-YEAR($K83)+$J83+1,1),14)))),0)} -> 0 | O83: {=IFERROR(IF(O$41<$K83,0,$F83*_xlfn.XLOOKUP($D83,'Capital Call&Distributions data'!$A:$A,INDEX('Capital Call&Distributions data'!$C:$O,0,MIN(MAX(YEAR(O$41)-YEAR($K83)+$J83+1,1),14)))),0)} -> 0 | P83: {=IFERROR(IF(P$41<$K83,0,$F83*_xlfn.XLOOKUP($D83,'Capital Call&Distributions data'!$A:$A,INDEX('Capital Call&Distributions data'!$C:$O,0,MIN(MAX(YEAR(P$41)-YEAR($K83)+$J83+1,1),14)))),0)} -> 0 | Q83: {=IFERROR(IF(Q$41<$K83,0,$F83*_xlfn.XLOOKUP($D83,'Capital Call&Distributions data'!$A:$A,INDEX('Capital Call&Distributions data'!$C:$O,0,MIN(MAX(YEAR(Q$41)-YEAR($K83)+$J83+1,1),14)))),0)} -> 0 | R83: {=IFERROR(IF(R$41<$K83,0,$F83*_xlfn.XLOOKUP($D83,'Capital Call&Distributions data'!$A:$A,INDEX('Capital Call&Distributions data'!$C:$O,0,MIN(MAX(YEAR(R$41)-YEAR($K83)+$J83+1,1),14)))),0)} -> 0 | S83: {=IFERROR(IF(S$41<$K83,0,$F83*_xlfn.XLOOKUP($D83,'Capital Call&Distributions data'!$A:$A,INDEX('Capital Call&Distributions data'!$C:$O,0,MIN(MAX(YEAR(S$41)-YEAR($K83)+$J83+1,1),14)))),0)} -> 0 | ... AU83: {=IFERROR(IF(AU$41<$K83,0,$F83*_xlfn.XLOOKUP($D83,'Capital Call&Distributions data'!$A:$A,INDEX('Capital Call&Distributions data'!$C:$O,0,MIN(MAX(YEAR(AU$41)-YEAR($K83)+$J83+1,1),14)))),0)} -> 0
D84: =_xlfn.XLOOKUP(C84,Fondsen!B:B,Fondsen!C:C,"0",0,1) -> 0 | E84: EUR | F84: Netted in year 2/3 | G84: =IFERROR(IF(SUM(OFFSET(INDEX('Capital Call&Distributions data'!A:A,MATCH(D84,'Capital Call&Distributions data'!A:A,0)),-1,2,1,1000))=0,"✔",""),"") | H84: =IFERROR(IRR(L84:AD84),"") | I84: 45658 | J84: =YEAR(K84)-YEAR(I84) -> 0 | K84: 45658 | L84: {=IFERROR(IF(L$41<$K84,0,$F84*_xlfn.XLOOKUP($D84,'Capital Call&Distributions data'!$A:$A,INDEX('Capital Call&Distributions data'!$C:$O,0,MIN(MAX(YEAR(L$41)-YEAR($K84)+$J84+1,1),14)))),0)} -> 0 | M84: {=IFERROR(IF(M$41<$K84,0,$F84*_xlfn.XLOOKUP($D84,'Capital Call&Distributions data'!$A:$A,INDEX('Capital Call&Distributions data'!$C:$O,0,MIN(MAX(YEAR(M$41)-YEAR($K84)+$J84+1,1),14)))),0)} -> 0 | N84: {=IFERROR(IF(N$41<$K84,0,$F84*_xlfn.XLOOKUP($D84,'Capital Call&Distributions data'!$A:$A,INDEX('Capital Call&Distributions data'!$C:$O,0,MIN(MAX(YEAR(N$41)-YEAR($K84)+$J84+1,1),14)))),0)} -> 0 | O84: {=IFERROR(IF(O$41<$K84,0,$F84*_xlfn.XLOOKUP($D84,'Capital Call&Distributions data'!$A:$A,INDEX('Capital Call&Distributions data'!$C:$O,0,MIN(MAX(YEAR(O$41)-YEAR($K84)+$J84+1,1),14)))),0)} -> 0 | P84: {=IFERROR(IF(P$41<$K84,0,$F84*_xlfn.XLOOKUP($D84,'Capital Call&Distributions data'!$A:$A,INDEX('Capital Call&Distributions data'!$C:$O,0,MIN(MAX(YEAR(P$41)-YEAR($K84)+$J84+1,1),14)))),0)} -> 0 | Q84: {=IFERROR(IF(Q$41<$K84,0,$F84*_xlfn.XLOOKUP($D84,'Capital Call&Distributions data'!$A:$A,INDEX('Capital Call&Distributions data'!$C:$O,0,MIN(MAX(YEAR(Q$41)-YEAR($K84)+$J84+1,1),14)))),0)} -> 0 | R84: {=IFERROR(IF(R$41<$K84,0,$F84*_xlfn.XLOOKUP($D84,'Capital Call&Distributions data'!$A:$A,INDEX('Capital Call&Distributions data'!$C:$O,0,MIN(MAX(YEAR(R$41)-YEAR($K84)+$J84+1,1),14)))),0)} -> 0 | S84: {=IFERROR(IF(S$41<$K84,0,$F84*_xlfn.XLOOKUP($D84,'Capital Call&Distributions data'!$A:$A,INDEX('Capital Call&Distributions data'!$C:$O,0,MIN(MAX(YEAR(S$41)-YEAR($K84)+$J84+1,1),14)))),0)} -> 0 | ... AU84: {=IFERROR(IF(AU$41<$K84,0,$F84*_xlfn.XLOOKUP($D84,'Capital Call&Distributions data'!$A:$A,INDEX('Capital Call&Distributions data'!$C:$O,0,MIN(MAX(YEAR(AU$41)-YEAR($K84)+$J84+1,1),14)))),0)} -> 0
D85: =_xlfn.XLOOKUP(C85,Fondsen!B:B,Fondsen!C:C,"0",0,1) -> 0 | E85: EUR | F85: Netted in year 2/3 | G85: =IFERROR(IF(SUM(OFFSET(INDEX('Capital Call&Distributions data'!A:A,MATCH(D85,'Capital Call&Distributions data'!A:A,0)),-1,2,1,1000))=0,"✔",""),"") | H85: =IFERROR(IRR(L85:AD85),"") | I85: 45658 | J85: =YEAR(K85)-YEAR(I85) -> 0 | K85: 45658 | L85: {=IFERROR(IF(L$41<$K85,0,$F85*_xlfn.XLOOKUP($D85,'Capital Call&Distributions data'!$A:$A,INDEX('Capital Call&Distributions data'!$C:$O,0,MIN(MAX(YEAR(L$41)-YEAR($K85)+$J85+1,1),14)))),0)} -> 0 | M85: {=IFERROR(IF(M$41<$K85,0,$F85*_xlfn.XLOOKUP($D85,'Capital Call&Distributions data'!$A:$A,INDEX('Capital Call&Distributions data'!$C:$O,0,MIN(MAX(YEAR(M$41)-YEAR($K85)+$J85+1,1),14)))),0)} -> 0 | N85: {=IFERROR(IF(N$41<$K85,0,$F85*_xlfn.XLOOKUP($D85,'Capital Call&Distributions data'!$A:$A,INDEX('Capital Call&Distributions data'!$C:$O,0,MIN(MAX(YEAR(N$41)-YEAR($K85)+$J85+1,1),14)))),0)} -> 0 | O85: {=IFERROR(IF(O$41<$K85,0,$F85*_xlfn.XLOOKUP($D85,'Capital Call&Distributions data'!$A:$A,INDEX('Capital Call&Distributions data'!$C:$O,0,MIN(MAX(YEAR(O$41)-YEAR($K85)+$J85+1,1),14)))),0)} -> 0 | P85: {=IFERROR(IF(P$41<$K85,0,$F85*_xlfn.XLOOKUP($D85,'Capital Call&Distributions data'!$A:$A,INDEX('Capital Call&Distributions data'!$C:$O,0,MIN(MAX(YEAR(P$41)-YEAR($K85)+$J85+1,1),14)))),0)} -> 0 | Q85: {=IFERROR(IF(Q$41<$K85,0,$F85*_xlfn.XLOOKUP($D85,'Capital Call&Distributions data'!$A:$A,INDEX('Capital Call&Distributions data'!$C:$O,0,MIN(MAX(YEAR(Q$41)-YEAR($K85)+$J85+1,1),14)))),0)} -> 0 | R85: {=IFERROR(IF(R$41<$K85,0,$F85*_xlfn.XLOOKUP($D85,'Capital Call&Distributions data'!$A:$A,INDEX('Capital Call&Distributions data'!$C:$O,0,MIN(MAX(YEAR(R$41)-YEAR($K85)+$J85+1,1),14)))),0)} -> 0 | S85: {=IFERROR(IF(S$41<$K85,0,$F85*_xlfn.XLOOKUP($D85,'Capital Call&Distributions data'!$A:$A,INDEX('Capital Call&Distributions data'!$C:$O,0,MIN(MAX(YEAR(S$41)-YEAR($K85)+$J85+1,1),14)))),0)} -> 0 | ... AU85: {=IFERROR(IF(AU$41<$K85,0,$F85*_xlfn.XLOOKUP($D85,'Capital Call&Distributions data'!$A:$A,INDEX('Capital Call&Distributions data'!$C:$O,0,MIN(MAX(YEAR(AU$41)-YEAR($K85)+$J85+1,1),14)))),0)} -> 0
D86: =_xlfn.XLOOKUP(C86,Fondsen!B:B,Fondsen!C:C,"0",0,1) -> 0 | E86: EUR | F86: Netted in year 2/3 | G86: =IFERROR(IF(SUM(OFFSET(INDEX('Capital Call&Distributions data'!A:A,MATCH(D86,'Capital Call&Distributions data'!A:A,0)),-1,2,1,1000))=0,"✔",""),"") | H86: =IFERROR(IRR(L86:AD86),"") | I86: 45658 | J86: =YEAR(K86)-YEAR(I86) -> 0 | K86: 45658 | L86: {=IFERROR(IF(L$41<$K86,0,$F86*_xlfn.XLOOKUP($D86,'Capital Call&Distributions data'!$A:$A,INDEX('Capital Call&Distributions data'!$C:$O,0,MIN(MAX(YEAR(L$41)-YEAR($K86)+$J86+1,1),14)))),0)} -> 0 | M86: {=IFERROR(IF(M$41<$K86,0,$F86*_xlfn.XLOOKUP($D86,'Capital Call&Distributions data'!$A:$A,INDEX('Capital Call&Distributions data'!$C:$O,0,MIN(MAX(YEAR(M$41)-YEAR($K86)+$J86+1,1),14)))),0)} -> 0 | N86: {=IFERROR(IF(N$41<$K86,0,$F86*_xlfn.XLOOKUP($D86,'Capital Call&Distributions data'!$A:$A,INDEX('Capital Call&Distributions data'!$C:$O,0,MIN(MAX(YEAR(N$41)-YEAR($K86)+$J86+1,1),14)))),0)} -> 0 | O86: {=IFERROR(IF(O$41<$K86,0,$F86*_xlfn.XLOOKUP($D86,'Capital Call&Distributions data'!$A:$A,INDEX('Capital Call&Distributions data'!$C:$O,0,MIN(MAX(YEAR(O$41)-YEAR($K86)+$J86+1,1),14)))),0)} -> 0 | P86: {=IFERROR(IF(P$41<$K86,0,$F86*_xlfn.XLOOKUP($D86,'Capital Call&Distributions data'!$A:$A,INDEX('Capital Call&Distributions data'!$C:$O,0,MIN(MAX(YEAR(P$41)-YEAR($K86)+$J86+1,1),14)))),0)} -> 0 | Q86: {=IFERROR(IF(Q$41<$K86,0,$F86*_xlfn.XLOOKUP($D86,'Capital Call&Distributions data'!$A:$A,INDEX('Capital Call&Distributions data'!$C:$O,0,MIN(MAX(YEAR(Q$41)-YEAR($K86)+$J86+1,1),14)))),0)} -> 0 | R86: {=IFERROR(IF(R$41<$K86,0,$F86*_xlfn.XLOOKUP($D86,'Capital Call&Distributions data'!$A:$A,INDEX('Capital Call&Distributions data'!$C:$O,0,MIN(MAX(YEAR(R$41)-YEAR($K86)+$J86+1,1),14)))),0)} -> 0 | S86: {=IFERROR(IF(S$41<$K86,0,$F86*_xlfn.XLOOKUP($D86,'Capital Call&Distributions data'!$A:$A,INDEX('Capital Call&Distributions data'!$C:$O,0,MIN(MAX(YEAR(S$41)-YEAR($K86)+$J86+1,1),14)))),0)} -> 0 | ... AU86: {=IFERROR(IF(AU$41<$K86,0,$F86*_xlfn.XLOOKUP($D86,'Capital Call&Distributions data'!$A:$A,INDEX('Capital Call&Distributions data'!$C:$O,0,MIN(MAX(YEAR(AU$41)-YEAR($K86)+$J86+1,1),14)))),0)} -> 0
D87: =_xlfn.XLOOKUP(C87,Fondsen!B:B,Fondsen!C:C,"0",0,1) -> 0 | E87: EUR | F87: Netted in year 2/4 | G87: =IFERROR(IF(SUM(OFFSET(INDEX('Capital Call&Distributions data'!A:A,MATCH(D87,'Capital Call&Distributions data'!A:A,0)),-1,2,1,1000))=0,"✔",""),"") | H87: =IFERROR(IRR(L87:AD87),"") | I87: 45658 | J87: =YEAR(K87)-YEAR(I87) -> 0 | K87: 45658 | L87: {=IFERROR(IF(L$41<$K87,0,$F87*_xlfn.XLOOKUP($D87,'Capital Call&Distributions data'!$A:$A,INDEX('Capital Call&Distributions data'!$C:$O,0,MIN(MAX(YEAR(L$41)-YEAR($K87)+$J87+1,1),14)))),0)} -> 0 | M87: {=IFERROR(IF(M$41<$K87,0,$F87*_xlfn.XLOOKUP($D87,'Capital Call&Distributions data'!$A:$A,INDEX('Capital Call&Distributions data'!$C:$O,0,MIN(MAX(YEAR(M$41)-YEAR($K87)+$J87+1,1),14)))),0)} -> 0 | N87: {=IFERROR(IF(N$41<$K87,0,$F87*_xlfn.XLOOKUP($D87,'Capital Call&Distributions data'!$A:$A,INDEX('Capital Call&Distributions data'!$C:$O,0,MIN(MAX(YEAR(N$41)-YEAR($K87)+$J87+1,1),14)))),0)} -> 0 | O87: {=IFERROR(IF(O$41<$K87,0,$F87*_xlfn.XLOOKUP($D87,'Capital Call&Distributions data'!$A:$A,INDEX('Capital Call&Distributions data'!$C:$O,0,MIN(MAX(YEAR(O$41)-YEAR($K87)+$J87+1,1),14)))),0)} -> 0 | P87: {=IFERROR(IF(P$41<$K87,0,$F87*_xlfn.XLOOKUP($D87,'Capital Call&Distributions data'!$A:$A,INDEX('Capital Call&Distributions data'!$C:$O,0,MIN(MAX(YEAR(P$41)-YEAR($K87)+$J87+1,1),14)))),0)} -> 0 | Q87: {=IFERROR(IF(Q$41<$K87,0,$F87*_xlfn.XLOOKUP($D87,'Capital Call&Distributions data'!$A:$A,INDEX('Capital Call&Distributions data'!$C:$O,0,MIN(MAX(YEAR(Q$41)-YEAR($K87)+$J87+1,1),14)))),0)} -> 0 | R87: {=IFERROR(IF(R$41<$K87,0,$F87*_xlfn.XLOOKUP($D87,'Capital Call&Distributions data'!$A:$A,INDEX('Capital Call&Distributions data'!$C:$O,0,MIN(MAX(YEAR(R$41)-YEAR($K87)+$J87+1,1),14)))),0)} -> 0 | S87: {=IFERROR(IF(S$41<$K87,0,$F87*_xlfn.XLOOKUP($D87,'Capital Call&Distributions data'!$A:$A,INDEX('Capital Call&Distributions data'!$C:$O,0,MIN(MAX(YEAR(S$41)-YEAR($K87)+$J87+1,1),14)))),0)} -> 0 | ... AU87: {=IFERROR(IF(AU$41<$K87,0,$F87*_xlfn.XLOOKUP($D87,'Capital Call&Distributions data'!$A:$A,INDEX('Capital Call&Distributions data'!$C:$O,0,MIN(MAX(YEAR(AU$41)-YEAR($K87)+$J87+1,1),14)))),0)} -> 0
D88: =_xlfn.XLOOKUP(C88,Fondsen!B:B,Fondsen!C:C,"0",0,1) -> 0 | E88: EUR | F88: Netted in year 2/3 | G88: =IFERROR(IF(SUM(OFFSET(INDEX('Capital Call&Distributions data'!A:A,MATCH(D88,'Capital Call&Distributions data'!A:A,0)),-1,2,1,1000))=0,"✔",""),"") | H88: =IFERROR(IRR(L88:AD88),"") | I88: 45658 | J88: =YEAR(K88)-YEAR(I88) -> 0 | K88: 45658 | L88: {=IFERROR(IF(L$41<$K88,0,$F88*_xlfn.XLOOKUP($D88,'Capital Call&Distributions data'!$A:$A,INDEX('Capital Call&Distributions data'!$C:$O,0,MIN(MAX(YEAR(L$41)-YEAR($K88)+$J88+1,1),14)))),0)} -> 0 | M88: {=IFERROR(IF(M$41<$K88,0,$F88*_xlfn.XLOOKUP($D88,'Capital Call&Distributions data'!$A:$A,INDEX('Capital Call&Distributions data'!$C:$O,0,MIN(MAX(YEAR(M$41)-YEAR($K88)+$J88+1,1),14)))),0)} -> 0 | N88: {=IFERROR(IF(N$41<$K88,0,$F88*_xlfn.XLOOKUP($D88,'Capital Call&Distributions data'!$A:$A,INDEX('Capital Call&Distributions data'!$C:$O,0,MIN(MAX(YEAR(N$41)-YEAR($K88)+$J88+1,1),14)))),0)} -> 0 | O88: {=IFERROR(IF(O$41<$K88,0,$F88*_xlfn.XLOOKUP($D88,'Capital Call&Distributions data'!$A:$A,INDEX('Capital Call&Distributions data'!$C:$O,0,MIN(MAX(YEAR(O$41)-YEAR($K88)+$J88+1,1),14)))),0)} -> 0 | P88: {=IFERROR(IF(P$41<$K88,0,$F88*_xlfn.XLOOKUP($D88,'Capital Call&Distributions data'!$A:$A,INDEX('Capital Call&Distributions data'!$C:$O,0,MIN(MAX(YEAR(P$41)-YEAR($K88)+$J88+1,1),14)))),0)} -> 0 | Q88: {=IFERROR(IF(Q$41<$K88,0,$F88*_xlfn.XLOOKUP($D88,'Capital Call&Distributions data'!$A:$A,INDEX('Capital Call&Distributions data'!$C:$O,0,MIN(MAX(YEAR(Q$41)-YEAR($K88)+$J88+1,1),14)))),0)} -> 0 | R88: {=IFERROR(IF(R$41<$K88,0,$F88*_xlfn.XLOOKUP($D88,'Capital Call&Distributions data'!$A:$A,INDEX('Capital Call&Distributions data'!$C:$O,0,MIN(MAX(YEAR(R$41)-YEAR($K88)+$J88+1,1),14)))),0)} -> 0 | S88: {=IFERROR(IF(S$41<$K88,0,$F88*_xlfn.XLOOKUP($D88,'Capital Call&Distributions data'!$A:$A,INDEX('Capital Call&Distributions data'!$C:$O,0,MIN(MAX(YEAR(S$41)-YEAR($K88)+$J88+1,1),14)))),0)} -> 0 | ... AU88: {=IFERROR(IF(AU$41<$K88,0,$F88*_xlfn.XLOOKUP($D88,'Capital Call&Distributions data'!$A:$A,INDEX('Capital Call&Distributions data'!$C:$O,0,MIN(MAX(YEAR(AU$41)-YEAR($K88)+$J88+1,1),14)))),0)} -> 0
D89: =_xlfn.XLOOKUP(C89,Fondsen!B:B,Fondsen!C:C,"0",0,1) -> 0 | E89: EUR | F89: Netted in year 2/3 | G89: =IFERROR(IF(SUM(OFFSET(INDEX('Capital Call&Distributions data'!A:A,MATCH(D89,'Capital Call&Distributions data'!A:A,0)),-1,2,1,1000))=0,"✔",""),"") | H89: =IFERROR(IRR(L89:AD89),"") | I89: 45658 | J89: =YEAR(K89)-YEAR(I89) -> 0 | K89: 45658 | L89: {=IFERROR(IF(L$41<$K89,0,$F89*_xlfn.XLOOKUP($D89,'Capital Call&Distributions data'!$A:$A,INDEX('Capital Call&Distributions data'!$C:$O,0,MIN(MAX(YEAR(L$41)-YEAR($K89)+$J89+1,1),14)))),0)} -> 0 | M89: {=IFERROR(IF(M$41<$K89,0,$F89*_xlfn.XLOOKUP($D89,'Capital Call&Distributions data'!$A:$A,INDEX('Capital Call&Distributions data'!$C:$O,0,MIN(MAX(YEAR(M$41)-YEAR($K89)+$J89+1,1),14)))),0)} -> 0 | N89: {=IFERROR(IF(N$41<$K89,0,$F89*_xlfn.XLOOKUP($D89,'Capital Call&Distributions data'!$A:$A,INDEX('Capital Call&Distributions data'!$C:$O,0,MIN(MAX(YEAR(N$41)-YEAR($K89)+$J89+1,1),14)))),0)} -> 0 | O89: {=IFERROR(IF(O$41<$K89,0,$F89*_xlfn.XLOOKUP($D89,'Capital Call&Distributions data'!$A:$A,INDEX('Capital Call&Distributions data'!$C:$O,0,MIN(MAX(YEAR(O$41)-YEAR($K89)+$J89+1,1),14)))),0)} -> 0 | P89: {=IFERROR(IF(P$41<$K89,0,$F89*_xlfn.XLOOKUP($D89,'Capital Call&Distributions data'!$A:$A,INDEX('Capital Call&Distributions data'!$C:$O,0,MIN(MAX(YEAR(P$41)-YEAR($K89)+$J89+1,1),14)))),0)} -> 0 | Q89: {=IFERROR(IF(Q$41<$K89,0,$F89*_xlfn.XLOOKUP($D89,'Capital Call&Distributions data'!$A:$A,INDEX('Capital Call&Distributions data'!$C:$O,0,MIN(MAX(YEAR(Q$41)-YEAR($K89)+$J89+1,1),14)))),0)} -> 0 | R89: {=IFERROR(IF(R$41<$K89,0,$F89*_xlfn.XLOOKUP($D89,'Capital Call&Distributions data'!$A:$A,INDEX('Capital Call&Distributions data'!$C:$O,0,MIN(MAX(YEAR(R$41)-YEAR($K89)+$J89+1,1),14)))),0)} -> 0 | S89: {=IFERROR(IF(S$41<$K89,0,$F89*_xlfn.XLOOKUP($D89,'Capital Call&Distributions data'!$A:$A,INDEX('Capital Call&Distributions data'!$C:$O,0,MIN(MAX(YEAR(S$41)-YEAR($K89)+$J89+1,1),14)))),0)} -> 0 | ... AU89: {=IFERROR(IF(AU$41<$K89,0,$F89*_xlfn.XLOOKUP($D89,'Capital Call&Distributions data'!$A:$A,INDEX('Capital Call&Distributions data'!$C:$O,0,MIN(MAX(YEAR(AU$41)-YEAR($K89)+$J89+1,1),14)))),0)} -> 0
D90: =_xlfn.XLOOKUP(C90,Fondsen!B:B,Fondsen!C:C,"0",0,1) -> 0 | E90: EUR | F90: Netted in year 2/3 | G90: =IFERROR(IF(SUM(OFFSET(INDEX('Capital Call&Distributions data'!A:A,MATCH(D90,'Capital Call&Distributions data'!A:A,0)),-1,2,1,1000))=0,"✔",""),"") | H90: =IFERROR(IRR(L90:AD90),"") | I90: 45658 | J90: =YEAR(K90)-YEAR(I90) -> 0 | K90: 45658 | L90: {=IFERROR(IF(L$41<$K90,0,$F90*_xlfn.XLOOKUP($D90,'Capital Call&Distributions data'!$A:$A,INDEX('Capital Call&Distributions data'!$C:$O,0,MIN(MAX(YEAR(L$41)-YEAR($K90)+$J90+1,1),14)))),0)} -> 0 | M90: {=IFERROR(IF(M$41<$K90,0,$F90*_xlfn.XLOOKUP($D90,'Capital Call&Distributions data'!$A:$A,INDEX('Capital Call&Distributions data'!$C:$O,0,MIN(MAX(YEAR(M$41)-YEAR($K90)+$J90+1,1),14)))),0)} -> 0 | N90: {=IFERROR(IF(N$41<$K90,0,$F90*_xlfn.XLOOKUP($D90,'Capital Call&Distributions data'!$A:$A,INDEX('Capital Call&Distributions data'!$C:$O,0,MIN(MAX(YEAR(N$41)-YEAR($K90)+$J90+1,1),14)))),0)} -> 0 | O90: {=IFERROR(IF(O$41<$K90,0,$F90*_xlfn.XLOOKUP($D90,'Capital Call&Distributions data'!$A:$A,INDEX('Capital Call&Distributions data'!$C:$O,0,MIN(MAX(YEAR(O$41)-YEAR($K90)+$J90+1,1),14)))),0)} -> 0 | P90: {=IFERROR(IF(P$41<$K90,0,$F90*_xlfn.XLOOKUP($D90,'Capital Call&Distributions data'!$A:$A,INDEX('Capital Call&Distributions data'!$C:$O,0,MIN(MAX(YEAR(P$41)-YEAR($K90)+$J90+1,1),14)))),0)} -> 0 | Q90: {=IFERROR(IF(Q$41<$K90,0,$F90*_xlfn.XLOOKUP($D90,'Capital Call&Distributions data'!$A:$A,INDEX('Capital Call&Distributions data'!$C:$O,0,MIN(MAX(YEAR(Q$41)-YEAR($K90)+$J90+1,1),14)))),0)} -> 0 | R90: {=IFERROR(IF(R$41<$K90,0,$F90*_xlfn.XLOOKUP($D90,'Capital Call&Distributions data'!$A:$A,INDEX('Capital Call&Distributions data'!$C:$O,0,MIN(MAX(YEAR(R$41)-YEAR($K90)+$J90+1,1),14)))),0)} -> 0 | S90: {=IFERROR(IF(S$41<$K90,0,$F90*_xlfn.XLOOKUP($D90,'Capital Call&Distributions data'!$A:$A,INDEX('Capital Call&Distributions data'!$C:$O,0,MIN(MAX(YEAR(S$41)-YEAR($K90)+$J90+1,1),14)))),0)} -> 0 | ... AU90: {=IFERROR(IF(AU$41<$K90,0,$F90*_xlfn.XLOOKUP($D90,'Capital Call&Distributions data'!$A:$A,INDEX('Capital Call&Distributions data'!$C:$O,0,MIN(MAX(YEAR(AU$41)-YEAR($K90)+$J90+1,1),14)))),0)} -> 0
D91: =_xlfn.XLOOKUP(C91,Fondsen!B:B,Fondsen!C:C,"0",0,1) -> 0 | E91: EUR | F91: Netted in year 2/3 | G91: =IFERROR(IF(SUM(OFFSET(INDEX('Capital Call&Distributions data'!A:A,MATCH(D91,'Capital Call&Distributions data'!A:A,0)),-1,2,1,1000))=0,"✔",""),"") | H91: =IFERROR(IRR(L91:AD91),"") | I91: 45658 | J91: =YEAR(K91)-YEAR(I91) -> 0 | K91: 45658 | L91: {=IFERROR(IF(L$41<$K91,0,$F91*_xlfn.XLOOKUP($D91,'Capital Call&Distributions data'!$A:$A,INDEX('Capital Call&Distributions data'!$C:$O,0,MIN(MAX(YEAR(L$41)-YEAR($K91)+$J91+1,1),14)))),0)} -> 0 | M91: {=IFERROR(IF(M$41<$K91,0,$F91*_xlfn.XLOOKUP($D91,'Capital Call&Distributions data'!$A:$A,INDEX('Capital Call&Distributions data'!$C:$O,0,MIN(MAX(YEAR(M$41)-YEAR($K91)+$J91+1,1),14)))),0)} -> 0 | N91: {=IFERROR(IF(N$41<$K91,0,$F91*_xlfn.XLOOKUP($D91,'Capital Call&Distributions data'!$A:$A,INDEX('Capital Call&Distributions data'!$C:$O,0,MIN(MAX(YEAR(N$41)-YEAR($K91)+$J91+1,1),14)))),0)} -> 0 | O91: {=IFERROR(IF(O$41<$K91,0,$F91*_xlfn.XLOOKUP($D91,'Capital Call&Distributions data'!$A:$A,INDEX('Capital Call&Distributions data'!$C:$O,0,MIN(MAX(YEAR(O$41)-YEAR($K91)+$J91+1,1),14)))),0)} -> 0 | P91: {=IFERROR(IF(P$41<$K91,0,$F91*_xlfn.XLOOKUP($D91,'Capital Call&Distributions data'!$A:$A,INDEX('Capital Call&Distributions data'!$C:$O,0,MIN(MAX(YEAR(P$41)-YEAR($K91)+$J91+1,1),14)))),0)} -> 0 | Q91: {=IFERROR(IF(Q$41<$K91,0,$F91*_xlfn.XLOOKUP($D91,'Capital Call&Distributions data'!$A:$A,INDEX('Capital Call&Distributions data'!$C:$O,0,MIN(MAX(YEAR(Q$41)-YEAR($K91)+$J91+1,1),14)))),0)} -> 0 | R91: {=IFERROR(IF(R$41<$K91,0,$F91*_xlfn.XLOOKUP($D91,'Capital Call&Distributions data'!$A:$A,INDEX('Capital Call&Distributions data'!$C:$O,0,MIN(MAX(YEAR(R$41)-YEAR($K91)+$J91+1,1),14)))),0)} -> 0 | S91: {=IFERROR(IF(S$41<$K91,0,$F91*_xlfn.XLOOKUP($D91,'Capital Call&Distributions data'!$A:$A,INDEX('Capital Call&Distributions data'!$C:$O,0,MIN(MAX(YEAR(S$41)-YEAR($K91)+$J91+1,1),14)))),0)} -> 0 | ... AU91: {=IFERROR(IF(AU$41<$K91,0,$F91*_xlfn.XLOOKUP($D91,'Capital Call&Distributions data'!$A:$A,INDEX('Capital Call&Distributions data'!$C:$O,0,MIN(MAX(YEAR(AU$41)-YEAR($K91)+$J91+1,1),14)))),0)} -> 0
D92: =_xlfn.XLOOKUP(C92,Fondsen!B:B,Fondsen!C:C,"0",0,1) -> 0 | E92: EUR | F92: Netted in year 2/3 | G92: =IFERROR(IF(SUM(OFFSET(INDEX('Capital Call&Distributions data'!A:A,MATCH(D92,'Capital Call&Distributions data'!A:A,0)),-1,2,1,1000))=0,"✔",""),"") | H92: =IFERROR(IRR(L92:AD92),"") | I92: 45658 | J92: =YEAR(K92)-YEAR(I92) -> 0 | K92: 45658 | L92: {=IFERROR(IF(L$41<$K92,0,$F92*_xlfn.XLOOKUP($D92,'Capital Call&Distributions data'!$A:$A,INDEX('Capital Call&Distributions data'!$C:$O,0,MIN(MAX(YEAR(L$41)-YEAR($K92)+$J92+1,1),14)))),0)} -> 0 | M92: {=IFERROR(IF(M$41<$K92,0,$F92*_xlfn.XLOOKUP($D92,'Capital Call&Distributions data'!$A:$A,INDEX('Capital Call&Distributions data'!$C:$O,0,MIN(MAX(YEAR(M$41)-YEAR($K92)+$J92+1,1),14)))),0)} -> 0 | N92: {=IFERROR(IF(N$41<$K92,0,$F92*_xlfn.XLOOKUP($D92,'Capital Call&Distributions data'!$A:$A,INDEX('Capital Call&Distributions data'!$C:$O,0,MIN(MAX(YEAR(N$41)-YEAR($K92)+$J92+1,1),14)))),0)} -> 0 | O92: {=IFERROR(IF(O$41<$K92,0,$F92*_xlfn.XLOOKUP($D92,'Capital Call&Distributions data'!$A:$A,INDEX('Capital Call&Distributions data'!$C:$O,0,MIN(MAX(YEAR(O$41)-YEAR($K92)+$J92+1,1),14)))),0)} -> 0 | P92: {=IFERROR(IF(P$41<$K92,0,$F92*_xlfn.XLOOKUP($D92,'Capital Call&Distributions data'!$A:$A,INDEX('Capital Call&Distributions data'!$C:$O,0,MIN(MAX(YEAR(P$41)-YEAR($K92)+$J92+1,1),14)))),0)} -> 0 | Q92: {=IFERROR(IF(Q$41<$K92,0,$F92*_xlfn.XLOOKUP($D92,'Capital Call&Distributions data'!$A:$A,INDEX('Capital Call&Distributions data'!$C:$O,0,MIN(MAX(YEAR(Q$41)-YEAR($K92)+$J92+1,1),14)))),0)} -> 0 | R92: {=IFERROR(IF(R$41<$K92,0,$F92*_xlfn.XLOOKUP($D92,'Capital Call&Distributions data'!$A:$A,INDEX('Capital Call&Distributions data'!$C:$O,0,MIN(MAX(YEAR(R$41)-YEAR($K92)+$J92+1,1),14)))),0)} -> 0 | S92: {=IFERROR(IF(S$41<$K92,0,$F92*_xlfn.XLOOKUP($D92,'Capital Call&Distributions data'!$A:$A,INDEX('Capital Call&Distributions data'!$C:$O,0,MIN(MAX(YEAR(S$41)-YEAR($K92)+$J92+1,1),14)))),0)} -> 0 | ... AU92: {=IFERROR(IF(AU$41<$K92,0,$F92*_xlfn.XLOOKUP($D92,'Capital Call&Distributions data'!$A:$A,INDEX('Capital Call&Distributions data'!$C:$O,0,MIN(MAX(YEAR(AU$41)-YEAR($K92)+$J92+1,1),14)))),0)} -> 0
... D97: =_xlfn.XLOOKUP(C97,Fondsen!B:B,Fondsen!C:C,"0",0,1) -> 0 | E97: EUR | F97: Netted in year 2/3 | G97: =IFERROR(IF(SUM(OFFSET(INDEX('Capital Call&Distributions data'!A:A,MATCH(D97,'Capital Call&Distributions data'!A:A,0)),-1,2,1,1000))=0,"✔",""),"") | H97: =IFERROR(IRR(L97:AD97),"") | I97: 45658 | J97: =YEAR(K97)-YEAR(I97) -> 0 | K97: 45658 | L97: {=IFERROR(IF(L$41<$K97,0,$F97*_xlfn.XLOOKUP($D97,'Capital Call&Distributions data'!$A:$A,INDEX('Capital Call&Distributions data'!$C:$O,0,MIN(MAX(YEAR(L$41)-YEAR($K97)+$J97+1,1),14)))),0)} -> 0 | M97: {=IFERROR(IF(M$41<$K97,0,$F97*_xlfn.XLOOKUP($D97,'Capital Call&Distributions data'!$A:$A,INDEX('Capital Call&Distributions data'!$C:$O,0,MIN(MAX(YEAR(M$41)-YEAR($K97)+$J97+1,1),14)))),0)} -> 0 | N97: {=IFERROR(IF(N$41<$K97,0,$F97*_xlfn.XLOOKUP($D97,'Capital Call&Distributions data'!$A:$A,INDEX('Capital Call&Distributions data'!$C:$O,0,MIN(MAX(YEAR(N$41)-YEAR($K97)+$J97+1,1),14)))),0)} -> 0 | O97: {=IFERROR(IF(O$41<$K97,0,$F97*_xlfn.XLOOKUP($D97,'Capital Call&Distributions data'!$A:$A,INDEX('Capital Call&Distributions data'!$C:$O,0,MIN(MAX(YEAR(O$41)-YEAR($K97)+$J97+1,1),14)))),0)} -> 0 | P97: {=IFERROR(IF(P$41<$K97,0,$F97*_xlfn.XLOOKUP($D97,'Capital Call&Distributions data'!$A:$A,INDEX('Capital Call&Distributions data'!$C:$O,0,MIN(MAX(YEAR(P$41)-YEAR($K97)+$J97+1,1),14)))),0)} -> 0 | Q97: {=IFERROR(IF(Q$41<$K97,0,$F97*_xlfn.XLOOKUP($D97,'Capital Call&Distributions data'!$A:$A,INDEX('Capital Call&Distributions data'!$C:$O,0,MIN(MAX(YEAR(Q$41)-YEAR($K97)+$J97+1,1),14)))),0)} -> 0 | R97: {=IFERROR(IF(R$41<$K97,0,$F97*_xlfn.XLOOKUP($D97,'Capital Call&Distributions data'!$A:$A,INDEX('Capital Call&Distributions data'!$C:$O,0,MIN(MAX(YEAR(R$41)-YEAR($K97)+$J97+1,1),14)))),0)} -> 0 | S97: {=IFERROR(IF(S$41<$K97,0,$F97*_xlfn.XLOOKUP($D97,'Capital Call&Distributions data'!$A:$A,INDEX('Capital Call&Distributions data'!$C:$O,0,MIN(MAX(YEAR(S$41)-YEAR($K97)+$J97+1,1),14)))),0)} -> 0 | ... AU97: {=IFERROR(IF(AU$41<$K97,0,$F97*_xlfn.XLOOKUP($D97,'Capital Call&Distributions data'!$A:$A,INDEX('Capital Call&Distributions data'!$C:$O,0,MIN(MAX(YEAR(AU$41)-YEAR($K97)+$J97+1,1),14)))),0)} -> 0
D98: =_xlfn.XLOOKUP(C98,Fondsen!B:B,Fondsen!C:C,"0",0,1) -> 0 | E98: EUR | G98: =IFERROR(IF(SUM(OFFSET(INDEX('Capital Call&Distributions data'!A:A,MATCH(D98,'Capital Call&Distributions data'!A:A,0)),-1,2,1,1000))=0,"✔",""),"") | H98: =IFERROR(IRR(L98:AD98),"") | I98: 45658 | J98: =YEAR(K98)-YEAR(I98) -> 0 | K98: 45658 | L98: {=IFERROR(IF(L$41<$K98,0,$F98*_xlfn.XLOOKUP($D98,'Capital Call&Distributions data'!$A:$A,INDEX('Capital Call&Distributions data'!$C:$O,0,MIN(MAX(YEAR(L$41)-YEAR($K98)+$J98+1,1),14)))),0)} -> 0 | M98: {=IFERROR(IF(M$41<$K98,0,$F98*_xlfn.XLOOKUP($D98,'Capital Call&Distributions data'!$A:$A,INDEX('Capital Call&Distributions data'!$C:$O,0,MIN(MAX(YEAR(M$41)-YEAR($K98)+$J98+1,1),14)))),0)} -> 0 | N98: {=IFERROR(IF(N$41<$K98,0,$F98*_xlfn.XLOOKUP($D98,'Capital Call&Distributions data'!$A:$A,INDEX('Capital Call&Distributions data'!$C:$O,0,MIN(MAX(YEAR(N$41)-YEAR($K98)+$J98+1,1),14)))),0)} -> 0 | O98: {=IFERROR(IF(O$41<$K98,0,$F98*_xlfn.XLOOKUP($D98,'Capital Call&Distributions data'!$A:$A,INDEX('Capital Call&Distributions data'!$C:$O,0,MIN(MAX(YEAR(O$41)-YEAR($K98)+$J98+1,1),14)))),0)} -> 0 | P98: {=IFERROR(IF(P$41<$K98,0,$F98*_xlfn.XLOOKUP($D98,'Capital Call&Distributions data'!$A:$A,INDEX('Capital Call&Distributions data'!$C:$O,0,MIN(MAX(YEAR(P$41)-YEAR($K98)+$J98+1,1),14)))),0)} -> 0 | Q98: {=IFERROR(IF(Q$41<$K98,0,$F98*_xlfn.XLOOKUP($D98,'Capital Call&Distributions data'!$A:$A,INDEX('Capital Call&Distributions data'!$C:$O,0,MIN(MAX(YEAR(Q$41)-YEAR($K98)+$J98+1,1),14)))),0)} -> 0 | R98: {=IFERROR(IF(R$41<$K98,0,$F98*_xlfn.XLOOKUP($D98,'Capital Call&Distributions data'!$A:$A,INDEX('Capital Call&Distributions data'!$C:$O,0,MIN(MAX(YEAR(R$41)-YEAR($K98)+$J98+1,1),14)))),0)} -> 0 | S98: {=IFERROR(IF(S$41<$K98,0,$F98*_xlfn.XLOOKUP($D98,'Capital Call&Distributions data'!$A:$A,INDEX('Capital Call&Distributions data'!$C:$O,0,MIN(MAX(YEAR(S$41)-YEAR($K98)+$J98+1,1),14)))),0)} -> 0 | ... AU98: {=IFERROR(IF(AU$41<$K98,0,$F98*_xlfn.XLOOKUP($D98,'Capital Call&Distributions data'!$A:$A,INDEX('Capital Call&Distributions data'!$C:$O,0,MIN(MAX(YEAR(AU$41)-YEAR($K98)+$J98+1,1),14)))),0)} -> 0
D99: =_xlfn.XLOOKUP(C99,Fondsen!B:B,Fondsen!C:C,"0",0,1) -> 0 | E99: EUR | G99: =IFERROR(IF(SUM(OFFSET(INDEX('Capital Call&Distributions data'!A:A,MATCH(D99,'Capital Call&Distributions data'!A:A,0)),-1,2,1,1000))=0,"✔",""),"") | H99: =IFERROR(IRR(L99:AD99),"") | I99: 45292 | J99: =YEAR(K99)-YEAR(I99) -> 0 | K99: 45292 | L99: {=IFERROR(IF(L$41<$K99,0,$F99*_xlfn.XLOOKUP($D99,'Capital Call&Distributions data'!$A:$A,INDEX('Capital Call&Distributions data'!$C:$O,0,MIN(MAX(YEAR(L$41)-YEAR($K99)+$J99+1,1),14)))),0)} -> 0 | M99: {=IFERROR(IF(M$41<$K99,0,$F99*_xlfn.XLOOKUP($D99,'Capital Call&Distributions data'!$A:$A,INDEX('Capital Call&Distributions data'!$C:$O,0,MIN(MAX(YEAR(M$41)-YEAR($K99)+$J99+1,1),14)))),0)} -> 0 | N99: {=IFERROR(IF(N$41<$K99,0,$F99*_xlfn.XLOOKUP($D99,'Capital Call&Distributions data'!$A:$A,INDEX('Capital Call&Distributions data'!$C:$O,0,MIN(MAX(YEAR(N$41)-YEAR($K99)+$J99+1,1),14)))),0)} -> 0 | O99: {=IFERROR(IF(O$41<$K99,0,$F99*_xlfn.XLOOKUP($D99,'Capital Call&Distributions data'!$A:$A,INDEX('Capital Call&Distributions data'!$C:$O,0,MIN(MAX(YEAR(O$41)-YEAR($K99)+$J99+1,1),14)))),0)} -> 0 | P99: {=IFERROR(IF(P$41<$K99,0,$F99*_xlfn.XLOOKUP($D99,'Capital Call&Distributions data'!$A:$A,INDEX('Capital Call&Distributions data'!$C:$O,0,MIN(MAX(YEAR(P$41)-YEAR($K99)+$J99+1,1),14)))),0)} -> 0 | Q99: {=IFERROR(IF(Q$41<$K99,0,$F99*_xlfn.XLOOKUP($D99,'Capital Call&Distributions data'!$A:$A,INDEX('Capital Call&Distributions data'!$C:$O,0,MIN(MAX(YEAR(Q$41)-YEAR($K99)+$J99+1,1),14)))),0)} -> 0 | R99: {=IFERROR(IF(R$41<$K99,0,$F99*_xlfn.XLOOKUP($D99,'Capital Call&Distributions data'!$A:$A,INDEX('Capital Call&Distributions data'!$C:$O,0,MIN(MAX(YEAR(R$41)-YEAR($K99)+$J99+1,1),14)))),0)} -> 0 | S99: {=IFERROR(IF(S$41<$K99,0,$F99*_xlfn.XLOOKUP($D99,'Capital Call&Distributions data'!$A:$A,INDEX('Capital Call&Distributions data'!$C:$O,0,MIN(MAX(YEAR(S$41)-YEAR($K99)+$J99+1,1),14)))),0)} -> 0 | ... AU99: {=IFERROR(IF(AU$41<$K99,0,$F99*_xlfn.XLOOKUP($D99,'Capital Call&Distributions data'!$A:$A,INDEX('Capital Call&Distributions data'!$C:$O,0,MIN(MAX(YEAR(AU$41)-YEAR($K99)+$J99+1,1),14)))),0)} -> 0
D100: =_xlfn.XLOOKUP(C100,Fondsen!B:B,Fondsen!C:C,"0",0,1) -> 0 | E100: EUR | G100: =IFERROR(IF(SUM(OFFSET(INDEX('Capital Call&Distributions data'!A:A,MATCH(D100,'Capital Call&Distributions data'!A:A,0)),-1,2,1,1000))=0,"✔",""),"") | H100: =IFERROR(IRR(L100:AD100),"") | I100: 45292 | J100: =YEAR(K100)-YEAR(I100) -> 0 | K100: 45292 | L100: {=IFERROR(IF(L$41<$K100,0,$F100*_xlfn.XLOOKUP($D100,'Capital Call&Distributions data'!$A:$A,INDEX('Capital Call&Distributions data'!$C:$O,0,MIN(MAX(YEAR(L$41)-YEAR($K100)+$J100+1,1),14)))),0)} -> 0 | M100: {=IFERROR(IF(M$41<$K100,0,$F100*_xlfn.XLOOKUP($D100,'Capital Call&Distributions data'!$A:$A,INDEX('Capital Call&Distributions data'!$C:$O,0,MIN(MAX(YEAR(M$41)-YEAR($K100)+$J100+1,1),14)))),0)} -> 0 | N100: {=IFERROR(IF(N$41<$K100,0,$F100*_xlfn.XLOOKUP($D100,'Capital Call&Distributions data'!$A:$A,INDEX('Capital Call&Distributions data'!$C:$O,0,MIN(MAX(YEAR(N$41)-YEAR($K100)+$J100+1,1),14)))),0)} -> 0 | O100: {=IFERROR(IF(O$41<$K100,0,$F100*_xlfn.XLOOKUP($D100,'Capital Call&Distributions data'!$A:$A,INDEX('Capital Call&Distributions data'!$C:$O,0,MIN(MAX(YEAR(O$41)-YEAR($K100)+$J100+1,1),14)))),0)} -> 0 | P100: {=IFERROR(IF(P$41<$K100,0,$F100*_xlfn.XLOOKUP($D100,'Capital Call&Distributions data'!$A:$A,INDEX('Capital Call&Distributions data'!$C:$O,0,MIN(MAX(YEAR(P$41)-YEAR($K100)+$J100+1,1),14)))),0)} -> 0 | Q100: {=IFERROR(IF(Q$41<$K100,0,$F100*_xlfn.XLOOKUP($D100,'Capital Call&Distributions data'!$A:$A,INDEX('Capital Call&Distributions data'!$C:$O,0,MIN(MAX(YEAR(Q$41)-YEAR($K100)+$J100+1,1),14)))),0)} -> 0 | R100: {=IFERROR(IF(R$41<$K100,0,$F100*_xlfn.XLOOKUP($D100,'Capital Call&Distributions data'!$A:$A,INDEX('Capital Call&Distributions data'!$C:$O,0,MIN(MAX(YEAR(R$41)-YEAR($K100)+$J100+1,1),14)))),0)} -> 0 | S100: {=IFERROR(IF(S$41<$K100,0,$F100*_xlfn.XLOOKUP($D100,'Capital Call&Distributions data'!$A:$A,INDEX('Capital Call&Distributions data'!$C:$O,0,MIN(MAX(YEAR(S$41)-YEAR($K100)+$J100+1,1),14)))),0)} -> 0 | ... AU100: {=IFERROR(IF(AU$41<$K100,0,$F100*_xlfn.XLOOKUP($D100,'Capital Call&Distributions data'!$A:$A,INDEX('Capital Call&Distributions data'!$C:$O,0,MIN(MAX(YEAR(AU$41)-YEAR($K100)+$J100+1,1),14)))),0)} -> 0
C101: Cumulative Cash Flow | E101: EUR | L101: =SUM(L43:L100) -> -3660881.3 | M101: =L101+SUM(M43:M100) -> -7815303.8 | N101: =M101+SUM(N43:N100) -> -10002771 | O101: =N101+SUM(O43:O100) -> -10002778 | P101: =O101+SUM(P43:P100) -> -10002943 | Q101: =P101+SUM(Q43:Q100) -> -10000747 | R101: =Q101+SUM(R43:R100) -> -10000926 | S101: =R101+SUM(S43:S100) -> -10000200 | T101: =S101+SUM(T43:T100) -> -5370909.7 | ... AU101: =AT101+SUM(AU43:AU100) -> 25938557
C102: Private debt | D102: Jaren | H102: Rente | I102: Start | K102: Einde looptijd
C103: private debt 1 | D103: =J103 -> 1 | E103: EUR | F103: 4154000 | H103: 0.08 | I103: 46023 | J103: =YEAR(K103)-YEAR(I103) -> 1 | K103: 46388 | L103: {=IF(OR(Samenvatting!$C103="",ISBLANK(Samenvatting!$C103)),"0,0",IFERROR(SUMPRODUCT((Renteberekening!$B$2:$B$29=Samenvatting!$C103) * (YEAR(Renteberekening!$J$1:$UK$1)=YEAR(Samenvatting!L$41)) * Renteberekening!$J$2:$UK$29),0))} -> -3930664.9 | M103: {=IF(OR(Samenvatting!$C103="",ISBLANK(Samenvatting!$C103)),"0,0",IFERROR(SUMPRODUCT((Renteberekening!$B$2:$B$29=Samenvatting!$C103) * (YEAR(Renteberekening!$J$1:$UK$1)=YEAR(Samenvatting!M$41)) * Renteberekening!$J$2:$UK$29),0))} -> 4154653 | N103: {=IF(OR(Samenvatting!$C103="",ISBLANK(Samenvatting!$C103)),"0,0",IFERROR(SUMPRODUCT((Renteberekening!$B$2:$B$29=Samenvatting!$C103) * (YEAR(Renteberekening!$J$1:$UK$1)=YEAR(Samenvatting!N$41)) * Renteberekening!$J$2:$UK$29),0))} -> 0 | O103: {=IF(OR(Samenvatting!$C103="",ISBLANK(Samenvatting!$C103)),"0,0",IFERROR(SUMPRODUCT((Renteberekening!$B$2:$B$29=Samenvatting!$C103) * (YEAR(Renteberekening!$J$1:$UK$1)=YEAR(Samenvatting!O$41)) * Renteberekening!$J$2:$UK$29),0))} -> 0 | P103: {=IF(OR(Samenvatting!$C103="",ISBLANK(Samenvatting!$C103)),"0,0",IFERROR(SUMPRODUCT((Renteberekening!$B$2:$B$29=Samenvatting!$C103) * (YEAR(Renteberekening!$J$1:$UK$1)=YEAR(Samenvatting!P$41)) * Renteberekening!$J$2:$UK$29),0))} -> 0 | Q103: {=IF(OR(Samenvatting!$C103="",ISBLANK(Samenvatting!$C103)),"0,0",IFERROR(SUMPRODUCT((Renteberekening!$B$2:$B$29=Samenvatting!$C103) * (YEAR(Renteberekening!$J$1:$UK$1)=YEAR(Samenvatting!Q$41)) * Renteberekening!$J$2:$UK$29),0))} -> 0 | R103: {=IF(OR(Samenvatting!$C103="",ISBLANK(Samenvatting!$C103)),"0,0",IFERROR(SUMPRODUCT((Renteberekening!$B$2:$B$29=Samenvatting!$C103) * (YEAR(Renteberekening!$J$1:$UK$1)=YEAR(Samenvatting!R$41)) * Renteberekening!$J$2:$UK$29),0))} -> 0 | S103: {=IF(OR(Samenvatting!$C103="",ISBLANK(Samenvatting!$C103)),"0,0",IFERROR(SUMPRODUCT((Renteberekening!$B$2:$B$29=Samenvatting!$C103) * (YEAR(Renteberekening!$J$1:$UK$1)=YEAR(Samenvatting!S$41)) * Renteberekening!$J$2:$UK$29),0))} -> 0 | ... AU103: {=IF(OR(Samenvatting!$C103="",ISBLANK(Samenvatting!$C103)),"0,0",IFERROR(SUMPRODUCT((Renteberekening!$B$2:$B$29=Samenvatting!$C103) * (YEAR(Renteberekening!$J$1:$UK$1)=YEAR(Samenvatting!AU$41)) * Renteberekening!$J$2:$UK$29),0))} -> 0
C104: private debt 2 | D104: =J104 -> 2 | E104: EUR | F104: 2187467 | H104: 0.08 | I104: 46023 | J104: =YEAR(K104)-YEAR(I104) -> 2 | K104: 46753 | L104: {=IF(OR(Samenvatting!$C104="",ISBLANK(Samenvatting!$C104)),"0,0",IFERROR(SUMPRODUCT((Renteberekening!$B$2:$B$29=Samenvatting!$C104) * (YEAR(Renteberekening!$J$1:$UK$1)=YEAR(Samenvatting!L$41)) * Renteberekening!$J$2:$UK$29),0))} -> -2069860.3 | M104: {=IF(OR(Samenvatting!$C104="",ISBLANK(Samenvatting!$C104)),"0,0",IFERROR(SUMPRODUCT((Renteberekening!$B$2:$B$29=Samenvatting!$C104) * (YEAR(Renteberekening!$J$1:$UK$1)=YEAR(Samenvatting!M$41)) * Renteberekening!$J$2:$UK$29),0))} -> 127923.07 | N104: {=IF(OR(Samenvatting!$C104="",ISBLANK(Samenvatting!$C104)),"0,0",IFERROR(SUMPRODUCT((Renteberekening!$B$2:$B$29=Samenvatting!$C104) * (YEAR(Renteberekening!$J$1:$UK$1)=YEAR(Samenvatting!N$41)) * Renteberekening!$J$2:$UK$29),0))} -> 2187810.9 | O104: {=IF(OR(Samenvatting!$C104="",ISBLANK(Samenvatting!$C104)),"0,0",IFERROR(SUMPRODUCT((Renteberekening!$B$2:$B$29=Samenvatting!$C104) * (YEAR(Renteberekening!$J$1:$UK$1)=YEAR(Samenvatting!O$41)) * Renteberekening!$J$2:$UK$29),0))} -> 0 | P104: {=IF(OR(Samenvatting!$C104="",ISBLANK(Samenvatting!$C104)),"0,0",IFERROR(SUMPRODUCT((Renteberekening!$B$2:$B$29=Samenvatting!$C104) * (YEAR(Renteberekening!$J$1:$UK$1)=YEAR(Samenvatting!P$41)) * Renteberekening!$J$2:$UK$29),0))} -> 0 | Q104: {=IF(OR(Samenvatting!$C104="",ISBLANK(Samenvatting!$C104)),"0,0",IFERROR(SUMPRODUCT((Renteberekening!$B$2:$B$29=Samenvatting!$C104) * (YEAR(Renteberekening!$J$1:$UK$1)=YEAR(Samenvatting!Q$41)) * Renteberekening!$J$2:$UK$29),0))} -> 0 | R104: {=IF(OR(Samenvatting!$C104="",ISBLANK(Samenvatting!$C104)),"0,0",IFERROR(SUMPRODUCT((Renteberekening!$B$2:$B$29=Samenvatting!$C104) * (YEAR(Renteberekening!$J$1:$UK$1)=YEAR(Samenvatting!R$41)) * Renteberekening!$J$2:$UK$29),0))} -> 0 | S104: {=IF(OR(Samenvatting!$C104="",ISBLANK(Samenvatting!$C104)),"0,0",IFERROR(SUMPRODUCT((Renteberekening!$B$2:$B$29=Samenvatting!$C104) * (YEAR(Renteberekening!$J$1:$UK$1)=YEAR(Samenvatting!S$41)) * Renteberekening!$J$2:$UK$29),0))} -> 0 | ... AU104: {=IF(OR(Samenvatting!$C104="",ISBLANK(Samenvatting!$C104)),"0,0",IFERROR(SUMPRODUCT((Renteberekening!$B$2:$B$29=Samenvatting!$C104) * (YEAR(Renteberekening!$J$1:$UK$1)=YEAR(Samenvatting!AU$41)) * Renteberekening!$J$2:$UK$29),0))} -> 0
D105: =J105 -> 5 | E105: EUR | H105: 0.08 | I105: 45867 | J105: =YEAR(K105)-YEAR(I105) -> 5 | K105: 47484 | L105: {=IF(OR(Samenvatting!$C105="",ISBLANK(Samenvatting!$C105)),"0,0",IFERROR(SUMPRODUCT((Renteberekening!$B$2:$B$29=Samenvatting!$C105) * (YEAR(Renteberekening!$J$1:$UK$1)=YEAR(Samenvatting!L$41)) * Renteberekening!$J$2:$UK$29),0))} -> 0,0 | M105: {=IF(OR(Samenvatting!$C105="",ISBLANK(Samenvatting!$C105)),"0,0",IFERROR(SUMPRODUCT((Renteberekening!$B$2:$B$29=Samenvatting!$C105) * (YEAR(Renteberekening!$J$1:$UK$1)=YEAR(Samenvatting!M$41)) * Renteberekening!$J$2:$UK$29),0))} -> 0,0 | N105: {=IF(OR(Samenvatting!$C105="",ISBLANK(Samenvatting!$C105)),"0,0",IFERROR(SUMPRODUCT((Renteberekening!$B$2:$B$29=Samenvatting!$C105) * (YEAR(Renteberekening!$J$1:$UK$1)=YEAR(Samenvatting!N$41)) * Renteberekening!$J$2:$UK$29),0))} -> 0,0 | O105: {=IF(OR(Samenvatting!$C105="",ISBLANK(Samenvatting!$C105)),"0,0",IFERROR(SUMPRODUCT((Renteberekening!$B$2:$B$29=Samenvatting!$C105) * (YEAR(Renteberekening!$J$1:$UK$1)=YEAR(Samenvatting!O$41)) * Renteberekening!$J$2:$UK$29),0))} -> 0,0 | P105: {=IF(OR(Samenvatting!$C105="",ISBLANK(Samenvatting!$C105)),"0,0",IFERROR(SUMPRODUCT((Renteberekening!$B$2:$B$29=Samenvatting!$C105) * (YEAR(Renteberekening!$J$1:$UK$1)=YEAR(Samenvatting!P$41)) * Renteberekening!$J$2:$UK$29),0))} -> 0,0 | Q105: {=IF(OR(Samenvatting!$C105="",ISBLANK(Samenvatting!$C105)),"0,0",IFERROR(SUMPRODUCT((Renteberekening!$B$2:$B$29=Samenvatting!$C105) * (YEAR(Renteberekening!$J$1:$UK$1)=YEAR(Samenvatting!Q$41)) * Renteberekening!$J$2:$UK$29),0))} -> 0,0 | R105: {=IF(OR(Samenvatting!$C105="",ISBLANK(Samenvatting!$C105)),"0,0",IFERROR(SUMPRODUCT((Renteberekening!$B$2:$B$29=Samenvatting!$C105) * (YEAR(Renteberekening!$J$1:$UK$1)=YEAR(Samenvatting!R$41)) * Renteberekening!$J$2:$UK$29),0))} -> 0,0 | S105: {=IF(OR(Samenvatting!$C105="",ISBLANK(Samenvatting!$C105)),"0,0",IFERROR(SUMPRODUCT((Renteberekening!$B$2:$B$29=Samenvatting!$C105) * (YEAR(Renteberekening!$J$1:$UK$1)=YEAR(Samenvatting!S$41)) * Renteberekening!$J$2:$UK$29),0))} -> 0,0 | ... AU105: {=IF(OR(Samenvatting!$C105="",ISBLANK(Samenvatting!$C105)),"0,0",IFERROR(SUMPRODUCT((Renteberekening!$B$2:$B$29=Samenvatting!$C105) * (YEAR(Renteberekening!$J$1:$UK$1)=YEAR(Samenvatting!AU$41)) * Renteberekening!$J$2:$UK$29),0))} -> 0,0
D106: 1 | E106: EUR | H106: 0.075 | I106: 45867 | J106: =YEAR(K106)-YEAR(I106) -> 0 | K106: 45658 | L106: {=IF(OR(Samenvatting!$C106="",ISBLANK(Samenvatting!$C106)),"0,0",IFERROR(SUMPRODUCT((Renteberekening!$B$2:$B$29=Samenvatting!$C106) * (YEAR(Renteberekening!$J$1:$UK$1)=YEAR(Samenvatting!L$41)) * Renteberekening!$J$2:$UK$29),0))} -> 0,0 | M106: {=IF(OR(Samenvatting!$C106="",ISBLANK(Samenvatting!$C106)),"0,0",IFERROR(SUMPRODUCT((Renteberekening!$B$2:$B$29=Samenvatting!$C106) * (YEAR(Renteberekening!$J$1:$UK$1)=YEAR(Samenvatting!M$41)) * Renteberekening!$J$2:$UK$29),0))} -> 0,0 | N106: {=IF(OR(Samenvatting!$C106="",ISBLANK(Samenvatting!$C106)),"0,0",IFERROR(SUMPRODUCT((Renteberekening!$B$2:$B$29=Samenvatting!$C106) * (YEAR(Renteberekening!$J$1:$UK$1)=YEAR(Samenvatting!N$41)) * Renteberekening!$J$2:$UK$29),0))} -> 0,0 | O106: {=IF(OR(Samenvatting!$C106="",ISBLANK(Samenvatting!$C106)),"0,0",IFERROR(SUMPRODUCT((Renteberekening!$B$2:$B$29=Samenvatting!$C106) * (YEAR(Renteberekening!$J$1:$UK$1)=YEAR(Samenvatting!O$41)) * Renteberekening!$J$2:$UK$29),0))} -> 0,0 | P106: {=IF(OR(Samenvatting!$C106="",ISBLANK(Samenvatting!$C106)),"0,0",IFERROR(SUMPRODUCT((Renteberekening!$B$2:$B$29=Samenvatting!$C106) * (YEAR(Renteberekening!$J$1:$UK$1)=YEAR(Samenvatting!P$41)) * Renteberekening!$J$2:$UK$29),0))} -> 0,0 | Q106: {=IF(OR(Samenvatting!$C106="",ISBLANK(Samenvatting!$C106)),"0,0",IFERROR(SUMPRODUCT((Renteberekening!$B$2:$B$29=Samenvatting!$C106) * (YEAR(Renteberekening!$J$1:$UK$1)=YEAR(Samenvatting!Q$41)) * Renteberekening!$J$2:$UK$29),0))} -> 0,0 | R106: {=IF(OR(Samenvatting!$C106="",ISBLANK(Samenvatting!$C106)),"0,0",IFERROR(SUMPRODUCT((Renteberekening!$B$2:$B$29=Samenvatting!$C106) * (YEAR(Renteberekening!$J$1:$UK$1)=YEAR(Samenvatting!R$41)) * Renteberekening!$J$2:$UK$29),0))} -> 0,0 | S106: {=IF(OR(Samenvatting!$C106="",ISBLANK(Samenvatting!$C106)),"0,0",IFERROR(SUMPRODUCT((Renteberekening!$B$2:$B$29=Samenvatting!$C106) * (YEAR(Renteberekening!$J$1:$UK$1)=YEAR(Samenvatting!S$41)) * Renteberekening!$J$2:$UK$29),0))} -> 0,0 | ... AU106: {=IF(OR(Samenvatting!$C106="",ISBLANK(Samenvatting!$C106)),"0,0",IFERROR(SUMPRODUCT((Renteberekening!$B$2:$B$29=Samenvatting!$C106) * (YEAR(Renteberekening!$J$1:$UK$1)=YEAR(Samenvatting!AU$41)) * Renteberekening!$J$2:$UK$29),0))} -> 0,0
D107: 1 | E107: EUR | H107: 0.075 | I107: 45239 | J107: =YEAR(K107)-YEAR(I107) -> 0 | K107: 45239 | L107: {=IF(OR(Samenvatting!$C107="",ISBLANK(Samenvatting!$C107)),"0,0",IFERROR(SUMPRODUCT((Renteberekening!$B$2:$B$29=Samenvatting!$C107) * (YEAR(Renteberekening!$J$1:$UK$1)=YEAR(Samenvatting!L$41)) * Renteberekening!$J$2:$UK$29),0))} -> 0,0 | M107: {=IF(OR(Samenvatting!$C107="",ISBLANK(Samenvatting!$C107)),"0,0",IFERROR(SUMPRODUCT((Renteberekening!$B$2:$B$29=Samenvatting!$C107) * (YEAR(Renteberekening!$J$1:$UK$1)=YEAR(Samenvatting!M$41)) * Renteberekening!$J$2:$UK$29),0))} -> 0,0 | N107: {=IF(OR(Samenvatting!$C107="",ISBLANK(Samenvatting!$C107)),"0,0",IFERROR(SUMPRODUCT((Renteberekening!$B$2:$B$29=Samenvatting!$C107) * (YEAR(Renteberekening!$J$1:$UK$1)=YEAR(Samenvatting!N$41)) * Renteberekening!$J$2:$UK$29),0))} -> 0,0 | O107: {=IF(OR(Samenvatting!$C107="",ISBLANK(Samenvatting!$C107)),"0,0",IFERROR(SUMPRODUCT((Renteberekening!$B$2:$B$29=Samenvatting!$C107) * (YEAR(Renteberekening!$J$1:$UK$1)=YEAR(Samenvatting!O$41)) * Renteberekening!$J$2:$UK$29),0))} -> 0,0 | P107: {=IF(OR(Samenvatting!$C107="",ISBLANK(Samenvatting!$C107)),"0,0",IFERROR(SUMPRODUCT((Renteberekening!$B$2:$B$29=Samenvatting!$C107) * (YEAR(Renteberekening!$J$1:$UK$1)=YEAR(Samenvatting!P$41)) * Renteberekening!$J$2:$UK$29),0))} -> 0,0 | Q107: {=IF(OR(Samenvatting!$C107="",ISBLANK(Samenvatting!$C107)),"0,0",IFERROR(SUMPRODUCT((Renteberekening!$B$2:$B$29=Samenvatting!$C107) * (YEAR(Renteberekening!$J$1:$UK$1)=YEAR(Samenvatting!Q$41)) * Renteberekening!$J$2:$UK$29),0))} -> 0,0 | R107: {=IF(OR(Samenvatting!$C107="",ISBLANK(Samenvatting!$C107)),"0,0",IFERROR(SUMPRODUCT((Renteberekening!$B$2:$B$29=Samenvatting!$C107) * (YEAR(Renteberekening!$J$1:$UK$1)=YEAR(Samenvatting!R$41)) * Renteberekening!$J$2:$UK$29),0))} -> 0,0 | S107: {=IF(OR(Samenvatting!$C107="",ISBLANK(Samenvatting!$C107)),"0,0",IFERROR(SUMPRODUCT((Renteberekening!$B$2:$B$29=Samenvatting!$C107) * (YEAR(Renteberekening!$J$1:$UK$1)=YEAR(Samenvatting!S$41)) * Renteberekening!$J$2:$UK$29),0))} -> 0,0 | ... AU107: {=IF(OR(Samenvatting!$C107="",ISBLANK(Samenvatting!$C107)),"0,0",IFERROR(SUMPRODUCT((Renteberekening!$B$2:$B$29=Samenvatting!$C107) * (YEAR(Renteberekening!$J$1:$UK$1)=YEAR(Samenvatting!AU$41)) * Renteberekening!$J$2:$UK$29),0))} -> 0,0
D108: 1 | E108: EUR | H108: 0.075 | I108: 45292 | J108: =YEAR(K108)-YEAR(I108) -> 1 | K108: 45867 | L108: {=IF(OR(Samenvatting!$C108="",ISBLANK(Samenvatting!$C108)),"0,0",IFERROR(SUMPRODUCT((Renteberekening!$B$2:$B$29=Samenvatting!$C108) * (YEAR(Renteberekening!$J$1:$UK$1)=YEAR(Samenvatting!L$41)) * Renteberekening!$J$2:$UK$29),0))} -> 0,0 | M108: {=IF(OR(Samenvatting!$C108="",ISBLANK(Samenvatting!$C108)),"0,0",IFERROR(SUMPRODUCT((Renteberekening!$B$2:$B$29=Samenvatting!$C108) * (YEAR(Renteberekening!$J$1:$UK$1)=YEAR(Samenvatting!M$41)) * Renteberekening!$J$2:$UK$29),0))} -> 0,0 | N108: {=IF(OR(Samenvatting!$C108="",ISBLANK(Samenvatting!$C108)),"0,0",IFERROR(SUMPRODUCT((Renteberekening!$B$2:$B$29=Samenvatting!$C108) * (YEAR(Renteberekening!$J$1:$UK$1)=YEAR(Samenvatting!N$41)) * Renteberekening!$J$2:$UK$29),0))} -> 0,0 | O108: {=IF(OR(Samenvatting!$C108="",ISBLANK(Samenvatting!$C108)),"0,0",IFERROR(SUMPRODUCT((Renteberekening!$B$2:$B$29=Samenvatting!$C108) * (YEAR(Renteberekening!$J$1:$UK$1)=YEAR(Samenvatting!O$41)) * Renteberekening!$J$2:$UK$29),0))} -> 0,0 | P108: {=IF(OR(Samenvatting!$C108="",ISBLANK(Samenvatting!$C108)),"0,0",IFERROR(SUMPRODUCT((Renteberekening!$B$2:$B$29=Samenvatting!$C108) * (YEAR(Renteberekening!$J$1:$UK$1)=YEAR(Samenvatting!P$41)) * Renteberekening!$J$2:$UK$29),0))} -> 0,0 | Q108: {=IF(OR(Samenvatting!$C108="",ISBLANK(Samenvatting!$C108)),"0,0",IFERROR(SUMPRODUCT((Renteberekening!$B$2:$B$29=Samenvatting!$C108) * (YEAR(Renteberekening!$J$1:$UK$1)=YEAR(Samenvatting!Q$41)) * Renteberekening!$J$2:$UK$29),0))} -> 0,0 | R108: {=IF(OR(Samenvatting!$C108="",ISBLANK(Samenvatting!$C108)),"0,0",IFERROR(SUMPRODUCT((Renteberekening!$B$2:$B$29=Samenvatting!$C108) * (YEAR(Renteberekening!$J$1:$UK$1)=YEAR(Samenvatting!R$41)) * Renteberekening!$J$2:$UK$29),0))} -> 0,0 | S108: {=IF(OR(Samenvatting!$C108="",ISBLANK(Samenvatting!$C108)),"0,0",IFERROR(SUMPRODUCT((Renteberekening!$B$2:$B$29=Samenvatting!$C108) * (YEAR(Renteberekening!$J$1:$UK$1)=YEAR(Samenvatting!S$41)) * Renteberekening!$J$2:$UK$29),0))} -> 0,0 | ... AU108: {=IF(OR(Samenvatting!$C108="",ISBLANK(Samenvatting!$C108)),"0,0",IFERROR(SUMPRODUCT((Renteberekening!$B$2:$B$29=Samenvatting!$C108) * (YEAR(Renteberekening!$J$1:$UK$1)=YEAR(Samenvatting!AU$41)) * Renteberekening!$J$2:$UK$29),0))} -> 0,0
D109: 1 | E109: EUR | H109: 0.075 | I109: 45292 | J109: =YEAR(K109)-YEAR(I109) -> 2 | K109: 46060 | L109: {=IF(OR(Samenvatting!$C109="",ISBLANK(Samenvatting!$C109)),"0,0",IFERROR(SUMPRODUCT((Renteberekening!$B$2:$B$29=Samenvatting!$C109) * (YEAR(Renteberekening!$J$1:$UK$1)=YEAR(Samenvatting!L$41)) * Renteberekening!$J$2:$UK$29),0))} -> 0,0 | M109: {=IF(OR(Samenvatting!$C109="",ISBLANK(Samenvatting!$C109)),"0,0",IFERROR(SUMPRODUCT((Renteberekening!$B$2:$B$29=Samenvatting!$C109) * (YEAR(Renteberekening!$J$1:$UK$1)=YEAR(Samenvatting!M$41)) * Renteberekening!$J$2:$UK$29),0))} -> 0,0 | N109: {=IF(OR(Samenvatting!$C109="",ISBLANK(Samenvatting!$C109)),"0,0",IFERROR(SUMPRODUCT((Renteberekening!$B$2:$B$29=Samenvatting!$C109) * (YEAR(Renteberekening!$J$1:$UK$1)=YEAR(Samenvatting!N$41)) * Renteberekening!$J$2:$UK$29),0))} -> 0,0 | O109: {=IF(OR(Samenvatting!$C109="",ISBLANK(Samenvatting!$C109)),"0,0",IFERROR(SUMPRODUCT((Renteberekening!$B$2:$B$29=Samenvatting!$C109) * (YEAR(Renteberekening!$J$1:$UK$1)=YEAR(Samenvatting!O$41)) * Renteberekening!$J$2:$UK$29),0))} -> 0,0 | P109: {=IF(OR(Samenvatting!$C109="",ISBLANK(Samenvatting!$C109)),"0,0",IFERROR(SUMPRODUCT((Renteberekening!$B$2:$B$29=Samenvatting!$C109) * (YEAR(Renteberekening!$J$1:$UK$1)=YEAR(Samenvatting!P$41)) * Renteberekening!$J$2:$UK$29),0))} -> 0,0 | Q109: {=IF(OR(Samenvatting!$C109="",ISBLANK(Samenvatting!$C109)),"0,0",IFERROR(SUMPRODUCT((Renteberekening!$B$2:$B$29=Samenvatting!$C109) * (YEAR(Renteberekening!$J$1:$UK$1)=YEAR(Samenvatting!Q$41)) * Renteberekening!$J$2:$UK$29),0))} -> 0,0 | R109: {=IF(OR(Samenvatting!$C109="",ISBLANK(Samenvatting!$C109)),"0,0",IFERROR(SUMPRODUCT((Renteberekening!$B$2:$B$29=Samenvatting!$C109) * (YEAR(Renteberekening!$J$1:$UK$1)=YEAR(Samenvatting!R$41)) * Renteberekening!$J$2:$UK$29),0))} -> 0,0 | S109: {=IF(OR(Samenvatting!$C109="",ISBLANK(Samenvatting!$C109)),"0,0",IFERROR(SUMPRODUCT((Renteberekening!$B$2:$B$29=Samenvatting!$C109) * (YEAR(Renteberekening!$J$1:$UK$1)=YEAR(Samenvatting!S$41)) * Renteberekening!$J$2:$UK$29),0))} -> 0,0 | ... AU109: {=IF(OR(Samenvatting!$C109="",ISBLANK(Samenvatting!$C109)),"0,0",IFERROR(SUMPRODUCT((Renteberekening!$B$2:$B$29=Samenvatting!$C109) * (YEAR(Renteberekening!$J$1:$UK$1)=YEAR(Samenvatting!AU$41)) * Renteberekening!$J$2:$UK$29),0))} -> 0,0
D110: 1 | E110: EUR | H110: 0.075 | I110: 45292 | J110: =YEAR(K110)-YEAR(I110) -> 1 | K110: 45695 | L110: {=IF(OR(Samenvatting!$C110="",ISBLANK(Samenvatting!$C110)),"0,0",IFERROR(SUMPRODUCT((Renteberekening!$B$2:$B$29=Samenvatting!$C110) * (YEAR(Renteberekening!$J$1:$UK$1)=YEAR(Samenvatting!L$41)) * Renteberekening!$J$2:$UK$29),0))} -> 0,0 | M110: {=IF(OR(Samenvatting!$C110="",ISBLANK(Samenvatting!$C110)),"0,0",IFERROR(SUMPRODUCT((Renteberekening!$B$2:$B$29=Samenvatting!$C110) * (YEAR(Renteberekening!$J$1:$UK$1)=YEAR(Samenvatting!M$41)) * Renteberekening!$J$2:$UK$29),0))} -> 0,0 | N110: {=IF(OR(Samenvatting!$C110="",ISBLANK(Samenvatting!$C110)),"0,0",IFERROR(SUMPRODUCT((Renteberekening!$B$2:$B$29=Samenvatting!$C110) * (YEAR(Renteberekening!$J$1:$UK$1)=YEAR(Samenvatting!N$41)) * Renteberekening!$J$2:$UK$29),0))} -> 0,0 | O110: {=IF(OR(Samenvatting!$C110="",ISBLANK(Samenvatting!$C110)),"0,0",IFERROR(SUMPRODUCT((Renteberekening!$B$2:$B$29=Samenvatting!$C110) * (YEAR(Renteberekening!$J$1:$UK$1)=YEAR(Samenvatting!O$41)) * Renteberekening!$J$2:$UK$29),0))} -> 0,0 | P110: {=IF(OR(Samenvatting!$C110="",ISBLANK(Samenvatting!$C110)),"0,0",IFERROR(SUMPRODUCT((Renteberekening!$B$2:$B$29=Samenvatting!$C110) * (YEAR(Renteberekening!$J$1:$UK$1)=YEAR(Samenvatting!P$41)) * Renteberekening!$J$2:$UK$29),0))} -> 0,0 | Q110: {=IF(OR(Samenvatting!$C110="",ISBLANK(Samenvatting!$C110)),"0,0",IFERROR(SUMPRODUCT((Renteberekening!$B$2:$B$29=Samenvatting!$C110) * (YEAR(Renteberekening!$J$1:$UK$1)=YEAR(Samenvatting!Q$41)) * Renteberekening!$J$2:$UK$29),0))} -> 0,0 | R110: {=IF(OR(Samenvatting!$C110="",ISBLANK(Samenvatting!$C110)),"0,0",IFERROR(SUMPRODUCT((Renteberekening!$B$2:$B$29=Samenvatting!$C110) * (YEAR(Renteberekening!$J$1:$UK$1)=YEAR(Samenvatting!R$41)) * Renteberekening!$J$2:$UK$29),0))} -> 0,0 | S110: {=IF(OR(Samenvatting!$C110="",ISBLANK(Samenvatting!$C110)),"0,0",IFERROR(SUMPRODUCT((Renteberekening!$B$2:$B$29=Samenvatting!$C110) * (YEAR(Renteberekening!$J$1:$UK$1)=YEAR(Samenvatting!S$41)) * Renteberekening!$J$2:$UK$29),0))} -> 0,0 | ... AU110: {=IF(OR(Samenvatting!$C110="",ISBLANK(Samenvatting!$C110)),"0,0",IFERROR(SUMPRODUCT((Renteberekening!$B$2:$B$29=Samenvatting!$C110) * (YEAR(Renteberekening!$J$1:$UK$1)=YEAR(Samenvatting!AU$41)) * Renteberekening!$J$2:$UK$29),0))} -> 0,0
D111: 1 | E111: EUR | H111: 0.075 | I111: 45292 | J111: =YEAR(K111)-YEAR(I111) -> 3 | K111: 46447 | L111: {=IF(OR(Samenvatting!$C111="",ISBLANK(Samenvatting!$C111)),"0,0",IFERROR(SUMPRODUCT((Renteberekening!$B$2:$B$29=Samenvatting!$C111) * (YEAR(Renteberekening!$J$1:$UK$1)=YEAR(Samenvatting!L$41)) * Renteberekening!$J$2:$UK$29),0))} -> 0,0 | M111: {=IF(OR(Samenvatting!$C111="",ISBLANK(Samenvatting!$C111)),"0,0",IFERROR(SUMPRODUCT((Renteberekening!$B$2:$B$29=Samenvatting!$C111) * (YEAR(Renteberekening!$J$1:$UK$1)=YEAR(Samenvatting!M$41)) * Renteberekening!$J$2:$UK$29),0))} -> 0,0 | N111: {=IF(OR(Samenvatting!$C111="",ISBLANK(Samenvatting!$C111)),"0,0",IFERROR(SUMPRODUCT((Renteberekening!$B$2:$B$29=Samenvatting!$C111) * (YEAR(Renteberekening!$J$1:$UK$1)=YEAR(Samenvatting!N$41)) * Renteberekening!$J$2:$UK$29),0))} -> 0,0 | O111: {=IF(OR(Samenvatting!$C111="",ISBLANK(Samenvatting!$C111)),"0,0",IFERROR(SUMPRODUCT((Renteberekening!$B$2:$B$29=Samenvatting!$C111) * (YEAR(Renteberekening!$J$1:$UK$1)=YEAR(Samenvatting!O$41)) * Renteberekening!$J$2:$UK$29),0))} -> 0,0 | P111: {=IF(OR(Samenvatting!$C111="",ISBLANK(Samenvatting!$C111)),"0,0",IFERROR(SUMPRODUCT((Renteberekening!$B$2:$B$29=Samenvatting!$C111) * (YEAR(Renteberekening!$J$1:$UK$1)=YEAR(Samenvatting!P$41)) * Renteberekening!$J$2:$UK$29),0))} -> 0,0 | Q111: {=IF(OR(Samenvatting!$C111="",ISBLANK(Samenvatting!$C111)),"0,0",IFERROR(SUMPRODUCT((Renteberekening!$B$2:$B$29=Samenvatting!$C111) * (YEAR(Renteberekening!$J$1:$UK$1)=YEAR(Samenvatting!Q$41)) * Renteberekening!$J$2:$UK$29),0))} -> 0,0 | R111: {=IF(OR(Samenvatting!$C111="",ISBLANK(Samenvatting!$C111)),"0,0",IFERROR(SUMPRODUCT((Renteberekening!$B$2:$B$29=Samenvatting!$C111) * (YEAR(Renteberekening!$J$1:$UK$1)=YEAR(Samenvatting!R$41)) * Renteberekening!$J$2:$UK$29),0))} -> 0,0 | S111: {=IF(OR(Samenvatting!$C111="",ISBLANK(Samenvatting!$C111)),"0,0",IFERROR(SUMPRODUCT((Renteberekening!$B$2:$B$29=Samenvatting!$C111) * (YEAR(Renteberekening!$J$1:$UK$1)=YEAR(Samenvatting!S$41)) * Renteberekening!$J$2:$UK$29),0))} -> 0,0 | ... AU111: {=IF(OR(Samenvatting!$C111="",ISBLANK(Samenvatting!$C111)),"0,0",IFERROR(SUMPRODUCT((Renteberekening!$B$2:$B$29=Samenvatting!$C111) * (YEAR(Renteberekening!$J$1:$UK$1)=YEAR(Samenvatting!AU$41)) * Renteberekening!$J$2:$UK$29),0))} -> 0,0
D112: 1 | E112: EUR | H112: 0.075 | I112: 45292 | J112: =YEAR(K112)-YEAR(I112) -> 3 | K112: 46447 | L112: {=IF(OR(Samenvatting!$C112="",ISBLANK(Samenvatting!$C112)),"0,0",IFERROR(SUMPRODUCT((Renteberekening!$B$2:$B$29=Samenvatting!$C112) * (YEAR(Renteberekening!$J$1:$UK$1)=YEAR(Samenvatting!L$41)) * Renteberekening!$J$2:$UK$29),0))} -> 0,0 | M112: {=IF(OR(Samenvatting!$C112="",ISBLANK(Samenvatting!$C112)),"0,0",IFERROR(SUMPRODUCT((Renteberekening!$B$2:$B$29=Samenvatting!$C112) * (YEAR(Renteberekening!$J$1:$UK$1)=YEAR(Samenvatting!M$41)) * Renteberekening!$J$2:$UK$29),0))} -> 0,0 | N112: {=IF(OR(Samenvatting!$C112="",ISBLANK(Samenvatting!$C112)),"0,0",IFERROR(SUMPRODUCT((Renteberekening!$B$2:$B$29=Samenvatting!$C112) * (YEAR(Renteberekening!$J$1:$UK$1)=YEAR(Samenvatting!N$41)) * Renteberekening!$J$2:$UK$29),0))} -> 0,0 | O112: {=IF(OR(Samenvatting!$C112="",ISBLANK(Samenvatting!$C112)),"0,0",IFERROR(SUMPRODUCT((Renteberekening!$B$2:$B$29=Samenvatting!$C112) * (YEAR(Renteberekening!$J$1:$UK$1)=YEAR(Samenvatting!O$41)) * Renteberekening!$J$2:$UK$29),0))} -> 0,0 | P112: {=IF(OR(Samenvatting!$C112="",ISBLANK(Samenvatting!$C112)),"0,0",IFERROR(SUMPRODUCT((Renteberekening!$B$2:$B$29=Samenvatting!$C112) * (YEAR(Renteberekening!$J$1:$UK$1)=YEAR(Samenvatting!P$41)) * Renteberekening!$J$2:$UK$29),0))} -> 0,0 | Q112: {=IF(OR(Samenvatting!$C112="",ISBLANK(Samenvatting!$C112)),"0,0",IFERROR(SUMPRODUCT((Renteberekening!$B$2:$B$29=Samenvatting!$C112) * (YEAR(Renteberekening!$J$1:$UK$1)=YEAR(Samenvatting!Q$41)) * Renteberekening!$J$2:$UK$29),0))} -> 0,0 | R112: {=IF(OR(Samenvatting!$C112="",ISBLANK(Samenvatting!$C112)),"0,0",IFERROR(SUMPRODUCT((Renteberekening!$B$2:$B$29=Samenvatting!$C112) * (YEAR(Renteberekening!$J$1:$UK$1)=YEAR(Samenvatting!R$41)) * Renteberekening!$J$2:$UK$29),0))} -> 0,0 | S112: {=IF(OR(Samenvatting!$C112="",ISBLANK(Samenvatting!$C112)),"0,0",IFERROR(SUMPRODUCT((Renteberekening!$B$2:$B$29=Samenvatting!$C112) * (YEAR(Renteberekening!$J$1:$UK$1)=YEAR(Samenvatting!S$41)) * Renteberekening!$J$2:$UK$29),0))} -> 0,0 | ... AU112: {=IF(OR(Samenvatting!$C112="",ISBLANK(Samenvatting!$C112)),"0,0",IFERROR(SUMPRODUCT((Renteberekening!$B$2:$B$29=Samenvatting!$C112) * (YEAR(Renteberekening!$J$1:$UK$1)=YEAR(Samenvatting!AU$41)) * Renteberekening!$J$2:$UK$29),0))} -> 0,0
D113: 1 | E113: EUR | H113: 0.075 | I113: 45292 | J113: =YEAR(K113)-YEAR(I113) -> 3 | K113: 46447 | L113: {=IF(OR(Samenvatting!$C113="",ISBLANK(Samenvatting!$C113)),"0,0",IFERROR(SUMPRODUCT((Renteberekening!$B$2:$B$29=Samenvatting!$C113) * (YEAR(Renteberekening!$J$1:$UK$1)=YEAR(Samenvatting!L$41)) * Renteberekening!$J$2:$UK$29),0))} -> 0,0 | M113: {=IF(OR(Samenvatting!$C113="",ISBLANK(Samenvatting!$C113)),"0,0",IFERROR(SUMPRODUCT((Renteberekening!$B$2:$B$29=Samenvatting!$C113) * (YEAR(Renteberekening!$J$1:$UK$1)=YEAR(Samenvatting!M$41)) * Renteberekening!$J$2:$UK$29),0))} -> 0,0 | N113: {=IF(OR(Samenvatting!$C113="",ISBLANK(Samenvatting!$C113)),"0,0",IFERROR(SUMPRODUCT((Renteberekening!$B$2:$B$29=Samenvatting!$C113) * (YEAR(Renteberekening!$J$1:$UK$1)=YEAR(Samenvatting!N$41)) * Renteberekening!$J$2:$UK$29),0))} -> 0,0 | O113: {=IF(OR(Samenvatting!$C113="",ISBLANK(Samenvatting!$C113)),"0,0",IFERROR(SUMPRODUCT((Renteberekening!$B$2:$B$29=Samenvatting!$C113) * (YEAR(Renteberekening!$J$1:$UK$1)=YEAR(Samenvatting!O$41)) * Renteberekening!$J$2:$UK$29),0))} -> 0,0 | P113: {=IF(OR(Samenvatting!$C113="",ISBLANK(Samenvatting!$C113)),"0,0",IFERROR(SUMPRODUCT((Renteberekening!$B$2:$B$29=Samenvatting!$C113) * (YEAR(Renteberekening!$J$1:$UK$1)=YEAR(Samenvatting!P$41)) * Renteberekening!$J$2:$UK$29),0))} -> 0,0 | Q113: {=IF(OR(Samenvatting!$C113="",ISBLANK(Samenvatting!$C113)),"0,0",IFERROR(SUMPRODUCT((Renteberekening!$B$2:$B$29=Samenvatting!$C113) * (YEAR(Renteberekening!$J$1:$UK$1)=YEAR(Samenvatting!Q$41)) * Renteberekening!$J$2:$UK$29),0))} -> 0,0 | R113: {=IF(OR(Samenvatting!$C113="",ISBLANK(Samenvatting!$C113)),"0,0",IFERROR(SUMPRODUCT((Renteberekening!$B$2:$B$29=Samenvatting!$C113) * (YEAR(Renteberekening!$J$1:$UK$1)=YEAR(Samenvatting!R$41)) * Renteberekening!$J$2:$UK$29),0))} -> 0,0 | S113: {=IF(OR(Samenvatting!$C113="",ISBLANK(Samenvatting!$C113)),"0,0",IFERROR(SUMPRODUCT((Renteberekening!$B$2:$B$29=Samenvatting!$C113) * (YEAR(Renteberekening!$J$1:$UK$1)=YEAR(Samenvatting!S$41)) * Renteberekening!$J$2:$UK$29),0))} -> 0,0 | ... AU113: {=IF(OR(Samenvatting!$C113="",ISBLANK(Samenvatting!$C113)),"0,0",IFERROR(SUMPRODUCT((Renteberekening!$B$2:$B$29=Samenvatting!$C113) * (YEAR(Renteberekening!$J$1:$UK$1)=YEAR(Samenvatting!AU$41)) * Renteberekening!$J$2:$UK$29),0))} -> 0,0
D114: 1 | E114: EUR | H114: 0.075 | I114: 45292 | J114: =YEAR(K114)-YEAR(I114) -> 3 | K114: 46478 | L114: {=IF(OR(Samenvatting!$C114="",ISBLANK(Samenvatting!$C114)),"0,0",IFERROR(SUMPRODUCT((Renteberekening!$B$2:$B$29=Samenvatting!$C114) * (YEAR(Renteberekening!$J$1:$UK$1)=YEAR(Samenvatting!L$41)) * Renteberekening!$J$2:$UK$29),0))} -> 0,0 | M114: {=IF(OR(Samenvatting!$C114="",ISBLANK(Samenvatting!$C114)),"0,0",IFERROR(SUMPRODUCT((Renteberekening!$B$2:$B$29=Samenvatting!$C114) * (YEAR(Renteberekening!$J$1:$UK$1)=YEAR(Samenvatting!M$41)) * Renteberekening!$J$2:$UK$29),0))} -> 0,0 | N114: {=IF(OR(Samenvatting!$C114="",ISBLANK(Samenvatting!$C114)),"0,0",IFERROR(SUMPRODUCT((Renteberekening!$B$2:$B$29=Samenvatting!$C114) * (YEAR(Renteberekening!$J$1:$UK$1)=YEAR(Samenvatting!N$41)) * Renteberekening!$J$2:$UK$29),0))} -> 0,0 | O114: {=IF(OR(Samenvatting!$C114="",ISBLANK(Samenvatting!$C114)),"0,0",IFERROR(SUMPRODUCT((Renteberekening!$B$2:$B$29=Samenvatting!$C114) * (YEAR(Renteberekening!$J$1:$UK$1)=YEAR(Samenvatting!O$41)) * Renteberekening!$J$2:$UK$29),0))} -> 0,0 | P114: {=IF(OR(Samenvatting!$C114="",ISBLANK(Samenvatting!$C114)),"0,0",IFERROR(SUMPRODUCT((Renteberekening!$B$2:$B$29=Samenvatting!$C114) * (YEAR(Renteberekening!$J$1:$UK$1)=YEAR(Samenvatting!P$41)) * Renteberekening!$J$2:$UK$29),0))} -> 0,0 | Q114: {=IF(OR(Samenvatting!$C114="",ISBLANK(Samenvatting!$C114)),"0,0",IFERROR(SUMPRODUCT((Renteberekening!$B$2:$B$29=Samenvatting!$C114) * (YEAR(Renteberekening!$J$1:$UK$1)=YEAR(Samenvatting!Q$41)) * Renteberekening!$J$2:$UK$29),0))} -> 0,0 | R114: {=IF(OR(Samenvatting!$C114="",ISBLANK(Samenvatting!$C114)),"0,0",IFERROR(SUMPRODUCT((Renteberekening!$B$2:$B$29=Samenvatting!$C114) * (YEAR(Renteberekening!$J$1:$UK$1)=YEAR(Samenvatting!R$41)) * Renteberekening!$J$2:$UK$29),0))} -> 0,0 | S114: {=IF(OR(Samenvatting!$C114="",ISBLANK(Samenvatting!$C114)),"0,0",IFERROR(SUMPRODUCT((Renteberekening!$B$2:$B$29=Samenvatting!$C114) * (YEAR(Renteberekening!$J$1:$UK$1)=YEAR(Samenvatting!S$41)) * Renteberekening!$J$2:$UK$29),0))} -> 0,0 | ... AU114: {=IF(OR(Samenvatting!$C114="",ISBLANK(Samenvatting!$C114)),"0,0",IFERROR(SUMPRODUCT((Renteberekening!$B$2:$B$29=Samenvatting!$C114) * (YEAR(Renteberekening!$J$1:$UK$1)=YEAR(Samenvatting!AU$41)) * Renteberekening!$J$2:$UK$29),0))} -> 0,0
D115: 1 | E115: EUR | H115: 0.075 | I115: 45292 | J115: =YEAR(K115)-YEAR(I115) -> 3 | K115: 46631 | L115: {=IF(OR(Samenvatting!$C115="",ISBLANK(Samenvatting!$C115)),"0,0",IFERROR(SUMPRODUCT((Renteberekening!$B$2:$B$29=Samenvatting!$C115) * (YEAR(Renteberekening!$J$1:$UK$1)=YEAR(Samenvatting!L$41)) * Renteberekening!$J$2:$UK$29),0))} -> 0,0 | M115: {=IF(OR(Samenvatting!$C115="",ISBLANK(Samenvatting!$C115)),"0,0",IFERROR(SUMPRODUCT((Renteberekening!$B$2:$B$29=Samenvatting!$C115) * (YEAR(Renteberekening!$J$1:$UK$1)=YEAR(Samenvatting!M$41)) * Renteberekening!$J$2:$UK$29),0))} -> 0,0 | N115: {=IF(OR(Samenvatting!$C115="",ISBLANK(Samenvatting!$C115)),"0,0",IFERROR(SUMPRODUCT((Renteberekening!$B$2:$B$29=Samenvatting!$C115) * (YEAR(Renteberekening!$J$1:$UK$1)=YEAR(Samenvatting!N$41)) * Renteberekening!$J$2:$UK$29),0))} -> 0,0 | O115: {=IF(OR(Samenvatting!$C115="",ISBLANK(Samenvatting!$C115)),"0,0",IFERROR(SUMPRODUCT((Renteberekening!$B$2:$B$29=Samenvatting!$C115) * (YEAR(Renteberekening!$J$1:$UK$1)=YEAR(Samenvatting!O$41)) * Renteberekening!$J$2:$UK$29),0))} -> 0,0 | P115: {=IF(OR(Samenvatting!$C115="",ISBLANK(Samenvatting!$C115)),"0,0",IFERROR(SUMPRODUCT((Renteberekening!$B$2:$B$29=Samenvatting!$C115) * (YEAR(Renteberekening!$J$1:$UK$1)=YEAR(Samenvatting!P$41)) * Renteberekening!$J$2:$UK$29),0))} -> 0,0 | Q115: {=IF(OR(Samenvatting!$C115="",ISBLANK(Samenvatting!$C115)),"0,0",IFERROR(SUMPRODUCT((Renteberekening!$B$2:$B$29=Samenvatting!$C115) * (YEAR(Renteberekening!$J$1:$UK$1)=YEAR(Samenvatting!Q$41)) * Renteberekening!$J$2:$UK$29),0))} -> 0,0 | R115: {=IF(OR(Samenvatting!$C115="",ISBLANK(Samenvatting!$C115)),"0,0",IFERROR(SUMPRODUCT((Renteberekening!$B$2:$B$29=Samenvatting!$C115) * (YEAR(Renteberekening!$J$1:$UK$1)=YEAR(Samenvatting!R$41)) * Renteberekening!$J$2:$UK$29),0))} -> 0,0 | S115: {=IF(OR(Samenvatting!$C115="",ISBLANK(Samenvatting!$C115)),"0,0",IFERROR(SUMPRODUCT((Renteberekening!$B$2:$B$29=Samenvatting!$C115) * (YEAR(Renteberekening!$J$1:$UK$1)=YEAR(Samenvatting!S$41)) * Renteberekening!$J$2:$UK$29),0))} -> 0,0 | ... AU115: {=IF(OR(Samenvatting!$C115="",ISBLANK(Samenvatting!$C115)),"0,0",IFERROR(SUMPRODUCT((Renteberekening!$B$2:$B$29=Samenvatting!$C115) * (YEAR(Renteberekening!$J$1:$UK$1)=YEAR(Samenvatting!AU$41)) * Renteberekening!$J$2:$UK$29),0))} -> 0,0
D116: 1 | E116: EUR | H116: 0.075 | I116: 45292 | J116: =YEAR(K116)-YEAR(I116) -> 1 | K116: 45962 | L116: {=IF(OR(Samenvatting!$C116="",ISBLANK(Samenvatting!$C116)),"0,0",IFERROR(SUMPRODUCT((Renteberekening!$B$2:$B$29=Samenvatting!$C116) * (YEAR(Renteberekening!$J$1:$UK$1)=YEAR(Samenvatting!L$41)) * Renteberekening!$J$2:$UK$29),0))} -> 0,0 | M116: {=IF(OR(Samenvatting!$C116="",ISBLANK(Samenvatting!$C116)),"0,0",IFERROR(SUMPRODUCT((Renteberekening!$B$2:$B$29=Samenvatting!$C116) * (YEAR(Renteberekening!$J$1:$UK$1)=YEAR(Samenvatting!M$41)) * Renteberekening!$J$2:$UK$29),0))} -> 0,0 | N116: {=IF(OR(Samenvatting!$C116="",ISBLANK(Samenvatting!$C116)),"0,0",IFERROR(SUMPRODUCT((Renteberekening!$B$2:$B$29=Samenvatting!$C116) * (YEAR(Renteberekening!$J$1:$UK$1)=YEAR(Samenvatting!N$41)) * Renteberekening!$J$2:$UK$29),0))} -> 0,0 | O116: {=IF(OR(Samenvatting!$C116="",ISBLANK(Samenvatting!$C116)),"0,0",IFERROR(SUMPRODUCT((Renteberekening!$B$2:$B$29=Samenvatting!$C116) * (YEAR(Renteberekening!$J$1:$UK$1)=YEAR(Samenvatting!O$41)) * Renteberekening!$J$2:$UK$29),0))} -> 0,0 | P116: {=IF(OR(Samenvatting!$C116="",ISBLANK(Samenvatting!$C116)),"0,0",IFERROR(SUMPRODUCT((Renteberekening!$B$2:$B$29=Samenvatting!$C116) * (YEAR(Renteberekening!$J$1:$UK$1)=YEAR(Samenvatting!P$41)) * Renteberekening!$J$2:$UK$29),0))} -> 0,0 | Q116: {=IF(OR(Samenvatting!$C116="",ISBLANK(Samenvatting!$C116)),"0,0",IFERROR(SUMPRODUCT((Renteberekening!$B$2:$B$29=Samenvatting!$C116) * (YEAR(Renteberekening!$J$1:$UK$1)=YEAR(Samenvatting!Q$41)) * Renteberekening!$J$2:$UK$29),0))} -> 0,0 | R116: {=IF(OR(Samenvatting!$C116="",ISBLANK(Samenvatting!$C116)),"0,0",IFERROR(SUMPRODUCT((Renteberekening!$B$2:$B$29=Samenvatting!$C116) * (YEAR(Renteberekening!$J$1:$UK$1)=YEAR(Samenvatting!R$41)) * Renteberekening!$J$2:$UK$29),0))} -> 0,0 | S116: {=IF(OR(Samenvatting!$C116="",ISBLANK(Samenvatting!$C116)),"0,0",IFERROR(SUMPRODUCT((Renteberekening!$B$2:$B$29=Samenvatting!$C116) * (YEAR(Renteberekening!$J$1:$UK$1)=YEAR(Samenvatting!S$41)) * Renteberekening!$J$2:$UK$29),0))} -> 0,0 | ... AU116: {=IF(OR(Samenvatting!$C116="",ISBLANK(Samenvatting!$C116)),"0,0",IFERROR(SUMPRODUCT((Renteberekening!$B$2:$B$29=Samenvatting!$C116) * (YEAR(Renteberekening!$J$1:$UK$1)=YEAR(Samenvatting!AU$41)) * Renteberekening!$J$2:$UK$29),0))} -> 0,0
D117: 1 | E117: EUR | H117: 0.075 | I117: 45292 | J117: =YEAR(K117)-YEAR(I117) -> 1 | K117: 45809 | L117: {=IF(OR(Samenvatting!$C117="",ISBLANK(Samenvatting!$C117)),"0,0",IFERROR(SUMPRODUCT((Renteberekening!$B$2:$B$29=Samenvatting!$C117) * (YEAR(Renteberekening!$J$1:$UK$1)=YEAR(Samenvatting!L$41)) * Renteberekening!$J$2:$UK$29),0))} -> 0,0 | M117: {=IF(OR(Samenvatting!$C117="",ISBLANK(Samenvatting!$C117)),"0,0",IFERROR(SUMPRODUCT((Renteberekening!$B$2:$B$29=Samenvatting!$C117) * (YEAR(Renteberekening!$J$1:$UK$1)=YEAR(Samenvatting!M$41)) * Renteberekening!$J$2:$UK$29),0))} -> 0,0 | N117: {=IF(OR(Samenvatting!$C117="",ISBLANK(Samenvatting!$C117)),"0,0",IFERROR(SUMPRODUCT((Renteberekening!$B$2:$B$29=Samenvatting!$C117) * (YEAR(Renteberekening!$J$1:$UK$1)=YEAR(Samenvatting!N$41)) * Renteberekening!$J$2:$UK$29),0))} -> 0,0 | O117: {=IF(OR(Samenvatting!$C117="",ISBLANK(Samenvatting!$C117)),"0,0",IFERROR(SUMPRODUCT((Renteberekening!$B$2:$B$29=Samenvatting!$C117) * (YEAR(Renteberekening!$J$1:$UK$1)=YEAR(Samenvatting!O$41)) * Renteberekening!$J$2:$UK$29),0))} -> 0,0 | P117: {=IF(OR(Samenvatting!$C117="",ISBLANK(Samenvatting!$C117)),"0,0",IFERROR(SUMPRODUCT((Renteberekening!$B$2:$B$29=Samenvatting!$C117) * (YEAR(Renteberekening!$J$1:$UK$1)=YEAR(Samenvatting!P$41)) * Renteberekening!$J$2:$UK$29),0))} -> 0,0 | Q117: {=IF(OR(Samenvatting!$C117="",ISBLANK(Samenvatting!$C117)),"0,0",IFERROR(SUMPRODUCT((Renteberekening!$B$2:$B$29=Samenvatting!$C117) * (YEAR(Renteberekening!$J$1:$UK$1)=YEAR(Samenvatting!Q$41)) * Renteberekening!$J$2:$UK$29),0))} -> 0,0 | R117: {=IF(OR(Samenvatting!$C117="",ISBLANK(Samenvatting!$C117)),"0,0",IFERROR(SUMPRODUCT((Renteberekening!$B$2:$B$29=Samenvatting!$C117) * (YEAR(Renteberekening!$J$1:$UK$1)=YEAR(Samenvatting!R$41)) * Renteberekening!$J$2:$UK$29),0))} -> 0,0 | S117: {=IF(OR(Samenvatting!$C117="",ISBLANK(Samenvatting!$C117)),"0,0",IFERROR(SUMPRODUCT((Renteberekening!$B$2:$B$29=Samenvatting!$C117) * (YEAR(Renteberekening!$J$1:$UK$1)=YEAR(Samenvatting!S$41)) * Renteberekening!$J$2:$UK$29),0))} -> 0,0 | ... AU117: {=IF(OR(Samenvatting!$C117="",ISBLANK(Samenvatting!$C117)),"0,0",IFERROR(SUMPRODUCT((Renteberekening!$B$2:$B$29=Samenvatting!$C117) * (YEAR(Renteberekening!$J$1:$UK$1)=YEAR(Samenvatting!AU$41)) * Renteberekening!$J$2:$UK$29),0))} -> 0,0
... D130: 1 | E130: EUR | H130: 0.075 | I130: 47118 | J130: =YEAR(K130)-YEAR(I130) -> 3 | K130: 48213 | L130: {=IF(OR(Samenvatting!$C130="",ISBLANK(Samenvatting!$C130)),"0,0",IFERROR(SUMPRODUCT((Renteberekening!$B$2:$B$29=Samenvatting!$C130) * (YEAR(Renteberekening!$J$1:$UK$1)=YEAR(Samenvatting!L$41)) * Renteberekening!$J$2:$UK$29),0))} -> 0,0 | M130: {=IF(OR(Samenvatting!$C130="",ISBLANK(Samenvatting!$C130)),"0,0",IFERROR(SUMPRODUCT((Renteberekening!$B$2:$B$29=Samenvatting!$C130) * (YEAR(Renteberekening!$J$1:$UK$1)=YEAR(Samenvatting!M$41)) * Renteberekening!$J$2:$UK$29),0))} -> 0,0 | N130: {=IF(OR(Samenvatting!$C130="",ISBLANK(Samenvatting!$C130)),"0,0",IFERROR(SUMPRODUCT((Renteberekening!$B$2:$B$29=Samenvatting!$C130) * (YEAR(Renteberekening!$J$1:$UK$1)=YEAR(Samenvatting!N$41)) * Renteberekening!$J$2:$UK$29),0))} -> 0,0 | O130: {=IF(OR(Samenvatting!$C130="",ISBLANK(Samenvatting!$C130)),"0,0",IFERROR(SUMPRODUCT((Renteberekening!$B$2:$B$29=Samenvatting!$C130) * (YEAR(Renteberekening!$J$1:$UK$1)=YEAR(Samenvatting!O$41)) * Renteberekening!$J$2:$UK$29),0))} -> 0,0 | P130: {=IF(OR(Samenvatting!$C130="",ISBLANK(Samenvatting!$C130)),"0,0",IFERROR(SUMPRODUCT((Renteberekening!$B$2:$B$29=Samenvatting!$C130) * (YEAR(Renteberekening!$J$1:$UK$1)=YEAR(Samenvatting!P$41)) * Renteberekening!$J$2:$UK$29),0))} -> 0,0 | Q130: {=IF(OR(Samenvatting!$C130="",ISBLANK(Samenvatting!$C130)),"0,0",IFERROR(SUMPRODUCT((Renteberekening!$B$2:$B$29=Samenvatting!$C130) * (YEAR(Renteberekening!$J$1:$UK$1)=YEAR(Samenvatting!Q$41)) * Renteberekening!$J$2:$UK$29),0))} -> 0,0 | R130: {=IF(OR(Samenvatting!$C130="",ISBLANK(Samenvatting!$C130)),"0,0",IFERROR(SUMPRODUCT((Renteberekening!$B$2:$B$29=Samenvatting!$C130) * (YEAR(Renteberekening!$J$1:$UK$1)=YEAR(Samenvatting!R$41)) * Renteberekening!$J$2:$UK$29),0))} -> 0,0 | S130: {=IF(OR(Samenvatting!$C130="",ISBLANK(Samenvatting!$C130)),"0,0",IFERROR(SUMPRODUCT((Renteberekening!$B$2:$B$29=Samenvatting!$C130) * (YEAR(Renteberekening!$J$1:$UK$1)=YEAR(Samenvatting!S$41)) * Renteberekening!$J$2:$UK$29),0))} -> 0,0 | ... AU130: {=IF(OR(Samenvatting!$C130="",ISBLANK(Samenvatting!$C130)),"0,0",IFERROR(SUMPRODUCT((Renteberekening!$B$2:$B$29=Samenvatting!$C130) * (YEAR(Renteberekening!$J$1:$UK$1)=YEAR(Samenvatting!AU$41)) * Renteberekening!$J$2:$UK$29),0))} -> 0,0
C131: Cumulative Private Debt | E131: EUR | L131: =SUM(L103:L130) -> -6000525.2 | M131: =L131+SUM(M103:M130) -> -1717949.1 | N131: =M131+SUM(N103:N130) -> 469861.79 | O131: =N131+SUM(O103:O130) -> 469861.79 | P131: =O131+SUM(P103:P130) -> 469861.79 | Q131: =P131+SUM(Q103:Q130) -> 469861.79 | R131: =Q131+SUM(R103:R130) -> 469861.79 | S131: =R131+SUM(S103:S130) -> 469861.79 | T131: =S131+SUM(T103:T130) -> 469861.79 | ... AU131: =AT131+SUM(AU103:AU130) -> 469861.79
C132: Cumulative Cash Flow PE+PD | E132: EUR | L132: =L101+L131 -> -9661406.5 | M132: =L132+SUM(M43:M100)+SUM(M103:M130) -> -9533252.9 | N132: =M132+SUM(N43:N100)+SUM(N103:N130) -> -9532909.4 | O132: =N132+SUM(O43:O100)+SUM(O103:O130) -> -9532915.7 | P132: =O132+SUM(P43:P100)+SUM(P103:P130) -> -9533081.3 | Q132: =P132+SUM(Q43:Q100)+SUM(Q103:Q130) -> -9530885.2 | R132: =Q132+SUM(R43:R100)+SUM(R103:R130) -> -9531064.7 | S132: =R132+SUM(S43:S100)+SUM(S103:S130) -> -9530338.3 | T132: =S132+SUM(T43:T100)+SUM(T103:T130) -> -4901047.9 | ... AU132: =AT132+SUM(AU43:AU100)+SUM(AU103:AU130) -> 26408419
C133: Cash Exposure | E133: EUR | L133: =L132 -> -9661406.5 | M133: =M132 -> -9533252.9 | N133: =N132 -> -9532909.4 | O133: =O132 -> -9532915.7 | P133: =P132 -> -9533081.3 | Q133: =Q132 -> -9530885.2 | R133: =R132 -> -9531064.7 | S133: =S132 -> -9530338.3 | ... AU133: =AU132 -> 26408419
C134: Annual Net Cashflow | E134: EUR | L134: =SUM(L43:L100)+SUM(L103:L122) -> -9661406.5 | M134: =SUM(M43:M100)+SUM(M103:M122) -> 128153.64 | N134: =SUM(N43:N100)+SUM(N103:N122) -> 343.51475 | O134: =SUM(O43:O100)+SUM(O103:O122) -> -6.366089 | P134: =SUM(P43:P100)+SUM(P103:P122) -> -165.5425 | Q134: =SUM(Q43:Q100)+SUM(Q103:Q122) -> 2196.1314 | R134: =SUM(R43:R100)+SUM(R103:R122) -> -179.54616 | S134: =SUM(S43:S100)+SUM(S103:S122) -> 726.41696 | ... AU134: =SUM(AU43:AU100)+SUM(AU103:AU122) -> 0
C135: Commitment | E135: EUR | L135: =SUMIF(L43:L100,"<>0",$F$43:$F$100) -> 7900000 | M135: =SUMIF(M43:M100,"<>0",$F$43:$F$100) -> 15020000 | N135: =SUMIF(N43:N100,"<>0",$F$43:$F$100) -> 20220000 | O135: =SUMIF(O43:O100,"<>0",$F$43:$F$100) -> 22800000 | P135: =SUMIF(P43:P100,"<>0",$F$43:$F$100) -> 28080000 | Q135: =SUMIF(Q43:Q100,"<>0",$F$43:$F$100) -> 34230000 | R135: =SUMIF(R43:R100,"<>0",$F$43:$F$100) -> 42495000 | S135: =SUMIF(S43:S100,"<>0",$F$43:$F$100) -> 51268000 | ... AU135: =SUMIF(AU43:AU100,"<>0",$F$43:$F$100) -> 0
C137: Yield numerator | K137: 1 | L137: 1 | M137: 1 | N137: 1 | O137: 1 | P137: 1
C138: Yield denominator | K138: 1 | L138: 1 | M138: 1 | N138: 1 | O138: 1 | P138: 1
C139: Yield | K139: =K137/K138 -> 1 | L139: =L137/L138 -> 1 | M139: =M137/M138 -> 1 | N139: =N137/N138 -> 1 | O139: =O137/O138 -> 1 | P139: =P137/P138 -> 1
C141: Expected Performance | D141: Expected Multiple | E141: Expected IRR | F141: Average Yield (1)
C142: =C43 -> Secondaries Dummy | D142: =SUM(L115:X115)/SUM(L43:X43) -> 0 | E142: =IRR(L43:X43) -> 0.13229301 | F142: =AVERAGE(K139:P139) -> 1
C143: =C99 -> 0 | D143: =SUM(L116:X116)/SUM(L99:X99) -> #DIV/0! | E143: =IRR(L99:X99) -> #NUM! | F143: =AVERAGE(K140:P140) -> #DIV/0!
C144: =C100 -> 0 | D144: =SUM(L117:X117)/SUM(L100:X100) -> #DIV/0! | E144: =IRR(L100:X100) -> #NUM! | F144: =AVERAGE(K141:P141) -> #DIV/0!
C145: =#REF! -> #REF! | D145: =SUM(L118:X118)/SUM(#REF!) -> #REF! | E145: =IRR(#REF!) -> #REF! | F145: =AVERAGE(K142:P142) -> #DIV/0!
C146: Consolidated performance | D146: =X131/X101 -> 0.026270421 | E146: =AVERAGE(E142:E145) -> #NUM! | F146: =AVERAGE(K143:P143) -> #DIV/0!
M149: IRR | N149: =IRR(L134:AD134) -> 0.13285526
C152: Informatie en risico's
C153: Beleggen brengt risico’s en kosten met zich mee. De waarde van uw belegging kan fluctueren. In het verleden behaalde resultaten bieden geen garantie voor de toekomst. U kunt uw inleg of een deel hiervan verliezen. Het bovenstaande is uitsluitend bedoeld ter informatieve doeleinden en biedt geen indicatie van toekomstige prestaties of specifieke beleggingsadvies. De hierin verstrekte informatie is gebaseerd op gegevens die zijn aangeleverd door fondsen of verkregen uit externe databronnen, welke mogelijk onvolledig of niet verifieerbaar zijn. Derhalve kunnen er geen rechten aan dit overzicht worden ontleend. Voor de exacte fondsinformatie verwijzen wij naar de documentatie van de fondsmanager. Momentum Family Office is een handelsnaam van Momentum CFS B.V. Momentum CFS B.V. (KvK 76951707) beschikt over een vergunning van de Autoriteit Financiële Markten (AFM) voor het geven van beleggingsadvies en het ontvangen en doorgeven van orders in deelnemingsrechten in beleggingsinstellingen en icbe’s (beleggingsfondsen).Dit document mag niet worden opgevat als individueel beleggingsadvies, noch als een aanbod of verzoek tot het aangaan van een transactie. Het dient enkel ter ondersteuning van algemene discussie en overwegingen met betrekking tot toekomstige investeringsbeslissingen waarbij Momentum u mogelijk zal adviseren. De fiscale behandeling van een belegging kan afhankelijk zijn van individuele omstandigheden en aan wijzigingen onderhevig zijn. Momentum Family Office geeft geen belastingadvies, raadpleeg bij twijfel een fiscalist

Sheet Renteberekening
B1: Private debt | C1: Jaren | F1: Rente | G1: Start | I1: Einde looptijd | J1: 43982 | K1: 44012 | L1: 44043 | M1: 44074 | N1: 44104 | O1: 44135 | P1: 44165 | Q1: 44196 | R1: 44227 | S1: 44255 | T1: 44286 | U1: 44316 | V1: 44347 | W1: 44377 | X1: 44408 | Y1: 44439 | Z1: 44469 | AA1: 44500 | AB1: 44530 | AC1: 44561 | AD1: 44592 | AE1: 44620 | AF1: 44651 | AG1: 44681 | AH1: 44712 | AI1: 44742 | AJ1: 44773 | AK1: 44804 | AL1: 44834 | AM1: 44865 | AN1: 44895 | AO1: 44926 | AP1: 44957 | AQ1: 44985 | AR1: 45016 | AS1: 45046 | AT1: 45077 | AU1: 45107 | AV1: 45138 | AW1: 45169 | AX1: 45199 | AY1: 45230 | AZ1: 45260 | BA1: 45291 | BB1: 45322 | BC1: 45351 | BD1: 45382 | BE1: 45412 | BF1: 45443 | BG1: 45473 | BH1: 45504 | BI1: 45535 | BJ1: 45565 | BK1: 45596 | BL1: 45626 | BM1: 45657 | BN1: 45688 | BO1: 45716 | BP1: 45747 | BQ1: 45777 | BR1: 45808 | BS1: 45838 | BT1: 45869 | BU1: 45900 | BV1: 45930 | BW1: 45961 | BX1: 45991 | BY1: 46022 | BZ1: 46053 | CA1: 46081 | CB1: 46112 | CC1: 46142 | CD1: 46173 | CE1: 46203 | CF1: 46234 | CG1: 46265 | CH1: 46295 | CI1: 46326 | CJ1: 46356 | CK1: 46387 | CL1: 46418 | CM1: 46446 | CN1: 46477 | CO1: 46507 | CP1: 46538 | CQ1: 46568 | CR1: 46599 | CS1: 46630 | CT1: 46660 | CU1: 46691 | CV1: 46721 | CW1: 46752 | CX1: 46783 | CY1: 46812 | CZ1: 46843 | DA1: 46873 | DB1: 46904 | DC1: 46934 | DD1: 46965 | DE1: 46996 | DF1: 47026 | DG1: 47057 | DH1: 47087 | DI1: 47118 | DJ1: 47149 | DK1: 47177 | DL1: 47208 | DM1: 47238 | DN1: 47269 | DO1: 47299 | DP1: 47330 | DQ1: 47361 | DR1: 47391 | DS1: 47422 | DT1: 47452 | DU1: 47483 | DV1: 47514 | DW1: 47542 | DX1: 47573 | DY1: 47603 | DZ1: 47634 | EA1: 47664 | EB1: 47695 | EC1: 47726 | ED1: 47756 | EE1: 47787 | EF1: 47817 | EG1: 47848 | EH1: 47879 | EI1: 47907 | EJ1: 47938 | EK1: 47968 | EL1: 47999 | EM1: 48029 | EN1: 48060 | EO1: 48091 | EP1: 48121 | EQ1: 48152 | ER1: 48182 | ES1: 48213 | ET1: 48244 | EU1: 48273 | EV1: 48304 | EW1: 48334 | EX1: 48365 | EY1: 48395 | EZ1: 48426 | FA1: 48457 | FB1: 48487 | FC1: 48518 | FD1: 48548 | FE1: 48579 | FF1: 48610 | FG1: 48638 | FH1: 48669 | FI1: 48699 | FJ1: 48730 | FK1: 48760 | FL1: 48791 | FM1: 48822 | FN1: 48852 | FO1: 48883 | FP1: 48913 | FQ1: 48944 | FR1: 48975 | FS1: 49003 | FT1: 49034 | FU1: 49064 | FV1: 49095 | FW1: 49125 | FX1: 49156 | FY1: 49187 | FZ1: 49217 | GA1: 49248 | GB1: 49278 | GC1: 49309 | GD1: 49340 | GE1: 49368 | GF1: 49399 | GG1: 49429 | GH1: 49460 | GI1: 49490 | GJ1: 49521 | GK1: 49552 | GL1: 49582 | GM1: 49613 | GN1: 49643 | GO1: 49674 | GP1: 49705 | GQ1: 49734 | GR1: 49765 | GS1: 49795 | GT1: 49826 | GU1: 49856 | GV1: 49887 | GW1: 49918 | GX1: 49948 | GY1: 49979 | GZ1: 50009 | HA1: 50040 | HB1: 50071 | HC1: 50099 | HD1: 50130 | HE1: 50160 | HF1: 50191 | HG1: 50221 | HH1: 50252 | HI1: 50283 | HJ1: 50313 | HK1: 50344 | HL1: 50374 | HM1: 50405 | HN1: 50436 | HO1: 50464 | HP1: 50495 | HQ1: 50525 | HR1: 50556 | HS1: 50586 | HT1: 50617 | HU1: 50648 | HV1: 50678 | HW1: 50709 | HX1: 50739 | HY1: 50770 | HZ1: 50801 | IA1: 50829 | IB1: 50860 | IC1: 50890 | ID1: 50921 | IE1: 50951 | IF1: 50982 | IG1: 51013 | IH1: 51043 | II1: 51074 | IJ1: 51104 | IK1: 51135 | IL1: 51166 | IM1: 51195 | IN1: 51226 | IO1: 51256 | IP1: 51287 | IQ1: 51317 | IR1: 51348 | IS1: 51379 | IT1: 51409 | IU1: 51440 | IV1: 51470 | IW1: 51501 | IX1: 51532 | IY1: 51560 | IZ1: 51591 | JA1: 51621 | JB1: 51652 | JC1: 51682 | JD1: 51713 | JE1: 51744 | JF1: 51774 | JG1: 51805 | JH1: 51835 | JI1: 51866 | JJ1: 51897 | JK1: 51925 | JL1: 51956 | JM1: 51986 | JN1: 52017 | JO1: 52047 | JP1: 52078 | JQ1: 52109 | JR1: 52139 | JS1: 52170 | JT1: 52200 | JU1: 52231 | JV1: 52262 | JW1: 52290 | JX1: 52321 | JY1: 52351 | JZ1: 52382 | KA1: 52412 | KB1: 52443 | KC1: 52474 | KD1: 52504 | KE1: 52535 | KF1: 52565 | KG1: 52596 | KH1: 52627 | KI1: 52656 | KJ1: 52687 | KK1: 52717 | KL1: 52748 | KM1: 52778 | KN1: 52809 | KO1: 52840 | KP1: 52870 | KQ1: 52901 | KR1: 52931 | KS1: 52962 | KT1: 52993 | KU1: 53021 | KV1: 53052 | KW1: 53082 | KX1: 53113 | KY1: 53143 | KZ1: 53174 | LA1: 53205 | LB1: 53235 | LC1: 53266 | LD1: 53296 | LE1: 53327 | LF1: 53358 | LG1: 53386 | LH1: 53417 | LI1: 53447 | LJ1: 53478 | LK1: 53508 | LL1: 53539 | LM1: 53570 | LN1: 53600 | LO1: 53631 | LP1: 53661 | LQ1: 53692 | LR1: 53723 | LS1: 53751 | LT1: 53782 | LU1: 53812 | LV1: 53843 | LW1: 53873 | LX1: 53904 | LY1: 53935 | LZ1: 53965 | MA1: 53996 | MB1: 54026 | MC1: 54057 | MD1: 54088 | ME1: 54117 | MF1: 54148 | MG1: 54178 | MH1: 54209 | MI1: 54239 | MJ1: 54270 | MK1: 54301 | ML1: 54331 | MM1: 54362 | MN1: 54392 | MO1: 54423 | MP1: 54454 | MQ1: 54482 | MR1: 54513 | MS1: 54543 | MT1: 54574 | MU1: 54604 | MV1: 54635 | MW1: 54666 | MX1: 54696 | MY1: 54727 | MZ1: 54757 | NA1: 54788 | NB1: 54819 | NC1: 54847 | ND1: 54878 | NE1: 54908 | NF1: 54939 | NG1: 54969 | NH1: 55000 | NI1: 55031 | NJ1: 55061 | NK1: 55092 | NL1: 55122 | NM1: 55153 | NN1: 55184 | NO1: 55212 | NP1: 55243 | NQ1: 55273 | NR1: 55304 | NS1: 55334 | NT1: 55365 | NU1: 55396 | NV1: 55426 | NW1: 55457 | NX1: 55487 | NY1: 55518 | NZ1: 55549 | OA1: 55578 | OB1: 55609 | OC1: 55639 | OD1: 55670 | OE1: 55700 | OF1: 55731 | OG1: 55762 | OH1: 55792 | OI1: 55823 | OJ1: 55853 | OK1: 55884 | OL1: 55915 | OM1: 55943 | ON1: 55974 | OO1: 56004 | OP1: 56035 | OQ1: 56065 | OR1: 56096 | OS1: 56127 | OT1: 56157 | OU1: 56188 | OV1: 56218 | OW1: 56249 | OX1: 56280 | OY1: 56308 | OZ1: 56339 | PA1: 56369 | PB1: 56400 | PC1: 56430 | PD1: 56461 | PE1: 56492 | PF1: 56522 | PG1: 56553 | PH1: 56583 | PI1: 56614 | PJ1: 56645 | PK1: 56673 | PL1: 56704 | PM1: 56734 | PN1: 56765 | PO1: 56795 | PP1: 56826 | PQ1: 56857 | PR1: 56887 | PS1: 56918 | PT1: 56948 | PU1: 56979 | PV1: 57010 | PW1: 57039 | PX1: 57070 | PY1: 57100 | PZ1: 57131 | QA1: 57161 | QB1: 57192 | QC1: 57223 | QD1: 57253 | QE1: 57284 | QF1: 57314 | QG1: 57345 | QH1: 57376 | QI1: 57404 | QJ1: 57435 | QK1: 57465 | QL1: 57496 | QM1: 57526 | QN1: 57557 | QO1: 57588 | QP1: 57618 | QQ1: 57649 | QR1: 57679 | QS1: 57710 | QT1: 57741 | QU1: 57769 | QV1: 57800 | QW1: 57830 | QX1: 57861 | QY1: 57891 | QZ1: 57922 | RA1: 57953 | RB1: 57983 | RC1: 58014 | RD1: 58044 | RE1: 58075 | RF1: 58106 | RG1: 58134 | RH1: 58165 | RI1: 58195 | RJ1: 58226 | RK1: 58256 | RL1: 58287 | RM1: 58318 | RN1: 58348 | RO1: 58379 | RP1: 58409 | RQ1: 58440 | RR1: 58471 | RS1: 58500 | RT1: 58531 | RU1: 58561 | RV1: 58592 | RW1: 58622 | RX1: 58653 | RY1: 58684 | RZ1: 58714 | SA1: 58745 | SB1: 58775 | SC1: 58806 | SD1: 58837 | SE1: 58865 | SF1: 58896 | SG1: 58926 | SH1: 58957 | SI1: 58987 | SJ1: 59018 | SK1: 59049 | SL1: 59079 | SM1: 59110 | SN1: 59140 | SO1: 59171 | SP1: 59202 | SQ1: 59230 | SR1: 59261 | SS1: 59291 | ST1: 59322 | SU1: 59352 | SV1: 59383 | SW1: 59414 | SX1: 59444 | SY1: 59475 | SZ1: 59505 | TA1: 59536 | TB1: 59567 | TC1: 59595 | TD1: 59626 | TE1: 59656 | TF1: 59687 | TG1: 59717 | TH1: 59748 | TI1: 59779 | TJ1: 59809 | TK1: 59840 | TL1: 59870 | TM1: 59901 | TN1: 59932 | TO1: 59961 | TP1: 59992 | TQ1: 60022 | TR1: 60053 | TS1: 60083 | TT1: 60114 | TU1: 60145 | TV1: 60175 | TW1: 60206 | TX1: 60236 | TY1: 60267 | TZ1: 60298 | UA1: 60326 | UB1: 60357 | UC1: 60387 | UD1: 60418 | UE1: 60448 | UF1: 60479 | UG1: 60510 | UH1: 60540 | UI1: 60571 | UJ1: 60601 | UK1: 60632
B2: =IF(Samenvatting!$F103<>0,Samenvatting!C103,"") -> private debt 1 | C2: =IF(Samenvatting!$F103<>0,Samenvatting!D103,"") -> 1 | D2: =IF(Samenvatting!$F103<>0,Samenvatting!E103,"") -> EUR | E2: =IF(Samenvatting!$F103<>0,Samenvatting!F103,"") -> 4154000 | F2: =IF(Samenvatting!$F103<>0,Samenvatting!H103,"") -> 0.08 | G2: =IF(Samenvatting!$F103<>0,Samenvatting!I103,"") -> 46023 | H2: =IF(Samenvatting!$F103<>0,Samenvatting!J103,"") -> 1 | I2: =IF(Samenvatting!$F103<>0,Samenvatting!K103,"") -> 46388 | J2: =IFERROR(IF(J$1=EOMONTH($G2,0),(-$E2+($E2*(DAY($G2)/DAY(EOMONTH(J$1,0)))*$F2/12*(1-0.269))),IF(J$1=$G2,($E2+($E2*(DAY($I2)/DAY(EOMONTH(J$1,0)))*$F2/12*(1-0.269))),IFERROR(IF($I2<J$1,0,IF(J$1>$I2,(($F2/12)*$E2)*(DAY($I2)/DAY(EOMONTH(J$1,0)))*(1-26.9/100)+$E2,IF(AND(J$1>=$G2,J$1<$I2),(($F2/12)*$E2)*(1-26.9/100),""))-IF(J$1=EOMONTH($G2,0),$E2,"0")),0)+IF(J$1=EOMONTH($I2,0),($E2+($E2*(DAY($I2)/DAY(EOMONTH(J$1,0)))*$F2/12*(1-0.269))),"0"))),0) -> 0 | K2: =IFERROR(IF(K$1=EOMONTH($G2,0),(-$E2+($E2*(DAY($G2)/DAY(EOMONTH(K$1,0)))*$F2/12*(1-0.269))),IF(K$1=$G2,($E2+($E2*(DAY($I2)/DAY(EOMONTH(K$1,0)))*$F2/12*(1-0.269))),IFERROR(IF($I2<K$1,0,IF(K$1>$I2,(($F2/12)*$E2)*(DAY($I2)/DAY(EOMONTH(K$1,0)))*(1-26.9/100)+$E2,IF(AND(K$1>=$G2,K$1<$I2),(($F2/12)*$E2)*(1-26.9/100),""))-IF(K$1=EOMONTH($G2,0),$E2,"0")),0)+IF(K$1=EOMONTH($I2,0),($E2+($E2*(DAY($I2)/DAY(EOMONTH(K$1,0)))*$F2/12*(1-0.269))),"0"))),0) -> 0 | L2: =IFERROR(IF(L$1=EOMONTH($G2,0),(-$E2+($E2*(DAY($G2)/DAY(EOMONTH(L$1,0)))*$F2/12*(1-0.269))),IF(L$1=$G2,($E2+($E2*(DAY($I2)/DAY(EOMONTH(L$1,0)))*$F2/12*(1-0.269))),IFERROR(IF($I2<L$1,0,IF(L$1>$I2,(($F2/12)*$E2)*(DAY($I2)/DAY(EOMONTH(L$1,0)))*(1-26.9/100)+$E2,IF(AND(L$1>=$G2,L$1<$I2),(($F2/12)*$E2)*(1-26.9/100),""))-IF(L$1=EOMONTH($G2,0),$E2,"0")),0)+IF(L$1=EOMONTH($I2,0),($E2+($E2*(DAY($I2)/DAY(EOMONTH(L$1,0)))*$F2/12*(1-0.269))),"0"))),0) -> 0 | M2: =IFERROR(IF(M$1=EOMONTH($G2,0),(-$E2+($E2*(DAY($G2)/DAY(EOMONTH(M$1,0)))*$F2/12*(1-0.269))),IF(M$1=$G2,($E2+($E2*(DAY($I2)/DAY(EOMONTH(M$1,0)))*$F2/12*(1-0.269))),IFERROR(IF($I2<M$1,0,IF(M$1>$I2,(($F2/12)*$E2)*(DAY($I2)/DAY(EOMONTH(M$1,0)))*(1-26.9/100)+$E2,IF(AND(M$1>=$G2,M$1<$I2),(($F2/12)*$E2)*(1-26.9/100),""))-IF(M$1=EOMONTH($G2,0),$E2,"0")),0)+IF(M$1=EOMONTH($I2,0),($E2+($E2*(DAY($I2)/DAY(EOMONTH(M$1,0)))*$F2/12*(1-0.269))),"0"))),0) -> 0 | N2: =IFERROR(IF(N$1=EOMONTH($G2,0),(-$E2+($E2*(DAY($G2)/DAY(EOMONTH(N$1,0)))*$F2/12*(1-0.269))),IF(N$1=$G2,($E2+($E2*(DAY($I2)/DAY(EOMONTH(N$1,0)))*$F2/12*(1-0.269))),IFERROR(IF($I2<N$1,0,IF(N$1>$I2,(($F2/12)*$E2)*(DAY($I2)/DAY(EOMONTH(N$1,0)))*(1-26.9/100)+$E2,IF(AND(N$1>=$G2,N$1<$I2),(($F2/12)*$E2)*(1-26.9/100),""))-IF(N$1=EOMONTH($G2,0),$E2,"0")),0)+IF(N$1=EOMONTH($I2,0),($E2+($E2*(DAY($I2)/DAY(EOMONTH(N$1,0)))*$F2/12*(1-0.269))),"0"))),0) -> 0 | O2: =IFERROR(IF(O$1=EOMONTH($G2,0),(-$E2+($E2*(DAY($G2)/DAY(EOMONTH(O$1,0)))*$F2/12*(1-0.269))),IF(O$1=$G2,($E2+($E2*(DAY($I2)/DAY(EOMONTH(O$1,0)))*$F2/12*(1-0.269))),IFERROR(IF($I2<O$1,0,IF(O$1>$I2,(($F2/12)*$E2)*(DAY($I2)/DAY(EOMONTH(O$1,0)))*(1-26.9/100)+$E2,IF(AND(O$1>=$G2,O$1<$I2),(($F2/12)*$E2)*(1-26.9/100),""))-IF(O$1=EOMONTH($G2,0),$E2,"0")),0)+IF(O$1=EOMONTH($I2,0),($E2+($E2*(DAY($I2)/DAY(EOMONTH(O$1,0)))*$F2/12*(1-0.269))),"0"))),0) -> 0 | P2: =IFERROR(IF(P$1=EOMONTH($G2,0),(-$E2+($E2*(DAY($G2)/DAY(EOMONTH(P$1,0)))*$F2/12*(1-0.269))),IF(P$1=$G2,($E2+($E2*(DAY($I2)/DAY(EOMONTH(P$1,0)))*$F2/12*(1-0.269))),IFERROR(IF($I2<P$1,0,IF(P$1>$I2,(($F2/12)*$E2)*(DAY($I2)/DAY(EOMONTH(P$1,0)))*(1-26.9/100)+$E2,IF(AND(P$1>=$G2,P$1<$I2),(($F2/12)*$E2)*(1-26.9/100),""))-IF(P$1=EOMONTH($G2,0),$E2,"0")),0)+IF(P$1=EOMONTH($I2,0),($E2+($E2*(DAY($I2)/DAY(EOMONTH(P$1,0)))*$F2/12*(1-0.269))),"0"))),0) -> 0 | Q2: =IFERROR(IF(Q$1=EOMONTH($G2,0),(-$E2+($E2*(DAY($G2)/DAY(EOMONTH(Q$1,0)))*$F2/12*(1-0.269))),IF(Q$1=$G2,($E2+($E2*(DAY($I2)/DAY(EOMONTH(Q$1,0)))*$F2/12*(1-0.269))),IFERROR(IF($I2<Q$1,0,IF(Q$1>$I2,(($F2/12)*$E2)*(DAY($I2)/DAY(EOMONTH(Q$1,0)))*(1-26.9/100)+$E2,IF(AND(Q$1>=$G2,Q$1<$I2),(($F2/12)*$E2)*(1-26.9/100),""))-IF(Q$1=EOMONTH($G2,0),$E2,"0")),0)+IF(Q$1=EOMONTH($I2,0),($E2+($E2*(DAY($I2)/DAY(EOMONTH(Q$1,0)))*$F2/12*(1-0.269))),"0"))),0) -> 0 | ... UK2: =IFERROR(IF(UK$1=EOMONTH($G2,0),(-$E2+($E2*(DAY($G2)/DAY(EOMONTH(UK$1,0)))*$F2/12*(1-0.269))),IF(UK$1=$G2,($E2+($E2*(DAY($I2)/DAY(EOMONTH(UK$1,0)))*$F2/12*(1-0.269))),IFERROR(IF($I2<UK$1,0,IF(UK$1>$I2,(($F2/12)*$E2)*(DAY($I2)/DAY(EOMONTH(UK$1,0)))*(1-26.9/100)+$E2,IF(AND(UK$1>=$G2,UK$1<$I2),(($F2/12)*$E2)*(1-26.9/100),""))-IF(UK$1=EOMONTH($G2,0),$E2,"0")),0)+IF(UK$1=EOMONTH($I2,0),($E2+($E2*(DAY($I2)/DAY(EOMONTH(UK$1,0)))*$F2/12*(1-0.269))),"0"))),0) -> 0
B3: =IF(Samenvatting!$F104<>0,Samenvatting!C104,"") -> private debt 2 | C3: =IF(Samenvatting!$F104<>0,Samenvatting!D104,"") -> 2 | D3: =IF(Samenvatting!$F104<>0,Samenvatting!E104,"") -> EUR | E3: =IF(Samenvatting!$F104<>0,Samenvatting!F104,"") -> 2187467 | F3: =IF(Samenvatting!$F104<>0,Samenvatting!H104,"") -> 0.08 | G3: =IF(Samenvatting!$F104<>0,Samenvatting!I104,"") -> 46023 | H3: =IF(Samenvatting!$F104<>0,Samenvatting!J104,"") -> 2 | I3: =IF(Samenvatting!$F104<>0,Samenvatting!K104,"") -> 46753 | J3: =IFERROR(IF(J$1=EOMONTH($G3,0),(-$E3+($E3*(DAY($G3)/DAY(EOMONTH(J$1,0)))*$F3/12*(1-0.269))),IF(J$1=$G3,($E3+($E3*(DAY($I3)/DAY(EOMONTH(J$1,0)))*$F3/12*(1-0.269))),IFERROR(IF($I3<J$1,0,IF(J$1>$I3,(($F3/12)*$E3)*(DAY($I3)/DAY(EOMONTH(J$1,0)))*(1-26.9/100)+$E3,IF(AND(J$1>=$G3,J$1<$I3),(($F3/12)*$E3)*(1-26.9/100),""))-IF(J$1=EOMONTH($G3,0),$E3,"0")),0)+IF(J$1=EOMONTH($I3,0),($E3+($E3*(DAY($I3)/DAY(EOMONTH(J$1,0)))*$F3/12*(1-0.269))),"0"))),0) -> 0 | K3: =IFERROR(IF(K$1=EOMONTH($G3,0),(-$E3+($E3*(DAY($G3)/DAY(EOMONTH(K$1,0)))*$F3/12*(1-0.269))),IF(K$1=$G3,($E3+($E3*(DAY($I3)/DAY(EOMONTH(K$1,0)))*$F3/12*(1-0.269))),IFERROR(IF($I3<K$1,0,IF(K$1>$I3,(($F3/12)*$E3)*(DAY($I3)/DAY(EOMONTH(K$1,0)))*(1-26.9/100)+$E3,IF(AND(K$1>=$G3,K$1<$I3),(($F3/12)*$E3)*(1-26.9/100),""))-IF(K$1=EOMONTH($G3,0),$E3,"0")),0)+IF(K$1=EOMONTH($I3,0),($E3+($E3*(DAY($I3)/DAY(EOMONTH(K$1,0)))*$F3/12*(1-0.269))),"0"))),0) -> 0 | L3: =IFERROR(IF(L$1=EOMONTH($G3,0),(-$E3+($E3*(DAY($G3)/DAY(EOMONTH(L$1,0)))*$F3/12*(1-0.269))),IF(L$1=$G3,($E3+($E3*(DAY($I3)/DAY(EOMONTH(L$1,0)))*$F3/12*(1-0.269))),IFERROR(IF($I3<L$1,0,IF(L$1>$I3,(($F3/12)*$E3)*(DAY($I3)/DAY(EOMONTH(L$1,0)))*(1-26.9/100)+$E3,IF(AND(L$1>=$G3,L$1<$I3),(($F3/12)*$E3)*(1-26.9/100),""))-IF(L$1=EOMONTH($G3,0),$E3,"0")),0)+IF(L$1=EOMONTH($I3,0),($E3+($E3*(DAY($I3)/DAY(EOMONTH(L$1,0)))*$F3/12*(1-0.269))),"0"))),0) -> 0 | M3: =IFERROR(IF(M$1=EOMONTH($G3,0),(-$E3+($E3*(DAY($G3)/DAY(EOMONTH(M$1,0)))*$F3/12*(1-0.269))),IF(M$1=$G3,($E3+($E3*(DAY($I3)/DAY(EOMONTH(M$1,0)))*$F3/12*(1-0.269))),IFERROR(IF($I3<M$1,0,IF(M$1>$I3,(($F3/12)*$E3)*(DAY($I3)/DAY(EOMONTH(M$1,0)))*(1-26.9/100)+$E3,IF(AND(M$1>=$G3,M$1<$I3),(($F3/12)*$E3)*(1-26.9/100),""))-IF(M$1=EOMONTH($G3,0),$E3,"0")),0)+IF(M$1=EOMONTH($I3,0),($E3+($E3*(DAY($I3)/DAY(EOMONTH(M$1,0)))*$F3/12*(1-0.269))),"0"))),0) -> 0 | N3: =IFERROR(IF(N$1=EOMONTH($G3,0),(-$E3+($E3*(DAY($G3)/DAY(EOMONTH(N$1,0)))*$F3/12*(1-0.269))),IF(N$1=$G3,($E3+($E3*(DAY($I3)/DAY(EOMONTH(N$1,0)))*$F3/12*(1-0.269))),IFERROR(IF($I3<N$1,0,IF(N$1>$I3,(($F3/12)*$E3)*(DAY($I3)/DAY(EOMONTH(N$1,0)))*(1-26.9/100)+$E3,IF(AND(N$1>=$G3,N$1<$I3),(($F3/12)*$E3)*(1-26.9/100),""))-IF(N$1=EOMONTH($G3,0),$E3,"0")),0)+IF(N$1=EOMONTH($I3,0),($E3+($E3*(DAY($I3)/DAY(EOMONTH(N$1,0)))*$F3/12*(1-0.269))),"0"))),0) -> 0 | O3: =IFERROR(IF(O$1=EOMONTH($G3,0),(-$E3+($E3*(DAY($G3)/DAY(EOMONTH(O$1,0)))*$F3/12*(1-0.269))),IF(O$1=$G3,($E3+($E3*(DAY($I3)/DAY(EOMONTH(O$1,0)))*$F3/12*(1-0.269))),IFERROR(IF($I3<O$1,0,IF(O$1>$I3,(($F3/12)*$E3)*(DAY($I3)/DAY(EOMONTH(O$1,0)))*(1-26.9/100)+$E3,IF(AND(O$1>=$G3,O$1<$I3),(($F3/12)*$E3)*(1-26.9/100),""))-IF(O$1=EOMONTH($G3,0),$E3,"0")),0)+IF(O$1=EOMONTH($I3,0),($E3+($E3*(DAY($I3)/DAY(EOMONTH(O$1,0)))*$F3/12*(1-0.269))),"0"))),0) -> 0 | P3: =IFERROR(IF(P$1=EOMONTH($G3,0),(-$E3+($E3*(DAY($G3)/DAY(EOMONTH(P$1,0)))*$F3/12*(1-0.269))),IF(P$1=$G3,($E3+($E3*(DAY($I3)/DAY(EOMONTH(P$1,0)))*$F3/12*(1-0.269))),IFERROR(IF($I3<P$1,0,IF(P$1>$I3,(($F3/12)*$E3)*(DAY($I3)/DAY(EOMONTH(P$1,0)))*(1-26.9/100)+$E3,IF(AND(P$1>=$G3,P$1<$I3),(($F3/12)*$E3)*(1-26.9/100),""))-IF(P$1=EOMONTH($G3,0),$E3,"0")),0)+IF(P$1=EOMONTH($I3,0),($E3+($E3*(DAY($I3)/DAY(EOMONTH(P$1,0)))*$F3/12*(1-0.269))),"0"))),0) -> 0 | Q3: =IFERROR(IF(Q$1=EOMONTH($G3,0),(-$E3+($E3*(DAY($G3)/DAY(EOMONTH(Q$1,0)))*$F3/12*(1-0.269))),IF(Q$1=$G3,($E3+($E3*(DAY($I3)/DAY(EOMONTH(Q$1,0)))*$F3/12*(1-0.269))),IFERROR(IF($I3<Q$1,0,IF(Q$1>$I3,(($F3/12)*$E3)*(DAY($I3)/DAY(EOMONTH(Q$1,0)))*(1-26.9/100)+$E3,IF(AND(Q$1>=$G3,Q$1<$I3),(($F3/12)*$E3)*(1-26.9/100),""))-IF(Q$1=EOMONTH($G3,0),$E3,"0")),0)+IF(Q$1=EOMONTH($I3,0),($E3+($E3*(DAY($I3)/DAY(EOMONTH(Q$1,0)))*$F3/12*(1-0.269))),"0"))),0) -> 0 | ... UK3: =IFERROR(IF(UK$1=EOMONTH($G3,0),(-$E3+($E3*(DAY($G3)/DAY(EOMONTH(UK$1,0)))*$F3/12*(1-0.269))),IF(UK$1=$G3,($E3+($E3*(DAY($I3)/DAY(EOMONTH(UK$1,0)))*$F3/12*(1-0.269))),IFERROR(IF($I3<UK$1,0,IF(UK$1>$I3,(($F3/12)*$E3)*(DAY($I3)/DAY(EOMONTH(UK$1,0)))*(1-26.9/100)+$E3,IF(AND(UK$1>=$G3,UK$1<$I3),(($F3/12)*$E3)*(1-26.9/100),""))-IF(UK$1=EOMONTH($G3,0),$E3,"0")),0)+IF(UK$1=EOMONTH($I3,0),($E3+($E3*(DAY($I3)/DAY(EOMONTH(UK$1,0)))*$F3/12*(1-0.269))),"0"))),0) -> 0
B4: =IF(Samenvatting!$F105<>0,Samenvatting!C105,"") | C4: =IF(Samenvatting!$F105<>0,Samenvatting!D105,"") | D4: =IF(Samenvatting!$F105<>0,Samenvatting!E105,"") | E4: =IF(Samenvatting!$F105<>0,Samenvatting!F105,"") | F4: =IF(Samenvatting!$F105<>0,Samenvatting!H105,"") | G4: =IF(Samenvatting!$F105<>0,Samenvatting!I105,"") | H4: =IF(Samenvatting!$F105<>0,Samenvatting!J105,"") | I4: =IF(Samenvatting!$F105<>0,Samenvatting!K105,"") | J4: =IFERROR(IF(J$1=EOMONTH($G4,0),(-$E4+($E4*(DAY($G4)/DAY(EOMONTH(J$1,0)))*$F4/12*(1-0.269))),IF(J$1=$G4,($E4+($E4*(DAY($I4)/DAY(EOMONTH(J$1,0)))*$F4/12*(1-0.269))),IFERROR(IF($I4<J$1,0,IF(J$1>$I4,(($F4/12)*$E4)*(DAY($I4)/DAY(EOMONTH(J$1,0)))*(1-26.9/100)+$E4,IF(AND(J$1>=$G4,J$1<$I4),(($F4/12)*$E4)*(1-26.9/100),""))-IF(J$1=EOMONTH($G4,0),$E4,"0")),0)+IF(J$1=EOMONTH($I4,0),($E4+($E4*(DAY($I4)/DAY(EOMONTH(J$1,0)))*$F4/12*(1-0.269))),"0"))),0) -> 0 | K4: =IFERROR(IF(K$1=EOMONTH($G4,0),(-$E4+($E4*(DAY($G4)/DAY(EOMONTH(K$1,0)))*$F4/12*(1-0.269))),IF(K$1=$G4,($E4+($E4*(DAY($I4)/DAY(EOMONTH(K$1,0)))*$F4/12*(1-0.269))),IFERROR(IF($I4<K$1,0,IF(K$1>$I4,(($F4/12)*$E4)*(DAY($I4)/DAY(EOMONTH(K$1,0)))*(1-26.9/100)+$E4,IF(AND(K$1>=$G4,K$1<$I4),(($F4/12)*$E4)*(1-26.9/100),""))-IF(K$1=EOMONTH($G4,0),$E4,"0")),0)+IF(K$1=EOMONTH($I4,0),($E4+($E4*(DAY($I4)/DAY(EOMONTH(K$1,0)))*$F4/12*(1-0.269))),"0"))),0) -> 0 | L4: =IFERROR(IF(L$1=EOMONTH($G4,0),(-$E4+($E4*(DAY($G4)/DAY(EOMONTH(L$1,0)))*$F4/12*(1-0.269))),IF(L$1=$G4,($E4+($E4*(DAY($I4)/DAY(EOMONTH(L$1,0)))*$F4/12*(1-0.269))),IFERROR(IF($I4<L$1,0,IF(L$1>$I4,(($F4/12)*$E4)*(DAY($I4)/DAY(EOMONTH(L$1,0)))*(1-26.9/100)+$E4,IF(AND(L$1>=$G4,L$1<$I4),(($F4/12)*$E4)*(1-26.9/100),""))-IF(L$1=EOMONTH($G4,0),$E4,"0")),0)+IF(L$1=EOMONTH($I4,0),($E4+($E4*(DAY($I4)/DAY(EOMONTH(L$1,0)))*$F4/12*(1-0.269))),"0"))),0) -> 0 | M4: =IFERROR(IF(M$1=EOMONTH($G4,0),(-$E4+($E4*(DAY($G4)/DAY(EOMONTH(M$1,0)))*$F4/12*(1-0.269))),IF(M$1=$G4,($E4+($E4*(DAY($I4)/DAY(EOMONTH(M$1,0)))*$F4/12*(1-0.269))),IFERROR(IF($I4<M$1,0,IF(M$1>$I4,(($F4/12)*$E4)*(DAY($I4)/DAY(EOMONTH(M$1,0)))*(1-26.9/100)+$E4,IF(AND(M$1>=$G4,M$1<$I4),(($F4/12)*$E4)*(1-26.9/100),""))-IF(M$1=EOMONTH($G4,0),$E4,"0")),0)+IF(M$1=EOMONTH($I4,0),($E4+($E4*(DAY($I4)/DAY(EOMONTH(M$1,0)))*$F4/12*(1-0.269))),"0"))),0) -> 0 | N4: =IFERROR(IF(N$1=EOMONTH($G4,0),(-$E4+($E4*(DAY($G4)/DAY(EOMONTH(N$1,0)))*$F4/12*(1-0.269))),IF(N$1=$G4,($E4+($E4*(DAY($I4)/DAY(EOMONTH(N$1,0)))*$F4/12*(1-0.269))),IFERROR(IF($I4<N$1,0,IF(N$1>$I4,(($F4/12)*$E4)*(DAY($I4)/DAY(EOMONTH(N$1,0)))*(1-26.9/100)+$E4,IF(AND(N$1>=$G4,N$1<$I4),(($F4/12)*$E4)*(1-26.9/100),""))-IF(N$1=EOMONTH($G4,0),$E4,"0")),0)+IF(N$1=EOMONTH($I4,0),($E4+($E4*(DAY($I4)/DAY(EOMONTH(N$1,0)))*$F4/12*(1-0.269))),"0"))),0) -> 0 | O4: =IFERROR(IF(O$1=EOMONTH($G4,0),(-$E4+($E4*(DAY($G4)/DAY(EOMONTH(O$1,0)))*$F4/12*(1-0.269))),IF(O$1=$G4,($E4+($E4*(DAY($I4)/DAY(EOMONTH(O$1,0)))*$F4/12*(1-0.269))),IFERROR(IF($I4<O$1,0,IF(O$1>$I4,(($F4/12)*$E4)*(DAY($I4)/DAY(EOMONTH(O$1,0)))*(1-26.9/100)+$E4,IF(AND(O$1>=$G4,O$1<$I4),(($F4/12)*$E4)*(1-26.9/100),""))-IF(O$1=EOMONTH($G4,0),$E4,"0")),0)+IF(O$1=EOMONTH($I4,0),($E4+($E4*(DAY($I4)/DAY(EOMONTH(O$1,0)))*$F4/12*(1-0.269))),"0"))),0) -> 0 | P4: =IFERROR(IF(P$1=EOMONTH($G4,0),(-$E4+($E4*(DAY($G4)/DAY(EOMONTH(P$1,0)))*$F4/12*(1-0.269))),IF(P$1=$G4,($E4+($E4*(DAY($I4)/DAY(EOMONTH(P$1,0)))*$F4/12*(1-0.269))),IFERROR(IF($I4<P$1,0,IF(P$1>$I4,(($F4/12)*$E4)*(DAY($I4)/DAY(EOMONTH(P$1,0)))*(1-26.9/100)+$E4,IF(AND(P$1>=$G4,P$1<$I4),(($F4/12)*$E4)*(1-26.9/100),""))-IF(P$1=EOMONTH($G4,0),$E4,"0")),0)+IF(P$1=EOMONTH($I4,0),($E4+($E4*(DAY($I4)/DAY(EOMONTH(P$1,0)))*$F4/12*(1-0.269))),"0"))),0) -> 0 | Q4: =IFERROR(IF(Q$1=EOMONTH($G4,0),(-$E4+($E4*(DAY($G4)/DAY(EOMONTH(Q$1,0)))*$F4/12*(1-0.269))),IF(Q$1=$G4,($E4+($E4*(DAY($I4)/DAY(EOMONTH(Q$1,0)))*$F4/12*(1-0.269))),IFERROR(IF($I4<Q$1,0,IF(Q$1>$I4,(($F4/12)*$E4)*(DAY($I4)/DAY(EOMONTH(Q$1,0)))*(1-26.9/100)+$E4,IF(AND(Q$1>=$G4,Q$1<$I4),(($F4/12)*$E4)*(1-26.9/100),""))-IF(Q$1=EOMONTH($G4,0),$E4,"0")),0)+IF(Q$1=EOMONTH($I4,0),($E4+($E4*(DAY($I4)/DAY(EOMONTH(Q$1,0)))*$F4/12*(1-0.269))),"0"))),0) -> 0 | ... UK4: =IFERROR(IF(UK$1=EOMONTH($G4,0),(-$E4+($E4*(DAY($G4)/DAY(EOMONTH(UK$1,0)))*$F4/12*(1-0.269))),IF(UK$1=$G4,($E4+($E4*(DAY($I4)/DAY(EOMONTH(UK$1,0)))*$F4/12*(1-0.269))),IFERROR(IF($I4<UK$1,0,IF(UK$1>$I4,(($F4/12)*$E4)*(DAY($I4)/DAY(EOMONTH(UK$1,0)))*(1-26.9/100)+$E4,IF(AND(UK$1>=$G4,UK$1<$I4),(($F4/12)*$E4)*(1-26.9/100),""))-IF(UK$1=EOMONTH($G4,0),$E4,"0")),0)+IF(UK$1=EOMONTH($I4,0),($E4+($E4*(DAY($I4)/DAY(EOMONTH(UK$1,0)))*$F4/12*(1-0.269))),"0"))),0) -> 0
B5: =IF(Samenvatting!$F106<>0,Samenvatting!C106,"") | C5: =IF(Samenvatting!$F106<>0,Samenvatting!D106,"") | D5: =IF(Samenvatting!$F106<>0,Samenvatting!E106,"") | E5: =IF(Samenvatting!$F106<>0,Samenvatting!F106,"") | F5: =IF(Samenvatting!$F106<>0,Samenvatting!H106,"") | G5: =IF(Samenvatting!$F106<>0,Samenvatting!I106,"") | H5: =IF(Samenvatting!$F106<>0,Samenvatting!J106,"") | I5: =IF(Samenvatting!$F106<>0,Samenvatting!K106,"") | J5: =IFERROR(IF(J$1=EOMONTH($G5,0),(-$E5+($E5*(DAY($G5)/DAY(EOMONTH(J$1,0)))*$F5/12*(1-0.269))),IF(J$1=$G5,($E5+($E5*(DAY($I5)/DAY(EOMONTH(J$1,0)))*$F5/12*(1-0.269))),IFERROR(IF($I5<J$1,0,IF(J$1>$I5,(($F5/12)*$E5)*(DAY($I5)/DAY(EOMONTH(J$1,0)))*(1-26.9/100)+$E5,IF(AND(J$1>=$G5,J$1<$I5),(($F5/12)*$E5)*(1-26.9/100),""))-IF(J$1=EOMONTH($G5,0),$E5,"0")),0)+IF(J$1=EOMONTH($I5,0),($E5+($E5*(DAY($I5)/DAY(EOMONTH(J$1,0)))*$F5/12*(1-0.269))),"0"))),0) -> 0 | K5: =IFERROR(IF(K$1=EOMONTH($G5,0),(-$E5+($E5*(DAY($G5)/DAY(EOMONTH(K$1,0)))*$F5/12*(1-0.269))),IF(K$1=$G5,($E5+($E5*(DAY($I5)/DAY(EOMONTH(K$1,0)))*$F5/12*(1-0.269))),IFERROR(IF($I5<K$1,0,IF(K$1>$I5,(($F5/12)*$E5)*(DAY($I5)/DAY(EOMONTH(K$1,0)))*(1-26.9/100)+$E5,IF(AND(K$1>=$G5,K$1<$I5),(($F5/12)*$E5)*(1-26.9/100),""))-IF(K$1=EOMONTH($G5,0),$E5,"0")),0)+IF(K$1=EOMONTH($I5,0),($E5+($E5*(DAY($I5)/DAY(EOMONTH(K$1,0)))*$F5/12*(1-0.269))),"0"))),0) -> 0 | L5: =IFERROR(IF(L$1=EOMONTH($G5,0),(-$E5+($E5*(DAY($G5)/DAY(EOMONTH(L$1,0)))*$F5/12*(1-0.269))),IF(L$1=$G5,($E5+($E5*(DAY($I5)/DAY(EOMONTH(L$1,0)))*$F5/12*(1-0.269))),IFERROR(IF($I5<L$1,0,IF(L$1>$I5,(($F5/12)*$E5)*(DAY($I5)/DAY(EOMONTH(L$1,0)))*(1-26.9/100)+$E5,IF(AND(L$1>=$G5,L$1<$I5),(($F5/12)*$E5)*(1-26.9/100),""))-IF(L$1=EOMONTH($G5,0),$E5,"0")),0)+IF(L$1=EOMONTH($I5,0),($E5+($E5*(DAY($I5)/DAY(EOMONTH(L$1,0)))*$F5/12*(1-0.269))),"0"))),0) -> 0 | M5: =IFERROR(IF(M$1=EOMONTH($G5,0),(-$E5+($E5*(DAY($G5)/DAY(EOMONTH(M$1,0)))*$F5/12*(1-0.269))),IF(M$1=$G5,($E5+($E5*(DAY($I5)/DAY(EOMONTH(M$1,0)))*$F5/12*(1-0.269))),IFERROR(IF($I5<M$1,0,IF(M$1>$I5,(($F5/12)*$E5)*(DAY($I5)/DAY(EOMONTH(M$1,0)))*(1-26.9/100)+$E5,IF(AND(M$1>=$G5,M$1<$I5),(($F5/12)*$E5)*(1-26.9/100),""))-IF(M$1=EOMONTH($G5,0),$E5,"0")),0)+IF(M$1=EOMONTH($I5,0),($E5+($E5*(DAY($I5)/DAY(EOMONTH(M$1,0)))*$F5/12*(1-0.269))),"0"))),0) -> 0 | N5: =IFERROR(IF(N$1=EOMONTH($G5,0),(-$E5+($E5*(DAY($G5)/DAY(EOMONTH(N$1,0)))*$F5/12*(1-0.269))),IF(N$1=$G5,($E5+($E5*(DAY($I5)/DAY(EOMONTH(N$1,0)))*$F5/12*(1-0.269))),IFERROR(IF($I5<N$1,0,IF(N$1>$I5,(($F5/12)*$E5)*(DAY($I5)/DAY(EOMONTH(N$1,0)))*(1-26.9/100)+$E5,IF(AND(N$1>=$G5,N$1<$I5),(($F5/12)*$E5)*(1-26.9/100),""))-IF(N$1=EOMONTH($G5,0),$E5,"0")),0)+IF(N$1=EOMONTH($I5,0),($E5+($E5*(DAY($I5)/DAY(EOMONTH(N$1,0)))*$F5/12*(1-0.269))),"0"))),0) -> 0 | O5: =IFERROR(IF(O$1=EOMONTH($G5,0),(-$E5+($E5*(DAY($G5)/DAY(EOMONTH(O$1,0)))*$F5/12*(1-0.269))),IF(O$1=$G5,($E5+($E5*(DAY($I5)/DAY(EOMONTH(O$1,0)))*$F5/12*(1-0.269))),IFERROR(IF($I5<O$1,0,IF(O$1>$I5,(($F5/12)*$E5)*(DAY($I5)/DAY(EOMONTH(O$1,0)))*(1-26.9/100)+$E5,IF(AND(O$1>=$G5,O$1<$I5),(($F5/12)*$E5)*(1-26.9/100),""))-IF(O$1=EOMONTH($G5,0),$E5,"0")),0)+IF(O$1=EOMONTH($I5,0),($E5+($E5*(DAY($I5)/DAY(EOMONTH(O$1,0)))*$F5/12*(1-0.269))),"0"))),0) -> 0 | P5: =IFERROR(IF(P$1=EOMONTH($G5,0),(-$E5+($E5*(DAY($G5)/DAY(EOMONTH(P$1,0)))*$F5/12*(1-0.269))),IF(P$1=$G5,($E5+($E5*(DAY($I5)/DAY(EOMONTH(P$1,0)))*$F5/12*(1-0.269))),IFERROR(IF($I5<P$1,0,IF(P$1>$I5,(($F5/12)*$E5)*(DAY($I5)/DAY(EOMONTH(P$1,0)))*(1-26.9/100)+$E5,IF(AND(P$1>=$G5,P$1<$I5),(($F5/12)*$E5)*(1-26.9/100),""))-IF(P$1=EOMONTH($G5,0),$E5,"0")),0)+IF(P$1=EOMONTH($I5,0),($E5+($E5*(DAY($I5)/DAY(EOMONTH(P$1,0)))*$F5/12*(1-0.269))),"0"))),0) -> 0 | Q5: =IFERROR(IF(Q$1=EOMONTH($G5,0),(-$E5+($E5*(DAY($G5)/DAY(EOMONTH(Q$1,0)))*$F5/12*(1-0.269))),IF(Q$1=$G5,($E5+($E5*(DAY($I5)/DAY(EOMONTH(Q$1,0)))*$F5/12*(1-0.269))),IFERROR(IF($I5<Q$1,0,IF(Q$1>$I5,(($F5/12)*$E5)*(DAY($I5)/DAY(EOMONTH(Q$1,0)))*(1-26.9/100)+$E5,IF(AND(Q$1>=$G5,Q$1<$I5),(($F5/12)*$E5)*(1-26.9/100),""))-IF(Q$1=EOMONTH($G5,0),$E5,"0")),0)+IF(Q$1=EOMONTH($I5,0),($E5+($E5*(DAY($I5)/DAY(EOMONTH(Q$1,0)))*$F5/12*(1-0.269))),"0"))),0) -> 0 | ... UK5: =IFERROR(IF(UK$1=EOMONTH($G5,0),(-$E5+($E5*(DAY($G5)/DAY(EOMONTH(UK$1,0)))*$F5/12*(1-0.269))),IF(UK$1=$G5,($E5+($E5*(DAY($I5)/DAY(EOMONTH(UK$1,0)))*$F5/12*(1-0.269))),IFERROR(IF($I5<UK$1,0,IF(UK$1>$I5,(($F5/12)*$E5)*(DAY($I5)/DAY(EOMONTH(UK$1,0)))*(1-26.9/100)+$E5,IF(AND(UK$1>=$G5,UK$1<$I5),(($F5/12)*$E5)*(1-26.9/100),""))-IF(UK$1=EOMONTH($G5,0),$E5,"0")),0)+IF(UK$1=EOMONTH($I5,0),($E5+($E5*(DAY($I5)/DAY(EOMONTH(UK$1,0)))*$F5/12*(1-0.269))),"0"))),0) -> 0
B6: =IF(Samenvatting!$F107<>0,Samenvatting!C107,"") | C6: =IF(Samenvatting!$F107<>0,Samenvatting!D107,"") | D6: =IF(Samenvatting!$F107<>0,Samenvatting!E107,"") | E6: =IF(Samenvatting!$F107<>0,Samenvatting!F107,"") | F6: =IF(Samenvatting!$F107<>0,Samenvatting!H107,"") | G6: =IF(Samenvatting!$F107<>0,Samenvatting!I107,"") | H6: =IF(Samenvatting!$F107<>0,Samenvatting!J107,"") | I6: =IF(Samenvatting!$F107<>0,Samenvatting!K107,"") | J6: =IFERROR(IF(J$1=EOMONTH($G6,0),(-$E6+($E6*(DAY($G6)/DAY(EOMONTH(J$1,0)))*$F6/12*(1-0.269))),IF(J$1=$G6,($E6+($E6*(DAY($I6)/DAY(EOMONTH(J$1,0)))*$F6/12*(1-0.269))),IFERROR(IF($I6<J$1,0,IF(J$1>$I6,(($F6/12)*$E6)*(DAY($I6)/DAY(EOMONTH(J$1,0)))*(1-26.9/100)+$E6,IF(AND(J$1>=$G6,J$1<$I6),(($F6/12)*$E6)*(1-26.9/100),""))-IF(J$1=EOMONTH($G6,0),$E6,"0")),0)+IF(J$1=EOMONTH($I6,0),($E6+($E6*(DAY($I6)/DAY(EOMONTH(J$1,0)))*$F6/12*(1-0.269))),"0"))),0) -> 0 | K6: =IFERROR(IF(K$1=EOMONTH($G6,0),(-$E6+($E6*(DAY($G6)/DAY(EOMONTH(K$1,0)))*$F6/12*(1-0.269))),IF(K$1=$G6,($E6+($E6*(DAY($I6)/DAY(EOMONTH(K$1,0)))*$F6/12*(1-0.269))),IFERROR(IF($I6<K$1,0,IF(K$1>$I6,(($F6/12)*$E6)*(DAY($I6)/DAY(EOMONTH(K$1,0)))*(1-26.9/100)+$E6,IF(AND(K$1>=$G6,K$1<$I6),(($F6/12)*$E6)*(1-26.9/100),""))-IF(K$1=EOMONTH($G6,0),$E6,"0")),0)+IF(K$1=EOMONTH($I6,0),($E6+($E6*(DAY($I6)/DAY(EOMONTH(K$1,0)))*$F6/12*(1-0.269))),"0"))),0) -> 0 | L6: =IFERROR(IF(L$1=EOMONTH($G6,0),(-$E6+($E6*(DAY($G6)/DAY(EOMONTH(L$1,0)))*$F6/12*(1-0.269))),IF(L$1=$G6,($E6+($E6*(DAY($I6)/DAY(EOMONTH(L$1,0)))*$F6/12*(1-0.269))),IFERROR(IF($I6<L$1,0,IF(L$1>$I6,(($F6/12)*$E6)*(DAY($I6)/DAY(EOMONTH(L$1,0)))*(1-26.9/100)+$E6,IF(AND(L$1>=$G6,L$1<$I6),(($F6/12)*$E6)*(1-26.9/100),""))-IF(L$1=EOMONTH($G6,0),$E6,"0")),0)+IF(L$1=EOMONTH($I6,0),($E6+($E6*(DAY($I6)/DAY(EOMONTH(L$1,0)))*$F6/12*(1-0.269))),"0"))),0) -> 0 | M6: =IFERROR(IF(M$1=EOMONTH($G6,0),(-$E6+($E6*(DAY($G6)/DAY(EOMONTH(M$1,0)))*$F6/12*(1-0.269))),IF(M$1=$G6,($E6+($E6*(DAY($I6)/DAY(EOMONTH(M$1,0)))*$F6/12*(1-0.269))),IFERROR(IF($I6<M$1,0,IF(M$1>$I6,(($F6/12)*$E6)*(DAY($I6)/DAY(EOMONTH(M$1,0)))*(1-26.9/100)+$E6,IF(AND(M$1>=$G6,M$1<$I6),(($F6/12)*$E6)*(1-26.9/100),""))-IF(M$1=EOMONTH($G6,0),$E6,"0")),0)+IF(M$1=EOMONTH($I6,0),($E6+($E6*(DAY($I6)/DAY(EOMONTH(M$1,0)))*$F6/12*(1-0.269))),"0"))),0) -> 0 | N6: =IFERROR(IF(N$1=EOMONTH($G6,0),(-$E6+($E6*(DAY($G6)/DAY(EOMONTH(N$1,0)))*$F6/12*(1-0.269))),IF(N$1=$G6,($E6+($E6*(DAY($I6)/DAY(EOMONTH(N$1,0)))*$F6/12*(1-0.269))),IFERROR(IF($I6<N$1,0,IF(N$1>$I6,(($F6/12)*$E6)*(DAY($I6)/DAY(EOMONTH(N$1,0)))*(1-26.9/100)+$E6,IF(AND(N$1>=$G6,N$1<$I6),(($F6/12)*$E6)*(1-26.9/100),""))-IF(N$1=EOMONTH($G6,0),$E6,"0")),0)+IF(N$1=EOMONTH($I6,0),($E6+($E6*(DAY($I6)/DAY(EOMONTH(N$1,0)))*$F6/12*(1-0.269))),"0"))),0) -> 0 | O6: =IFERROR(IF(O$1=EOMONTH($G6,0),(-$E6+($E6*(DAY($G6)/DAY(EOMONTH(O$1,0)))*$F6/12*(1-0.269))),IF(O$1=$G6,($E6+($E6*(DAY($I6)/DAY(EOMONTH(O$1,0)))*$F6/12*(1-0.269))),IFERROR(IF($I6<O$1,0,IF(O$1>$I6,(($F6/12)*$E6)*(DAY($I6)/DAY(EOMONTH(O$1,0)))*(1-26.9/100)+$E6,IF(AND(O$1>=$G6,O$1<$I6),(($F6/12)*$E6)*(1-26.9/100),""))-IF(O$1=EOMONTH($G6,0),$E6,"0")),0)+IF(O$1=EOMONTH($I6,0),($E6+($E6*(DAY($I6)/DAY(EOMONTH(O$1,0)))*$F6/12*(1-0.269))),"0"))),0) -> 0 | P6: =IFERROR(IF(P$1=EOMONTH($G6,0),(-$E6+($E6*(DAY($G6)/DAY(EOMONTH(P$1,0)))*$F6/12*(1-0.269))),IF(P$1=$G6,($E6+($E6*(DAY($I6)/DAY(EOMONTH(P$1,0)))*$F6/12*(1-0.269))),IFERROR(IF($I6<P$1,0,IF(P$1>$I6,(($F6/12)*$E6)*(DAY($I6)/DAY(EOMONTH(P$1,0)))*(1-26.9/100)+$E6,IF(AND(P$1>=$G6,P$1<$I6),(($F6/12)*$E6)*(1-26.9/100),""))-IF(P$1=EOMONTH($G6,0),$E6,"0")),0)+IF(P$1=EOMONTH($I6,0),($E6+($E6*(DAY($I6)/DAY(EOMONTH(P$1,0)))*$F6/12*(1-0.269))),"0"))),0) -> 0 | Q6: =IFERROR(IF(Q$1=EOMONTH($G6,0),(-$E6+($E6*(DAY($G6)/DAY(EOMONTH(Q$1,0)))*$F6/12*(1-0.269))),IF(Q$1=$G6,($E6+($E6*(DAY($I6)/DAY(EOMONTH(Q$1,0)))*$F6/12*(1-0.269))),IFERROR(IF($I6<Q$1,0,IF(Q$1>$I6,(($F6/12)*$E6)*(DAY($I6)/DAY(EOMONTH(Q$1,0)))*(1-26.9/100)+$E6,IF(AND(Q$1>=$G6,Q$1<$I6),(($F6/12)*$E6)*(1-26.9/100),""))-IF(Q$1=EOMONTH($G6,0),$E6,"0")),0)+IF(Q$1=EOMONTH($I6,0),($E6+($E6*(DAY($I6)/DAY(EOMONTH(Q$1,0)))*$F6/12*(1-0.269))),"0"))),0) -> 0 | ... UK6: =IFERROR(IF(UK$1=EOMONTH($G6,0),(-$E6+($E6*(DAY($G6)/DAY(EOMONTH(UK$1,0)))*$F6/12*(1-0.269))),IF(UK$1=$G6,($E6+($E6*(DAY($I6)/DAY(EOMONTH(UK$1,0)))*$F6/12*(1-0.269))),IFERROR(IF($I6<UK$1,0,IF(UK$1>$I6,(($F6/12)*$E6)*(DAY($I6)/DAY(EOMONTH(UK$1,0)))*(1-26.9/100)+$E6,IF(AND(UK$1>=$G6,UK$1<$I6),(($F6/12)*$E6)*(1-26.9/100),""))-IF(UK$1=EOMONTH($G6,0),$E6,"0")),0)+IF(UK$1=EOMONTH($I6,0),($E6+($E6*(DAY($I6)/DAY(EOMONTH(UK$1,0)))*$F6/12*(1-0.269))),"0"))),0) -> 0
B7: =IF(Samenvatting!$F108<>0,Samenvatting!C108,"") | C7: =IF(Samenvatting!$F108<>0,Samenvatting!D108,"") | D7: =IF(Samenvatting!$F108<>0,Samenvatting!E108,"") | E7: =IF(Samenvatting!$F108<>0,Samenvatting!F108,"") | F7: =IF(Samenvatting!$F108<>0,Samenvatting!H108,"") | G7: =IF(Samenvatting!$F108<>0,Samenvatting!I108,"") | H7: =IF(Samenvatting!$F108<>0,Samenvatting!J108,"") | I7: =IF(Samenvatting!$F108<>0,Samenvatting!K108,"") | J7: =IFERROR(IF(J$1=EOMONTH($G7,0),(-$E7+($E7*(DAY($G7)/DAY(EOMONTH(J$1,0)))*$F7/12*(1-0.269))),IF(J$1=$G7,($E7+($E7*(DAY($I7)/DAY(EOMONTH(J$1,0)))*$F7/12*(1-0.269))),IFERROR(IF($I7<J$1,0,IF(J$1>$I7,(($F7/12)*$E7)*(DAY($I7)/DAY(EOMONTH(J$1,0)))*(1-26.9/100)+$E7,IF(AND(J$1>=$G7,J$1<$I7),(($F7/12)*$E7)*(1-26.9/100),""))-IF(J$1=EOMONTH($G7,0),$E7,"0")),0)+IF(J$1=EOMONTH($I7,0),($E7+($E7*(DAY($I7)/DAY(EOMONTH(J$1,0)))*$F7/12*(1-0.269))),"0"))),0) -> 0 | K7: =IFERROR(IF(K$1=EOMONTH($G7,0),(-$E7+($E7*(DAY($G7)/DAY(EOMONTH(K$1,0)))*$F7/12*(1-0.269))),IF(K$1=$G7,($E7+($E7*(DAY($I7)/DAY(EOMONTH(K$1,0)))*$F7/12*(1-0.269))),IFERROR(IF($I7<K$1,0,IF(K$1>$I7,(($F7/12)*$E7)*(DAY($I7)/DAY(EOMONTH(K$1,0)))*(1-26.9/100)+$E7,IF(AND(K$1>=$G7,K$1<$I7),(($F7/12)*$E7)*(1-26.9/100),""))-IF(K$1=EOMONTH($G7,0),$E7,"0")),0)+IF(K$1=EOMONTH($I7,0),($E7+($E7*(DAY($I7)/DAY(EOMONTH(K$1,0)))*$F7/12*(1-0.269))),"0"))),0) -> 0 | L7: =IFERROR(IF(L$1=EOMONTH($G7,0),(-$E7+($E7*(DAY($G7)/DAY(EOMONTH(L$1,0)))*$F7/12*(1-0.269))),IF(L$1=$G7,($E7+($E7*(DAY($I7)/DAY(EOMONTH(L$1,0)))*$F7/12*(1-0.269))),IFERROR(IF($I7<L$1,0,IF(L$1>$I7,(($F7/12)*$E7)*(DAY($I7)/DAY(EOMONTH(L$1,0)))*(1-26.9/100)+$E7,IF(AND(L$1>=$G7,L$1<$I7),(($F7/12)*$E7)*(1-26.9/100),""))-IF(L$1=EOMONTH($G7,0),$E7,"0")),0)+IF(L$1=EOMONTH($I7,0),($E7+($E7*(DAY($I7)/DAY(EOMONTH(L$1,0)))*$F7/12*(1-0.269))),"0"))),0) -> 0 | M7: =IFERROR(IF(M$1=EOMONTH($G7,0),(-$E7+($E7*(DAY($G7)/DAY(EOMONTH(M$1,0)))*$F7/12*(1-0.269))),IF(M$1=$G7,($E7+($E7*(DAY($I7)/DAY(EOMONTH(M$1,0)))*$F7/12*(1-0.269))),IFERROR(IF($I7<M$1,0,IF(M$1>$I7,(($F7/12)*$E7)*(DAY($I7)/DAY(EOMONTH(M$1,0)))*(1-26.9/100)+$E7,IF(AND(M$1>=$G7,M$1<$I7),(($F7/12)*$E7)*(1-26.9/100),""))-IF(M$1=EOMONTH($G7,0),$E7,"0")),0)+IF(M$1=EOMONTH($I7,0),($E7+($E7*(DAY($I7)/DAY(EOMONTH(M$1,0)))*$F7/12*(1-0.269))),"0"))),0) -> 0 | N7: =IFERROR(IF(N$1=EOMONTH($G7,0),(-$E7+($E7*(DAY($G7)/DAY(EOMONTH(N$1,0)))*$F7/12*(1-0.269))),IF(N$1=$G7,($E7+($E7*(DAY($I7)/DAY(EOMONTH(N$1,0)))*$F7/12*(1-0.269))),IFERROR(IF($I7<N$1,0,IF(N$1>$I7,(($F7/12)*$E7)*(DAY($I7)/DAY(EOMONTH(N$1,0)))*(1-26.9/100)+$E7,IF(AND(N$1>=$G7,N$1<$I7),(($F7/12)*$E7)*(1-26.9/100),""))-IF(N$1=EOMONTH($G7,0),$E7,"0")),0)+IF(N$1=EOMONTH($I7,0),($E7+($E7*(DAY($I7)/DAY(EOMONTH(N$1,0)))*$F7/12*(1-0.269))),"0"))),0) -> 0 | O7: =IFERROR(IF(O$1=EOMONTH($G7,0),(-$E7+($E7*(DAY($G7)/DAY(EOMONTH(O$1,0)))*$F7/12*(1-0.269))),IF(O$1=$G7,($E7+($E7*(DAY($I7)/DAY(EOMONTH(O$1,0)))*$F7/12*(1-0.269))),IFERROR(IF($I7<O$1,0,IF(O$1>$I7,(($F7/12)*$E7)*(DAY($I7)/DAY(EOMONTH(O$1,0)))*(1-26.9/100)+$E7,IF(AND(O$1>=$G7,O$1<$I7),(($F7/12)*$E7)*(1-26.9/100),""))-IF(O$1=EOMONTH($G7,0),$E7,"0")),0)+IF(O$1=EOMONTH($I7,0),($E7+($E7*(DAY($I7)/DAY(EOMONTH(O$1,0)))*$F7/12*(1-0.269))),"0"))),0) -> 0 | P7: =IFERROR(IF(P$1=EOMONTH($G7,0),(-$E7+($E7*(DAY($G7)/DAY(EOMONTH(P$1,0)))*$F7/12*(1-0.269))),IF(P$1=$G7,($E7+($E7*(DAY($I7)/DAY(EOMONTH(P$1,0)))*$F7/12*(1-0.269))),IFERROR(IF($I7<P$1,0,IF(P$1>$I7,(($F7/12)*$E7)*(DAY($I7)/DAY(EOMONTH(P$1,0)))*(1-26.9/100)+$E7,IF(AND(P$1>=$G7,P$1<$I7),(($F7/12)*$E7)*(1-26.9/100),""))-IF(P$1=EOMONTH($G7,0),$E7,"0")),0)+IF(P$1=EOMONTH($I7,0),($E7+($E7*(DAY($I7)/DAY(EOMONTH(P$1,0)))*$F7/12*(1-0.269))),"0"))),0) -> 0 | Q7: =IFERROR(IF(Q$1=EOMONTH($G7,0),(-$E7+($E7*(DAY($G7)/DAY(EOMONTH(Q$1,0)))*$F7/12*(1-0.269))),IF(Q$1=$G7,($E7+($E7*(DAY($I7)/DAY(EOMONTH(Q$1,0)))*$F7/12*(1-0.269))),IFERROR(IF($I7<Q$1,0,IF(Q$1>$I7,(($F7/12)*$E7)*(DAY($I7)/DAY(EOMONTH(Q$1,0)))*(1-26.9/100)+$E7,IF(AND(Q$1>=$G7,Q$1<$I7),(($F7/12)*$E7)*(1-26.9/100),""))-IF(Q$1=EOMONTH($G7,0),$E7,"0")),0)+IF(Q$1=EOMONTH($I7,0),($E7+($E7*(DAY($I7)/DAY(EOMONTH(Q$1,0)))*$F7/12*(1-0.269))),"0"))),0) -> 0 | ... UK7: =IFERROR(IF(UK$1=EOMONTH($G7,0),(-$E7+($E7*(DAY($G7)/DAY(EOMONTH(UK$1,0)))*$F7/12*(1-0.269))),IF(UK$1=$G7,($E7+($E7*(DAY($I7)/DAY(EOMONTH(UK$1,0)))*$F7/12*(1-0.269))),IFERROR(IF($I7<UK$1,0,IF(UK$1>$I7,(($F7/12)*$E7)*(DAY($I7)/DAY(EOMONTH(UK$1,0)))*(1-26.9/100)+$E7,IF(AND(UK$1>=$G7,UK$1<$I7),(($F7/12)*$E7)*(1-26.9/100),""))-IF(UK$1=EOMONTH($G7,0),$E7,"0")),0)+IF(UK$1=EOMONTH($I7,0),($E7+($E7*(DAY($I7)/DAY(EOMONTH(UK$1,0)))*$F7/12*(1-0.269))),"0"))),0) -> 0
B8: =IF(Samenvatting!$F109<>0,Samenvatting!C109,"") | C8: =IF(Samenvatting!$F109<>0,Samenvatting!D109,"") | D8: =IF(Samenvatting!$F109<>0,Samenvatting!E109,"") | E8: =IF(Samenvatting!$F109<>0,Samenvatting!F109,"") | F8: =IF(Samenvatting!$F109<>0,Samenvatting!H109,"") | G8: =IF(Samenvatting!$F109<>0,Samenvatting!I109,"") | H8: =IF(Samenvatting!$F109<>0,Samenvatting!J109,"") | I8: =IF(Samenvatting!$F109<>0,Samenvatting!K109,"") | J8: =IFERROR(IF(J$1=EOMONTH($G8,0),(-$E8+($E8*(DAY($G8)/DAY(EOMONTH(J$1,0)))*$F8/12*(1-0.269))),IF(J$1=$G8,($E8+($E8*(DAY($I8)/DAY(EOMONTH(J$1,0)))*$F8/12*(1-0.269))),IFERROR(IF($I8<J$1,0,IF(J$1>$I8,(($F8/12)*$E8)*(DAY($I8)/DAY(EOMONTH(J$1,0)))*(1-26.9/100)+$E8,IF(AND(J$1>=$G8,J$1<$I8),(($F8/12)*$E8)*(1-26.9/100),""))-IF(J$1=EOMONTH($G8,0),$E8,"0")),0)+IF(J$1=EOMONTH($I8,0),($E8+($E8*(DAY($I8)/DAY(EOMONTH(J$1,0)))*$F8/12*(1-0.269))),"0"))),0) -> 0 | K8: =IFERROR(IF(K$1=EOMONTH($G8,0),(-$E8+($E8*(DAY($G8)/DAY(EOMONTH(K$1,0)))*$F8/12*(1-0.269))),IF(K$1=$G8,($E8+($E8*(DAY($I8)/DAY(EOMONTH(K$1,0)))*$F8/12*(1-0.269))),IFERROR(IF($I8<K$1,0,IF(K$1>$I8,(($F8/12)*$E8)*(DAY($I8)/DAY(EOMONTH(K$1,0)))*(1-26.9/100)+$E8,IF(AND(K$1>=$G8,K$1<$I8),(($F8/12)*$E8)*(1-26.9/100),""))-IF(K$1=EOMONTH($G8,0),$E8,"0")),0)+IF(K$1=EOMONTH($I8,0),($E8+($E8*(DAY($I8)/DAY(EOMONTH(K$1,0)))*$F8/12*(1-0.269))),"0"))),0) -> 0 | L8: =IFERROR(IF(L$1=EOMONTH($G8,0),(-$E8+($E8*(DAY($G8)/DAY(EOMONTH(L$1,0)))*$F8/12*(1-0.269))),IF(L$1=$G8,($E8+($E8*(DAY($I8)/DAY(EOMONTH(L$1,0)))*$F8/12*(1-0.269))),IFERROR(IF($I8<L$1,0,IF(L$1>$I8,(($F8/12)*$E8)*(DAY($I8)/DAY(EOMONTH(L$1,0)))*(1-26.9/100)+$E8,IF(AND(L$1>=$G8,L$1<$I8),(($F8/12)*$E8)*(1-26.9/100),""))-IF(L$1=EOMONTH($G8,0),$E8,"0")),0)+IF(L$1=EOMONTH($I8,0),($E8+($E8*(DAY($I8)/DAY(EOMONTH(L$1,0)))*$F8/12*(1-0.269))),"0"))),0) -> 0 | M8: =IFERROR(IF(M$1=EOMONTH($G8,0),(-$E8+($E8*(DAY($G8)/DAY(EOMONTH(M$1,0)))*$F8/12*(1-0.269))),IF(M$1=$G8,($E8+($E8*(DAY($I8)/DAY(EOMONTH(M$1,0)))*$F8/12*(1-0.269))),IFERROR(IF($I8<M$1,0,IF(M$1>$I8,(($F8/12)*$E8)*(DAY($I8)/DAY(EOMONTH(M$1,0)))*(1-26.9/100)+$E8,IF(AND(M$1>=$G8,M$1<$I8),(($F8/12)*$E8)*(1-26.9/100),""))-IF(M$1=EOMONTH($G8,0),$E8,"0")),0)+IF(M$1=EOMONTH($I8,0),($E8+($E8*(DAY($I8)/DAY(EOMONTH(M$1,0)))*$F8/12*(1-0.269))),"0"))),0) -> 0 | N8: =IFERROR(IF(N$1=EOMONTH($G8,0),(-$E8+($E8*(DAY($G8)/DAY(EOMONTH(N$1,0)))*$F8/12*(1-0.269))),IF(N$1=$G8,($E8+($E8*(DAY($I8)/DAY(EOMONTH(N$1,0)))*$F8/12*(1-0.269))),IFERROR(IF($I8<N$1,0,IF(N$1>$I8,(($F8/12)*$E8)*(DAY($I8)/DAY(EOMONTH(N$1,0)))*(1-26.9/100)+$E8,IF(AND(N$1>=$G8,N$1<$I8),(($F8/12)*$E8)*(1-26.9/100),""))-IF(N$1=EOMONTH($G8,0),$E8,"0")),0)+IF(N$1=EOMONTH($I8,0),($E8+($E8*(DAY($I8)/DAY(EOMONTH(N$1,0)))*$F8/12*(1-0.269))),"0"))),0) -> 0 | O8: =IFERROR(IF(O$1=EOMONTH($G8,0),(-$E8+($E8*(DAY($G8)/DAY(EOMONTH(O$1,0)))*$F8/12*(1-0.269))),IF(O$1=$G8,($E8+($E8*(DAY($I8)/DAY(EOMONTH(O$1,0)))*$F8/12*(1-0.269))),IFERROR(IF($I8<O$1,0,IF(O$1>$I8,(($F8/12)*$E8)*(DAY($I8)/DAY(EOMONTH(O$1,0)))*(1-26.9/100)+$E8,IF(AND(O$1>=$G8,O$1<$I8),(($F8/12)*$E8)*(1-26.9/100),""))-IF(O$1=EOMONTH($G8,0),$E8,"0")),0)+IF(O$1=EOMONTH($I8,0),($E8+($E8*(DAY($I8)/DAY(EOMONTH(O$1,0)))*$F8/12*(1-0.269))),"0"))),0) -> 0 | P8: =IFERROR(IF(P$1=EOMONTH($G8,0),(-$E8+($E8*(DAY($G8)/DAY(EOMONTH(P$1,0)))*$F8/12*(1-0.269))),IF(P$1=$G8,($E8+($E8*(DAY($I8)/DAY(EOMONTH(P$1,0)))*$F8/12*(1-0.269))),IFERROR(IF($I8<P$1,0,IF(P$1>$I8,(($F8/12)*$E8)*(DAY($I8)/DAY(EOMONTH(P$1,0)))*(1-26.9/100)+$E8,IF(AND(P$1>=$G8,P$1<$I8),(($F8/12)*$E8)*(1-26.9/100),""))-IF(P$1=EOMONTH($G8,0),$E8,"0")),0)+IF(P$1=EOMONTH($I8,0),($E8+($E8*(DAY($I8)/DAY(EOMONTH(P$1,0)))*$F8/12*(1-0.269))),"0"))),0) -> 0 | Q8: =IFERROR(IF(Q$1=EOMONTH($G8,0),(-$E8+($E8*(DAY($G8)/DAY(EOMONTH(Q$1,0)))*$F8/12*(1-0.269))),IF(Q$1=$G8,($E8+($E8*(DAY($I8)/DAY(EOMONTH(Q$1,0)))*$F8/12*(1-0.269))),IFERROR(IF($I8<Q$1,0,IF(Q$1>$I8,(($F8/12)*$E8)*(DAY($I8)/DAY(EOMONTH(Q$1,0)))*(1-26.9/100)+$E8,IF(AND(Q$1>=$G8,Q$1<$I8),(($F8/12)*$E8)*(1-26.9/100),""))-IF(Q$1=EOMONTH($G8,0),$E8,"0")),0)+IF(Q$1=EOMONTH($I8,0),($E8+($E8*(DAY($I8)/DAY(EOMONTH(Q$1,0)))*$F8/12*(1-0.269))),"0"))),0) -> 0 | ... UK8: =IFERROR(IF(UK$1=EOMONTH($G8,0),(-$E8+($E8*(DAY($G8)/DAY(EOMONTH(UK$1,0)))*$F8/12*(1-0.269))),IF(UK$1=$G8,($E8+($E8*(DAY($I8)/DAY(EOMONTH(UK$1,0)))*$F8/12*(1-0.269))),IFERROR(IF($I8<UK$1,0,IF(UK$1>$I8,(($F8/12)*$E8)*(DAY($I8)/DAY(EOMONTH(UK$1,0)))*(1-26.9/100)+$E8,IF(AND(UK$1>=$G8,UK$1<$I8),(($F8/12)*$E8)*(1-26.9/100),""))-IF(UK$1=EOMONTH($G8,0),$E8,"0")),0)+IF(UK$1=EOMONTH($I8,0),($E8+($E8*(DAY($I8)/DAY(EOMONTH(UK$1,0)))*$F8/12*(1-0.269))),"0"))),0) -> 0
B9: =IF(Samenvatting!$F110<>0,Samenvatting!C110,"") | C9: =IF(Samenvatting!$F110<>0,Samenvatting!D110,"") | D9: =IF(Samenvatting!$F110<>0,Samenvatting!E110,"") | E9: =IF(Samenvatting!$F110<>0,Samenvatting!F110,"") | F9: =IF(Samenvatting!$F110<>0,Samenvatting!H110,"") | G9: =IF(Samenvatting!$F110<>0,Samenvatting!I110,"") | H9: =IF(Samenvatting!$F110<>0,Samenvatting!J110,"") | I9: =IF(Samenvatting!$F110<>0,Samenvatting!K110,"") | J9: =IFERROR(IF(J$1=EOMONTH($G9,0),(-$E9+($E9*(DAY($G9)/DAY(EOMONTH(J$1,0)))*$F9/12*(1-0.269))),IF(J$1=$G9,($E9+($E9*(DAY($I9)/DAY(EOMONTH(J$1,0)))*$F9/12*(1-0.269))),IFERROR(IF($I9<J$1,0,IF(J$1>$I9,(($F9/12)*$E9)*(DAY($I9)/DAY(EOMONTH(J$1,0)))*(1-26.9/100)+$E9,IF(AND(J$1>=$G9,J$1<$I9),(($F9/12)*$E9)*(1-26.9/100),""))-IF(J$1=EOMONTH($G9,0),$E9,"0")),0)+IF(J$1=EOMONTH($I9,0),($E9+($E9*(DAY($I9)/DAY(EOMONTH(J$1,0)))*$F9/12*(1-0.269))),"0"))),0) -> 0 | K9: =IFERROR(IF(K$1=EOMONTH($G9,0),(-$E9+($E9*(DAY($G9)/DAY(EOMONTH(K$1,0)))*$F9/12*(1-0.269))),IF(K$1=$G9,($E9+($E9*(DAY($I9)/DAY(EOMONTH(K$1,0)))*$F9/12*(1-0.269))),IFERROR(IF($I9<K$1,0,IF(K$1>$I9,(($F9/12)*$E9)*(DAY($I9)/DAY(EOMONTH(K$1,0)))*(1-26.9/100)+$E9,IF(AND(K$1>=$G9,K$1<$I9),(($F9/12)*$E9)*(1-26.9/100),""))-IF(K$1=EOMONTH($G9,0),$E9,"0")),0)+IF(K$1=EOMONTH($I9,0),($E9+($E9*(DAY($I9)/DAY(EOMONTH(K$1,0)))*$F9/12*(1-0.269))),"0"))),0) -> 0 | L9: =IFERROR(IF(L$1=EOMONTH($G9,0),(-$E9+($E9*(DAY($G9)/DAY(EOMONTH(L$1,0)))*$F9/12*(1-0.269))),IF(L$1=$G9,($E9+($E9*(DAY($I9)/DAY(EOMONTH(L$1,0)))*$F9/12*(1-0.269))),IFERROR(IF($I9<L$1,0,IF(L$1>$I9,(($F9/12)*$E9)*(DAY($I9)/DAY(EOMONTH(L$1,0)))*(1-26.9/100)+$E9,IF(AND(L$1>=$G9,L$1<$I9),(($F9/12)*$E9)*(1-26.9/100),""))-IF(L$1=EOMONTH($G9,0),$E9,"0")),0)+IF(L$1=EOMONTH($I9,0),($E9+($E9*(DAY($I9)/DAY(EOMONTH(L$1,0)))*$F9/12*(1-0.269))),"0"))),0) -> 0 | M9: =IFERROR(IF(M$1=EOMONTH($G9,0),(-$E9+($E9*(DAY($G9)/DAY(EOMONTH(M$1,0)))*$F9/12*(1-0.269))),IF(M$1=$G9,($E9+($E9*(DAY($I9)/DAY(EOMONTH(M$1,0)))*$F9/12*(1-0.269))),IFERROR(IF($I9<M$1,0,IF(M$1>$I9,(($F9/12)*$E9)*(DAY($I9)/DAY(EOMONTH(M$1,0)))*(1-26.9/100)+$E9,IF(AND(M$1>=$G9,M$1<$I9),(($F9/12)*$E9)*(1-26.9/100),""))-IF(M$1=EOMONTH($G9,0),$E9,"0")),0)+IF(M$1=EOMONTH($I9,0),($E9+($E9*(DAY($I9)/DAY(EOMONTH(M$1,0)))*$F9/12*(1-0.269))),"0"))),0) -> 0 | N9: =IFERROR(IF(N$1=EOMONTH($G9,0),(-$E9+($E9*(DAY($G9)/DAY(EOMONTH(N$1,0)))*$F9/12*(1-0.269))),IF(N$1=$G9,($E9+($E9*(DAY($I9)/DAY(EOMONTH(N$1,0)))*$F9/12*(1-0.269))),IFERROR(IF($I9<N$1,0,IF(N$1>$I9,(($F9/12)*$E9)*(DAY($I9)/DAY(EOMONTH(N$1,0)))*(1-26.9/100)+$E9,IF(AND(N$1>=$G9,N$1<$I9),(($F9/12)*$E9)*(1-26.9/100),""))-IF(N$1=EOMONTH($G9,0),$E9,"0")),0)+IF(N$1=EOMONTH($I9,0),($E9+($E9*(DAY($I9)/DAY(EOMONTH(N$1,0)))*$F9/12*(1-0.269))),"0"))),0) -> 0 | O9: =IFERROR(IF(O$1=EOMONTH($G9,0),(-$E9+($E9*(DAY($G9)/DAY(EOMONTH(O$1,0)))*$F9/12*(1-0.269))),IF(O$1=$G9,($E9+($E9*(DAY($I9)/DAY(EOMONTH(O$1,0)))*$F9/12*(1-0.269))),IFERROR(IF($I9<O$1,0,IF(O$1>$I9,(($F9/12)*$E9)*(DAY($I9)/DAY(EOMONTH(O$1,0)))*(1-26.9/100)+$E9,IF(AND(O$1>=$G9,O$1<$I9),(($F9/12)*$E9)*(1-26.9/100),""))-IF(O$1=EOMONTH($G9,0),$E9,"0")),0)+IF(O$1=EOMONTH($I9,0),($E9+($E9*(DAY($I9)/DAY(EOMONTH(O$1,0)))*$F9/12*(1-0.269))),"0"))),0) -> 0 | P9: =IFERROR(IF(P$1=EOMONTH($G9,0),(-$E9+($E9*(DAY($G9)/DAY(EOMONTH(P$1,0)))*$F9/12*(1-0.269))),IF(P$1=$G9,($E9+($E9*(DAY($I9)/DAY(EOMONTH(P$1,0)))*$F9/12*(1-0.269))),IFERROR(IF($I9<P$1,0,IF(P$1>$I9,(($F9/12)*$E9)*(DAY($I9)/DAY(EOMONTH(P$1,0)))*(1-26.9/100)+$E9,IF(AND(P$1>=$G9,P$1<$I9),(($F9/12)*$E9)*(1-26.9/100),""))-IF(P$1=EOMONTH($G9,0),$E9,"0")),0)+IF(P$1=EOMONTH($I9,0),($E9+($E9*(DAY($I9)/DAY(EOMONTH(P$1,0)))*$F9/12*(1-0.269))),"0"))),0) -> 0 | Q9: =IFERROR(IF(Q$1=EOMONTH($G9,0),(-$E9+($E9*(DAY($G9)/DAY(EOMONTH(Q$1,0)))*$F9/12*(1-0.269))),IF(Q$1=$G9,($E9+($E9*(DAY($I9)/DAY(EOMONTH(Q$1,0)))*$F9/12*(1-0.269))),IFERROR(IF($I9<Q$1,0,IF(Q$1>$I9,(($F9/12)*$E9)*(DAY($I9)/DAY(EOMONTH(Q$1,0)))*(1-26.9/100)+$E9,IF(AND(Q$1>=$G9,Q$1<$I9),(($F9/12)*$E9)*(1-26.9/100),""))-IF(Q$1=EOMONTH($G9,0),$E9,"0")),0)+IF(Q$1=EOMONTH($I9,0),($E9+($E9*(DAY($I9)/DAY(EOMONTH(Q$1,0)))*$F9/12*(1-0.269))),"0"))),0) -> 0 | ... UK9: =IFERROR(IF(UK$1=EOMONTH($G9,0),(-$E9+($E9*(DAY($G9)/DAY(EOMONTH(UK$1,0)))*$F9/12*(1-0.269))),IF(UK$1=$G9,($E9+($E9*(DAY($I9)/DAY(EOMONTH(UK$1,0)))*$F9/12*(1-0.269))),IFERROR(IF($I9<UK$1,0,IF(UK$1>$I9,(($F9/12)*$E9)*(DAY($I9)/DAY(EOMONTH(UK$1,0)))*(1-26.9/100)+$E9,IF(AND(UK$1>=$G9,UK$1<$I9),(($F9/12)*$E9)*(1-26.9/100),""))-IF(UK$1=EOMONTH($G9,0),$E9,"0")),0)+IF(UK$1=EOMONTH($I9,0),($E9+($E9*(DAY($I9)/DAY(EOMONTH(UK$1,0)))*$F9/12*(1-0.269))),"0"))),0) -> 0
B10: =IF(Samenvatting!$F111<>0,Samenvatting!C111,"") | C10: =IF(Samenvatting!$F111<>0,Samenvatting!D111,"") | D10: =IF(Samenvatting!$F111<>0,Samenvatting!E111,"") | E10: =IF(Samenvatting!$F111<>0,Samenvatting!F111,"") | F10: =IF(Samenvatting!$F111<>0,Samenvatting!H111,"") | G10: =IF(Samenvatting!$F111<>0,Samenvatting!I111,"") | H10: =IF(Samenvatting!$F111<>0,Samenvatting!J111,"") | I10: =IF(Samenvatting!$F111<>0,Samenvatting!K111,"") | J10: =IFERROR(IF(J$1=EOMONTH($G10,0),(-$E10+($E10*(DAY($G10)/DAY(EOMONTH(J$1,0)))*$F10/12*(1-0.269))),IF(J$1=$G10,($E10+($E10*(DAY($I10)/DAY(EOMONTH(J$1,0)))*$F10/12*(1-0.269))),IFERROR(IF($I10<J$1,0,IF(J$1>$I10,(($F10/12)*$E10)*(DAY($I10)/DAY(EOMONTH(J$1,0)))*(1-26.9/100)+$E10,IF(AND(J$1>=$G10,J$1<$I10),(($F10/12)*$E10)*(1-26.9/100),""))-IF(J$1=EOMONTH($G10,0),$E10,"0")),0)+IF(J$1=EOMONTH($I10,0),($E10+($E10*(DAY($I10)/DAY(EOMONTH(J$1,0)))*$F10/12*(1-0.269))),"0"))),0) -> 0 | K10: =IFERROR(IF(K$1=EOMONTH($G10,0),(-$E10+($E10*(DAY($G10)/DAY(EOMONTH(K$1,0)))*$F10/12*(1-0.269))),IF(K$1=$G10,($E10+($E10*(DAY($I10)/DAY(EOMONTH(K$1,0)))*$F10/12*(1-0.269))),IFERROR(IF($I10<K$1,0,IF(K$1>$I10,(($F10/12)*$E10)*(DAY($I10)/DAY(EOMONTH(K$1,0)))*(1-26.9/100)+$E10,IF(AND(K$1>=$G10,K$1<$I10),(($F10/12)*$E10)*(1-26.9/100),""))-IF(K$1=EOMONTH($G10,0),$E10,"0")),0)+IF(K$1=EOMONTH($I10,0),($E10+($E10*(DAY($I10)/DAY(EOMONTH(K$1,0)))*$F10/12*(1-0.269))),"0"))),0) -> 0 | L10: =IFERROR(IF(L$1=EOMONTH($G10,0),(-$E10+($E10*(DAY($G10)/DAY(EOMONTH(L$1,0)))*$F10/12*(1-0.269))),IF(L$1=$G10,($E10+($E10*(DAY($I10)/DAY(EOMONTH(L$1,0)))*$F10/12*(1-0.269))),IFERROR(IF($I10<L$1,0,IF(L$1>$I10,(($F10/12)*$E10)*(DAY($I10)/DAY(EOMONTH(L$1,0)))*(1-26.9/100)+$E10,IF(AND(L$1>=$G10,L$1<$I10),(($F10/12)*$E10)*(1-26.9/100),""))-IF(L$1=EOMONTH($G10,0),$E10,"0")),0)+IF(L$1=EOMONTH($I10,0),($E10+($E10*(DAY($I10)/DAY(EOMONTH(L$1,0)))*$F10/12*(1-0.269))),"0"))),0) -> 0 | M10: =IFERROR(IF(M$1=EOMONTH($G10,0),(-$E10+($E10*(DAY($G10)/DAY(EOMONTH(M$1,0)))*$F10/12*(1-0.269))),IF(M$1=$G10,($E10+($E10*(DAY($I10)/DAY(EOMONTH(M$1,0)))*$F10/12*(1-0.269))),IFERROR(IF($I10<M$1,0,IF(M$1>$I10,(($F10/12)*$E10)*(DAY($I10)/DAY(EOMONTH(M$1,0)))*(1-26.9/100)+$E10,IF(AND(M$1>=$G10,M$1<$I10),(($F10/12)*$E10)*(1-26.9/100),""))-IF(M$1=EOMONTH($G10,0),$E10,"0")),0)+IF(M$1=EOMONTH($I10,0),($E10+($E10*(DAY($I10)/DAY(EOMONTH(M$1,0)))*$F10/12*(1-0.269))),"0"))),0) -> 0 | N10: =IFERROR(IF(N$1=EOMONTH($G10,0),(-$E10+($E10*(DAY($G10)/DAY(EOMONTH(N$1,0)))*$F10/12*(1-0.269))),IF(N$1=$G10,($E10+($E10*(DAY($I10)/DAY(EOMONTH(N$1,0)))*$F10/12*(1-0.269))),IFERROR(IF($I10<N$1,0,IF(N$1>$I10,(($F10/12)*$E10)*(DAY($I10)/DAY(EOMONTH(N$1,0)))*(1-26.9/100)+$E10,IF(AND(N$1>=$G10,N$1<$I10),(($F10/12)*$E10)*(1-26.9/100),""))-IF(N$1=EOMONTH($G10,0),$E10,"0")),0)+IF(N$1=EOMONTH($I10,0),($E10+($E10*(DAY($I10)/DAY(EOMONTH(N$1,0)))*$F10/12*(1-0.269))),"0"))),0) -> 0 | O10: =IFERROR(IF(O$1=EOMONTH($G10,0),(-$E10+($E10*(DAY($G10)/DAY(EOMONTH(O$1,0)))*$F10/12*(1-0.269))),IF(O$1=$G10,($E10+($E10*(DAY($I10)/DAY(EOMONTH(O$1,0)))*$F10/12*(1-0.269))),IFERROR(IF($I10<O$1,0,IF(O$1>$I10,(($F10/12)*$E10)*(DAY($I10)/DAY(EOMONTH(O$1,0)))*(1-26.9/100)+$E10,IF(AND(O$1>=$G10,O$1<$I10),(($F10/12)*$E10)*(1-26.9/100),""))-IF(O$1=EOMONTH($G10,0),$E10,"0")),0)+IF(O$1=EOMONTH($I10,0),($E10+($E10*(DAY($I10)/DAY(EOMONTH(O$1,0)))*$F10/12*(1-0.269))),"0"))),0) -> 0 | P10: =IFERROR(IF(P$1=EOMONTH($G10,0),(-$E10+($E10*(DAY($G10)/DAY(EOMONTH(P$1,0)))*$F10/12*(1-0.269))),IF(P$1=$G10,($E10+($E10*(DAY($I10)/DAY(EOMONTH(P$1,0)))*$F10/12*(1-0.269))),IFERROR(IF($I10<P$1,0,IF(P$1>$I10,(($F10/12)*$E10)*(DAY($I10)/DAY(EOMONTH(P$1,0)))*(1-26.9/100)+$E10,IF(AND(P$1>=$G10,P$1<$I10),(($F10/12)*$E10)*(1-26.9/100),""))-IF(P$1=EOMONTH($G10,0),$E10,"0")),0)+IF(P$1=EOMONTH($I10,0),($E10+($E10*(DAY($I10)/DAY(EOMONTH(P$1,0)))*$F10/12*(1-0.269))),"0"))),0) -> 0 | Q10: =IFERROR(IF(Q$1=EOMONTH($G10,0),(-$E10+($E10*(DAY($G10)/DAY(EOMONTH(Q$1,0)))*$F10/12*(1-0.269))),IF(Q$1=$G10,($E10+($E10*(DAY($I10)/DAY(EOMONTH(Q$1,0)))*$F10/12*(1-0.269))),IFERROR(IF($I10<Q$1,0,IF(Q$1>$I10,(($F10/12)*$E10)*(DAY($I10)/DAY(EOMONTH(Q$1,0)))*(1-26.9/100)+$E10,IF(AND(Q$1>=$G10,Q$1<$I10),(($F10/12)*$E10)*(1-26.9/100),""))-IF(Q$1=EOMONTH($G10,0),$E10,"0")),0)+IF(Q$1=EOMONTH($I10,0),($E10+($E10*(DAY($I10)/DAY(EOMONTH(Q$1,0)))*$F10/12*(1-0.269))),"0"))),0) -> 0 | ... UK10: =IFERROR(IF(UK$1=EOMONTH($G10,0),(-$E10+($E10*(DAY($G10)/DAY(EOMONTH(UK$1,0)))*$F10/12*(1-0.269))),IF(UK$1=$G10,($E10+($E10*(DAY($I10)/DAY(EOMONTH(UK$1,0)))*$F10/12*(1-0.269))),IFERROR(IF($I10<UK$1,0,IF(UK$1>$I10,(($F10/12)*$E10)*(DAY($I10)/DAY(EOMONTH(UK$1,0)))*(1-26.9/100)+$E10,IF(AND(UK$1>=$G10,UK$1<$I10),(($F10/12)*$E10)*(1-26.9/100),""))-IF(UK$1=EOMONTH($G10,0),$E10,"0")),0)+IF(UK$1=EOMONTH($I10,0),($E10+($E10*(DAY($I10)/DAY(EOMONTH(UK$1,0)))*$F10/12*(1-0.269))),"0"))),0) -> 0
B11: =IF(Samenvatting!$F112<>0,Samenvatting!C112,"") | C11: =IF(Samenvatting!$F112<>0,Samenvatting!D112,"") | D11: =IF(Samenvatting!$F112<>0,Samenvatting!E112,"") | E11: =IF(Samenvatting!$F112<>0,Samenvatting!F112,"") | F11: =IF(Samenvatting!$F112<>0,Samenvatting!H112,"") | G11: =IF(Samenvatting!$F112<>0,Samenvatting!I112,"") | H11: =IF(Samenvatting!$F112<>0,Samenvatting!J112,"") | I11: =IF(Samenvatting!$F112<>0,Samenvatting!K112,"") | J11: =IFERROR(IF(J$1=EOMONTH($G11,0),(-$E11+($E11*(DAY($G11)/DAY(EOMONTH(J$1,0)))*$F11/12*(1-0.269))),IF(J$1=$G11,($E11+($E11*(DAY($I11)/DAY(EOMONTH(J$1,0)))*$F11/12*(1-0.269))),IFERROR(IF($I11<J$1,0,IF(J$1>$I11,(($F11/12)*$E11)*(DAY($I11)/DAY(EOMONTH(J$1,0)))*(1-26.9/100)+$E11,IF(AND(J$1>=$G11,J$1<$I11),(($F11/12)*$E11)*(1-26.9/100),""))-IF(J$1=EOMONTH($G11,0),$E11,"0")),0)+IF(J$1=EOMONTH($I11,0),($E11+($E11*(DAY($I11)/DAY(EOMONTH(J$1,0)))*$F11/12*(1-0.269))),"0"))),0) -> 0 | K11: =IFERROR(IF(K$1=EOMONTH($G11,0),(-$E11+($E11*(DAY($G11)/DAY(EOMONTH(K$1,0)))*$F11/12*(1-0.269))),IF(K$1=$G11,($E11+($E11*(DAY($I11)/DAY(EOMONTH(K$1,0)))*$F11/12*(1-0.269))),IFERROR(IF($I11<K$1,0,IF(K$1>$I11,(($F11/12)*$E11)*(DAY($I11)/DAY(EOMONTH(K$1,0)))*(1-26.9/100)+$E11,IF(AND(K$1>=$G11,K$1<$I11),(($F11/12)*$E11)*(1-26.9/100),""))-IF(K$1=EOMONTH($G11,0),$E11,"0")),0)+IF(K$1=EOMONTH($I11,0),($E11+($E11*(DAY($I11)/DAY(EOMONTH(K$1,0)))*$F11/12*(1-0.269))),"0"))),0) -> 0 | L11: =IFERROR(IF(L$1=EOMONTH($G11,0),(-$E11+($E11*(DAY($G11)/DAY(EOMONTH(L$1,0)))*$F11/12*(1-0.269))),IF(L$1=$G11,($E11+($E11*(DAY($I11)/DAY(EOMONTH(L$1,0)))*$F11/12*(1-0.269))),IFERROR(IF($I11<L$1,0,IF(L$1>$I11,(($F11/12)*$E11)*(DAY($I11)/DAY(EOMONTH(L$1,0)))*(1-26.9/100)+$E11,IF(AND(L$1>=$G11,L$1<$I11),(($F11/12)*$E11)*(1-26.9/100),""))-IF(L$1=EOMONTH($G11,0),$E11,"0")),0)+IF(L$1=EOMONTH($I11,0),($E11+($E11*(DAY($I11)/DAY(EOMONTH(L$1,0)))*$F11/12*(1-0.269))),"0"))),0) -> 0 | M11: =IFERROR(IF(M$1=EOMONTH($G11,0),(-$E11+($E11*(DAY($G11)/DAY(EOMONTH(M$1,0)))*$F11/12*(1-0.269))),IF(M$1=$G11,($E11+($E11*(DAY($I11)/DAY(EOMONTH(M$1,0)))*$F11/12*(1-0.269))),IFERROR(IF($I11<M$1,0,IF(M$1>$I11,(($F11/12)*$E11)*(DAY($I11)/DAY(EOMONTH(M$1,0)))*(1-26.9/100)+$E11,IF(AND(M$1>=$G11,M$1<$I11),(($F11/12)*$E11)*(1-26.9/100),""))-IF(M$1=EOMONTH($G11,0),$E11,"0")),0)+IF(M$1=EOMONTH($I11,0),($E11+($E11*(DAY($I11)/DAY(EOMONTH(M$1,0)))*$F11/12*(1-0.269))),"0"))),0) -> 0 | N11: =IFERROR(IF(N$1=EOMONTH($G11,0),(-$E11+($E11*(DAY($G11)/DAY(EOMONTH(N$1,0)))*$F11/12*(1-0.269))),IF(N$1=$G11,($E11+($E11*(DAY($I11)/DAY(EOMONTH(N$1,0)))*$F11/12*(1-0.269))),IFERROR(IF($I11<N$1,0,IF(N$1>$I11,(($F11/12)*$E11)*(DAY($I11)/DAY(EOMONTH(N$1,0)))*(1-26.9/100)+$E11,IF(AND(N$1>=$G11,N$1<$I11),(($F11/12)*$E11)*(1-26.9/100),""))-IF(N$1=EOMONTH($G11,0),$E11,"0")),0)+IF(N$1=EOMONTH($I11,0),($E11+($E11*(DAY($I11)/DAY(EOMONTH(N$1,0)))*$F11/12*(1-0.269))),"0"))),0) -> 0 | O11: =IFERROR(IF(O$1=EOMONTH($G11,0),(-$E11+($E11*(DAY($G11)/DAY(EOMONTH(O$1,0)))*$F11/12*(1-0.269))),IF(O$1=$G11,($E11+($E11*(DAY($I11)/DAY(EOMONTH(O$1,0)))*$F11/12*(1-0.269))),IFERROR(IF($I11<O$1,0,IF(O$1>$I11,(($F11/12)*$E11)*(DAY($I11)/DAY(EOMONTH(O$1,0)))*(1-26.9/100)+$E11,IF(AND(O$1>=$G11,O$1<$I11),(($F11/12)*$E11)*(1-26.9/100),""))-IF(O$1=EOMONTH($G11,0),$E11,"0")),0)+IF(O$1=EOMONTH($I11,0),($E11+($E11*(DAY($I11)/DAY(EOMONTH(O$1,0)))*$F11/12*(1-0.269))),"0"))),0) -> 0 | P11: =IFERROR(IF(P$1=EOMONTH($G11,0),(-$E11+($E11*(DAY($G11)/DAY(EOMONTH(P$1,0)))*$F11/12*(1-0.269))),IF(P$1=$G11,($E11+($E11*(DAY($I11)/DAY(EOMONTH(P$1,0)))*$F11/12*(1-0.269))),IFERROR(IF($I11<P$1,0,IF(P$1>$I11,(($F11/12)*$E11)*(DAY($I11)/DAY(EOMONTH(P$1,0)))*(1-26.9/100)+$E11,IF(AND(P$1>=$G11,P$1<$I11),(($F11/12)*$E11)*(1-26.9/100),""))-IF(P$1=EOMONTH($G11,0),$E11,"0")),0)+IF(P$1=EOMONTH($I11,0),($E11+($E11*(DAY($I11)/DAY(EOMONTH(P$1,0)))*$F11/12*(1-0.269))),"0"))),0) -> 0 | Q11: =IFERROR(IF(Q$1=EOMONTH($G11,0),(-$E11+($E11*(DAY($G11)/DAY(EOMONTH(Q$1,0)))*$F11/12*(1-0.269))),IF(Q$1=$G11,($E11+($E11*(DAY($I11)/DAY(EOMONTH(Q$1,0)))*$F11/12*(1-0.269))),IFERROR(IF($I11<Q$1,0,IF(Q$1>$I11,(($F11/12)*$E11)*(DAY($I11)/DAY(EOMONTH(Q$1,0)))*(1-26.9/100)+$E11,IF(AND(Q$1>=$G11,Q$1<$I11),(($F11/12)*$E11)*(1-26.9/100),""))-IF(Q$1=EOMONTH($G11,0),$E11,"0")),0)+IF(Q$1=EOMONTH($I11,0),($E11+($E11*(DAY($I11)/DAY(EOMONTH(Q$1,0)))*$F11/12*(1-0.269))),"0"))),0) -> 0 | ... UK11: =IFERROR(IF(UK$1=EOMONTH($G11,0),(-$E11+($E11*(DAY($G11)/DAY(EOMONTH(UK$1,0)))*$F11/12*(1-0.269))),IF(UK$1=$G11,($E11+($E11*(DAY($I11)/DAY(EOMONTH(UK$1,0)))*$F11/12*(1-0.269))),IFERROR(IF($I11<UK$1,0,IF(UK$1>$I11,(($F11/12)*$E11)*(DAY($I11)/DAY(EOMONTH(UK$1,0)))*(1-26.9/100)+$E11,IF(AND(UK$1>=$G11,UK$1<$I11),(($F11/12)*$E11)*(1-26.9/100),""))-IF(UK$1=EOMONTH($G11,0),$E11,"0")),0)+IF(UK$1=EOMONTH($I11,0),($E11+($E11*(DAY($I11)/DAY(EOMONTH(UK$1,0)))*$F11/12*(1-0.269))),"0"))),0) -> 0
