Workbook

Sheet Cashflow Matrix
A1: Private Equity Commitment Planning Tool
A2: Cashflow Matrix
A4: Klantnaam:
A5: Beschikbaar kapitaal:
M6: PROJECTED
A7: Selecteer een fonds uit de dropdown (kolom B) - Type wordt automatisch ingevuld
A8: TYPE | B8: FONDSNAAM | C8: COMMITMENT | D8: CURR. | E8: INSTAP | F8: 2025 | G8: 2026 | H8: 2027 | I8: 2028 | J8: 2029 | K8: 2030 | L8: 2031 | M8: 2032 | N8: 2033 | O8: 2034 | P8: 2035 | Q8: 2036 | R8: 2037 | S8: 2038 | T8: 2039 | U8: 2040 | V8: 2041 | W8: 2042 | X8: 2043 | Y8: 2044 | Z8: 2045 | AA8: 2046 | AB8: 2047 | AC8: 2048 | AD8: 2049 | AE8: 2050 | AF8: 2051 | AG8: 2052 | AH8: 2053 | AI8: 2054 | AJ8: 2055 | AK8: 2056 | AL8: 2057 | AM8: 2058 | AN8: 2059 | AO8: 2060 | AP8: 2061 | AQ8: 2062 | AR8: 2063 | AS8: 2064 | AT8: 2065
A9: =IF(B9="","",IFERROR(VLOOKUP(B9,Fondsen!$A$5:$B$30,2,FALSE()),"")) | D9: EUR | E9: 2025 | F9: {=IF(OR($B9="",$C9="",$E9=""),"",IF(OR(F$8<$E9,F$8-$E9>=12),0,$C9*INDEX(Fondsen!$F$5:$Q$30,MATCH($B9,Fondsen!$A$5:$A$30,0),F$8-$E9+1)))} | G9: {=IF(OR($B9="",$C9="",$E9=""),"",IF(OR(G$8<$E9,G$8-$E9>=12),0,$C9*INDEX(Fondsen!$F$5:$Q$30,MATCH($B9,Fondsen!$A$5:$A$30,0),G$8-$E9+1)))} | H9: {=IF(OR($B9="",$C9="",$E9=""),"",IF(OR(H$8<$E9,H$8-$E9>=12),0,$C9*INDEX(Fondsen!$F$5:$Q$30,MATCH($B9,Fondsen!$A$5:$A$30,0),H$8-$E9+1)))} | I9: {=IF(OR($B9="",$C9="",$E9=""),"",IF(OR(I$8<$E9,I$8-$E9>=12),0,$C9*INDEX(Fondsen!$F$5:$Q$30,MATCH($B9,Fondsen!$A$5:$A$30,0),I$8-$E9+1)))} | J9: {=IF(OR($B9="",$C9="",$E9=""),"",IF(OR(J$8<$E9,J$8-$E9>=12),0,$C9*INDEX(Fondsen!$F$5:$Q$30,MATCH($B9,Fondsen!$A$5:$A$30,0),J$8-$E9+1)))} | K9: {=IF(OR($B9="",$C9="",$E9=""),"",IF(OR(K$8<$E9,K$8-$E9>=12),0,$C9*INDEX(Fondsen!$F$5:$Q$30,MATCH($B9,Fondsen!$A$5:$A$30,0),K$8-$E9+1)))} | L9: {=IF(OR($B9="",$C9="",$E9=""),"",IF(OR(L$8<$E9,L$8-$E9>=12),0,$C9*INDEX(Fondsen!$F$5:$Q$30,MATCH($B9,Fondsen!$A$5:$A$30,0),L$8-$E9+1)))} | M9: {=IF(OR($B9="",$C9="",$E9=""),"",IF(OR(M$8<$E9,M$8-$E9>=12),0,$C9*INDEX(Fondsen!$F$5:$Q$30,MATCH($B9,Fondsen!$A$5:$A$30,0),M$8-$E9+1)))} | ... AS9: {=IF(OR($B9="",$C9="",$E9=""),"",IF(OR(AS$8<$E9,AS$8-$E9>=12),0,$C9*INDEX(Fondsen!$F$5:$Q$30,MATCH($B9,Fondsen!$A$5:$A$30,0),AS$8-$E9+1)))}
A10: =IF(B10="","",IFERROR(VLOOKUP(B10,Fondsen!$A$5:$B$30,2,FALSE()),"")) | D10: EUR | E10: 2026 | F10: {=IF(OR($B10="",$C10="",$E10=""),"",IF(OR(F$8<$E10,F$8-$E10>=12),0,$C10*INDEX(Fondsen!$F$5:$Q$30,MATCH($B10,Fondsen!$A$5:$A$30,0),F$8-$E10+1)))} | G10: {=IF(OR($B10="",$C10="",$E10=""),"",IF(OR(G$8<$E10,G$8-$E10>=12),0,$C10*INDEX(Fondsen!$F$5:$Q$30,MATCH($B10,Fondsen!$A$5:$A$30,0),G$8-$E10+1)))} | H10: {=IF(OR($B10="",$C10="",$E10=""),"",IF(OR(H$8<$E10,H$8-$E10>=12),0,$C10*INDEX(Fondsen!$F$5:$Q$30,MATCH($B10,Fondsen!$A$5:$A$30,0),H$8-$E10+1)))} | I10: {=IF(OR($B10="",$C10="",$E10=""),"",IF(OR(I$8<$E10,I$8-$E10>=12),0,$C10*INDEX(Fondsen!$F$5:$Q$30,MATCH($B10,Fondsen!$A$5:$A$30,0),I$8-$E10+1)))} | J10: {=IF(OR($B10="",$C10="",$E10=""),"",IF(OR(J$8<$E10,J$8-$E10>=12),0,$C10*INDEX(Fondsen!$F$5:$Q$30,MATCH($B10,Fondsen!$A$5:$A$30,0),J$8-$E10+1)))} | K10: {=IF(OR($B10="",$C10="",$E10=""),"",IF(OR(K$8<$E10,K$8-$E10>=12),0,$C10*INDEX(Fondsen!$F$5:$Q$30,MATCH($B10,Fondsen!$A$5:$A$30,0),K$8-$E10+1)))} | L10: {=IF(OR($B10="",$C10="",$E10=""),"",IF(OR(L$8<$E10,L$8-$E10>=12),0,$C10*INDEX(Fondsen!$F$5:$Q$30,MATCH($B10,Fondsen!$A$5:$A$30,0),L$8-$E10+1)))} | M10: {=IF(OR($B10="",$C10="",$E10=""),"",IF(OR(M$8<$E10,M$8-$E10>=12),0,$C10*INDEX(Fondsen!$F$5:$Q$30,MATCH($B10,Fondsen!$A$5:$A$30,0),M$8-$E10+1)))} | ... AS10: {=IF(OR($B10="",$C10="",$E10=""),"",IF(OR(AS$8<$E10,AS$8-$E10>=12),0,$C10*INDEX(Fondsen!$F$5:$Q$30,MATCH($B10,Fondsen!$A$5:$A$30,0),AS$8-$E10+1)))}
A11: =IF(B11="","",IFERROR(VLOOKUP(B11,Fondsen!$A$5:$B$30,2,FALSE()),"")) | D11: EUR | E11: 2025 | F11: {=IF(OR($B11="",$C11="",$E11=""),"",IF(OR(F$8<$E11,F$8-$E11>=12),0,$C11*INDEX(Fondsen!$F$5:$Q$30,MATCH($B11,Fondsen!$A$5:$A$30,0),F$8-$E11+1)))} | G11: {=IF(OR($B11="",$C11="",$E11=""),"",IF(OR(G$8<$E11,G$8-$E11>=12),0,$C11*INDEX(Fondsen!$F$5:$Q$30,MATCH($B11,Fondsen!$A$5:$A$30,0),G$8-$E11+1)))} | H11: {=IF(OR($B11="",$C11="",$E11=""),"",IF(OR(H$8<$E11,H$8-$E11>=12),0,$C11*INDEX(Fondsen!$F$5:$Q$30,MATCH($B11,Fondsen!$A$5:$A$30,0),H$8-$E11+1)))} | I11: {=IF(OR($B11="",$C11="",$E11=""),"",IF(OR(I$8<$E11,I$8-$E11>=12),0,$C11*INDEX(Fondsen!$F$5:$Q$30,MATCH($B11,Fondsen!$A$5:$A$30,0),I$8-$E11+1)))} | J11: {=IF(OR($B11="",$C11="",$E11=""),"",IF(OR(J$8<$E11,J$8-$E11>=12),0,$C11*INDEX(Fondsen!$F$5:$Q$30,MATCH($B11,Fondsen!$A$5:$A$30,0),J$8-$E11+1)))} | K11: {=IF(OR($B11="",$C11="",$E11=""),"",IF(OR(K$8<$E11,K$8-$E11>=12),0,$C11*INDEX(Fondsen!$F$5:$Q$30,MATCH($B11,Fondsen!$A$5:$A$30,0),K$8-$E11+1)))} | L11: {=IF(OR($B11="",$C11="",$E11=""),"",IF(OR(L$8<$E11,L$8-$E11>=12),0,$C11*INDEX(Fondsen!$F$5:$Q$30,MATCH($B11,Fondsen!$A$5:$A$30,0),L$8-$E11+1)))} | M11: {=IF(OR($B11="",$C11="",$E11=""),"",IF(OR(M$8<$E11,M$8-$E11>=12),0,$C11*INDEX(Fondsen!$F$5:$Q$30,MATCH($B11,Fondsen!$A$5:$A$30,0),M$8-$E11+1)))} | ... AS11: {=IF(OR($B11="",$C11="",$E11=""),"",IF(OR(AS$8<$E11,AS$8-$E11>=12),0,$C11*INDEX(Fondsen!$F$5:$Q$30,MATCH($B11,Fondsen!$A$5:$A$30,0),AS$8-$E11+1)))}
A12: =IF(B12="","",IFERROR(VLOOKUP(B12,Fondsen!$A$5:$B$30,2,FALSE()),"")) | D12: EUR | E12: 2026 | F12: {=IF(OR($B12="",$C12="",$E12=""),"",IF(OR(F$8<$E12,F$8-$E12>=12),0,$C12*INDEX(Fondsen!$F$5:$Q$30,MATCH($B12,Fondsen!$A$5:$A$30,0),F$8-$E12+1)))} | G12: {=IF(OR($B12="",$C12="",$E12=""),"",IF(OR(G$8<$E12,G$8-$E12>=12),0,$C12*INDEX(Fondsen!$F$5:$Q$30,MATCH($B12,Fondsen!$A$5:$A$30,0),G$8-$E12+1)))} | H12: {=IF(OR($B12="",$C12="",$E12=""),"",IF(OR(H$8<$E12,H$8-$E12>=12),0,$C12*INDEX(Fondsen!$F$5:$Q$30,MATCH($B12,Fondsen!$A$5:$A$30,0),H$8-$E12+1)))} | I12: {=IF(OR($B12="",$C12="",$E12=""),"",IF(OR(I$8<$E12,I$8-$E12>=12),0,$C12*INDEX(Fondsen!$F$5:$Q$30,MATCH($B12,Fondsen!$A$5:$A$30,0),I$8-$E12+1)))} | J12: {=IF(OR($B12="",$C12="",$E12=""),"",IF(OR(J$8<$E12,J$8-$E12>=12),0,$C12*INDEX(Fondsen!$F$5:$Q$30,MATCH($B12,Fondsen!$A$5:$A$30,0),J$8-$E12+1)))} | K12: {=IF(OR($B12="",$C12="",$E12=""),"",IF(OR(K$8<$E12,K$8-$E12>=12),0,$C12*INDEX(Fondsen!$F$5:$Q$30,MATCH($B12,Fondsen!$A$5:$A$30,0),K$8-$E12+1)))} | L12: {=IF(OR($B12="",$C12="",$E12=""),"",IF(OR(L$8<$E12,L$8-$E12>=12),0,$C12*INDEX(Fondsen!$F$5:$Q$30,MATCH($B12,Fondsen!$A$5:$A$30,0),L$8-$E12+1)))} | M12: {=IF(OR($B12="",$C12="",$E12=""),"",IF(OR(M$8<$E12,M$8-$E12>=12),0,$C12*INDEX(Fondsen!$F$5:$Q$30,MATCH($B12,Fondsen!$A$5:$A$30,0),M$8-$E12+1)))} | ... AS12: {=IF(OR($B12="",$C12="",$E12=""),"",IF(OR(AS$8<$E12,AS$8-$E12>=12),0,$C12*INDEX(Fondsen!$F$5:$Q$30,MATCH($B12,Fondsen!$A$5:$A$30,0),AS$8-$E12+1)))}
A13: =IF(B13="","",IFERROR(VLOOKUP(B13,Fondsen!$A$5:$B$30,2,FALSE()),"")) | D13: EUR | E13: 2026 | F13: {=IF(OR($B13="",$C13="",$E13=""),"",IF(OR(F$8<$E13,F$8-$E13>=12),0,$C13*INDEX(Fondsen!$F$5:$Q$30,MATCH($B13,Fondsen!$A$5:$A$30,0),F$8-$E13+1)))} | G13: {=IF(OR($B13="",$C13="",$E13=""),"",IF(OR(G$8<$E13,G$8-$E13>=12),0,$C13*INDEX(Fondsen!$F$5:$Q$30,MATCH($B13,Fondsen!$A$5:$A$30,0),G$8-$E13+1)))} | H13: {=IF(OR($B13="",$C13="",$E13=""),"",IF(OR(H$8<$E13,H$8-$E13>=12),0,$C13*INDEX(Fondsen!$F$5:$Q$30,MATCH($B13,Fondsen!$A$5:$A$30,0),H$8-$E13+1)))} | I13: {=IF(OR($B13="",$C13="",$E13=""),"",IF(OR(I$8<$E13,I$8-$E13>=12),0,$C13*INDEX(Fondsen!$F$5:$Q$30,MATCH($B13,Fondsen!$A$5:$A$30,0),I$8-$E13+1)))} | J13: {=IF(OR($B13="",$C13="",$E13=""),"",IF(OR(J$8<$E13,J$8-$E13>=12),0,$C13*INDEX(Fondsen!$F$5:$Q$30,MATCH($B13,Fondsen!$A$5:$A$30,0),J$8-$E13+1)))} | K13: {=IF(OR($B13="",$C13="",$E13=""),"",IF(OR(K$8<$E13,K$8-$E13>=12),0,$C13*INDEX(Fondsen!$F$5:$Q$30,MATCH($B13,Fondsen!$A$5:$A$30,0),K$8-$E13+1)))} | L13: {=IF(OR($B13="",$C13="",$E13=""),"",IF(OR(L$8<$E13,L$8-$E13>=12),0,$C13*INDEX(Fondsen!$F$5:$Q$30,MATCH($B13,Fondsen!$A$5:$A$30,0),L$8-$E13+1)))} | M13: {=IF(OR($B13="",$C13="",$E13=""),"",IF(OR(M$8<$E13,M$8-$E13>=12),0,$C13*INDEX(Fondsen!$F$5:$Q$30,MATCH($B13,Fondsen!$A$5:$A$30,0),M$8-$E13+1)))} | ... AS13: {=IF(OR($B13="",$C13="",$E13=""),"",IF(OR(AS$8<$E13,AS$8-$E13>=12),0,$C13*INDEX(Fondsen!$F$5:$Q$30,MATCH($B13,Fondsen!$A$5:$A$30,0),AS$8-$E13+1)))}
A14: =IF(B14="","",IFERROR(VLOOKUP(B14,Fondsen!$A$5:$B$30,2,FALSE()),"")) | D14: EUR | F14: {=IF(OR($B14="",$C14="",$E14=""),"",IF(OR(F$8<$E14,F$8-$E14>=12),0,$C14*INDEX(Fondsen!$F$5:$Q$30,MATCH($B14,Fondsen!$A$5:$A$30,0),F$8-$E14+1)))} | G14: {=IF(OR($B14="",$C14="",$E14=""),"",IF(OR(G$8<$E14,G$8-$E14>=12),0,$C14*INDEX(Fondsen!$F$5:$Q$30,MATCH($B14,Fondsen!$A$5:$A$30,0),G$8-$E14+1)))} | H14: {=IF(OR($B14="",$C14="",$E14=""),"",IF(OR(H$8<$E14,H$8-$E14>=12),0,$C14*INDEX(Fondsen!$F$5:$Q$30,MATCH($B14,Fondsen!$A$5:$A$30,0),H$8-$E14+1)))} | I14: {=IF(OR($B14="",$C14="",$E14=""),"",IF(OR(I$8<$E14,I$8-$E14>=12),0,$C14*INDEX(Fondsen!$F$5:$Q$30,MATCH($B14,Fondsen!$A$5:$A$30,0),I$8-$E14+1)))} | J14: {=IF(OR($B14="",$C14="",$E14=""),"",IF(OR(J$8<$E14,J$8-$E14>=12),0,$C14*INDEX(Fondsen!$F$5:$Q$30,MATCH($B14,Fondsen!$A$5:$A$30,0),J$8-$E14+1)))} | K14: {=IF(OR($B14="",$C14="",$E14=""),"",IF(OR(K$8<$E14,K$8-$E14>=12),0,$C14*INDEX(Fondsen!$F$5:$Q$30,MATCH($B14,Fondsen!$A$5:$A$30,0),K$8-$E14+1)))} | L14: {=IF(OR($B14="",$C14="",$E14=""),"",IF(OR(L$8<$E14,L$8-$E14>=12),0,$C14*INDEX(Fondsen!$F$5:$Q$30,MATCH($B14,Fondsen!$A$5:$A$30,0),L$8-$E14+1)))} | M14: {=IF(OR($B14="",$C14="",$E14=""),"",IF(OR(M$8<$E14,M$8-$E14>=12),0,$C14*INDEX(Fondsen!$F$5:$Q$30,MATCH($B14,Fondsen!$A$5:$A$30,0),M$8-$E14+1)))} | ... AS14: {=IF(OR($B14="",$C14="",$E14=""),"",IF(OR(AS$8<$E14,AS$8-$E14>=12),0,$C14*INDEX(Fondsen!$F$5:$Q$30,MATCH($B14,Fondsen!$A$5:$A$30,0),AS$8-$E14+1)))}
A15: =IF(B15="","",IFERROR(VLOOKUP(B15,Fondsen!$A$5:$B$30,2,FALSE()),"")) | D15: EUR | F15: {=IF(OR($B15="",$C15="",$E15=""),"",IF(OR(F$8<$E15,F$8-$E15>=12),0,$C15*INDEX(Fondsen!$F$5:$Q$30,MATCH($B15,Fondsen!$A$5:$A$30,0),F$8-$E15+1)))} | G15: {=IF(OR($B15="",$C15="",$E15=""),"",IF(OR(G$8<$E15,G$8-$E15>=12),0,$C15*INDEX(Fondsen!$F$5:$Q$30,MATCH($B15,Fondsen!$A$5:$A$30,0),G$8-$E15+1)))} | H15: {=IF(OR($B15="",$C15="",$E15=""),"",IF(OR(H$8<$E15,H$8-$E15>=12),0,$C15*INDEX(Fondsen!$F$5:$Q$30,MATCH($B15,Fondsen!$A$5:$A$30,0),H$8-$E15+1)))} | I15: {=IF(OR($B15="",$C15="",$E15=""),"",IF(OR(I$8<$E15,I$8-$E15>=12),0,$C15*INDEX(Fondsen!$F$5:$Q$30,MATCH($B15,Fondsen!$A$5:$A$30,0),I$8-$E15+1)))} | J15: {=IF(OR($B15="",$C15="",$E15=""),"",IF(OR(J$8<$E15,J$8-$E15>=12),0,$C15*INDEX(Fondsen!$F$5:$Q$30,MATCH($B15,Fondsen!$A$5:$A$30,0),J$8-$E15+1)))} | K15: {=IF(OR($B15="",$C15="",$E15=""),"",IF(OR(K$8<$E15,K$8-$E15>=12),0,$C15*INDEX(Fondsen!$F$5:$Q$30,MATCH($B15,Fondsen!$A$5:$A$30,0),K$8-$E15+1)))} | L15: {=IF(OR($B15="",$C15="",$E15=""),"",IF(OR(L$8<$E15,L$8-$E15>=12),0,$C15*INDEX(Fondsen!$F$5:$Q$30,MATCH($B15,Fondsen!$A$5:$A$30,0),L$8-$E15+1)))} | M15: {=IF(OR($B15="",$C15="",$E15=""),"",IF(OR(M$8<$E15,M$8-$E15>=12),0,$C15*INDEX(Fondsen!$F$5:$Q$30,MATCH($B15,Fondsen!$A$5:$A$30,0),M$8-$E15+1)))} | ... AS15: {=IF(OR($B15="",$C15="",$E15=""),"",IF(OR(AS$8<$E15,AS$8-$E15>=12),0,$C15*INDEX(Fondsen!$F$5:$Q$30,MATCH($B15,Fondsen!$A$5:$A$30,0),AS$8-$E15+1)))}
A16: =IF(B16="","",IFERROR(VLOOKUP(B16,Fondsen!$A$5:$B$30,2,FALSE()),"")) | D16: EUR | F16: {=IF(OR($B16="",$C16="",$E16=""),"",IF(OR(F$8<$E16,F$8-$E16>=12),0,$C16*INDEX(Fondsen!$F$5:$Q$30,MATCH($B16,Fondsen!$A$5:$A$30,0),F$8-$E16+1)))} | G16: {=IF(OR($B16="",$C16="",$E16=""),"",IF(OR(G$8<$E16,G$8-$E16>=12),0,$C16*INDEX(Fondsen!$F$5:$Q$30,MATCH($B16,Fondsen!$A$5:$A$30,0),G$8-$E16+1)))} | H16: {=IF(OR($B16="",$C16="",$E16=""),"",IF(OR(H$8<$E16,H$8-$E16>=12),0,$C16*INDEX(Fondsen!$F$5:$Q$30,MATCH($B16,Fondsen!$A$5:$A$30,0),H$8-$E16+1)))} | I16: {=IF(OR($B16="",$C16="",$E16=""),"",IF(OR(I$8<$E16,I$8-$E16>=12),0,$C16*INDEX(Fondsen!$F$5:$Q$30,MATCH($B16,Fondsen!$A$5:$A$30,0),I$8-$E16+1)))} | J16: {=IF(OR($B16="",$C16="",$E16=""),"",IF(OR(J$8<$E16,J$8-$E16>=12),0,$C16*INDEX(Fondsen!$F$5:$Q$30,MATCH($B16,Fondsen!$A$5:$A$30,0),J$8-$E16+1)))} | K16: {=IF(OR($B16="",$C16="",$E16=""),"",IF(OR(K$8<$E16,K$8-$E16>=12),0,$C16*INDEX(Fondsen!$F$5:$Q$30,MATCH($B16,Fondsen!$A$5:$A$30,0),K$8-$E16+1)))} | L16: {=IF(OR($B16="",$C16="",$E16=""),"",IF(OR(L$8<$E16,L$8-$E16>=12),0,$C16*INDEX(Fondsen!$F$5:$Q$30,MATCH($B16,Fondsen!$A$5:$A$30,0),L$8-$E16+1)))} | M16: {=IF(OR($B16="",$C16="",$E16=""),"",IF(OR(M$8<$E16,M$8-$E16>=12),0,$C16*INDEX(Fondsen!$F$5:$Q$30,MATCH($B16,Fondsen!$A$5:$A$30,0),M$8-$E16+1)))} | ... AS16: {=IF(OR($B16="",$C16="",$E16=""),"",IF(OR(AS$8<$E16,AS$8-$E16>=12),0,$C16*INDEX(Fondsen!$F$5:$Q$30,MATCH($B16,Fondsen!$A$5:$A$30,0),AS$8-$E16+1)))}
A17: =IF(B17="","",IFERROR(VLOOKUP(B17,Fondsen!$A$5:$B$30,2,FALSE()),"")) | D17: EUR | F17: {=IF(OR($B17="",$C17="",$E17=""),"",IF(OR(F$8<$E17,F$8-$E17>=12),0,$C17*INDEX(Fondsen!$F$5:$Q$30,MATCH($B17,Fondsen!$A$5:$A$30,0),F$8-$E17+1)))} | G17: {=IF(OR($B17="",$C17="",$E17=""),"",IF(OR(G$8<$E17,G$8-$E17>=12),0,$C17*INDEX(Fondsen!$F$5:$Q$30,MATCH($B17,Fondsen!$A$5:$A$30,0),G$8-$E17+1)))} | H17: {=IF(OR($B17="",$C17="",$E17=""),"",IF(OR(H$8<$E17,H$8-$E17>=12),0,$C17*INDEX(Fondsen!$F$5:$Q$30,MATCH($B17,Fondsen!$A$5:$A$30,0),H$8-$E17+1)))} | I17: {=IF(OR($B17="",$C17="",$E17=""),"",IF(OR(I$8<$E17,I$8-$E17>=12),0,$C17*INDEX(Fondsen!$F$5:$Q$30,MATCH($B17,Fondsen!$A$5:$A$30,0),I$8-$E17+1)))} | J17: {=IF(OR($B17="",$C17="",$E17=""),"",IF(OR(J$8<$E17,J$8-$E17>=12),0,$C17*INDEX(Fondsen!$F$5:$Q$30,MATCH($B17,Fondsen!$A$5:$A$30,0),J$8-$E17+1)))} | K17: {=IF(OR($B17="",$C17="",$E17=""),"",IF(OR(K$8<$E17,K$8-$E17>=12),0,$C17*INDEX(Fondsen!$F$5:$Q$30,MATCH($B17,Fondsen!$A$5:$A$30,0),K$8-$E17+1)))} | L17: {=IF(OR($B17="",$C17="",$E17=""),"",IF(OR(L$8<$E17,L$8-$E17>=12),0,$C17*INDEX(Fondsen!$F$5:$Q$30,MATCH($B17,Fondsen!$A$5:$A$30,0),L$8-$E17+1)))} | M17: {=IF(OR($B17="",$C17="",$E17=""),"",IF(OR(M$8<$E17,M$8-$E17>=12),0,$C17*INDEX(Fondsen!$F$5:$Q$30,MATCH($B17,Fondsen!$A$5:$A$30,0),M$8-$E17+1)))} | ... AS17: {=IF(OR($B17="",$C17="",$E17=""),"",IF(OR(AS$8<$E17,AS$8-$E17>=12),0,$C17*INDEX(Fondsen!$F$5:$Q$30,MATCH($B17,Fondsen!$A$5:$A$30,0),AS$8-$E17+1)))}
A18: =IF(B18="","",IFERROR(VLOOKUP(B18,Fondsen!$A$5:$B$30,2,FALSE()),"")) | D18: EUR | F18: {=IF(OR($B18="",$C18="",$E18=""),"",IF(OR(F$8<$E18,F$8-$E18>=12),0,$C18*INDEX(Fondsen!$F$5:$Q$30,MATCH($B18,Fondsen!$A$5:$A$30,0),F$8-$E18+1)))} | G18: {=IF(OR($B18="",$C18="",$E18=""),"",IF(OR(G$8<$E18,G$8-$E18>=12),0,$C18*INDEX(Fondsen!$F$5:$Q$30,MATCH($B18,Fondsen!$A$5:$A$30,0),G$8-$E18+1)))} | H18: {=IF(OR($B18="",$C18="",$E18=""),"",IF(OR(H$8<$E18,H$8-$E18>=12),0,$C18*INDEX(Fondsen!$F$5:$Q$30,MATCH($B18,Fondsen!$A$5:$A$30,0),H$8-$E18+1)))} | I18: {=IF(OR($B18="",$C18="",$E18=""),"",IF(OR(I$8<$E18,I$8-$E18>=12),0,$C18*INDEX(Fondsen!$F$5:$Q$30,MATCH($B18,Fondsen!$A$5:$A$30,0),I$8-$E18+1)))} | J18: {=IF(OR($B18="",$C18="",$E18=""),"",IF(OR(J$8<$E18,J$8-$E18>=12),0,$C18*INDEX(Fondsen!$F$5:$Q$30,MATCH($B18,Fondsen!$A$5:$A$30,0),J$8-$E18+1)))} | K18: {=IF(OR($B18="",$C18="",$E18=""),"",IF(OR(K$8<$E18,K$8-$E18>=12),0,$C18*INDEX(Fondsen!$F$5:$Q$30,MATCH($B18,Fondsen!$A$5:$A$30,0),K$8-$E18+1)))} | L18: {=IF(OR($B18="",$C18="",$E18=""),"",IF(OR(L$8<$E18,L$8-$E18>=12),0,$C18*INDEX(Fondsen!$F$5:$Q$30,MATCH($B18,Fondsen!$A$5:$A$30,0),L$8-$E18+1)))} | M18: {=IF(OR($B18="",$C18="",$E18=""),"",IF(OR(M$8<$E18,M$8-$E18>=12),0,$C18*INDEX(Fondsen!$F$5:$Q$30,MATCH($B18,Fondsen!$A$5:$A$30,0),M$8-$E18+1)))} | ... AS18: {=IF(OR($B18="",$C18="",$E18=""),"",IF(OR(AS$8<$E18,AS$8-$E18>=12),0,$C18*INDEX(Fondsen!$F$5:$Q$30,MATCH($B18,Fondsen!$A$5:$A$30,0),AS$8-$E18+1)))}
A19: =IF(B19="","",IFERROR(VLOOKUP(B19,Fondsen!$A$5:$B$30,2,FALSE()),"")) | D19: EUR | F19: {=IF(OR($B19="",$C19="",$E19=""),"",IF(OR(F$8<$E19,F$8-$E19>=12),0,$C19*INDEX(Fondsen!$F$5:$Q$30,MATCH($B19,Fondsen!$A$5:$A$30,0),F$8-$E19+1)))} | G19: {=IF(OR($B19="",$C19="",$E19=""),"",IF(OR(G$8<$E19,G$8-$E19>=12),0,$C19*INDEX(Fondsen!$F$5:$Q$30,MATCH($B19,Fondsen!$A$5:$A$30,0),G$8-$E19+1)))} | H19: {=IF(OR($B19="",$C19="",$E19=""),"",IF(OR(H$8<$E19,H$8-$E19>=12),0,$C19*INDEX(Fondsen!$F$5:$Q$30,MATCH($B19,Fondsen!$A$5:$A$30,0),H$8-$E19+1)))} | I19: {=IF(OR($B19="",$C19="",$E19=""),"",IF(OR(I$8<$E19,I$8-$E19>=12),0,$C19*INDEX(Fondsen!$F$5:$Q$30,MATCH($B19,Fondsen!$A$5:$A$30,0),I$8-$E19+1)))} | J19: {=IF(OR($B19="",$C19="",$E19=""),"",IF(OR(J$8<$E19,J$8-$E19>=12),0,$C19*INDEX(Fondsen!$F$5:$Q$30,MATCH($B19,Fondsen!$A$5:$A$30,0),J$8-$E19+1)))} | K19: {=IF(OR($B19="",$C19="",$E19=""),"",IF(OR(K$8<$E19,K$8-$E19>=12),0,$C19*INDEX(Fondsen!$F$5:$Q$30,MATCH($B19,Fondsen!$A$5:$A$30,0),K$8-$E19+1)))} | L19: {=IF(OR($B19="",$C19="",$E19=""),"",IF(OR(L$8<$E19,L$8-$E19>=12),0,$C19*INDEX(Fondsen!$F$5:$Q$30,MATCH($B19,Fondsen!$A$5:$A$30,0),L$8-$E19+1)))} | M19: {=IF(OR($B19="",$C19="",$E19=""),"",IF(OR(M$8<$E19,M$8-$E19>=12),0,$C19*INDEX(Fondsen!$F$5:$Q$30,MATCH($B19,Fondsen!$A$5:$A$30,0),M$8-$E19+1)))} | ... AS19: {=IF(OR($B19="",$C19="",$E19=""),"",IF(OR(AS$8<$E19,AS$8-$E19>=12),0,$C19*INDEX(Fondsen!$F$5:$Q$30,MATCH($B19,Fondsen!$A$5:$A$30,0),AS$8-$E19+1)))}
A20: =IF(B20="","",IFERROR(VLOOKUP(B20,Fondsen!$A$5:$B$30,2,FALSE()),"")) | D20: EUR | F20: {=IF(OR($B20="",$C20="",$E20=""),"",IF(OR(F$8<$E20,F$8-$E20>=12),0,$C20*INDEX(Fondsen!$F$5:$Q$30,MATCH($B20,Fondsen!$A$5:$A$30,0),F$8-$E20+1)))} | G20: {=IF(OR($B20="",$C20="",$E20=""),"",IF(OR(G$8<$E20,G$8-$E20>=12),0,$C20*INDEX(Fondsen!$F$5:$Q$30,MATCH($B20,Fondsen!$A$5:$A$30,0),G$8-$E20+1)))} | H20: {=IF(OR($B20="",$C20="",$E20=""),"",IF(OR(H$8<$E20,H$8-$E20>=12),0,$C20*INDEX(Fondsen!$F$5:$Q$30,MATCH($B20,Fondsen!$A$5:$A$30,0),H$8-$E20+1)))} | I20: {=IF(OR($B20="",$C20="",$E20=""),"",IF(OR(I$8<$E20,I$8-$E20>=12),0,$C20*INDEX(Fondsen!$F$5:$Q$30,MATCH($B20,Fondsen!$A$5:$A$30,0),I$8-$E20+1)))} | J20: {=IF(OR($B20="",$C20="",$E20=""),"",IF(OR(J$8<$E20,J$8-$E20>=12),0,$C20*INDEX(Fondsen!$F$5:$Q$30,MATCH($B20,Fondsen!$A$5:$A$30,0),J$8-$E20+1)))} | K20: {=IF(OR($B20="",$C20="",$E20=""),"",IF(OR(K$8<$E20,K$8-$E20>=12),0,$C20*INDEX(Fondsen!$F$5:$Q$30,MATCH($B20,Fondsen!$A$5:$A$30,0),K$8-$E20+1)))} | L20: {=IF(OR($B20="",$C20="",$E20=""),"",IF(OR(L$8<$E20,L$8-$E20>=12),0,$C20*INDEX(Fondsen!$F$5:$Q$30,MATCH($B20,Fondsen!$A$5:$A$30,0),L$8-$E20+1)))} | M20: {=IF(OR($B20="",$C20="",$E20=""),"",IF(OR(M$8<$E20,M$8-$E20>=12),0,$C20*INDEX(Fondsen!$F$5:$Q$30,MATCH($B20,Fondsen!$A$5:$A$30,0),M$8-$E20+1)))} | ... AS20: {=IF(OR($B20="",$C20="",$E20=""),"",IF(OR(AS$8<$E20,AS$8-$E20>=12),0,$C20*INDEX(Fondsen!$F$5:$Q$30,MATCH($B20,Fondsen!$A$5:$A$30,0),AS$8-$E20+1)))}
A21: =IF(B21="","",IFERROR(VLOOKUP(B21,Fondsen!$A$5:$B$30,2,FALSE()),"")) | D21: EUR | F21: {=IF(OR($B21="",$C21="",$E21=""),"",IF(OR(F$8<$E21,F$8-$E21>=12),0,$C21*INDEX(Fondsen!$F$5:$Q$30,MATCH($B21,Fondsen!$A$5:$A$30,0),F$8-$E21+1)))} | G21: {=IF(OR($B21="",$C21="",$E21=""),"",IF(OR(G$8<$E21,G$8-$E21>=12),0,$C21*INDEX(Fondsen!$F$5:$Q$30,MATCH($B21,Fondsen!$A$5:$A$30,0),G$8-$E21+1)))} | H21: {=IF(OR($B21="",$C21="",$E21=""),"",IF(OR(H$8<$E21,H$8-$E21>=12),0,$C21*INDEX(Fondsen!$F$5:$Q$30,MATCH($B21,Fondsen!$A$5:$A$30,0),H$8-$E21+1)))} | I21: {=IF(OR($B21="",$C21="",$E21=""),"",IF(OR(I$8<$E21,I$8-$E21>=12),0,$C21*INDEX(Fondsen!$F$5:$Q$30,MATCH($B21,Fondsen!$A$5:$A$30,0),I$8-$E21+1)))} | J21: {=IF(OR($B21="",$C21="",$E21=""),"",IF(OR(J$8<$E21,J$8-$E21>=12),0,$C21*INDEX(Fondsen!$F$5:$Q$30,MATCH($B21,Fondsen!$A$5:$A$30,0),J$8-$E21+1)))} | K21: {=IF(OR($B21="",$C21="",$E21=""),"",IF(OR(K$8<$E21,K$8-$E21>=12),0,$C21*INDEX(Fondsen!$F$5:$Q$30,MATCH($B21,Fondsen!$A$5:$A$30,0),K$8-$E21+1)))} | L21: {=IF(OR($B21="",$C21="",$E21=""),"",IF(OR(L$8<$E21,L$8-$E21>=12),0,$C21*INDEX(Fondsen!$F$5:$Q$30,MATCH($B21,Fondsen!$A$5:$A$30,0),L$8-$E21+1)))} | M21: {=IF(OR($B21="",$C21="",$E21=""),"",IF(OR(M$8<$E21,M$8-$E21>=12),0,$C21*INDEX(Fondsen!$F$5:$Q$30,MATCH($B21,Fondsen!$A$5:$A$30,0),M$8-$E21+1)))} | ... AS21: {=IF(OR($B21="",$C21="",$E21=""),"",IF(OR(AS$8<$E21,AS$8-$E21>=12),0,$C21*INDEX(Fondsen!$F$5:$Q$30,MATCH($B21,Fondsen!$A$5:$A$30,0),AS$8-$E21+1)))}
A22: =IF(B22="","",IFERROR(VLOOKUP(B22,Fondsen!$A$5:$B$30,2,FALSE()),"")) | D22: EUR | F22: {=IF(OR($B22="",$C22="",$E22=""),"",IF(OR(F$8<$E22,F$8-$E22>=12),0,$C22*INDEX(Fondsen!$F$5:$Q$30,MATCH($B22,Fondsen!$A$5:$A$30,0),F$8-$E22+1)))} | G22: {=IF(OR($B22="",$C22="",$E22=""),"",IF(OR(G$8<$E22,G$8-$E22>=12),0,$C22*INDEX(Fondsen!$F$5:$Q$30,MATCH($B22,Fondsen!$A$5:$A$30,0),G$8-$E22+1)))} | H22: {=IF(OR($B22="",$C22="",$E22=""),"",IF(OR(H$8<$E22,H$8-$E22>=12),0,$C22*INDEX(Fondsen!$F$5:$Q$30,MATCH($B22,Fondsen!$A$5:$A$30,0),H$8-$E22+1)))} | I22: {=IF(OR($B22="",$C22="",$E22=""),"",IF(OR(I$8<$E22,I$8-$E22>=12),0,$C22*INDEX(Fondsen!$F$5:$Q$30,MATCH($B22,Fondsen!$A$5:$A$30,0),I$8-$E22+1)))} | J22: {=IF(OR($B22="",$C22="",$E22=""),"",IF(OR(J$8<$E22,J$8-$E22>=12),0,$C22*INDEX(Fondsen!$F$5:$Q$30,MATCH($B22,Fondsen!$A$5:$A$30,0),J$8-$E22+1)))} | K22: {=IF(OR($B22="",$C22="",$E22=""),"",IF(OR(K$8<$E22,K$8-$E22>=12),0,$C22*INDEX(Fondsen!$F$5:$Q$30,MATCH($B22,Fondsen!$A$5:$A$30,0),K$8-$E22+1)))} | L22: {=IF(OR($B22="",$C22="",$E22=""),"",IF(OR(L$8<$E22,L$8-$E22>=12),0,$C22*INDEX(Fondsen!$F$5:$Q$30,MATCH($B22,Fondsen!$A$5:$A$30,0),L$8-$E22+1)))} | M22: {=IF(OR($B22="",$C22="",$E22=""),"",IF(OR(M$8<$E22,M$8-$E22>=12),0,$C22*INDEX(Fondsen!$F$5:$Q$30,MATCH($B22,Fondsen!$A$5:$A$30,0),M$8-$E22+1)))} | ... AS22: {=IF(OR($B22="",$C22="",$E22=""),"",IF(OR(AS$8<$E22,AS$8-$E22>=12),0,$C22*INDEX(Fondsen!$F$5:$Q$30,MATCH($B22,Fondsen!$A$5:$A$30,0),AS$8-$E22+1)))}
A23: =IF(B23="","",IFERROR(VLOOKUP(B23,Fondsen!$A$5:$B$30,2,FALSE()),"")) | D23: EUR | F23: {=IF(OR($B23="",$C23="",$E23=""),"",IF(OR(F$8<$E23,F$8-$E23>=12),0,$C23*INDEX(Fondsen!$F$5:$Q$30,MATCH($B23,Fondsen!$A$5:$A$30,0),F$8-$E23+1)))} | G23: {=IF(OR($B23="",$C23="",$E23=""),"",IF(OR(G$8<$E23,G$8-$E23>=12),0,$C23*INDEX(Fondsen!$F$5:$Q$30,MATCH($B23,Fondsen!$A$5:$A$30,0),G$8-$E23+1)))} | H23: {=IF(OR($B23="",$C23="",$E23=""),"",IF(OR(H$8<$E23,H$8-$E23>=12),0,$C23*INDEX(Fondsen!$F$5:$Q$30,MATCH($B23,Fondsen!$A$5:$A$30,0),H$8-$E23+1)))} | I23: {=IF(OR($B23="",$C23="",$E23=""),"",IF(OR(I$8<$E23,I$8-$E23>=12),0,$C23*INDEX(Fondsen!$F$5:$Q$30,MATCH($B23,Fondsen!$A$5:$A$30,0),I$8-$E23+1)))} | J23: {=IF(OR($B23="",$C23="",$E23=""),"",IF(OR(J$8<$E23,J$8-$E23>=12),0,$C23*INDEX(Fondsen!$F$5:$Q$30,MATCH($B23,Fondsen!$A$5:$A$30,0),J$8-$E23+1)))} | K23: {=IF(OR($B23="",$C23="",$E23=""),"",IF(OR(K$8<$E23,K$8-$E23>=12),0,$C23*INDEX(Fondsen!$F$5:$Q$30,MATCH($B23,Fondsen!$A$5:$A$30,0),K$8-$E23+1)))} | L23: {=IF(OR($B23="",$C23="",$E23=""),"",IF(OR(L$8<$E23,L$8-$E23>=12),0,$C23*INDEX(Fondsen!$F$5:$Q$30,MATCH($B23,Fondsen!$A$5:$A$30,0),L$8-$E23+1)))} | M23: {=IF(OR($B23="",$C23="",$E23=""),"",IF(OR(M$8<$E23,M$8-$E23>=12),0,$C23*INDEX(Fondsen!$F$5:$Q$30,MATCH($B23,Fondsen!$A$5:$A$30,0),M$8-$E23+1)))} | ... AS23: {=IF(OR($B23="",$C23="",$E23=""),"",IF(OR(AS$8<$E23,AS$8-$E23>=12),0,$C23*INDEX(Fondsen!$F$5:$Q$30,MATCH($B23,Fondsen!$A$5:$A$30,0),AS$8-$E23+1)))}
A24: =IF(B24="","",IFERROR(VLOOKUP(B24,Fondsen!$A$5:$B$30,2,FALSE()),"")) | D24: EUR | F24: {=IF(OR($B24="",$C24="",$E24=""),"",IF(OR(F$8<$E24,F$8-$E24>=12),0,$C24*INDEX(Fondsen!$F$5:$Q$30,MATCH($B24,Fondsen!$A$5:$A$30,0),F$8-$E24+1)))} | G24: {=IF(OR($B24="",$C24="",$E24=""),"",IF(OR(G$8<$E24,G$8-$E24>=12),0,$C24*INDEX(Fondsen!$F$5:$Q$30,MATCH($B24,Fondsen!$A$5:$A$30,0),G$8-$E24+1)))} | H24: {=IF(OR($B24="",$C24="",$E24=""),"",IF(OR(H$8<$E24,H$8-$E24>=12),0,$C24*INDEX(Fondsen!$F$5:$Q$30,MATCH($B24,Fondsen!$A$5:$A$30,0),H$8-$E24+1)))} | I24: {=IF(OR($B24="",$C24="",$E24=""),"",IF(OR(I$8<$E24,I$8-$E24>=12),0,$C24*INDEX(Fondsen!$F$5:$Q$30,MATCH($B24,Fondsen!$A$5:$A$30,0),I$8-$E24+1)))} | J24: {=IF(OR($B24="",$C24="",$E24=""),"",IF(OR(J$8<$E24,J$8-$E24>=12),0,$C24*INDEX(Fondsen!$F$5:$Q$30,MATCH($B24,Fondsen!$A$5:$A$30,0),J$8-$E24+1)))} | K24: {=IF(OR($B24="",$C24="",$E24=""),"",IF(OR(K$8<$E24,K$8-$E24>=12),0,$C24*INDEX(Fondsen!$F$5:$Q$30,MATCH($B24,Fondsen!$A$5:$A$30,0),K$8-$E24+1)))} | L24: {=IF(OR($B24="",$C24="",$E24=""),"",IF(OR(L$8<$E24,L$8-$E24>=12),0,$C24*INDEX(Fondsen!$F$5:$Q$30,MATCH($B24,Fondsen!$A$5:$A$30,0),L$8-$E24+1)))} | M24: {=IF(OR($B24="",$C24="",$E24=""),"",IF(OR(M$8<$E24,M$8-$E24>=12),0,$C24*INDEX(Fondsen!$F$5:$Q$30,MATCH($B24,Fondsen!$A$5:$A$30,0),M$8-$E24+1)))} | ... AS24: {=IF(OR($B24="",$C24="",$E24=""),"",IF(OR(AS$8<$E24,AS$8-$E24>=12),0,$C24*INDEX(Fondsen!$F$5:$Q$30,MATCH($B24,Fondsen!$A$5:$A$30,0),AS$8-$E24+1)))}
A25: =IF(B25="","",IFERROR(VLOOKUP(B25,Fondsen!$A$5:$B$30,2,FALSE()),"")) | D25: EUR | F25: {=IF(OR($B25="",$C25="",$E25=""),"",IF(OR(F$8<$E25,F$8-$E25>=12),0,$C25*INDEX(Fondsen!$F$5:$Q$30,MATCH($B25,Fondsen!$A$5:$A$30,0),F$8-$E25+1)))} | G25: {=IF(OR($B25="",$C25="",$E25=""),"",IF(OR(G$8<$E25,G$8-$E25>=12),0,$C25*INDEX(Fondsen!$F$5:$Q$30,MATCH($B25,Fondsen!$A$5:$A$30,0),G$8-$E25+1)))} | H25: {=IF(OR($B25="",$C25="",$E25=""),"",IF(OR(H$8<$E25,H$8-$E25>=12),0,$C25*INDEX(Fondsen!$F$5:$Q$30,MATCH($B25,Fondsen!$A$5:$A$30,0),H$8-$E25+1)))} | I25: {=IF(OR($B25="",$C25="",$E25=""),"",IF(OR(I$8<$E25,I$8-$E25>=12),0,$C25*INDEX(Fondsen!$F$5:$Q$30,MATCH($B25,Fondsen!$A$5:$A$30,0),I$8-$E25+1)))} | J25: {=IF(OR($B25="",$C25="",$E25=""),"",IF(OR(J$8<$E25,J$8-$E25>=12),0,$C25*INDEX(Fondsen!$F$5:$Q$30,MATCH($B25,Fondsen!$A$5:$A$30,0),J$8-$E25+1)))} | K25: {=IF(OR($B25="",$C25="",$E25=""),"",IF(OR(K$8<$E25,K$8-$E25>=12),0,$C25*INDEX(Fondsen!$F$5:$Q$30,MATCH($B25,Fondsen!$A$5:$A$30,0),K$8-$E25+1)))} | L25: {=IF(OR($B25="",$C25="",$E25=""),"",IF(OR(L$8<$E25,L$8-$E25>=12),0,$C25*INDEX(Fondsen!$F$5:$Q$30,MATCH($B25,Fondsen!$A$5:$A$30,0),L$8-$E25+1)))} | M25: {=IF(OR($B25="",$C25="",$E25=""),"",IF(OR(M$8<$E25,M$8-$E25>=12),0,$C25*INDEX(Fondsen!$F$5:$Q$30,MATCH($B25,Fondsen!$A$5:$A$30,0),M$8-$E25+1)))} | ... AS25: {=IF(OR($B25="",$C25="",$E25=""),"",IF(OR(AS$8<$E25,AS$8-$E25>=12),0,$C25*INDEX(Fondsen!$F$5:$Q$30,MATCH($B25,Fondsen!$A$5:$A$30,0),AS$8-$E25+1)))}
... A99: =IF(B99="","",IFERROR(VLOOKUP(B99,Fondsen!$A$5:$B$30,2,FALSE()),"")) | D99: EUR | F99: {=IF(OR($B99="",$C99="",$E99=""),"",IF(OR(F$8<$E99,F$8-$E99>=12),0,$C99*INDEX(Fondsen!$F$5:$Q$30,MATCH($B99,Fondsen!$A$5:$A$30,0),F$8-$E99+1)))} | G99: {=IF(OR($B99="",$C99="",$E99=""),"",IF(OR(G$8<$E99,G$8-$E99>=12),0,$C99*INDEX(Fondsen!$F$5:$Q$30,MATCH($B99,Fondsen!$A$5:$A$30,0),G$8-$E99+1)))} | H99: {=IF(OR($B99="",$C99="",$E99=""),"",IF(OR(H$8<$E99,H$8-$E99>=12),0,$C99*INDEX(Fondsen!$F$5:$Q$30,MATCH($B99,Fondsen!$A$5:$A$30,0),H$8-$E99+1)))} | I99: {=IF(OR($B99="",$C99="",$E99=""),"",IF(OR(I$8<$E99,I$8-$E99>=12),0,$C99*INDEX(Fondsen!$F$5:$Q$30,MATCH($B99,Fondsen!$A$5:$A$30,0),I$8-$E99+1)))} | J99: {=IF(OR($B99="",$C99="",$E99=""),"",IF(OR(J$8<$E99,J$8-$E99>=12),0,$C99*INDEX(Fondsen!$F$5:$Q$30,MATCH($B99,Fondsen!$A$5:$A$30,0),J$8-$E99+1)))} | K99: {=IF(OR($B99="",$C99="",$E99=""),"",IF(OR(K$8<$E99,K$8-$E99>=12),0,$C99*INDEX(Fondsen!$F$5:$Q$30,MATCH($B99,Fondsen!$A$5:$A$30,0),K$8-$E99+1)))} | L99: {=IF(OR($B99="",$C99="",$E99=""),"",IF(OR(L$8<$E99,L$8-$E99>=12),0,$C99*INDEX(Fondsen!$F$5:$Q$30,MATCH($B99,Fondsen!$A$5:$A$30,0),L$8-$E99+1)))} | M99: {=IF(OR($B99="",$C99="",$E99=""),"",IF(OR(M$8<$E99,M$8-$E99>=12),0,$C99*INDEX(Fondsen!$F$5:$Q$30,MATCH($B99,Fondsen!$A$5:$A$30,0),M$8-$E99+1)))} | ... AS99: {=IF(OR($B99="",$C99="",$E99=""),"",IF(OR(AS$8<$E99,AS$8-$E99>=12),0,$C99*INDEX(Fondsen!$F$5:$Q$30,MATCH($B99,Fondsen!$A$5:$A$30,0),AS$8-$E99+1)))}
A101: STARTKAPITAAL | C101: =C5
A102: Beschikbaar Kapitaal | F102: =$C$101-F101 -> 0 | G102: =$C$101-G101 -> 0 | H102: =$C$101-H101 -> 0 | I102: =$C$101-I101 -> 0 | J102: =$C$101-J101 -> 0 | K102: =$C$101-K101 -> 0 | L102: =$C$101-L101 -> 0 | M102: =$C$101-M101 -> 0 | ... AS102: =$C$101-AS101 -> 0
A103: Jaarlijkse Netto Cashflow | F103: =SUM(F9:F99) -> 0 | G103: =SUM(G9:G99) -> 0 | H103: =SUM(H9:H99) -> 0 | I103: =SUM(I9:I99) -> 0 | J103: =SUM(J9:J99) -> 0 | K103: =SUM(K9:K99) -> 0 | L103: =SUM(L9:L99) -> 0 | M103: =SUM(M9:M99) -> 0 | ... AS103: =SUM(AS9:AS99) -> 0
A104: Cumulatief Capital Called | F104: =ABS(MIN(F103,0)) -> 0 | G104: =F104+ABS(MIN(G103,0)) -> 0 | H104: =G104+ABS(MIN(H103,0)) -> 0 | I104: =H104+ABS(MIN(I103,0)) -> 0 | J104: =I104+ABS(MIN(J103,0)) -> 0 | K104: =J104+ABS(MIN(K103,0)) -> 0 | L104: =K104+ABS(MIN(L103,0)) -> 0 | M104: =L104+ABS(MIN(M103,0)) -> 0 | N104: =M104+ABS(MIN(N103,0)) -> 0 | ... AS104: =AR104+ABS(MIN(AS103,0)) -> 0
A105: Beschikbaar Kapitaal | F105: =$C$101-F104 -> 0 | G105: =$C$101-G104 -> 0 | H105: =$C$101-H104 -> 0 | I105: =$C$101-I104 -> 0 | J105: =$C$101-J104 -> 0 | K105: =$C$101-K104 -> 0 | L105: =$C$101-L104 -> 0 | M105: =$C$101-M104 -> 0 | ... AS105: =$C$101-AS104 -> 0

Sheet Portfolio Projectie
A1: Portfolio Projectie
A2: Overzicht cashflows en kapitaal per jaar
A4: Jaar | B4: Beschikbaar Kapitaal | C4: Capital Called | D4: Netto Cashflow
A5: 2025 | B5: ='Cashflow Matrix'!F105 -> 0 | C5: ='Cashflow Matrix'!F104 -> 0 | D5: ='Cashflow Matrix'!F103 -> 0
A6: 2026 | B6: ='Cashflow Matrix'!G105 -> 0 | C6: ='Cashflow Matrix'!G104 -> 0 | D6: ='Cashflow Matrix'!G103 -> 0
A7: 2027 | B7: ='Cashflow Matrix'!H105 -> 0 | C7: ='Cashflow Matrix'!H104 -> 0 | D7: ='Cashflow Matrix'!H103 -> 0
A8: 2028 | B8: ='Cashflow Matrix'!I105 -> 0 | C8: ='Cashflow Matrix'!I104 -> 0 | D8: ='Cashflow Matrix'!I103 -> 0
A9: 2029 | B9: ='Cashflow Matrix'!J105 -> 0 | C9: ='Cashflow Matrix'!J104 -> 0 | D9: ='Cashflow Matrix'!J103 -> 0
A10: 2030 | B10: ='Cashflow Matrix'!K105 -> 0 | C10: ='Cashflow Matrix'!K104 -> 0 | D10: ='Cashflow Matrix'!K103 -> 0
A11: 2031 | B11: ='Cashflow Matrix'!L105 -> 0 | C11: ='Cashflow Matrix'!L104 -> 0 | D11: ='Cashflow Matrix'!L103 -> 0
A12: 2032 | B12: ='Cashflow Matrix'!M105 -> 0 | C12: ='Cashflow Matrix'!M104 -> 0 | D12: ='Cashflow Matrix'!M103 -> 0
A13: 2033 | B13: ='Cashflow Matrix'!N105 -> 0 | C13: ='Cashflow Matrix'!N104 -> 0 | D13: ='Cashflow Matrix'!N103 -> 0
A14: 2034 | B14: ='Cashflow Matrix'!O105 -> 0 | C14: ='Cashflow Matrix'!O104 -> 0 | D14: ='Cashflow Matrix'!O103 -> 0
A15: 2035 | B15: ='Cashflow Matrix'!P105 -> 0 | C15: ='Cashflow Matrix'!P104 -> 0 | D15: ='Cashflow Matrix'!P103 -> 0
A16: 2036 | B16: ='Cashflow Matrix'!Q105 -> 0 | C16: ='Cashflow Matrix'!Q104 -> 0 | D16: ='Cashflow Matrix'!Q103 -> 0
A17: 2037 | B17: ='Cashflow Matrix'!R105 -> 0 | C17: ='Cashflow Matrix'!R104 -> 0 | D17: ='Cashflow Matrix'!R103 -> 0
A18: 2038 | B18: ='Cashflow Matrix'!S105 -> 0 | C18: ='Cashflow Matrix'!S104 -> 0 | D18: ='Cashflow Matrix'!S103 -> 0
A19: 2039 | B19: ='Cashflow Matrix'!T105 -> 0 | C19: ='Cashflow Matrix'!T104 -> 0 | D19: ='Cashflow Matrix'!T103 -> 0

Sheet Fondsen
A1: FONDSEN DATABASE
A2: Capital Call Profiles & Fund Registry
F3: CASHFLOW PROFIEL (% van Commitment, negatief = capital call, positief = distributie)
A4: Fondsnaam | B4: Type | C4: Status | D4: Notities | F4: Jaar 1 | G4: Jaar 2 | H4: Jaar 3 | I4: Jaar 4 | J4: Jaar 5 | K4: Jaar 6 | L4: Jaar 7 | M4: Jaar 8 | N4: Jaar 9 | O4: Jaar 10 | P4: Jaar 11 | Q4: Jaar 12
A5: Dummy PE | B5: PE | C5: Template | D5: Gemiddeld PE profiel - vervang door echt fonds | F5: -0.2383 | G5: -0.2383 | H5: -0.149 | I5: -0.074 | J5: 0.2522 | K5: 0.5253 | L5: 0.4363 | M5: 0.3728 | N5: 0.2753 | O5: 0.1585 | P5: 0.097 | Q5: 0
A6: Dummy VC | B6: VC | C6: Template | D6: Gemiddeld VC profiel - vervang door echt fonds | F6: -0.0555 | G6: -0.065 | H6: -0.2645 | I6: -0.2238 | J6: -0.0538 | K6: 0.1045 | L6: 0.3125 | M6: 0.6218 | N6: 0.572 | O6: 0.4133 | P6: 0.1865 | Q6: 0
A7: Dummy Secondaries | B7: Secondaries | C7: Template | D7: Gemiddeld Secondaries profiel - vervang door echt fonds | F7: -0.531 | G7: -0.0476 | H7: 0.3026 | I7: 0.2489 | J7: 0.185 | K7: 0.131 | L7: 0.1471 | M7: 0.1215 | N7: 0.0843 | O7: 0.0131 | P7: 0.0057 | Q7: 0
A8: Alpinvest PE Fund | B8: PE | C8: Active | D8: Leading European PE fund | F8: -0.25 | G8: -0.22 | H8: -0.16 | I8: -0.08 | J8: 0.22 | K8: 0.48 | L8: 0.42 | M8: 0.35 | N8: 0.26 | O8: 0.14 | P8: 0.08 | Q8: 0
A9: Rhein Invest II | B9: PE | C9: Active | D9: German mid-market PE | F9: -0.22 | G9: -0.25 | H9: -0.14 | I9: -0.09 | J9: 0.28 | K9: 0.5 | L9: 0.45 | M9: 0.38 | N9: 0.29 | O9: 0.16 | P9: 0.1 | Q9: 0
A10: GP Buyout Fund | B10: PE | C10: Active | D10: Large-cap buyout focus | F10: -0.2383 | G10: -0.2383 | H10: -0.149 | I10: -0.074 | J10: 0.2522 | K10: 0.5253 | L10: 0.4363 | M10: 0.3728 | N10: 0.2753 | O10: 0.1585 | P10: 0.097 | Q10: 0
A11: OGF II | B11: VC | C11: Active | D11: Tech focused VC fund | F11: -0.06 | G11: -0.07 | H11: -0.28 | I11: -0.24 | J11: -0.06 | K11: 0.12 | L11: 0.3 | M11: 0.58 | N11: 0.55 | O11: 0.4 | P11: 0.17 | Q11: 0
A12: Impact VC Fund | B12: VC | C12: Active | D12: Impact investing focus | F12: -0.05 | G12: -0.06 | H12: -0.25 | I12: -0.21 | J12: -0.05 | K12: 0.09 | L12: 0.28 | M12: 0.55 | N12: 0.52 | O12: 0.38 | P12: 0.16 | Q12: 0
A13: Blockchain Ventures | B13: VC | C13: Active | D13: Crypto/blockchain focus | F13: -0.0555 | G13: -0.065 | H13: -0.2645 | I13: -0.2238 | J13: -0.0538 | K13: 0.1045 | L13: 0.3125 | M13: 0.6218 | N13: 0.572 | O13: 0.4133 | P13: 0.1865 | Q13: 0
A14: ICG I - LP Fund | B14: Secondaries | C14: Active | D14: Credit focused secondaries | F14: -0.55 | G14: -0.05 | H14: 0.28 | I14: 0.23 | J14: 0.17 | K14: 0.12 | L14: 0.14 | M14: 0.11 | N14: 0.08 | O14: 0.015 | P14: 0.006 | Q14: 0
A15: Bcapital II | B15: Secondaries | C15: Active | D15: European secondaries specialist | F15: -0.5 | G15: -0.045 | H15: 0.32 | I15: 0.26 | J15: 0.19 | K15: 0.14 | L15: 0.15 | M15: 0.13 | N15: 0.09 | O15: 0.012 | P15: 0.005 | Q15: 0
A16: Secondary Feeder I | B16: Secondaries | C16: Active | D16: Diversified secondary portfolio | F16: -0.531 | G16: -0.0476 | H16: 0.3026 | I16: 0.2489 | J16: 0.185 | K16: 0.131 | L16: 0.1471 | M16: 0.1215 | N16: 0.0843 | O16: 0.0131 | P16: 0.0057 | Q16: 0
A32: Instructies:
A33: • Voeg nieuwe fondsen toe door een rij in te vullen (naam, type, status, notities)
A34: • Vul het cashflow profiel in: negatieve % = capital call, positieve % = distributie
A35: • Gebruik 'Dummy' fondsen voor initiële berekeningen, vervang later door echte fondsen
A36: • Fondsen verschijnen automatisch in de dropdown in Cashflow Matrix
A37: • Het TYPE wordt automatisch ingevuld in de Cashflow Matrix wanneer je een fonds selecteert
